Workbook

Sheet Cover
B3: ASML Holding N.V.
B5: Discounted Cash Flow Valuation
B8: Ticker | C8: ASML (Euronext Amsterdam) / ASML (Nasdaq)
B9: Valuation date | C9: =Assumptions!$C$5 -> 46302
B10: Currency | C10: EUR, millions unless stated
B11: Analyst | C11: Ates Parilti
B12: Active scenario | C12: =Assumptions!$C$9 -> Base
B13: DCF price (blended) | C13: =DCF!$E$35 -> 935.30172
B14: DCF Gordon / Exit | C14: =TEXT(DCF!$C$35,"€#,##0")&" / "&TEXT(DCF!$D$35,"€#,##0") -> €759 / €1,112
B15: Trading comps (peer range) | C15: =TEXT(Comps!$E$24,"€#,##0")&" - "&TEXT(Comps!$G$24,"€#,##0") -> €1,251 - €1,690
B16: Current share price | C16: =Assumptions!$C$16 -> 1611.4
B17: Upside / (downside), blended DCF | C17: =DCF!$E$37 -> -0.41957198
B18: Model checks | C18: =Checks!$C$4 -> ALL PASS
B20: Company
C21: ASML designs and builds the lithography systems that print circuit patterns onto silicon wafers. It is the sole supplier of EUV lithography, which every leading-edge logic and DRAM fab depends on. Revenue comes from system sales (EUV, DUV, metrology & inspection) and a growing, recurring installed-base business (service and upgrades).
B23: How to use
B24: 1. Change inputs only on Assumptions (blue on yellow). The scenario selector switches Bear / Base / Bull.
B25: 2. Revenue Build, Forecast, WACC, DCF, Sensitivity, Scenarios, Comps valuation and Dashboard are formulas.
B26: 3. Checks tests the model; the status is shown above and on the Dashboard.
B27: Colour code: blue = hard-coded input; black = formula; green = link to another sheet; grey header = historical; blue header = forecast; light blue = fade.
B29: Sources
B30: [S1] ASML Form 20-F / Annual Report 2025 (US GAAP), filed 25 Feb 2026, incl. XBRL data | C30: https://www.sec.gov/Archives/edgar/data/937966/000162828026011378/asml-20251231.htm
B31: [S2] SEC EDGAR XBRL company facts for ASML (20-F filings FY2020-FY2025) | C31: https://data.sec.gov/api/xbrl/companyfacts/CIK0000937966.json
B32: [S3] ASML Financial Statements US GAAP Q4 2025 (Form 6-K, 28 Jan 2026) | C32: https://www.sec.gov/Archives/edgar/data/937966/000162828026003701/
B33: [S4] ASML Q2 2026 press release and Financial Statements US GAAP (Form 6-K, 15 Jul 2026) | C33: https://www.sec.gov/Archives/edgar/data/0000937966/000162828026048235/pressreleasefinancialresul.htm
B34: [S5] ASML (Euronext Amsterdam: ASML) closing price 7 Oct 2026, via stockanalysis.com | C34: https://stockanalysis.com/quote/ams/ASML/history/
B35: [S6] Germany 10Y Bund yield, 7 Oct 2026, Trading Economics | C35: https://tradingeconomics.com/germany/government-bond-yield
B36: [S7] A. Damodaran, Country risk premiums (Jan 2026): Netherlands total ERP 4.23%, CRP 0% | C36: https://pages.stern.nyu.edu/~adamodar/New_Home_Page/datafile/ctryprem.html
B37: [S8] A. Damodaran, Betas by sector (Jan 2026): Semiconductor Equip unlevered beta corrected for cash 1.39 | C37: https://pages.stern.nyu.edu/~adamodar/New_Home_Page/datafile/Betas.html
B38: [S9] Yahoo Finance monthly and daily prices: ASML.AS and STOXX Europe 600 (^STOXX); regression beta, 52-week range, year-end prices | C38: https://finance.yahoo.com/quote/ASML.AS/history/
B39: [S10] ASML 2024 Investor Day: 2030 revenue opportunity EUR 44-60bn, gross margin 56-60% | C39: https://investor.asml.com/news-releases/news-release-details/asml-provides-updated-view-market-opportunities-2024-investor-day-meeting
B40: [S11] ASML Q4 2025 press release: 2025 sales EUR 32.7bn, backlog EUR 38.8bn | C40: https://www.asml.com/en/news/press-releases/2026/q4-2025-financial-results
B41: [S12] Peer trading data (price, market cap, EV, TTM EBITDA, forward P/E, margins) for AMAT, LRCX, KLAC, Tokyo Electron, ASML, 7-8 Oct 2026, stockanalysis.com | C41: https://stockanalysis.com/stocks/amat/statistics/
B43: For educational purposes only. Not investment advice.

Sheet Assumptions
B1: Assumptions
B2: All model inputs live here. Blue on yellow = hard-coded input; black = formula; green fill = live (selected scenario). EUR millions unless stated.
B4: General | J4: Type | K4: Source / note
B5: Valuation date | C5: 46302 | K5: Pricing date for market data
B6: Latest balance sheet date | C6: 46201 | J6: REPORTED | K6: [S4] Q2 2026 balance sheet; cash flows after this date are valued
B7: FY2026 year end | C7: 46387 | K7: ASML fiscal year = calendar year
B8: Scenario selector (1 Bear, 2 Base, 3 Bull) | C8: 2 | J8: INPUT | K8: Drives the live model (Revenue Build, Forecast, DCF, Sensitivity)
B9: Active scenario | C9: =CHOOSE(Assumptions!$C$8,"Bear","Base","Bull") -> Base
B10: Method switches | J10: Type | K10: Source / note
B11: Mid-year discounting (1 = on, 0 = off) | C11: 1 | J11: INPUT | K11: Cash flows arrive evenly through each year (standard banking convention)
B12: Weight of Gordon Growth in blended price | C12: 0.5 | J12: ASSUMPTION | K12: Blended DCF price = weight x Gordon + (1 - weight) x Exit Multiple
B13: Fade period length (years) | C13: 5 | J13: ASSUMPTION | K13: FY31-FY35: growth steps linearly from the FY30 rate to terminal g; margins, capex, NWC held at FY30
B15: Market data & latest balance sheet | J15: Type | K15: Source / note
B16: Current share price (EUR) | C16: 1611.4 | J16: MARKET | K16: [S5] Closing price Euronext Amsterdam, 7 Oct 2026 (EUR)
B17: Diluted shares outstanding (m) | C17: 384.9 | J17: REPORTED | K17: [S4] Diluted weighted avg. shares Q2 2026 (m)
B18: Cash & short-term investments | C18: 7581.5 | J18: REPORTED | K18: [S4] Cash 6,671.9 + short-term investments 909.6 at 28 Jun 2026
B19: Total debt (bonds + commercial paper) | C19: 3697.7 | J19: DERIVED | K19: [S1/S4] FY25 borrowings 4,390.9 (LT 2,709.0 + current 1,681.9 incl. ECP) less H1-26 repayments 693.2
B20: Non-operating investments | C20: 2310.7 | J20: REPORTED | K20: [S4] Equity investments 1,324.9 + equity-method investments 985.8 at 28 Jun 2026
B21: H1-2026 actual unlevered FCF | C21: -1290.9 | J21: DERIVED | K21: [S4] H1-26 CFO (482.5) - PP&E capex 701.8 - intangibles 106.6; already reflected in 28 Jun cash
B22: 52-week low (EUR) | C22: 813.9 | J22: MARKET | K22: [S9] 52-week low close, Euronext Amsterdam (Oct-25 to Oct-26)
B23: 52-week high (EUR) | C23: 1721.4 | J23: MARKET | K23: [S9] 52-week high close, Euronext Amsterdam (Oct-25 to Oct-26)
B25: LTM EBITDA inputs (for trading comps) | J25: Type | K25: Source / note
B26: H1-2026 income from operations | C26: 6613.9 | J26: REPORTED | K26: [S4] Six months to 28 Jun 2026
B27: H1-2026 depreciation & amortization | C27: 506.3 | J27: REPORTED | K27: [S4] Cash flow statement
B28: H1-2025 income from operations | C28: 5402 | J28: REPORTED | K28: [S4] Six months to 29 Jun 2025
B29: H1-2025 depreciation & amortization | C29: 496.2 | J29: REPORTED | K29: [S4] Cash flow statement
B31: Cost of capital inputs | J31: Type | K31: Source / note
B32: Risk-free rate (10Y Bund) | C32: 0.0351 | J32: MARKET | K32: [S6] German 10Y Bund yield 7 Oct 2026; EUR risk-free matching EUR cash flows
B33: Equity risk premium | C33: 0.0423 | J33: MARKET | K33: [S7] Damodaran implied mature-market ERP, Netherlands CRP = 0
B34: Regression beta vs STOXX Europe 600 (5Y monthly) | C34: 1.79 | J34: DERIVED | K34: [S9] Regression vs STOXX Europe 600, 60 monthly returns Oct-21 to Sep-26 (R² 0.33, std. error ~0.34): too noisy to use alone
B35: Industry unlevered beta (semi equipment) | C35: 1.39 | J35: MARKET | K35: [S8] Semiconductor equipment unlevered beta, cash-corrected
B36: Weight on regression beta | C36: 0 | J36: ASSUMPTION | K36: 0% weight on regression: bottom-up industry beta is used (standard practice when the regression is imprecise)
B37: Credit spread over risk-free (A1/A+) | C37: 0.006 | J37: ASSUMPTION | K37: [S1] Credit spread for A1/A+ (Moody's/Fitch) EUR corporate issuer
B38: Marginal tax rate (debt tax shield) | C38: 0.258 | J38: ASSUMPTION | K38: Dutch statutory CIT rate 25.8% for the interest tax shield
B40: FY2025 revenue mix (base year for the revenue build) | J40: Type | K40: Source / note
B41: EUV low-NA (NXE) systems recognised | C41: 44 | J41: REPORTED | K41: [S1] Note 2, net system sales per technology
B42: EUV low-NA (NXE) sales | C42: 10445.8 | J42: REPORTED | K42: [S1]
B43: EUV High-NA (EXE) systems recognised | C43: 4 | J43: REPORTED | K43: [S1] R&D systems at customers
B44: EUV High-NA (EXE) sales | C44: 1156.9 | J44: REPORTED | K44: [S1]
B45: DUV immersion (ArFi) systems | C45: 131 | J45: REPORTED | K45: [S1]
B46: DUV immersion (ArFi) sales | C46: 10311.4 | J46: REPORTED | K46: [S1]
B47: Other DUV sales (ArF dry, KrF, i-line) | C47: 1735.6 | J47: REPORTED | K47: [S1] 427.0 + 1,001.3 + 307.3
B48: Metrology & inspection sales | C48: 824.6 | J48: REPORTED | K48: [S1]
B49: Installed base management sales | C49: 8193 | J49: REPORTED | K49: [S3] Net service and field option sales
B50: 2026 low-NA EUV capacity (systems) | C50: 65 | J50: REPORTED | K50: [S4] '2026 low NA EUV capacity of around 65'
B51: 2026 DUV immersion capacity (systems) | C51: 130 | J51: REPORTED | K51: [S4] '2026 DUV immersion capacity of around 130'
B52: Annual capacity expansion 2027 and 2028 | C52: 0.3 | J52: REPORTED | K52: [S4] +30% planned for 2027; +30% under investigation for 2028
... B54: 2026 revenue guidance, high | C54: 45000 | J54: REPORTED | K54: [S4]
B56: Scenario drivers: revenue build (FY2026E - FY2030E)
B57: Driver | C57: Case | D57: Unit | E57: FY26E | F57: FY27E | G57: FY28E | H57: FY29E | I57: FY30E | J57: Average | K57: Rationale
B58: EUV low-NA (NXE) systems | C58: Bear | D58: # | E58: 64 | F58: 66 | G58: 60 | H58: 66 | I58: 70 | J58: =AVERAGE(E58:I58) -> 65.2 | K58: Units are anchored to ASML's stated capacity: ~65 low-NA EUV and ~130 DUV immersion systems in 2026, +30% planned for 2027 and +30% being studied for 2028. Base runs below full capacity from 2028 (utilisation ~80%). ASPs start from FY25 actuals (NXE EUR 237m, ArFi EUR 79m) and rise 2%/yr with mix (NXE:3800E, NXT:2100i). High-NA ramps from 4 R&D tools to 22 in 2030. Installed base +30% in 2026 (H1-26: +28%), then grows with the fleet. FY26 total is calibrated to the EUR 43-45bn guidance.
C59: Base | D59: # | E59: 65 | F59: 75 | G59: 82 | H59: 86 | I59: 88 | J59: =AVERAGE(E59:I59) -> 79.2
C60: Bull | D60: # | E60: 65 | F60: 84 | G60: 100 | H60: 106 | I60: 110 | J60: =AVERAGE(E60:I60) -> 93
C61: Live ► | D61: # | E61: =CHOOSE(Assumptions!$C$8,E58,E59,E60) -> 65 | F61: =CHOOSE(Assumptions!$C$8,F58,F59,F60) -> 75 | G61: =CHOOSE(Assumptions!$C$8,G58,G59,G60) -> 82 | H61: =CHOOSE(Assumptions!$C$8,H58,H59,H60) -> 86 | I61: =CHOOSE(Assumptions!$C$8,I58,I59,I60) -> 88 | J61: =AVERAGE(E61:I61) -> 79.2
B63: EUV low-NA ASP | C63: Bear | D63: EUR m | E63: 252 | F63: 250 | G63: 252 | H63: 255 | I63: 258 | J63: =AVERAGE(E63:I63) -> 253.4
C64: Base | D64: EUR m | E64: 255 | F64: 260 | G64: 265 | H64: 270 | I64: 275 | J64: =AVERAGE(E64:I64) -> 265
C65: Bull | D65: EUR m | E65: 258 | F65: 262 | G65: 270 | H65: 277 | I65: 284 | J65: =AVERAGE(E65:I65) -> 270.2
C66: Live ► | D66: EUR m | E66: =CHOOSE(Assumptions!$C$8,E63,E64,E65) -> 255 | F66: =CHOOSE(Assumptions!$C$8,F63,F64,F65) -> 260 | G66: =CHOOSE(Assumptions!$C$8,G63,G64,G65) -> 265 | H66: =CHOOSE(Assumptions!$C$8,H63,H64,H65) -> 270 | I66: =CHOOSE(Assumptions!$C$8,I63,I64,I65) -> 275 | J66: =AVERAGE(E66:I66) -> 265
B68: EUV High-NA (EXE) systems | C68: Bear | D68: # | E68: 8 | F68: 9 | G68: 10 | H68: 12 | I68: 14 | J68: =AVERAGE(E68:I68) -> 10.6
C69: Base | D69: # | E69: 8 | F69: 10 | G69: 14 | H69: 18 | I69: 22 | J69: =AVERAGE(E69:I69) -> 14.4
C70: Bull | D70: # | E70: 9 | F70: 14 | G70: 20 | H70: 26 | I70: 32 | J70: =AVERAGE(E70:I70) -> 20.2
C71: Live ► | D71: # | E71: =CHOOSE(Assumptions!$C$8,E68,E69,E70) -> 8 | F71: =CHOOSE(Assumptions!$C$8,F68,F69,F70) -> 10 | G71: =CHOOSE(Assumptions!$C$8,G68,G69,G70) -> 14 | H71: =CHOOSE(Assumptions!$C$8,H68,H69,H70) -> 18 | I71: =CHOOSE(Assumptions!$C$8,I68,I69,I70) -> 22 | J71: =AVERAGE(E71:I71) -> 14.4
B73: EUV High-NA ASP | C73: Bear | D73: EUR m | E73: 345 | F73: 350 | G73: 355 | H73: 360 | I73: 365 | J73: =AVERAGE(E73:I73) -> 355
C74: Base | D74: EUR m | E74: 350 | F74: 360 | G74: 370 | H74: 380 | I74: 390 | J74: =AVERAGE(E74:I74) -> 370
C75: Bull | D75: EUR m | E75: 355 | F75: 370 | G75: 385 | H75: 395 | I75: 405 | J75: =AVERAGE(E75:I75) -> 382
C76: Live ► | D76: EUR m | E76: =CHOOSE(Assumptions!$C$8,E73,E74,E75) -> 350 | F76: =CHOOSE(Assumptions!$C$8,F73,F74,F75) -> 360 | G76: =CHOOSE(Assumptions!$C$8,G73,G74,G75) -> 370 | H76: =CHOOSE(Assumptions!$C$8,H73,H74,H75) -> 380 | I76: =CHOOSE(Assumptions!$C$8,I73,I74,I75) -> 390 | J76: =AVERAGE(E76:I76) -> 370
B78: DUV immersion (ArFi) systems | C78: Bear | D78: # | E78: 130 | F78: 110 | G78: 95 | H78: 100 | I78: 105 | J78: =AVERAGE(E78:I78) -> 108
C79: Base | D79: # | E79: 130 | F79: 145 | G79: 150 | H79: 145 | I79: 140 | J79: =AVERAGE(E79:I79) -> 142
C80: Bull | D80: # | E80: 130 | F80: 165 | G80: 180 | H80: 175 | I80: 170 | J80: =AVERAGE(E80:I80) -> 164
C81: Live ► | D81: # | E81: =CHOOSE(Assumptions!$C$8,E78,E79,E80) -> 130 | F81: =CHOOSE(Assumptions!$C$8,F78,F79,F80) -> 145 | G81: =CHOOSE(Assumptions!$C$8,G78,G79,G80) -> 150 | H81: =CHOOSE(Assumptions!$C$8,H78,H79,H80) -> 145 | I81: =CHOOSE(Assumptions!$C$8,I78,I79,I80) -> 140 | J81: =AVERAGE(E81:I81) -> 142
B83: DUV immersion ASP | C83: Bear | D83: EUR m | E83: 84 | F83: 84 | G83: 84 | H83: 85 | I83: 86 | J83: =AVERAGE(E83:I83) -> 84.6
C84: Base | D84: EUR m | E84: 86 | F84: 87 | G84: 89 | H84: 91 | I84: 93 | J84: =AVERAGE(E84:I84) -> 89.2
C85: Bull | D85: EUR m | E85: 88 | F85: 89 | G85: 92 | H85: 94 | I85: 96 | J85: =AVERAGE(E85:I85) -> 91.8
C86: Live ► | D86: EUR m | E86: =CHOOSE(Assumptions!$C$8,E83,E84,E85) -> 86 | F86: =CHOOSE(Assumptions!$C$8,F83,F84,F85) -> 87 | G86: =CHOOSE(Assumptions!$C$8,G83,G84,G85) -> 89 | H86: =CHOOSE(Assumptions!$C$8,H83,H84,H85) -> 91 | I86: =CHOOSE(Assumptions!$C$8,I83,I84,I85) -> 93 | J86: =AVERAGE(E86:I86) -> 89.2
B88: Other DUV (dry, KrF, i-line) growth | C88: Bear | D88: % | E88: -0.05 | F88: -0.1 | G88: -0.1 | H88: 0 | I88: 0 | J88: =AVERAGE(E88:I88) -> -0.05
C89: Base | D89: % | E89: 0 | F89: 0 | G89: 0 | H89: 0 | I89: 0 | J89: =AVERAGE(E89:I89) -> 0
C90: Bull | D90: % | E90: 0.02 | F90: 0.05 | G90: 0 | H90: 0 | I90: 0 | J90: =AVERAGE(E90:I90) -> 0.014
C91: Live ► | D91: % | E91: =CHOOSE(Assumptions!$C$8,E88,E89,E90) -> 0 | F91: =CHOOSE(Assumptions!$C$8,F88,F89,F90) -> 0 | G91: =CHOOSE(Assumptions!$C$8,G88,G89,G90) -> 0 | H91: =CHOOSE(Assumptions!$C$8,H88,H89,H90) -> 0 | I91: =CHOOSE(Assumptions!$C$8,I88,I89,I90) -> 0 | J91: =AVERAGE(E91:I91) -> 0
B93: Metrology & inspection growth | C93: Bear | D93: % | E93: 0.1 | F93: 0.02 | G93: 0 | H93: 0.03 | I93: 0.03 | J93: =AVERAGE(E93:I93) -> 0.036
C94: Base | D94: % | E94: 0.2 | F94: 0.1 | G94: 0.08 | H94: 0.06 | I94: 0.05 | J94: =AVERAGE(E94:I94) -> 0.098
C95: Bull | D95: % | E95: 0.22 | F95: 0.14 | G95: 0.12 | H95: 0.1 | I95: 0.08 | J95: =AVERAGE(E95:I95) -> 0.132
C96: Live ► | D96: % | E96: =CHOOSE(Assumptions!$C$8,E93,E94,E95) -> 0.2 | F96: =CHOOSE(Assumptions!$C$8,F93,F94,F95) -> 0.1 | G96: =CHOOSE(Assumptions!$C$8,G93,G94,G95) -> 0.08 | H96: =CHOOSE(Assumptions!$C$8,H93,H94,H95) -> 0.06 | I96: =CHOOSE(Assumptions!$C$8,I93,I94,I95) -> 0.05 | J96: =AVERAGE(E96:I96) -> 0.098
B98: Installed base management growth | C98: Bear | D98: % | E98: 0.3 | F98: 0.04 | G98: 0.02 | H98: 0.04 | I98: 0.04 | J98: =AVERAGE(E98:I98) -> 0.088
C99: Base | D99: % | E99: 0.3 | F99: 0.12 | G99: 0.1 | H99: 0.08 | I99: 0.07 | J99: =AVERAGE(E99:I99) -> 0.134
C100: Bull | D100: % | E100: 0.31 | F100: 0.15 | G100: 0.13 | H100: 0.11 | I100: 0.1 | J100: =AVERAGE(E100:I100) -> 0.16
C101: Live ► | D101: % | E101: =CHOOSE(Assumptions!$C$8,E98,E99,E100) -> 0.3 | F101: =CHOOSE(Assumptions!$C$8,F98,F99,F100) -> 0.12 | G101: =CHOOSE(Assumptions!$C$8,G98,G99,G100) -> 0.1 | H101: =CHOOSE(Assumptions!$C$8,H98,H99,H100) -> 0.08 | I101: =CHOOSE(Assumptions!$C$8,I98,I99,I100) -> 0.07 | J101: =AVERAGE(E101:I101) -> 0.134
B103: Scenario drivers: margins, investment, tax (FY2026E - FY2030E; FY31-35 held at FY30)
B104: Gross margin | C104: Bear | D104: % | E104: 0.54 | F104: 0.51 | G104: 0.5 | H104: 0.51 | I104: 0.52 | J104: =AVERAGE(E104:I104) -> 0.516 | K104: FY26 guide 54-56%. Base trends to 57%, inside ASML's 2030 target band of 56-60% (EUV mix, High-NA maturing, services).
C105: Base | D105: % | E105: 0.55 | F105: 0.56 | G105: 0.565 | H105: 0.57 | I105: 0.57 | J105: =AVERAGE(E105:I105) -> 0.563
C106: Bull | D106: % | E106: 0.555 | F106: 0.57 | G106: 0.58 | H106: 0.59 | I106: 0.6 | J106: =AVERAGE(E106:I106) -> 0.579
C107: Live ► | D107: % | E107: =CHOOSE(Assumptions!$C$8,E104,E105,E106) -> 0.55 | F107: =CHOOSE(Assumptions!$C$8,F104,F105,F106) -> 0.56 | G107: =CHOOSE(Assumptions!$C$8,G104,G105,G106) -> 0.565 | H107: =CHOOSE(Assumptions!$C$8,H104,H105,H106) -> 0.57 | I107: =CHOOSE(Assumptions!$C$8,I104,I105,I106) -> 0.57 | J107: =AVERAGE(E107:I107) -> 0.563
B109: EBITDA margin | C109: Bear | D109: % | E109: 0.395 | F109: 0.36 | G109: 0.345 | H109: 0.355 | I109: 0.365 | J109: =AVERAGE(E109:I109) -> 0.364 | K109: FY25A 37.7%, H1-26 op. margin 36.6% with H2 guided higher. Opex (R&D ~14% of sales) grows slower than revenue = operating leverage. Bear shows a downturn with R&D held flat in absolute terms.
C110: Base | D110: % | E110: 0.41 | F110: 0.42 | G110: 0.425 | H110: 0.43 | I110: 0.43 | J110: =AVERAGE(E110:I110) -> 0.423
C111: Bull | D111: % | E111: 0.415 | F111: 0.435 | G111: 0.45 | H111: 0.46 | I111: 0.465 | J111: =AVERAGE(E111:I111) -> 0.445
C112: Live ► | D112: % | E112: =CHOOSE(Assumptions!$C$8,E109,E110,E111) -> 0.41 | F112: =CHOOSE(Assumptions!$C$8,F109,F110,F111) -> 0.42 | G112: =CHOOSE(Assumptions!$C$8,G109,G110,G111) -> 0.425 | H112: =CHOOSE(Assumptions!$C$8,H109,H110,H111) -> 0.43 | I112: =CHOOSE(Assumptions!$C$8,I109,I110,I111) -> 0.43 | J112: =AVERAGE(E112:I112) -> 0.423
B114: D&A % revenue | C114: Bear | D114: % | E114: 0.028 | F114: 0.03 | G114: 0.03 | H114: 0.03 | I114: 0.03 | J114: =AVERAGE(E114:I114) -> 0.0296 | K114: FY21-25 range 2.5-3.3%, FY25 3.1%. The new capacity build-out lifts the absolute D&A level.
C115: Base | D115: % | E115: 0.028 | F115: 0.028 | G115: 0.028 | H115: 0.028 | I115: 0.028 | J115: =AVERAGE(E115:I115) -> 0.028
C116: Bull | D116: % | E116: 0.028 | F116: 0.027 | G116: 0.027 | H116: 0.027 | I116: 0.027 | J116: =AVERAGE(E116:I116) -> 0.0272
C117: Live ► | D117: % | E117: =CHOOSE(Assumptions!$C$8,E114,E115,E116) -> 0.028 | F117: =CHOOSE(Assumptions!$C$8,F114,F115,F116) -> 0.028 | G117: =CHOOSE(Assumptions!$C$8,G114,G115,G116) -> 0.028 | H117: =CHOOSE(Assumptions!$C$8,H114,H115,H116) -> 0.028 | I117: =CHOOSE(Assumptions!$C$8,I114,I115,I116) -> 0.028 | J117: =AVERAGE(E117:I117) -> 0.028
B119: CapEx % revenue | C119: Bear | D119: % | E119: 0.06 | F119: 0.065 | G119: 0.065 | H119: 0.06 | I119: 0.06 | J119: =AVERAGE(E119:I119) -> 0.062 | K119: FY21-25 average 6.4% (peak 8.0% in FY23 capacity expansion, 5.0% in FY25). Base 5.5% as capex normalises but EUV/High-NA capacity is still added.
...

Sheet Historical
B1: Historical Financials
B2: Reported US GAAP figures (blue) from ASML 20-F filings via SEC XBRL [S1, S2, S3]; ratios and FCF are calculated (black). EUR millions.
B4: EUR m, fiscal year ending 31 Dec | C4: FY20A (ref) | D4: FY21A | E4: FY22A | F4: FY23A | G4: FY24A | H4: FY25A | I4: Type | J4: Source / definition
B5: Reported (US GAAP) and market
B6: Total net sales | C6: 13978.5 | D6: 18611 | E6: 21173.4 | F6: 27558.5 | G6: 28262.9 | H6: 32667.3 | I6: REPORTED | J6: [S2] XBRL 20-F
B7: Cost of sales | D7: 8802 | E7: 10473.3 | F7: 13422.4 | G7: 13770.9 | H7: 15409.3 | I7: REPORTED | J7: [S2] XBRL 20-F
B8: Gross profit | D8: 9809 | E8: 10700.1 | F8: 14136.1 | G8: 14492 | H8: 17258 | I8: REPORTED | J8: [S2] XBRL 20-F
B9: Research & development | D9: 2547 | E9: 3253.5 | F9: 3980.6 | G9: 4303.7 | H9: 4698.8 | I9: REPORTED | J9: [S2] XBRL 20-F
B10: Selling, general & administrative | D10: 725.6 | E10: 945.9 | F10: 1113.2 | G10: 1165.7 | H10: 1257.8 | I10: REPORTED | J10: [S2] XBRL 20-F
B11: Income from operations (EBIT) | D11: 6750.1 | E11: 6500.7 | F11: 9042.3 | G11: 9022.6 | H11: 11301.4 | I11: REPORTED | J11: [S2] XBRL 20-F
B12: Depreciation & amortization (cash flow statement) | D12: 471 | E12: 583.6 | F12: 739.8 | G12: 918.6 | H12: 1025.9 | I12: REPORTED | J12: [S2] XBRL 20-F
B13: Income before income taxes | D13: 6705.5 | E13: 6456.1 | F13: 9083.5 | G13: 9042.4 | H13: 11406.1 | I13: REPORTED | J13: [S2] XBRL 20-F
B14: Income tax expense | D14: 1021.4 | E14: 969.9 | F14: 1435.8 | G14: 1680.6 | H14: 2013.4 | I14: REPORTED | J14: [S2] XBRL 20-F
B15: Net income | D15: 5883.2 | E15: 5624.2 | F15: 7839 | G15: 7571.6 | H15: 9609.4 | I15: REPORTED | J15: [S2] XBRL 20-F
B16: Purchase of PP&E | D16: 900.7 | E16: 1281.8 | F16: 2155.6 | G16: 2067.2 | H16: 1573.6 | I16: REPORTED | J16: [S2] XBRL 20-F
B17: Purchase of intangible assets | D17: 39.6 | E17: 37.5 | F17: 40.6 | G17: 15.9 | H17: 57.6 | I17: REPORTED | J17: [S2] XBRL 20-F
B18: Net cash from operating activities | D18: 10845.8 | E18: 8486.8 | F18: 5443.4 | G18: 11166.2 | H18: 12658.5 | I18: REPORTED | J18: [S2] XBRL 20-F
B19: Cash & cash equivalents | C19: 6049.4 | D19: 6951.8 | E19: 7268.3 | F19: 7004.7 | G19: 12735.9 | H19: 12916 | I19: REPORTED | J19: [S2] XBRL 20-F
B20: Short-term investments | C20: 1302.2 | D20: 638.5 | E20: 107.7 | F20: 5.4 | G20: 5.4 | H20: 405.9 | I20: REPORTED | J20: [S2] XBRL 20-F
B21: Total current assets | C21: 15930 | D21: 18190.2 | E21: 23064.9 | F21: 24393.9 | G21: 30737.4 | H21: 30616.1 | I21: REPORTED | J21: [S2] XBRL 20-F
B22: Loans receivable, current (non-operating) | C22: 0 | D22: 0 | E22: 0 | F22: 0 | G22: 0 | H22: 266.1 | I22: REPORTED | J22: [S2] XBRL 20-F; new line in FY25 [S3]
B23: Total current liabilities | C23: 6603.5 | D23: 12298 | E23: 17983.6 | F23: 16274.7 | G23: 20051.4 | H23: 24263.9 | I23: REPORTED | J23: [S2] XBRL 20-F
B24: Current debt incl. commercial paper | C24: 15.4 | D24: 509.1 | E24: 746.2 | F24: 0.1 | G24: 1010.3 | H24: 1681.9 | I24: REPORTED | J24: [S2] XBRL 20-F; FY25 current debt = bonds 990.2 + ECP 691.7 [S1]
B25: Long-term debt | D25: 4075 | E25: 3514.2 | F25: 4631.5 | G25: 3677.3 | H25: 2709 | I25: REPORTED | J25: [S2] XBRL 20-F
B26: Contract liabilities, non-current | C26: 1639.9 | D26: 3225.7 | E26: 5269.9 | F26: 4825.5 | G26: 5625.4 | H26: 3366.3 | I26: REPORTED | J26: [S2] XBRL 20-F
B27: Diluted weighted avg. shares (m) | D27: 410.4 | E27: 398 | F27: 394.1 | G27: 393.6 | H27: 388.9 | I27: REPORTED | J27: [S2] XBRL 20-F
B28: Year-end share price, Euronext (EUR) | D28: 706.7 | E28: 503.8 | F28: 681.7 | G28: 678.7 | H28: 921.4 | I28: MARKET | J28: [S9] Yahoo Finance
B30: Calculated
B31: Revenue growth % | D31: =D6/C6-1 -> 0.3314018 | E31: =E6/D6-1 -> 0.13768202 | F31: =F6/E6-1 -> 0.30156234 | G31: =G6/F6-1 -> 0.025560172 | H31: =H6/G6-1 -> 0.1558368 | I31: CALCULATED | J31: Revenue / prior-year revenue - 1
B32: Gross margin % | D32: =D8/D6 -> 0.52705389 | E32: =E8/E6 -> 0.50535578 | F32: =F8/F6 -> 0.51294882 | G32: =G8/G6 -> 0.51275701 | H32: =H8/H6 -> 0.52829588 | I32: CALCULATED | J32: Gross profit / revenue
B33: EBITDA | D33: =D11+D12 -> 7221.1 | E33: =E11+E12 -> 7084.3 | F33: =F11+F12 -> 9782.1 | G33: =G11+G12 -> 9941.2 | H33: =H11+H12 -> 12327.3 | I33: CALCULATED | J33: EBIT + D&A
B34: EBITDA margin % | D34: =D33/D6 -> 0.38800172 | E34: =E33/E6 -> 0.3345849 | F34: =F33/F6 -> 0.35495764 | G34: =G33/G6 -> 0.35174027 | H34: =H33/H6 -> 0.37735901 | I34: CALCULATED | J34: EBITDA / revenue
B35: EBIT margin % | D35: =D11/D6 -> 0.36269411 | E35: =E11/E6 -> 0.30702202 | F35: =F11/F6 -> 0.32811292 | G35: =G11/G6 -> 0.31923829 | H35: =H11/H6 -> 0.34595452 | I35: CALCULATED | J35: EBIT / revenue
B36: D&A % revenue | D36: =D12/D6 -> 0.025307614 | E36: =E12/E6 -> 0.027562886 | F36: =F12/F6 -> 0.026844712 | G36: =G12/G6 -> 0.032501973 | H36: =H12/H6 -> 0.031404493 | I36: CALCULATED | J36: D&A / revenue
B37: R&D % revenue | D37: =D9/D6 -> 0.13685455 | E37: =E9/E6 -> 0.15365978 | F37: =F9/F6 -> 0.14444182 | G37: =G9/G6 -> 0.15227383 | H37: =H9/H6 -> 0.14383803 | I37: CALCULATED | J37: R&D / revenue
B38: Effective tax rate | D38: =D14/D13 -> 0.15232272 | E38: =E14/E13 -> 0.15023002 | F38: =F14/F13 -> 0.15806682 | G38: =G14/G13 -> 0.18585774 | H38: =H14/H13 -> 0.17651958 | I38: CALCULATED | J38: Income tax expense / income before taxes
B39: Taxes on EBIT | D39: =D11*D38 -> 1028.1936 | E39: =E11*E38 -> 976.60026 | F39: =F11*F38 -> 1429.2876 | G39: =G11*G38 -> 1676.92 | H39: =H11*H38 -> 1994.9184 | I39: CALCULATED | J39: EBIT x effective tax rate (unlevered taxes)
B40: NOPAT | D40: =D11-D39 -> 5721.9064 | E40: =E11-E39 -> 5524.0997 | F40: =F11-F39 -> 7613.0124 | G40: =G11-G39 -> 7345.68 | H40: =H11-H39 -> 9306.4816 | I40: CALCULATED | J40: EBIT - taxes on EBIT
B41: Total CapEx (PP&E + intangibles) | D41: =D16+D17 -> 940.3 | E41: =E16+E17 -> 1319.3 | F41: =F16+F17 -> 2196.2 | G41: =G16+G17 -> 2083.1 | H41: =H16+H17 -> 1631.2 | I41: CALCULATED
B42: CapEx % revenue | D42: =D41/D6 -> 0.050523884 | E42: =E41/E6 -> 0.062309313 | F42: =F41/F6 -> 0.079692291 | G42: =G41/G6 -> 0.073704397 | H42: =H41/H6 -> 0.049933726 | I42: CALCULATED
B43: Operating net working capital | C43: =(C21-C19-C20-C22)-(C23-C24)-C26 -> 350.4 | D43: =(D21-D19-D20-D22)-(D23-D24)-D26 -> -4414.7 | E43: =(E21-E19-E20-E22)-(E23-E24)-E26 -> -6818.4 | F43: =(F21-F19-F20-F22)-(F23-F24)-F26 -> -3716.3 | G43: =(G21-G19-G20-G22)-(G23-G24)-G26 -> -6670.4 | H43: =(H21-H19-H20-H22)-(H23-H24)-H26 -> -8920.2 | I43: CALCULATED | J43: (Current assets - cash - STI - current loans rec.) - (current liabilities - current debt) - non-current contract liabilities
B44: NWC % revenue | D44: =D43/D6 -> -0.23720918 | E44: =E43/E6 -> -0.32202669 | F44: =F43/F6 -> -0.13485132 | G44: =G43/G6 -> -0.23601258 | H44: =H43/H6 -> -0.27306205 | I44: CALCULATED | J44: Negative = customers pre-fund ASML via EUV down payments
B45: Change in NWC (increase = cash outflow) | D45: =D43-C43 -> -4765.1 | E45: =E43-D43 -> -2403.7 | F45: =F43-E43 -> 3102.1 | G45: =G43-F43 -> -2954.1 | H45: =H43-G43 -> -2249.8 | I45: CALCULATED
B46: Unlevered free cash flow | D46: =D40+D12-D41-D45 -> 10017.706 | E46: =E40+E12-E41-E45 -> 7192.0997 | F46: =F40+F12-F41-F45 -> 3054.5124 | G46: =G40+G12-G41-G45 -> 9135.28 | H46: =H40+H12-H41-H45 -> 10950.982 | I46: CALCULATED | J46: NOPAT + D&A - CapEx - change in NWC
B47: UFCF margin % | D47: =D46/D6 -> 0.53826804 | E47: =E46/E6 -> 0.33967619 | F47: =F46/F6 -> 0.1108374 | G47: =G46/G6 -> 0.32322515 | H47: =H46/H6 -> 0.33522763 | I47: CALCULATED
B48: UFCF / NOPAT (cash conversion) | D48: =D46/D40 -> 1.7507638 | E48: =E46/E40 -> 1.3019497 | F48: =F46/F40 -> 0.40122257 | G48: =G46/G40 -> 1.2436262 | H48: =H46/H40 -> 1.1767048 | I48: CALCULATED
B49: Total debt | D49: =D24+D25 -> 4584.1 | E49: =E24+E25 -> 4260.4 | F49: =F24+F25 -> 4631.6 | G49: =G24+G25 -> 4687.6 | H49: =H24+H25 -> 4390.9 | I49: CALCULATED
B50: Net cash (cash + STI - debt) | D50: =D19+D20-D49 -> 3006.2 | E50: =E19+E20-E49 -> 3115.6 | F50: =F19+F20-F49 -> 2378.5 | G50: =G19+G20-G49 -> 8053.7 | H50: =H19+H20-H49 -> 8931 | I50: CALCULATED
B51: Year-end market capitalisation | D51: =D28*D27 -> 290029.68 | E51: =E28*E27 -> 200512.4 | F51: =F28*F27 -> 268657.97 | G51: =G28*G27 -> 267136.32 | H51: =H28*H27 -> 358332.46 | I51: CALCULATED | J51: Year-end price x diluted shares
B52: Year-end enterprise value | D52: =D51-D50 -> 287023.48 | E52: =E51-E50 -> 197396.8 | F52: =F51-F50 -> 266279.47 | G52: =G51-G50 -> 259082.62 | H52: =H51-H50 -> 349401.46 | I52: CALCULATED | J52: Market cap - net cash
B53: EV / EBITDA (year-end) | D53: =D52/D33 -> 39.747889 | E53: =E52/E33 -> 27.863981 | F53: =F52/F33 -> 27.221095 | G53: =G52/G33 -> 26.061504 | H53: =H52/H33 -> 28.343714 | I53: CALCULATED | J53: Benchmark for the exit multiple
B54: Check: gross profit - (sales - COGS) | D54: =D8-(D6-D7) -> 0 | E54: =E8-(E6-E7) -> -1.8189894e-12 | F54: =F8-(F6-F7) -> 0 | G54: =G8-(G6-G7) -> -1.8189894e-12 | H54: =H8-(H6-H7) -> 0 | I54: CALCULATED | J54: Should be 0
B56: Summary FY21-FY25
B57: Revenue CAGR FY20-FY25 | C57: =(H6/C6)^(1/5)-1 -> 0.18503324
B58: Average gross margin | C58: =AVERAGE(D32:H32) -> 0.51728227
B59: Average EBITDA margin | C59: =AVERAGE(D34:H34) -> 0.36132871
B60: Average effective tax rate | C60: =AVERAGE(D38:H38) -> 0.16459938
B61: Average CapEx % revenue | C61: =AVERAGE(D42:H42) -> 0.063232722
B62: Average NWC % revenue | C62: =AVERAGE(D44:H44) -> -0.24063236
B63: Average year-end EV / EBITDA | C63: =AVERAGE(D53:H53) -> 29.847636
B64: Cumulative UFCF FY21-FY25 | C64: =SUM(D46:H46) -> 40350.58
B66: Trend analysis: what matters for the forecast
B67: 1. Growth is strong but cyclical: revenue rose from EUR 18.6bn (FY21) to EUR 32.7bn (FY25), but FY24 grew only 2.6%. The forecast is therefore built from units and prices against stated capacity, not extrapolated.
B68: 2. Margins expand with EUV mix and scale: gross margin 50.5% (FY22) to 52.8% (FY25); EBITDA margin 33.5% to 37.7%.
B69: 3. The tax rate is low and stable: ETR 15.0%-18.6% (Dutch innovation box).
B70: 4. Capex is light but lumpy: 5.0%-8.0% of sales.
B71: 5. Working capital is the swing factor: NWC is negative (-27% of FY25 sales) because customers prepay EUV systems.
B72: 6. The market has paid 26-40x year-end EBITDA (average 29.8x): the benchmark for the exit multiple.

Sheet Revenue Build
B1: Revenue Build
B2: Live scenario. System revenue = units x average selling price (ASP); other segments grow from their FY25 base. EUR millions.
B4: EUR m | C4: FY25A | D4: FY26E | E4: FY27E | F4: FY28E | G4: FY29E | H4: FY30E
B5: Scenario: | C5: =Assumptions!$C$9 -> Base
B7: EUV low-NA (NXE)
B8: Systems | C8: =Assumptions!$C$41 -> 44 | D8: =Assumptions!E61 -> 65 | E8: =Assumptions!F61 -> 75 | F8: =Assumptions!G61 -> 82 | G8: =Assumptions!H61 -> 86 | H8: =Assumptions!I61 -> 88
B9: ASP (EUR m) | C9: =C10/C8 -> 237.40455 | D9: =Assumptions!E66 -> 255 | E9: =Assumptions!F66 -> 260 | F9: =Assumptions!G66 -> 265 | G9: =Assumptions!H66 -> 270 | H9: =Assumptions!I66 -> 275 | J9: FY25A ASP = reported sales / units
B10: Revenue | C10: =Assumptions!$C$42 -> 10445.8 | D10: =D8*D9 -> 16575 | E10: =E8*E9 -> 19500 | F10: =F8*F9 -> 21730 | G10: =G8*G9 -> 23220 | H10: =H8*H9 -> 24200
B12: EUV High-NA (EXE)
B13: Systems | C13: =Assumptions!$C$43 -> 4 | D13: =Assumptions!E71 -> 8 | E13: =Assumptions!F71 -> 10 | F13: =Assumptions!G71 -> 14 | G13: =Assumptions!H71 -> 18 | H13: =Assumptions!I71 -> 22
B14: ASP (EUR m) | C14: =C15/C13 -> 289.225 | D14: =Assumptions!E76 -> 350 | E14: =Assumptions!F76 -> 360 | F14: =Assumptions!G76 -> 370 | G14: =Assumptions!H76 -> 380 | H14: =Assumptions!I76 -> 390
B15: Revenue | C15: =Assumptions!$C$44 -> 1156.9 | D15: =D13*D14 -> 2800 | E15: =E13*E14 -> 3600 | F15: =F13*F14 -> 5180 | G15: =G13*G14 -> 6840 | H15: =H13*H14 -> 8580
B17: DUV immersion (ArFi)
B18: Systems | C18: =Assumptions!$C$45 -> 131 | D18: =Assumptions!E81 -> 130 | E18: =Assumptions!F81 -> 145 | F18: =Assumptions!G81 -> 150 | G18: =Assumptions!H81 -> 145 | H18: =Assumptions!I81 -> 140
B19: ASP (EUR m) | C19: =C20/C18 -> 78.712977 | D19: =Assumptions!E86 -> 86 | E19: =Assumptions!F86 -> 87 | F19: =Assumptions!G86 -> 89 | G19: =Assumptions!H86 -> 91 | H19: =Assumptions!I86 -> 93
B20: Revenue | C20: =Assumptions!$C$46 -> 10311.4 | D20: =D18*D19 -> 11180 | E20: =E18*E19 -> 12615 | F20: =F18*F19 -> 13350 | G20: =G18*G19 -> 13195 | H20: =H18*H19 -> 13020
B22: Other segments
B23: Other DUV growth | D23: =Assumptions!E91 -> 0 | E23: =Assumptions!F91 -> 0 | F23: =Assumptions!G91 -> 0 | G23: =Assumptions!H91 -> 0 | H23: =Assumptions!I91 -> 0
B24: Other DUV revenue | C24: =Assumptions!$C$47 -> 1735.6 | D24: =C24*(1+D23) -> 1735.6 | E24: =D24*(1+E23) -> 1735.6 | F24: =E24*(1+F23) -> 1735.6 | G24: =F24*(1+G23) -> 1735.6 | H24: =G24*(1+H23) -> 1735.6
B25: Metrology & inspection growth | D25: =Assumptions!E96 -> 0.2 | E25: =Assumptions!F96 -> 0.1 | F25: =Assumptions!G96 -> 0.08 | G25: =Assumptions!H96 -> 0.06 | H25: =Assumptions!I96 -> 0.05
B26: Metrology & inspection revenue | C26: =Assumptions!$C$48 -> 824.6 | D26: =C26*(1+D25) -> 989.52 | E26: =D26*(1+E25) -> 1088.472 | F26: =E26*(1+F25) -> 1175.5498 | G26: =F26*(1+G25) -> 1246.0827 | H26: =G26*(1+H25) -> 1308.3869
B27: Installed base growth | D27: =Assumptions!E101 -> 0.3 | E27: =Assumptions!F101 -> 0.12 | F27: =Assumptions!G101 -> 0.1 | G27: =Assumptions!H101 -> 0.08 | H27: =Assumptions!I101 -> 0.07
B28: Installed base management revenue | C28: =Assumptions!$C$49 -> 8193 | D28: =C28*(1+D27) -> 10650.9 | E28: =D28*(1+E27) -> 11929.008 | F28: =E28*(1+F27) -> 13121.909 | G28: =F28*(1+G27) -> 14171.662 | H28: =G28*(1+H27) -> 15163.678
B30: Total
B31: Net system sales | C31: =C10+C15+C20+C24+C26 -> 24474.3 | D31: =D10+D15+D20+D24+D26 -> 33280.12 | E31: =E10+E15+E20+E24+E26 -> 38539.072 | F31: =F10+F15+F20+F24+F26 -> 43171.15 | G31: =G10+G15+G20+G24+G26 -> 46236.683 | H31: =H10+H15+H20+H24+H26 -> 48843.987
B32: Total net sales | C32: =C31+C28 -> 32667.3 | D32: =D31+D28 -> 43931.02 | E32: =E31+E28 -> 50468.08 | F32: =F31+F28 -> 56293.059 | G32: =G31+G28 -> 60408.344 | H32: =H31+H28 -> 64007.665 | J32: Feeds Forecast FY26E-FY30E revenue
B33: Growth % | C33: =C32/Historical!G6-1 -> 0.1558368 | D33: =D32/C32-1 -> 0.34480107 | E33: =E32/D32-1 -> 0.14880283 | F33: =F32/E32-1 -> 0.11541906 | G33: =G32/F32-1 -> 0.073104674 | H33: =H32/G32-1 -> 0.059583167
B34: EUV share of system sales | C34: =(C10+C15)/C31 -> 0.47407689 | D34: =(D10+D15)/D31 -> 0.58217939 | E34: =(E10+E15)/E31 -> 0.5993917 | F34: =(F10+F15)/F31 -> 0.62333295 | G34: =(G10+G15)/G31 -> 0.65013315 | H34: =(H10+H15)/H31 -> 0.67111639
B35: Installed base share of sales | C35: =C28/C32 -> 0.25080126 | D35: =D28/D32 -> 0.242446 | E35: =E28/E32 -> 0.23636738 | F35: =F28/F32 -> 0.23309994 | G35: =G28/G32 -> 0.23459775 | H35: =H28/H32 -> 0.23690409
B37: Capacity and guidance cross-checks
B38: Low-NA EUV capacity (stated, FY26-28) | D38: =Assumptions!$C$50 -> 65 | E38: =Assumptions!$C$50*(1+Assumptions!$C$52)^1 -> 84.5 | F38: =Assumptions!$C$50*(1+Assumptions!$C$52)^2 -> 109.85 | J38: FY26 stated; FY27 +30% planned; FY28 +30% under investigation [S4]
B39: Low-NA EUV utilisation | D39: =D8/D38 -> 1 | E39: =E8/E38 -> 0.88757396 | F39: =F8/F38 -> 0.74647246 | J39: Above 100% would need capacity ASML has not announced
B40: DUV immersion capacity (stated, FY26-28) | D40: =Assumptions!$C$51 -> 130 | E40: =Assumptions!$C$51*(1+Assumptions!$C$52)^1 -> 169 | F40: =Assumptions!$C$51*(1+Assumptions!$C$52)^2 -> 219.7
B41: DUV immersion utilisation | D41: =D18/D40 -> 1 | E41: =E18/E40 -> 0.85798817 | F41: =F18/F40 -> 0.6827492

Sheet Forecast
B1: Operating Forecast
B2: FY21A-FY25A linked from Historical (green); FY26E-FY30E from the revenue build and live drivers; FY31E-FY35E fade period. EUR millions.
B4: EUR m | C4: FY21A | D4: FY22A | E4: FY23A | F4: FY24A | G4: FY25A | H4: FY26E | I4: FY27E | J4: FY28E | K4: FY29E | L4: FY30E | M4: FY31E | N4: FY32E | O4: FY33E | P4: FY34E | Q4: FY35E | R4: Logic
B5: Scenario: | C5: =Assumptions!$C$9 -> Base | H5: Explicit forecast | M5: Fade period
B6: Fade step (years into fade) | M6: =COLUMN()-COLUMN($L$6) -> 1 | N6: =COLUMN()-COLUMN($L$6) -> 2 | O6: =COLUMN()-COLUMN($L$6) -> 3 | P6: =COLUMN()-COLUMN($L$6) -> 4 | Q6: =COLUMN()-COLUMN($L$6) -> 5
B8: Revenue | C8: =Historical!D6 -> 18611 | D8: =Historical!E6 -> 21173.4 | E8: =Historical!F6 -> 27558.5 | F8: =Historical!G6 -> 28262.9 | G8: =Historical!H6 -> 32667.3 | H8: ='Revenue Build'!D32 -> 43931.02 | I8: ='Revenue Build'!E32 -> 50468.08 | J8: ='Revenue Build'!F32 -> 56293.059 | K8: ='Revenue Build'!G32 -> 60408.344 | L8: ='Revenue Build'!H32 -> 64007.665 | M8: =L8*(1+M9) -> 67378.726 | N8: =M8*(1+N9) -> 70461.296 | O8: =N8*(1+O9) -> 73197.539 | P8: =O8*(1+P9) -> 75533.758 | Q8: =P8*(1+Q9) -> 77422.102 | R8: FY26-30: Revenue Build; FY31-35: prior x (1 + growth)
B9: Revenue growth % | C9: =Historical!D31 -> 0.3314018 | D9: =Historical!E31 -> 0.13768202 | E9: =Historical!F31 -> 0.30156234 | F9: =Historical!G31 -> 0.025560172 | G9: =Historical!H31 -> 0.1558368 | H9: =H8/G8-1 -> 0.34480107 | I9: =I8/H8-1 -> 0.14880283 | J9: =J8/I8-1 -> 0.11541906 | K9: =K8/J8-1 -> 0.073104674 | L9: =L8/K8-1 -> 0.059583167 | M9: =$L9+(Assumptions!$E$137-$L9)*M$6/Assumptions!$C$13 -> 0.052666533 | N9: =$L9+(Assumptions!$E$137-$L9)*N$6/Assumptions!$C$13 -> 0.0457499 | O9: =$L9+(Assumptions!$E$137-$L9)*O$6/Assumptions!$C$13 -> 0.038833267 | P9: =$L9+(Assumptions!$E$137-$L9)*P$6/Assumptions!$C$13 -> 0.031916633 | Q9: =$L9+(Assumptions!$E$137-$L9)*Q$6/Assumptions!$C$13 -> 0.025 | R9: Fade: FY30 growth + (g - FY30 growth) x step / fade years
B11: Gross profit | C11: =Historical!D8 -> 9809 | D11: =Historical!E8 -> 10700.1 | E11: =Historical!F8 -> 14136.1 | F11: =Historical!G8 -> 14492 | G11: =Historical!H8 -> 17258 | H11: =H8*H12 -> 24162.061 | I11: =I8*I12 -> 28262.125 | J11: =J8*J12 -> 31805.578 | K11: =K8*K12 -> 34432.756 | L11: =L8*L12 -> 36484.369 | M11: =M8*M12 -> 38405.874 | N11: =N8*N12 -> 40162.939 | O11: =O8*O12 -> 41722.597 | ... Q11: =Q8*Q12 -> 44130.598 | R11: Revenue x gross margin
B12: Gross margin % | C12: =Historical!D32 -> 0.52705389 | D12: =Historical!E32 -> 0.50535578 | E12: =Historical!F32 -> 0.51294882 | F12: =Historical!G32 -> 0.51275701 | G12: =Historical!H32 -> 0.52829588 | H12: =Assumptions!E107 -> 0.55 | I12: =Assumptions!F107 -> 0.56 | J12: =Assumptions!G107 -> 0.565 | K12: =Assumptions!H107 -> 0.57 | L12: =Assumptions!I107 -> 0.57 | M12: =$L12 -> 0.57 | N12: =$L12 -> 0.57 | O12: =$L12 -> 0.57 | P12: =$L12 -> 0.57 | Q12: =$L12 -> 0.57
B14: EBITDA | C14: =Historical!D33 -> 7221.1 | D14: =Historical!E33 -> 7084.3 | E14: =Historical!F33 -> 9782.1 | F14: =Historical!G33 -> 9941.2 | G14: =Historical!H33 -> 12327.3 | H14: =H8*H15 -> 18011.718 | I14: =I8*I15 -> 21196.594 | J14: =J8*J15 -> 23924.55 | K14: =K8*K15 -> 25975.588 | L14: =L8*L15 -> 27523.296 | M14: =M8*M15 -> 28972.852 | N14: =N8*N15 -> 30298.357 | O14: =O8*O15 -> 31474.942 | ... Q14: =Q8*Q15 -> 33291.504 | R14: Revenue x EBITDA margin
B15: EBITDA margin % | C15: =Historical!D34 -> 0.38800172 | D15: =Historical!E34 -> 0.3345849 | E15: =Historical!F34 -> 0.35495764 | F15: =Historical!G34 -> 0.35174027 | G15: =Historical!H34 -> 0.37735901 | H15: =Assumptions!E112 -> 0.41 | I15: =Assumptions!F112 -> 0.42 | J15: =Assumptions!G112 -> 0.425 | K15: =Assumptions!H112 -> 0.43 | L15: =Assumptions!I112 -> 0.43 | M15: =$L15 -> 0.43 | N15: =$L15 -> 0.43 | O15: =$L15 -> 0.43 | P15: =$L15 -> 0.43 | Q15: =$L15 -> 0.43 | R15: Fade years hold the FY30 ratio
B17: Depreciation & amortization | C17: =Historical!D12 -> 471 | D17: =Historical!E12 -> 583.6 | E17: =Historical!F12 -> 739.8 | F17: =Historical!G12 -> 918.6 | G17: =Historical!H12 -> 1025.9 | H17: =H8*H18 -> 1230.0686 | I17: =I8*I18 -> 1413.1062 | J17: =J8*J18 -> 1576.2056 | K17: =K8*K18 -> 1691.4336 | L17: =L8*L18 -> 1792.2146 | M17: =M8*M18 -> 1886.6043 | N17: =N8*N18 -> 1972.9163 | O17: =O8*O18 -> 2049.5311 | ... Q17: =Q8*Q18 -> 2167.8188 | R17: Revenue x D&A %
B18: D&A % revenue | C18: =Historical!D36 -> 0.025307614 | D18: =Historical!E36 -> 0.027562886 | E18: =Historical!F36 -> 0.026844712 | F18: =Historical!G36 -> 0.032501973 | G18: =Historical!H36 -> 0.031404493 | H18: =Assumptions!E117 -> 0.028 | I18: =Assumptions!F117 -> 0.028 | J18: =Assumptions!G117 -> 0.028 | K18: =Assumptions!H117 -> 0.028 | L18: =Assumptions!I117 -> 0.028 | M18: =$L18 -> 0.028 | N18: =$L18 -> 0.028 | O18: =$L18 -> 0.028 | P18: =$L18 -> 0.028 | Q18: =$L18 -> 0.028
B20: EBIT | C20: =Historical!D11 -> 6750.1 | D20: =Historical!E11 -> 6500.7 | E20: =Historical!F11 -> 9042.3 | F20: =Historical!G11 -> 9022.6 | G20: =Historical!H11 -> 11301.4 | H20: =H14-H17 -> 16781.65 | I20: =I14-I17 -> 19783.487 | J20: =J14-J17 -> 22348.344 | K20: =K14-K17 -> 24284.154 | L20: =L14-L17 -> 25731.081 | M20: =M14-M17 -> 27086.248 | N20: =N14-N17 -> 28325.441 | O20: =O14-O17 -> 29425.411 | ... Q20: =Q14-Q17 -> 31123.685 | R20: EBITDA - D&A
B21: EBIT margin % | C21: =Historical!D35 -> 0.36269411 | D21: =Historical!E35 -> 0.30702202 | E21: =Historical!F35 -> 0.32811292 | F21: =Historical!G35 -> 0.31923829 | G21: =Historical!H35 -> 0.34595452 | H21: =H20/H8 -> 0.382 | I21: =I20/I8 -> 0.392 | J21: =J20/J8 -> 0.397 | K21: =K20/K8 -> 0.402 | L21: =L20/L8 -> 0.402 | M21: =M20/M8 -> 0.402 | N21: =N20/N8 -> 0.402 | O21: =O20/O8 -> 0.402 | ... Q21: =Q20/Q8 -> 0.402
B23: Taxes on EBIT | C23: =Historical!D39 -> 1028.1936 | D23: =Historical!E39 -> 976.60026 | E23: =Historical!F39 -> 1429.2876 | F23: =Historical!G39 -> 1676.92 | G23: =Historical!H39 -> 1994.9184 | H23: =H20*H24 -> 2936.7887 | I23: =I20*I24 -> 3462.1103 | J23: =J20*J24 -> 3910.9602 | K23: =K20*K24 -> 4249.727 | L23: =L20*L24 -> 4502.9392 | M23: =M20*M24 -> 4740.0934 | N23: =N20*N24 -> 4956.9522 | O23: =O20*O24 -> 5149.4469 | ... Q23: =Q20*Q24 -> 5446.6449 | R23: EBIT x tax rate
B24: Tax rate | C24: =Historical!D38 -> 0.15232272 | D24: =Historical!E38 -> 0.15023002 | E24: =Historical!F38 -> 0.15806682 | F24: =Historical!G38 -> 0.18585774 | G24: =Historical!H38 -> 0.17651958 | H24: =Assumptions!E132 -> 0.175 | I24: =Assumptions!F132 -> 0.175 | J24: =Assumptions!G132 -> 0.175 | K24: =Assumptions!H132 -> 0.175 | L24: =Assumptions!I132 -> 0.175 | M24: =$L24 -> 0.175 | N24: =$L24 -> 0.175 | O24: =$L24 -> 0.175 | P24: =$L24 -> 0.175 | Q24: =$L24 -> 0.175
B25: NOPAT | C25: =Historical!D40 -> 5721.9064 | D25: =Historical!E40 -> 5524.0997 | E25: =Historical!F40 -> 7613.0124 | F25: =Historical!G40 -> 7345.68 | G25: =Historical!H40 -> 9306.4816 | H25: =H20-H23 -> 13844.861 | I25: =I20-I23 -> 16321.377 | J25: =J20-J23 -> 18437.384 | K25: =K20-K23 -> 20034.427 | L25: =L20-L23 -> 21228.142 | M25: =M20-M23 -> 22346.155 | N25: =N20-N23 -> 23368.489 | O25: =O20-O23 -> 24275.964 | ... Q25: =Q20-Q23 -> 25677.04 | R25: EBIT - taxes
B27: Capital expenditures | C27: =Historical!D41 -> 940.3 | D27: =Historical!E41 -> 1319.3 | E27: =Historical!F41 -> 2196.2 | F27: =Historical!G41 -> 2083.1 | G27: =Historical!H41 -> 1631.2 | H27: =H8*H28 -> 2416.2061 | I27: =I8*I28 -> 2775.7444 | J27: =J8*J28 -> 3096.1182 | K27: =K8*K28 -> 3322.4589 | L27: =L8*L28 -> 3520.4216 | M27: =M8*M28 -> 3705.83 | N27: =N8*N28 -> 3875.3713 | O27: =O8*O28 -> 4025.8646 | ... Q27: =Q8*Q28 -> 4258.2156 | R27: Revenue x CapEx %
B28: CapEx % revenue | C28: =Historical!D42 -> 0.050523884 | D28: =Historical!E42 -> 0.062309313 | E28: =Historical!F42 -> 0.079692291 | F28: =Historical!G42 -> 0.073704397 | G28: =Historical!H42 -> 0.049933726 | H28: =Assumptions!E122 -> 0.055 | I28: =Assumptions!F122 -> 0.055 | J28: =Assumptions!G122 -> 0.055 | K28: =Assumptions!H122 -> 0.055 | L28: =Assumptions!I122 -> 0.055 | M28: =$L28 -> 0.055 | N28: =$L28 -> 0.055 | O28: =$L28 -> 0.055 | P28: =$L28 -> 0.055 | Q28: =$L28 -> 0.055
B30: Net working capital | C30: =Historical!D43 -> -4414.7 | D30: =Historical!E43 -> -6818.4 | E30: =Historical!F43 -> -3716.3 | F30: =Historical!G43 -> -6670.4 | G30: =Historical!H43 -> -8920.2 | H30: =H8*H31 -> -5271.7224 | I30: =I8*I31 -> -6056.1696 | J30: =J8*J31 -> -6755.167 | K30: =K8*K31 -> -7249.0013 | L30: =L8*L31 -> -7680.9198 | M30: =M8*M31 -> -8085.4472 | N30: =N8*N31 -> -8455.3556 | O30: =O8*O31 -> -8783.7047 | ... Q30: =Q8*Q31 -> -9290.6522 | R30: Revenue x NWC %
B31: NWC % revenue | C31: =Historical!D44 -> -0.23720918 | D31: =Historical!E44 -> -0.32202669 | E31: =Historical!F44 -> -0.13485132 | F31: =Historical!G44 -> -0.23601258 | G31: =Historical!H44 -> -0.27306205 | H31: =Assumptions!E127 -> -0.12 | I31: =Assumptions!F127 -> -0.12 | J31: =Assumptions!G127 -> -0.12 | K31: =Assumptions!H127 -> -0.12 | L31: =Assumptions!I127 -> -0.12 | M31: =$L31 -> -0.12 | N31: =$L31 -> -0.12 | O31: =$L31 -> -0.12 | P31: =$L31 -> -0.12 | Q31: =$L31 -> -0.12
B32: Change in NWC (increase = outflow) | C32: =Historical!D45 -> -4765.1 | D32: =Historical!E45 -> -2403.7 | E32: =Historical!F45 -> 3102.1 | F32: =Historical!G45 -> -2954.1 | G32: =Historical!H45 -> -2249.8 | H32: =H30-G30 -> 3648.4776 | I32: =I30-H30 -> -784.4472 | J32: =J30-I30 -> -698.99743 | K32: =K30-J30 -> -493.83428 | L32: =L30-K30 -> -431.91845 | M32: =M30-L30 -> -404.52742 | N32: =N30-M30 -> -369.9084 | O32: =O30-N30 -> -328.34908 | ... Q32: =Q30-P30 -> -226.60127 | R32: NWC - prior NWC
B34: Unlevered free cash flow | C34: =Historical!D46 -> 10017.706 | D34: =Historical!E46 -> 7192.0997 | E34: =Historical!F46 -> 3054.5124 | F34: =Historical!G46 -> 9135.28 | G34: =Historical!H46 -> 10950.982 | H34: =H25+H17-H27-H32 -> 9010.2458 | I34: =I25+I17-I27-I32 -> 15743.186 | J34: =J25+J17-J27-J32 -> 17616.469 | K34: =K25+K17-K27-K32 -> 18897.236 | L34: =L25+L17-L27-L32 -> 19931.854 | M34: =M25+M17-M27-M32 -> 20931.456 | N34: =N25+N17-N27-N32 -> 21835.942 | O34: =O25+O17-O27-O32 -> 22627.979 | ... Q34: =Q25+Q17-Q27-Q32 -> 23813.245 | R34: NOPAT + D&A - CapEx - change in NWC
B35: UFCF margin % | C35: =Historical!D47 -> 0.53826804 | D35: =Historical!E47 -> 0.33967619 | E35: =Historical!F47 -> 0.1108374 | F35: =Historical!G47 -> 0.32322515 | G35: =Historical!H47 -> 0.33522763 | H35: =H34/H8 -> 0.20509985 | I35: =I34/I8 -> 0.31194343 | J35: =J34/J8 -> 0.31294212 | K35: =K34/K8 -> 0.31282493 | L35: =L34/L8 -> 0.31139792 | M35: =M34/M8 -> 0.31065379 | N35: =N34/N8 -> 0.30989981 | O35: =O34/O8 -> 0.30913579 | ... Q35: =Q34/Q8 -> 0.30757683
B37: Memo: implied opex % (GM - EBIT margin) | C37: =C12-C21 -> 0.16435979 | D37: =D12-D21 -> 0.19833376 | E37: =E12-E21 -> 0.18483589 | F37: =F12-F21 -> 0.19351871 | G37: =G12-G21 -> 0.18234136 | H37: =H12-H21 -> 0.168 | I37: =I12-I21 -> 0.168 | J37: =J12-J21 -> 0.168 | ... Q37: =Q12-Q21 -> 0.168 | R37: Sanity check: R&D + SG&A ~ 16-19% historically
B39: Revenue CAGR FY25A-FY30E | C39: =(L8/G8)^(1/5)-1 -> 0.143994
B40: Average EBITDA margin FY26-30 | C40: =AVERAGE(H15:L15) -> 0.423
B41: FY30E revenue vs 2030 company range (EUR 44-60bn) [S10] | C41: =IF(L8>60000,"Above range",IF(L8<44000,"Below range","Within range")) -> Above range

Sheet WACC
B1: Weighted Average Cost of Capital
B2: CAPM cost of equity, market-value weights. Inputs are linked from Assumptions (green).
B5: Cost of equity
B6: Risk-free rate | C6: =Assumptions!$C$32 -> 0.0351 | D6: 10Y German Bund: EUR, long-duration, matches EUR cash flows
B7: Regression beta vs STOXX Europe 600 (cross-check) | C7: =Assumptions!$C$34 -> 1.79 | D7: 60 monthly returns; R² 0.33, standard error ~0.34, so the 95% range is ~1.1-2.5
B8: Industry unlevered beta | C8: =Assumptions!$C$35 -> 1.39 | D8: Semiconductor equipment peers, cash-corrected (Damodaran)
B9: ASML market D/E | C9: =C27/C26 -> 0.0059618412 | D9: Debt / market capitalisation
B10: Relevered industry beta | C10: =C8*(1+(1-C20)*C9) -> 1.3961489 | D10: Hamada: Bu x (1 + (1 - t) x D/E)
B11: Weight on regression beta | C11: =Assumptions!$C$36 -> 0 | D11: 0% = pure bottom-up beta
B12: Selected beta | C12: =C11*C7+(1-C11)*C10 -> 1.3961489 | D12: Bottom-up beta: more stable than a single-stock regression
B13: Equity risk premium | C13: =Assumptions!$C$33 -> 0.0423 | D13: Implied mature-market ERP; Netherlands has no country premium
B14: Cost of equity (CAPM) | C14: =C6+C12*C13 -> 0.094157099 | D14: Rf + beta x ERP
B16: Cost of debt
B17: Risk-free rate | C17: =C6 -> 0.0351
B18: Credit spread (A1 / A+) | C18: =Assumptions!$C$37 -> 0.006 | D18: Spread for single-A EUR corporate bonds
B19: Pre-tax cost of debt | C19: =C17+C18 -> 0.0411 | D19: Rf + spread
B20: Tax rate (statutory) | C20: =Assumptions!$C$38 -> 0.258 | D20: Interest is deductible at the Dutch statutory rate
B21: After-tax cost of debt | C21: =C19*(1-C20) -> 0.0304962 | D21: Kd x (1 - t)
B23: Capital structure (market values)
B24: Share price (EUR) | C24: =Assumptions!$C$16 -> 1611.4
B25: Diluted shares (m) | C25: =Assumptions!$C$17 -> 384.9
B26: Market value of equity (E) | C26: =C24*C25 -> 620227.86 | D26: Price x diluted shares
B27: Debt (D) | C27: =Assumptions!$C$19 -> 3697.7 | D27: Book value as proxy for market value
B28: Total capital (D + E) | C28: =C26+C27 -> 623925.56
B29: Equity weight E / (D + E) | C29: =C26/C28 -> 0.99407349
B30: Debt weight D / (D + E) | C30: =C27/C28 -> 0.0059265083
B32: WACC
B33: WACC (CAPM) | C33: =C29*C14+C30*C21 -> 0.093779813 | D33: E/(D+E) x Ke + D/(D+E) x Kd x (1 - t)
B34: Scenario adjustment | C34: =Assumptions!$E$147 -> 0 | D34: 0 in Base; +/-0.5% in Bear/Bull
B35: WACC applied in DCF | C35: =C33+C34 -> 0.093779813

Sheet DCF
B1: Discounted Cash Flow
B2: Valuation at the valuation date on the 28-Jun-26 balance sheet. FY26 counts only H2 cash flow (stub); FY31-35 is the fade period; terminal value at end FY35.
B4: EUR m | E4: FY26E | F4: FY27E | G4: FY28E | H4: FY29E | I4: FY30E | J4: FY31E | K4: FY32E | L4: FY33E | M4: FY34E | N4: FY35E
B5: Period end | E5: =Assumptions!$C$7 -> 46387 | F5: =DATE(YEAR(E5)+1,12,31) -> 46752 | G5: =DATE(YEAR(F5)+1,12,31) -> 47118 | H5: =DATE(YEAR(G5)+1,12,31) -> 47483 | I5: =DATE(YEAR(H5)+1,12,31) -> 47848 | J5: =DATE(YEAR(I5)+1,12,31) -> 48213 | K5: =DATE(YEAR(J5)+1,12,31) -> 48579 | L5: =DATE(YEAR(K5)+1,12,31) -> 48944 | M5: =DATE(YEAR(L5)+1,12,31) -> 49309 | N5: =DATE(YEAR(M5)+1,12,31) -> 49674
B6: Years from valuation date to period end | E6: =(E5-Assumptions!$C$5)/365 -> 0.23287671 | F6: =E6+1 -> 1.2328767 | G6: =F6+1 -> 2.2328767 | H6: =G6+1 -> 3.2328767 | I6: =H6+1 -> 4.2328767 | J6: =I6+1 -> 5.2328767 | K6: =J6+1 -> 6.2328767 | L6: =K6+1 -> 7.2328767 | M6: =L6+1 -> 8.2328767 | N6: =M6+1 -> 9.2328767
B7: Discount period (mid-year if switched on) | E7: =IF(Assumptions!$C$11=1,E6/2,E6) -> 0.11643836 | F7: =IF(Assumptions!$C$11=1,F6-0.5,F6) -> 0.73287671 | G7: =IF(Assumptions!$C$11=1,G6-0.5,G6) -> 1.7328767 | H7: =IF(Assumptions!$C$11=1,H6-0.5,H6) -> 2.7328767 | I7: =IF(Assumptions!$C$11=1,I6-0.5,I6) -> 3.7328767 | J7: =IF(Assumptions!$C$11=1,J6-0.5,J6) -> 4.7328767 | K7: =IF(Assumptions!$C$11=1,K6-0.5,K6) -> 5.7328767 | L7: =IF(Assumptions!$C$11=1,L6-0.5,L6) -> 6.7328767 | M7: =IF(Assumptions!$C$11=1,M6-0.5,M6) -> 7.7328767 | N7: =IF(Assumptions!$C$11=1,N6-0.5,N6) -> 8.7328767 | O7: FY26 stub: mid-point of remaining period; later years: mid-year
B9: Unlevered free cash flow | E9: =Forecast!H34 -> 9010.2458 | F9: =Forecast!I34 -> 15743.186 | G9: =Forecast!J34 -> 17616.469 | H9: =Forecast!K34 -> 18897.236 | I9: =Forecast!L34 -> 19931.854 | J9: =Forecast!M34 -> 20931.456 | K9: =Forecast!N34 -> 21835.942 | L9: =Forecast!O34 -> 22627.979 | ... N9: =Forecast!Q34 -> 23813.245
B10: Less: H1-26 actual UFCF (already in 28-Jun cash) | E10: =-Assumptions!$C$21 -> 1290.9 | F10: 0 | G10: 0 | H10: 0 | I10: 0 | J10: 0 | K10: 0 | L10: 0 | M10: 0 | N10: 0 | O10: Avoids double counting: H1 cash flows are in the balance sheet already
B11: Cash flow to discount | E11: =E9+E10 -> 10301.146 | F11: =F9+F10 -> 15743.186 | G11: =G9+G10 -> 17616.469 | H11: =H9+H10 -> 18897.236 | I11: =I9+I10 -> 19931.854 | J11: =J9+J10 -> 20931.456 | K11: =K9+K10 -> 21835.942 | L11: =L9+L10 -> 22627.979 | ... N11: =N9+N10 -> 23813.245
B12: WACC | E12: =WACC!$C$35 -> 0.093779813 | F12: =WACC!$C$35 -> 0.093779813 | G12: =WACC!$C$35 -> 0.093779813 | H12: =WACC!$C$35 -> 0.093779813 | I12: =WACC!$C$35 -> 0.093779813 | J12: =WACC!$C$35 -> 0.093779813 | K12: =WACC!$C$35 -> 0.093779813 | L12: =WACC!$C$35 -> 0.093779813 | ... N12: =WACC!$C$35 -> 0.093779813
B13: Discount factor | E13: =1/(1+E12)^E7 -> 0.98961682 | F13: =1/(1+F12)^F7 -> 0.93641676 | G13: =1/(1+G12)^G7 -> 0.85612913 | H13: =1/(1+H12)^H7 -> 0.7827253 | I13: =1/(1+I12)^I7 -> 0.71561506 | J13: =1/(1+J12)^J7 -> 0.65425879 | K13: =1/(1+K12)^K7 -> 0.59816316 | L13: =1/(1+L12)^L7 -> 0.54687713 | ... N13: =1/(1+N12)^N7 -> 0.45711971
B14: PV of cash flow | E14: =E11*E13 -> 10194.187 | F14: =F11*F13 -> 14742.183 | G14: =G11*G13 -> 15081.972 | H14: =H11*H13 -> 14791.345 | I14: =I11*I13 -> 14263.534 | J14: =J11*J13 -> 13694.589 | K14: =K11*K13 -> 13061.456 | L14: =L11*L13 -> 12374.724 | ... N14: =N11*N13 -> 10885.504
B15: Sum of PV of cash flows FY26-FY35 | C15: =SUM(E14:N14) -> 130735.08
B16: of which explicit forecast FY26-FY30 | C16: =SUM(E14:I14) -> 69073.222
B17: of which fade period FY31-FY35 | C17: =SUM(J14:N14) -> 61661.854
B19: Valuation | C19: Gordon Growth | D19: Exit Multiple | E19: Blended
B20: Terminal-year UFCF (FY35E) | C20: =N9 -> 23813.245
B21: Terminal growth rate | C21: =Assumptions!$E$137 -> 0.025
B22: Terminal-year EBITDA (FY35E) | D22: =Forecast!Q14 -> 33291.504
B23: Exit EV/EBITDA multiple | D23: =Assumptions!$E$142 -> 20
B24: Terminal value at end FY35 | C24: =C20*(1+C21)/(WACC!$C$35-C21) -> 354879.94 | D24: =D22*D23 -> 665830.08 | F24: Gordon: FCF35 x (1 + g) / (WACC - g). Exit: EBITDA35 x multiple
B25: Discount period for terminal value | C25: =$N$6 -> 9.2328767 | D25: =$N$6 -> 9.2328767 | F25: Both terminal values discounted from end of FY35 (conservative)
B26: PV of terminal value | C26: =C24/(1+WACC!$C$35)^C25 -> 155112.38 | D26: =D24/(1+WACC!$C$35)^D25 -> 291023.73
B27: PV of FY26-FY35 cash flows | C27: =$C$15 -> 130735.08 | D27: =$C$15 -> 130735.08
B28: Enterprise value | C28: =C27+C26 -> 285847.45 | D28: =D27+D26 -> 421758.81 | E28: =Assumptions!$C$12*C28+(1-Assumptions!$C$12)*D28 -> 353803.13
B29: Terminal value % of EV | C29: =C26/C28 -> 0.5426404 | D29: =D26/D28 -> 0.69002408
B30: Plus: cash & short-term investments | C30: =Assumptions!$C$18 -> 7581.5 | D30: =Assumptions!$C$18 -> 7581.5
B31: Less: total debt | C31: =Assumptions!$C$19 -> 3697.7 | D31: =Assumptions!$C$19 -> 3697.7 | F31: Bonds + commercial paper; US GAAP operating leases excluded (lease cost already in EBITDA)
B32: Plus: non-operating investments | C32: =Assumptions!$C$20 -> 2310.7 | D32: =Assumptions!$C$20 -> 2310.7 | F32: Equity stakes (e.g. Mistral AI) and equity-method investments; their income is not in EBIT
B33: Equity value | C33: =C28+C30-C31+C32 -> 292041.95 | D33: =D28+D30-D31+D32 -> 427953.31 | E33: =Assumptions!$C$12*C33+(1-Assumptions!$C$12)*D33 -> 359997.63
B34: Diluted shares (m) | C34: =Assumptions!$C$17 -> 384.9 | D34: =Assumptions!$C$17 -> 384.9
B35: Implied share price (EUR) | C35: =C33/C34 -> 758.7476 | D35: =D33/D34 -> 1111.8558 | E35: =Assumptions!$C$12*C35+(1-Assumptions!$C$12)*D35 -> 935.30172
B36: Current share price (EUR) | C36: =Assumptions!$C$16 -> 1611.4 | D36: =Assumptions!$C$16 -> 1611.4 | E36: =Assumptions!$C$16 -> 1611.4
B37: Upside / (downside) | C37: =C35/C36-1 -> -0.52913764 | D37: =D35/D36-1 -> -0.31000631 | E37: =E35/E36-1 -> -0.41957198
B38: Cross-check: implied exit multiple / implied g | C38: =C24/D22 -> 10.659775 | D38: =(D24*WACC!$C$35-C20)/(D24+C20) -> 0.056011817 | F38: Gordon TV / EBITDA (x) | g implied by exit TV
B39: Reverse DCF: exit multiple implied by market price | D39: =((C36*C34-C30+C31-C32-C27)*(1+WACC!$C$35)^D25)/D22 -> 33.213668 | F39: Multiple needed in the Exit method to justify today's price
B40: Reverse DCF: perpetual growth implied by market price | C40: =(((C36*C34-C30+C31-C32-C27)*(1+WACC!$C$35)^C25)*WACC!$C$35-C20)/(((C36*C34-C30+C31-C32-C27)*(1+WACC!$C$35)^C25)+C20) -> 0.0707206 | F40: Perpetual growth needed in the Gordon method to justify today's price

Sheet Sensitivity
B1: Sensitivity Analysis
B2: Implied share price (EUR). Every cell is a live closed-form DCF; the grid centres on the live WACC, g and multiple. Base case boxed and shaded.
B4: Table 1: WACC vs terminal growth (Gordon Growth method) | M4: Grid steps
C5: WACC → | M5: WACC step | N5: 0.005
B6: g ↓ / WACC → | C6: =$G$6+(-4)*$N$5 -> 0.073779813 | D6: =$G$6+(-3)*$N$5 -> 0.078779813 | E6: =$G$6+(-2)*$N$5 -> 0.083779813 | F6: =$G$6+(-1)*$N$5 -> 0.088779813 | G6: =WACC!$C$35 -> 0.093779813 | H6: =$G$6+(1)*$N$5 -> 0.098779813 | I6: =$G$6+(2)*$N$5 -> 0.10377981 | J6: =$G$6+(3)*$N$5 -> 0.10877981 | K6: =$G$6+(4)*$N$5 -> 0.11377981 | M6: Terminal growth step | N6: 0.0025
B7: =$B$11+(-4)*$N$6 -> 0.015 | C7: =(SUMPRODUCT(DCF!$E$11:$N$11,1/(1+C$6)^DCF!$E$7:$N$7)+DCF!$N$9*(1+$B7)/(C$6-$B7)/(1+C$6)^DCF!$N$6+(DCF!$C$30-DCF!$C$31+DCF!$C$32))/DCF!$C$34 -> 936.80743 | D7: =(SUMPRODUCT(DCF!$E$11:$N$11,1/(1+D$6)^DCF!$E$7:$N$7)+DCF!$N$9*(1+$B7)/(D$6-$B7)/(1+D$6)^DCF!$N$6+(DCF!$C$30-DCF!$C$31+DCF!$C$32))/DCF!$C$34 -> 864.80327 | E7: =(SUMPRODUCT(DCF!$E$11:$N$11,1/(1+E$6)^DCF!$E$7:$N$7)+DCF!$N$9*(1+$B7)/(E$6-$B7)/(1+E$6)^DCF!$N$6+(DCF!$C$30-DCF!$C$31+DCF!$C$32))/DCF!$C$34 -> 803.37337 | F7: =(SUMPRODUCT(DCF!$E$11:$N$11,1/(1+F$6)^DCF!$E$7:$N$7)+DCF!$N$9*(1+$B7)/(F$6-$B7)/(1+F$6)^DCF!$N$6+(DCF!$C$30-DCF!$C$31+DCF!$C$32))/DCF!$C$34 -> 750.36185 | G7: =(SUMPRODUCT(DCF!$E$11:$N$11,1/(1+G$6)^DCF!$E$7:$N$7)+DCF!$N$9*(1+$B7)/(G$6-$B7)/(1+G$6)^DCF!$N$6+(DCF!$C$30-DCF!$C$31+DCF!$C$32))/DCF!$C$34 -> 704.16055 | H7: =(SUMPRODUCT(DCF!$E$11:$N$11,1/(1+H$6)^DCF!$E$7:$N$7)+DCF!$N$9*(1+$B7)/(H$6-$B7)/(1+H$6)^DCF!$N$6+(DCF!$C$30-DCF!$C$31+DCF!$C$32))/DCF!$C$34 -> 663.54553 | I7: =(SUMPRODUCT(DCF!$E$11:$N$11,1/(1+I$6)^DCF!$E$7:$N$7)+DCF!$N$9*(1+$B7)/(I$6-$B7)/(1+I$6)^DCF!$N$6+(DCF!$C$30-DCF!$C$31+DCF!$C$32))/DCF!$C$34 -> 627.56884 | J7: =(SUMPRODUCT(DCF!$E$11:$N$11,1/(1+J$6)^DCF!$E$7:$N$7)+DCF!$N$9*(1+$B7)/(J$6-$B7)/(1+J$6)^DCF!$N$6+(DCF!$C$30-DCF!$C$31+DCF!$C$32))/DCF!$C$34 -> 595.48497 | K7: =(SUMPRODUCT(DCF!$E$11:$N$11,1/(1+K$6)^DCF!$E$7:$N$7)+DCF!$N$9*(1+$B7)/(K$6-$B7)/(1+K$6)^DCF!$N$6+(DCF!$C$30-DCF!$C$31+DCF!$C$32))/DCF!$C$34 -> 566.69956 | M7: Exit multiple step | N7: 2
B8: =$B$11+(-3)*$N$6 -> 0.0175 | C8: =(SUMPRODUCT(DCF!$E$11:$N$11,1/(1+C$6)^DCF!$E$7:$N$7)+DCF!$N$9*(1+$B8)/(C$6-$B8)/(1+C$6)^DCF!$N$6+(DCF!$C$30-DCF!$C$31+DCF!$C$32))/DCF!$C$34 -> 962.8275 | D8: =(SUMPRODUCT(DCF!$E$11:$N$11,1/(1+D$6)^DCF!$E$7:$N$7)+DCF!$N$9*(1+$B8)/(D$6-$B8)/(1+D$6)^DCF!$N$6+(DCF!$C$30-DCF!$C$31+DCF!$C$32))/DCF!$C$34 -> 886.00046 | E8: =(SUMPRODUCT(DCF!$E$11:$N$11,1/(1+E$6)^DCF!$E$7:$N$7)+DCF!$N$9*(1+$B8)/(E$6-$B8)/(1+E$6)^DCF!$N$6+(DCF!$C$30-DCF!$C$31+DCF!$C$32))/DCF!$C$34 -> 820.86792 | F8: =(SUMPRODUCT(DCF!$E$11:$N$11,1/(1+F$6)^DCF!$E$7:$N$7)+DCF!$N$9*(1+$B8)/(F$6-$B8)/(1+F$6)^DCF!$N$6+(DCF!$C$30-DCF!$C$31+DCF!$C$32))/DCF!$C$34 -> 764.96288 | G8: =(SUMPRODUCT(DCF!$E$11:$N$11,1/(1+G$6)^DCF!$E$7:$N$7)+DCF!$N$9*(1+$B8)/(G$6-$B8)/(1+G$6)^DCF!$N$6+(DCF!$C$30-DCF!$C$31+DCF!$C$32))/DCF!$C$34 -> 716.46553 | H8: =(SUMPRODUCT(DCF!$E$11:$N$11,1/(1+H$6)^DCF!$E$7:$N$7)+DCF!$N$9*(1+$B8)/(H$6-$B8)/(1+H$6)^DCF!$N$6+(DCF!$C$30-DCF!$C$31+DCF!$C$32))/DCF!$C$34 -> 674.00419 | I8: =(SUMPRODUCT(DCF!$E$11:$N$11,1/(1+I$6)^DCF!$E$7:$N$7)+DCF!$N$9*(1+$B8)/(I$6-$B8)/(1+I$6)^DCF!$N$6+(DCF!$C$30-DCF!$C$31+DCF!$C$32))/DCF!$C$34 -> 636.52541 | J8: =(SUMPRODUCT(DCF!$E$11:$N$11,1/(1+J$6)^DCF!$E$7:$N$7)+DCF!$N$9*(1+$B8)/(J$6-$B8)/(1+J$6)^DCF!$N$6+(DCF!$C$30-DCF!$C$31+DCF!$C$32))/DCF!$C$34 -> 603.20681 | K8: =(SUMPRODUCT(DCF!$E$11:$N$11,1/(1+K$6)^DCF!$E$7:$N$7)+DCF!$N$9*(1+$B8)/(K$6-$B8)/(1+K$6)^DCF!$N$6+(DCF!$C$30-DCF!$C$31+DCF!$C$32))/DCF!$C$34 -> 573.39708
B9: =$B$11+(-2)*$N$6 -> 0.02 | C9: =(SUMPRODUCT(DCF!$E$11:$N$11,1/(1+C$6)^DCF!$E$7:$N$7)+DCF!$N$9*(1+$B9)/(C$6-$B9)/(1+C$6)^DCF!$N$6+(DCF!$C$30-DCF!$C$31+DCF!$C$32))/DCF!$C$34 -> 991.2667 | D9: =(SUMPRODUCT(DCF!$E$11:$N$11,1/(1+D$6)^DCF!$E$7:$N$7)+DCF!$N$9*(1+$B9)/(D$6-$B9)/(1+D$6)^DCF!$N$6+(DCF!$C$30-DCF!$C$31+DCF!$C$32))/DCF!$C$34 -> 909.00075 | E9: =(SUMPRODUCT(DCF!$E$11:$N$11,1/(1+E$6)^DCF!$E$7:$N$7)+DCF!$N$9*(1+$B9)/(E$6-$B9)/(1+E$6)^DCF!$N$6+(DCF!$C$30-DCF!$C$31+DCF!$C$32))/DCF!$C$34 -> 839.73396 | F9: =(SUMPRODUCT(DCF!$E$11:$N$11,1/(1+F$6)^DCF!$E$7:$N$7)+DCF!$N$9*(1+$B9)/(F$6-$B9)/(1+F$6)^DCF!$N$6+(DCF!$C$30-DCF!$C$31+DCF!$C$32))/DCF!$C$34 -> 780.62535 | G9: =(SUMPRODUCT(DCF!$E$11:$N$11,1/(1+G$6)^DCF!$E$7:$N$7)+DCF!$N$9*(1+$B9)/(G$6-$B9)/(1+G$6)^DCF!$N$6+(DCF!$C$30-DCF!$C$31+DCF!$C$32))/DCF!$C$34 -> 729.60442 | H9: =(SUMPRODUCT(DCF!$E$11:$N$11,1/(1+H$6)^DCF!$E$7:$N$7)+DCF!$N$9*(1+$B9)/(H$6-$B9)/(1+H$6)^DCF!$N$6+(DCF!$C$30-DCF!$C$31+DCF!$C$32))/DCF!$C$34 -> 685.12664 | I9: =(SUMPRODUCT(DCF!$E$11:$N$11,1/(1+I$6)^DCF!$E$7:$N$7)+DCF!$N$9*(1+$B9)/(I$6-$B9)/(1+I$6)^DCF!$N$6+(DCF!$C$30-DCF!$C$31+DCF!$C$32))/DCF!$C$34 -> 646.0165 | J9: =(SUMPRODUCT(DCF!$E$11:$N$11,1/(1+J$6)^DCF!$E$7:$N$7)+DCF!$N$9*(1+$B9)/(J$6-$B9)/(1+J$6)^DCF!$N$6+(DCF!$C$30-DCF!$C$31+DCF!$C$32))/DCF!$C$34 -> 611.36353 | K9: =(SUMPRODUCT(DCF!$E$11:$N$11,1/(1+K$6)^DCF!$E$7:$N$7)+DCF!$N$9*(1+$B9)/(K$6-$B9)/(1+K$6)^DCF!$N$6+(DCF!$C$30-DCF!$C$31+DCF!$C$32))/DCF!$C$34 -> 580.45168
B10: =$B$11+(-1)*$N$6 -> 0.0225 | C10: =(SUMPRODUCT(DCF!$E$11:$N$11,1/(1+C$6)^DCF!$E$7:$N$7)+DCF!$N$9*(1+$B10)/(C$6-$B10)/(1+C$6)^DCF!$N$6+(DCF!$C$30-DCF!$C$31+DCF!$C$32))/DCF!$C$34 -> 1022.4788 | D10: =(SUMPRODUCT(DCF!$E$11:$N$11,1/(1+D$6)^DCF!$E$7:$N$7)+DCF!$N$9*(1+$B10)/(D$6-$B10)/(1+D$6)^DCF!$N$6+(DCF!$C$30-DCF!$C$31+DCF!$C$32))/DCF!$C$34 -> 934.04442 | E10: =(SUMPRODUCT(DCF!$E$11:$N$11,1/(1+E$6)^DCF!$E$7:$N$7)+DCF!$N$9*(1+$B10)/(E$6-$B10)/(1+E$6)^DCF!$N$6+(DCF!$C$30-DCF!$C$31+DCF!$C$32))/DCF!$C$34 -> 860.13934 | F10: =(SUMPRODUCT(DCF!$E$11:$N$11,1/(1+F$6)^DCF!$E$7:$N$7)+DCF!$N$9*(1+$B10)/(F$6-$B10)/(1+F$6)^DCF!$N$6+(DCF!$C$30-DCF!$C$31+DCF!$C$32))/DCF!$C$34 -> 797.46936 | G10: =(SUMPRODUCT(DCF!$E$11:$N$11,1/(1+G$6)^DCF!$E$7:$N$7)+DCF!$N$9*(1+$B10)/(G$6-$B10)/(1+G$6)^DCF!$N$6+(DCF!$C$30-DCF!$C$31+DCF!$C$32))/DCF!$C$34 -> 743.66494 | H10: =(SUMPRODUCT(DCF!$E$11:$N$11,1/(1+H$6)^DCF!$E$7:$N$7)+DCF!$N$9*(1+$B10)/(H$6-$B10)/(1+H$6)^DCF!$N$6+(DCF!$C$30-DCF!$C$31+DCF!$C$32))/DCF!$C$34 -> 696.97815 | I10: =(SUMPRODUCT(DCF!$E$11:$N$11,1/(1+I$6)^DCF!$E$7:$N$7)+DCF!$N$9*(1+$B10)/(I$6-$B10)/(1+I$6)^DCF!$N$6+(DCF!$C$30-DCF!$C$31+DCF!$C$32))/DCF!$C$34 -> 656.09144 | J10: =(SUMPRODUCT(DCF!$E$11:$N$11,1/(1+J$6)^DCF!$E$7:$N$7)+DCF!$N$9*(1+$B10)/(J$6-$B10)/(1+J$6)^DCF!$N$6+(DCF!$C$30-DCF!$C$31+DCF!$C$32))/DCF!$C$34 -> 619.99295 | K10: =(SUMPRODUCT(DCF!$E$11:$N$11,1/(1+K$6)^DCF!$E$7:$N$7)+DCF!$N$9*(1+$B10)/(K$6-$B10)/(1+K$6)^DCF!$N$6+(DCF!$C$30-DCF!$C$31+DCF!$C$32))/DCF!$C$34 -> 587.89272
B11: =Assumptions!$E$137 -> 0.025 | C11: =(SUMPRODUCT(DCF!$E$11:$N$11,1/(1+C$6)^DCF!$E$7:$N$7)+DCF!$N$9*(1+$B11)/(C$6-$B11)/(1+C$6)^DCF!$N$6+(DCF!$C$30-DCF!$C$31+DCF!$C$32))/DCF!$C$34 -> 1056.8903 | D11: =(SUMPRODUCT(DCF!$E$11:$N$11,1/(1+D$6)^DCF!$E$7:$N$7)+DCF!$N$9*(1+$B11)/(D$6-$B11)/(1+D$6)^DCF!$N$6+(DCF!$C$30-DCF!$C$31+DCF!$C$32))/DCF!$C$34 -> 961.41645 | E11: =(SUMPRODUCT(DCF!$E$11:$N$11,1/(1+E$6)^DCF!$E$7:$N$7)+DCF!$N$9*(1+$B11)/(E$6-$B11)/(1+E$6)^DCF!$N$6+(DCF!$C$30-DCF!$C$31+DCF!$C$32))/DCF!$C$34 -> 882.28046 | F11: =(SUMPRODUCT(DCF!$E$11:$N$11,1/(1+F$6)^DCF!$E$7:$N$7)+DCF!$N$9*(1+$B11)/(F$6-$B11)/(1+F$6)^DCF!$N$6+(DCF!$C$30-DCF!$C$31+DCF!$C$32))/DCF!$C$34 -> 815.63385 | G11: =(SUMPRODUCT(DCF!$E$11:$N$11,1/(1+G$6)^DCF!$E$7:$N$7)+DCF!$N$9*(1+$B11)/(G$6-$B11)/(1+G$6)^DCF!$N$6+(DCF!$C$30-DCF!$C$31+DCF!$C$32))/DCF!$C$34 -> 758.7476 | H11: =(SUMPRODUCT(DCF!$E$11:$N$11,1/(1+H$6)^DCF!$E$7:$N$7)+DCF!$N$9*(1+$B11)/(H$6-$B11)/(1+H$6)^DCF!$N$6+(DCF!$C$30-DCF!$C$31+DCF!$C$32))/DCF!$C$34 -> 709.63282 | I11: =(SUMPRODUCT(DCF!$E$11:$N$11,1/(1+I$6)^DCF!$E$7:$N$7)+DCF!$N$9*(1+$B11)/(I$6-$B11)/(1+I$6)^DCF!$N$6+(DCF!$C$30-DCF!$C$31+DCF!$C$32))/DCF!$C$34 -> 666.80583 | J11: =(SUMPRODUCT(DCF!$E$11:$N$11,1/(1+J$6)^DCF!$E$7:$N$7)+DCF!$N$9*(1+$B11)/(J$6-$B11)/(1+J$6)^DCF!$N$6+(DCF!$C$30-DCF!$C$31+DCF!$C$32))/DCF!$C$34 -> 629.13737 | K11: =(SUMPRODUCT(DCF!$E$11:$N$11,1/(1+K$6)^DCF!$E$7:$N$7)+DCF!$N$9*(1+$B11)/(K$6-$B11)/(1+K$6)^DCF!$N$6+(DCF!$C$30-DCF!$C$31+DCF!$C$32))/DCF!$C$34 -> 595.75283
B12: =$B$11+(1)*$N$6 -> 0.0275 | C12: =(SUMPRODUCT(DCF!$E$11:$N$11,1/(1+C$6)^DCF!$E$7:$N$7)+DCF!$N$9*(1+$B12)/(C$6-$B12)/(1+C$6)^DCF!$N$6+(DCF!$C$30-DCF!$C$31+DCF!$C$32))/DCF!$C$34 -> 1095.0195 | D12: =(SUMPRODUCT(DCF!$E$11:$N$11,1/(1+D$6)^DCF!$E$7:$N$7)+DCF!$N$9*(1+$B12)/(D$6-$B12)/(1+D$6)^DCF!$N$6+(DCF!$C$30-DCF!$C$31+DCF!$C$32))/DCF!$C$34 -> 991.45737 | E12: =(SUMPRODUCT(DCF!$E$11:$N$11,1/(1+E$6)^DCF!$E$7:$N$7)+DCF!$N$9*(1+$B12)/(E$6-$B12)/(1+E$6)^DCF!$N$6+(DCF!$C$30-DCF!$C$31+DCF!$C$32))/DCF!$C$34 -> 906.38864 | F12: =(SUMPRODUCT(DCF!$E$11:$N$11,1/(1+F$6)^DCF!$E$7:$N$7)+DCF!$N$9*(1+$B12)/(F$6-$B12)/(1+F$6)^DCF!$N$6+(DCF!$C$30-DCF!$C$31+DCF!$C$32))/DCF!$C$34 -> 835.28043 | G12: =(SUMPRODUCT(DCF!$E$11:$N$11,1/(1+G$6)^DCF!$E$7:$N$7)+DCF!$N$9*(1+$B12)/(G$6-$B12)/(1+G$6)^DCF!$N$6+(DCF!$C$30-DCF!$C$31+DCF!$C$32))/DCF!$C$34 -> 774.96807 | H12: =(SUMPRODUCT(DCF!$E$11:$N$11,1/(1+H$6)^DCF!$E$7:$N$7)+DCF!$N$9*(1+$B12)/(H$6-$B12)/(1+H$6)^DCF!$N$6+(DCF!$C$30-DCF!$C$31+DCF!$C$32))/DCF!$C$34 -> 723.17517 | I12: =(SUMPRODUCT(DCF!$E$11:$N$11,1/(1+I$6)^DCF!$E$7:$N$7)+DCF!$N$9*(1+$B12)/(I$6-$B12)/(1+I$6)^DCF!$N$6+(DCF!$C$30-DCF!$C$31+DCF!$C$32))/DCF!$C$34 -> 678.22252 | J12: =(SUMPRODUCT(DCF!$E$11:$N$11,1/(1+J$6)^DCF!$E$7:$N$7)+DCF!$N$9*(1+$B12)/(J$6-$B12)/(1+J$6)^DCF!$N$6+(DCF!$C$30-DCF!$C$31+DCF!$C$32))/DCF!$C$34 -> 638.84432 | K12: =(SUMPRODUCT(DCF!$E$11:$N$11,1/(1+K$6)^DCF!$E$7:$N$7)+DCF!$N$9*(1+$B12)/(K$6-$B12)/(1+K$6)^DCF!$N$6+(DCF!$C$30-DCF!$C$31+DCF!$C$32))/DCF!$C$34 -> 604.06844
B13: =$B$11+(2)*$N$6 -> 0.03 | C13: =(SUMPRODUCT(DCF!$E$11:$N$11,1/(1+C$6)^DCF!$E$7:$N$7)+DCF!$N$9*(1+$B13)/(C$6-$B13)/(1+C$6)^DCF!$N$6+(DCF!$C$30-DCF!$C$31+DCF!$C$32))/DCF!$C$34 -> 1137.5033 | D13: =(SUMPRODUCT(DCF!$E$11:$N$11,1/(1+D$6)^DCF!$E$7:$N$7)+DCF!$N$9*(1+$B13)/(D$6-$B13)/(1+D$6)^DCF!$N$6+(DCF!$C$30-DCF!$C$31+DCF!$C$32))/DCF!$C$34 -> 1024.5775 | E13: =(SUMPRODUCT(DCF!$E$11:$N$11,1/(1+E$6)^DCF!$E$7:$N$7)+DCF!$N$9*(1+$B13)/(E$6-$B13)/(1+E$6)^DCF!$N$6+(DCF!$C$30-DCF!$C$31+DCF!$C$32))/DCF!$C$34 -> 932.7382 | F13: =(SUMPRODUCT(DCF!$E$11:$N$11,1/(1+F$6)^DCF!$E$7:$N$7)+DCF!$N$9*(1+$B13)/(F$6-$B13)/(1+F$6)^DCF!$N$6+(DCF!$C$30-DCF!$C$31+DCF!$C$32))/DCF!$C$34 -> 856.59822 | G13: =(SUMPRODUCT(DCF!$E$11:$N$11,1/(1+G$6)^DCF!$E$7:$N$7)+DCF!$N$9*(1+$B13)/(G$6-$B13)/(1+G$6)^DCF!$N$6+(DCF!$C$30-DCF!$C$31+DCF!$C$32))/DCF!$C$34 -> 792.46013 | H13: =(SUMPRODUCT(DCF!$E$11:$N$11,1/(1+H$6)^DCF!$E$7:$N$7)+DCF!$N$9*(1+$B13)/(H$6-$B13)/(1+H$6)^DCF!$N$6+(DCF!$C$30-DCF!$C$31+DCF!$C$32))/DCF!$C$34 -> 737.702 | I13: =(SUMPRODUCT(DCF!$E$11:$N$11,1/(1+I$6)^DCF!$E$7:$N$7)+DCF!$N$9*(1+$B13)/(I$6-$B13)/(1+I$6)^DCF!$N$6+(DCF!$C$30-DCF!$C$31+DCF!$C$32))/DCF!$C$34 -> 690.41291 | J13: =(SUMPRODUCT(DCF!$E$11:$N$11,1/(1+J$6)^DCF!$E$7:$N$7)+DCF!$N$9*(1+$B13)/(J$6-$B13)/(1+J$6)^DCF!$N$6+(DCF!$C$30-DCF!$C$31+DCF!$C$32))/DCF!$C$34 -> 649.16735 | K13: =(SUMPRODUCT(DCF!$E$11:$N$11,1/(1+K$6)^DCF!$E$7:$N$7)+DCF!$N$9*(1+$B13)/(K$6-$B13)/(1+K$6)^DCF!$N$6+(DCF!$C$30-DCF!$C$31+DCF!$C$32))/DCF!$C$34 -> 612.88032
B14: =$B$11+(3)*$N$6 -> 0.0325 | C14: =(SUMPRODUCT(DCF!$E$11:$N$11,1/(1+C$6)^DCF!$E$7:$N$7)+DCF!$N$9*(1+$B14)/(C$6-$B14)/(1+C$6)^DCF!$N$6+(DCF!$C$30-DCF!$C$31+DCF!$C$32))/DCF!$C$34 -> 1185.133 | D14: =(SUMPRODUCT(DCF!$E$11:$N$11,1/(1+D$6)^DCF!$E$7:$N$7)+DCF!$N$9*(1+$B14)/(D$6-$B14)/(1+D$6)^DCF!$N$6+(DCF!$C$30-DCF!$C$31+DCF!$C$32))/DCF!$C$34 -> 1061.2759 | E14: =(SUMPRODUCT(DCF!$E$11:$N$11,1/(1+E$6)^DCF!$E$7:$N$7)+DCF!$N$9*(1+$B14)/(E$6-$B14)/(1+E$6)^DCF!$N$6+(DCF!$C$30-DCF!$C$31+DCF!$C$32))/DCF!$C$34 -> 961.65695 | F14: =(SUMPRODUCT(DCF!$E$11:$N$11,1/(1+F$6)^DCF!$E$7:$N$7)+DCF!$N$9*(1+$B14)/(F$6-$B14)/(1+F$6)^DCF!$N$6+(DCF!$C$30-DCF!$C$31+DCF!$C$32))/DCF!$C$34 -> 879.80991 | G14: =(SUMPRODUCT(DCF!$E$11:$N$11,1/(1+G$6)^DCF!$E$7:$N$7)+DCF!$N$9*(1+$B14)/(G$6-$B14)/(1+G$6)^DCF!$N$6+(DCF!$C$30-DCF!$C$31+DCF!$C$32))/DCF!$C$34 -> 811.37943 | H14: =(SUMPRODUCT(DCF!$E$11:$N$11,1/(1+H$6)^DCF!$E$7:$N$7)+DCF!$N$9*(1+$B14)/(H$6-$B14)/(1+H$6)^DCF!$N$6+(DCF!$C$30-DCF!$C$31+DCF!$C$32))/DCF!$C$34 -> 753.32469 | I14: =(SUMPRODUCT(DCF!$E$11:$N$11,1/(1+I$6)^DCF!$E$7:$N$7)+DCF!$N$9*(1+$B14)/(I$6-$B14)/(1+I$6)^DCF!$N$6+(DCF!$C$30-DCF!$C$31+DCF!$C$32))/DCF!$C$34 -> 703.4584 | J14: =(SUMPRODUCT(DCF!$E$11:$N$11,1/(1+J$6)^DCF!$E$7:$N$7)+DCF!$N$9*(1+$B14)/(J$6-$B14)/(1+J$6)^DCF!$N$6+(DCF!$C$30-DCF!$C$31+DCF!$C$32))/DCF!$C$34 -> 660.16703 | K14: =(SUMPRODUCT(DCF!$E$11:$N$11,1/(1+K$6)^DCF!$E$7:$N$7)+DCF!$N$9*(1+$B14)/(K$6-$B14)/(1+K$6)^DCF!$N$6+(DCF!$C$30-DCF!$C$31+DCF!$C$32))/DCF!$C$34 -> 622.23428
B15: =$B$11+(4)*$N$6 -> 0.035 | C15: =(SUMPRODUCT(DCF!$E$11:$N$11,1/(1+C$6)^DCF!$E$7:$N$7)+DCF!$N$9*(1+$B15)/(C$6-$B15)/(1+C$6)^DCF!$N$6+(DCF!$C$30-DCF!$C$31+DCF!$C$32))/DCF!$C$34 -> 1238.9037 | D15: =(SUMPRODUCT(DCF!$E$11:$N$11,1/(1+D$6)^DCF!$E$7:$N$7)+DCF!$N$9*(1+$B15)/(D$6-$B15)/(1+D$6)^DCF!$N$6+(DCF!$C$30-DCF!$C$31+DCF!$C$32))/DCF!$C$34 -> 1102.1656 | E15: =(SUMPRODUCT(DCF!$E$11:$N$11,1/(1+E$6)^DCF!$E$7:$N$7)+DCF!$N$9*(1+$B15)/(E$6-$B15)/(1+E$6)^DCF!$N$6+(DCF!$C$30-DCF!$C$31+DCF!$C$32))/DCF!$C$34 -> 993.53991 | F15: =(SUMPRODUCT(DCF!$E$11:$N$11,1/(1+F$6)^DCF!$E$7:$N$7)+DCF!$N$9*(1+$B15)/(F$6-$B15)/(1+F$6)^DCF!$N$6+(DCF!$C$30-DCF!$C$31+DCF!$C$32))/DCF!$C$34 -> 905.17964 | G15: =(SUMPRODUCT(DCF!$E$11:$N$11,1/(1+G$6)^DCF!$E$7:$N$7)+DCF!$N$9*(1+$B15)/(G$6-$B15)/(1+G$6)^DCF!$N$6+(DCF!$C$30-DCF!$C$31+DCF!$C$32))/DCF!$C$34 -> 831.90805 | H15: =(SUMPRODUCT(DCF!$E$11:$N$11,1/(1+H$6)^DCF!$E$7:$N$7)+DCF!$N$9*(1+$B15)/(H$6-$B15)/(1+H$6)^DCF!$N$6+(DCF!$C$30-DCF!$C$31+DCF!$C$32))/DCF!$C$34 -> 770.17212 | I15: =(SUMPRODUCT(DCF!$E$11:$N$11,1/(1+I$6)^DCF!$E$7:$N$7)+DCF!$N$9*(1+$B15)/(I$6-$B15)/(1+I$6)^DCF!$N$6+(DCF!$C$30-DCF!$C$31+DCF!$C$32))/DCF!$C$34 -> 717.45226 | J15: =(SUMPRODUCT(DCF!$E$11:$N$11,1/(1+J$6)^DCF!$E$7:$N$7)+DCF!$N$9*(1+$B15)/(J$6-$B15)/(1+J$6)^DCF!$N$6+(DCF!$C$30-DCF!$C$31+DCF!$C$32))/DCF!$C$34 -> 671.91215 | K15: =(SUMPRODUCT(DCF!$E$11:$N$11,1/(1+K$6)^DCF!$E$7:$N$7)+DCF!$N$9*(1+$B15)/(K$6-$B15)/(1+K$6)^DCF!$N$6+(DCF!$C$30-DCF!$C$31+DCF!$C$32))/DCF!$C$34 -> 632.18191
B17: Table 2: WACC vs exit EV/EBITDA multiple (Exit Multiple method)
C18: WACC →
B19: Multiple ↓ / WACC → | C19: =$G$19+(-4)*$N$5 -> 0.073779813 | D19: =$G$19+(-3)*$N$5 -> 0.078779813 | E19: =$G$19+(-2)*$N$5 -> 0.083779813 | F19: =$G$19+(-1)*$N$5 -> 0.088779813 | G19: =WACC!$C$35 -> 0.093779813 | H19: =$G$19+(1)*$N$5 -> 0.098779813 | I19: =$G$19+(2)*$N$5 -> 0.10377981 | J19: =$G$19+(3)*$N$5 -> 0.10877981 | K19: =$G$19+(4)*$N$5 -> 0.11377981
B20: =$B$24+(-4)*$N$7 -> 12 | C20: =(SUMPRODUCT(DCF!$E$11:$N$11,1/(1+C$19)^DCF!$E$7:$N$7)+Forecast!$Q$14*$B20/(1+C$19)^DCF!$N$6+(DCF!$C$30-DCF!$C$31+DCF!$C$32))/DCF!$C$34 -> 921.04619 | D20: =(SUMPRODUCT(DCF!$E$11:$N$11,1/(1+D$19)^DCF!$E$7:$N$7)+Forecast!$Q$14*$B20/(1+D$19)^DCF!$N$6+(DCF!$C$30-DCF!$C$31+DCF!$C$32))/DCF!$C$34 -> 891.28821 | E20: =(SUMPRODUCT(DCF!$E$11:$N$11,1/(1+E$19)^DCF!$E$7:$N$7)+Forecast!$Q$14*$B20/(1+E$19)^DCF!$N$6+(DCF!$C$30-DCF!$C$31+DCF!$C$32))/DCF!$C$34 -> 862.80439 | F20: =(SUMPRODUCT(DCF!$E$11:$N$11,1/(1+F$19)^DCF!$E$7:$N$7)+Forecast!$Q$14*$B20/(1+F$19)^DCF!$N$6+(DCF!$C$30-DCF!$C$31+DCF!$C$32))/DCF!$C$34 -> 835.53284 | G20: =(SUMPRODUCT(DCF!$E$11:$N$11,1/(1+G$19)^DCF!$E$7:$N$7)+Forecast!$Q$14*$B20/(1+G$19)^DCF!$N$6+(DCF!$C$30-DCF!$C$31+DCF!$C$32))/DCF!$C$34 -> 809.41496 | H20: =(SUMPRODUCT(DCF!$E$11:$N$11,1/(1+H$19)^DCF!$E$7:$N$7)+Forecast!$Q$14*$B20/(1+H$19)^DCF!$N$6+(DCF!$C$30-DCF!$C$31+DCF!$C$32))/DCF!$C$34 -> 784.39528 | I20: =(SUMPRODUCT(DCF!$E$11:$N$11,1/(1+I$19)^DCF!$E$7:$N$7)+Forecast!$Q$14*$B20/(1+I$19)^DCF!$N$6+(DCF!$C$30-DCF!$C$31+DCF!$C$32))/DCF!$C$34 -> 760.42128 | J20: =(SUMPRODUCT(DCF!$E$11:$N$11,1/(1+J$19)^DCF!$E$7:$N$7)+Forecast!$Q$14*$B20/(1+J$19)^DCF!$N$6+(DCF!$C$30-DCF!$C$31+DCF!$C$32))/DCF!$C$34 -> 737.44319 | K20: =(SUMPRODUCT(DCF!$E$11:$N$11,1/(1+K$19)^DCF!$E$7:$N$7)+Forecast!$Q$14*$B20/(1+K$19)^DCF!$N$6+(DCF!$C$30-DCF!$C$31+DCF!$C$32))/DCF!$C$34 -> 715.41386
B21: =$B$24+(-3)*$N$7 -> 14 | C21: =(SUMPRODUCT(DCF!$E$11:$N$11,1/(1+C$19)^DCF!$E$7:$N$7)+Forecast!$Q$14*$B21/(1+C$19)^DCF!$N$6+(DCF!$C$30-DCF!$C$31+DCF!$C$32))/DCF!$C$34 -> 1010.7021 | D21: =(SUMPRODUCT(DCF!$E$11:$N$11,1/(1+D$19)^DCF!$E$7:$N$7)+Forecast!$Q$14*$B21/(1+D$19)^DCF!$N$6+(DCF!$C$30-DCF!$C$31+DCF!$C$32))/DCF!$C$34 -> 977.17985 | E21: =(SUMPRODUCT(DCF!$E$11:$N$11,1/(1+E$19)^DCF!$E$7:$N$7)+Forecast!$Q$14*$B21/(1+E$19)^DCF!$N$6+(DCF!$C$30-DCF!$C$31+DCF!$C$32))/DCF!$C$34 -> 945.10613 | F21: =(SUMPRODUCT(DCF!$E$11:$N$11,1/(1+F$19)^DCF!$E$7:$N$7)+Forecast!$Q$14*$B21/(1+F$19)^DCF!$N$6+(DCF!$C$30-DCF!$C$31+DCF!$C$32))/DCF!$C$34 -> 914.41022 | G21: =(SUMPRODUCT(DCF!$E$11:$N$11,1/(1+G$19)^DCF!$E$7:$N$7)+Forecast!$Q$14*$B21/(1+G$19)^DCF!$N$6+(DCF!$C$30-DCF!$C$31+DCF!$C$32))/DCF!$C$34 -> 885.02518 | H21: =(SUMPRODUCT(DCF!$E$11:$N$11,1/(1+H$19)^DCF!$E$7:$N$7)+Forecast!$Q$14*$B21/(1+H$19)^DCF!$N$6+(DCF!$C$30-DCF!$C$31+DCF!$C$32))/DCF!$C$34 -> 856.88765 | I21: =(SUMPRODUCT(DCF!$E$11:$N$11,1/(1+I$19)^DCF!$E$7:$N$7)+Forecast!$Q$14*$B21/(1+I$19)^DCF!$N$6+(DCF!$C$30-DCF!$C$31+DCF!$C$32))/DCF!$C$34 -> 829.93766 | J21: =(SUMPRODUCT(DCF!$E$11:$N$11,1/(1+J$19)^DCF!$E$7:$N$7)+Forecast!$Q$14*$B21/(1+J$19)^DCF!$N$6+(DCF!$C$30-DCF!$C$31+DCF!$C$32))/DCF!$C$34 -> 804.11838 | K21: =(SUMPRODUCT(DCF!$E$11:$N$11,1/(1+K$19)^DCF!$E$7:$N$7)+Forecast!$Q$14*$B21/(1+K$19)^DCF!$N$6+(DCF!$C$30-DCF!$C$31+DCF!$C$32))/DCF!$C$34 -> 779.376
B22: =$B$24+(-2)*$N$7 -> 16 | C22: =(SUMPRODUCT(DCF!$E$11:$N$11,1/(1+C$19)^DCF!$E$7:$N$7)+Forecast!$Q$14*$B22/(1+C$19)^DCF!$N$6+(DCF!$C$30-DCF!$C$31+DCF!$C$32))/DCF!$C$34 -> 1100.358 | D22: =(SUMPRODUCT(DCF!$E$11:$N$11,1/(1+D$19)^DCF!$E$7:$N$7)+Forecast!$Q$14*$B22/(1+D$19)^DCF!$N$6+(DCF!$C$30-DCF!$C$31+DCF!$C$32))/DCF!$C$34 -> 1063.0715 | E22: =(SUMPRODUCT(DCF!$E$11:$N$11,1/(1+E$19)^DCF!$E$7:$N$7)+Forecast!$Q$14*$B22/(1+E$19)^DCF!$N$6+(DCF!$C$30-DCF!$C$31+DCF!$C$32))/DCF!$C$34 -> 1027.4079 | F22: =(SUMPRODUCT(DCF!$E$11:$N$11,1/(1+F$19)^DCF!$E$7:$N$7)+Forecast!$Q$14*$B22/(1+F$19)^DCF!$N$6+(DCF!$C$30-DCF!$C$31+DCF!$C$32))/DCF!$C$34 -> 993.2876 | G22: =(SUMPRODUCT(DCF!$E$11:$N$11,1/(1+G$19)^DCF!$E$7:$N$7)+Forecast!$Q$14*$B22/(1+G$19)^DCF!$N$6+(DCF!$C$30-DCF!$C$31+DCF!$C$32))/DCF!$C$34 -> 960.63539 | H22: =(SUMPRODUCT(DCF!$E$11:$N$11,1/(1+H$19)^DCF!$E$7:$N$7)+Forecast!$Q$14*$B22/(1+H$19)^DCF!$N$6+(DCF!$C$30-DCF!$C$31+DCF!$C$32))/DCF!$C$34 -> 929.38002 | I22: =(SUMPRODUCT(DCF!$E$11:$N$11,1/(1+I$19)^DCF!$E$7:$N$7)+Forecast!$Q$14*$B22/(1+I$19)^DCF!$N$6+(DCF!$C$30-DCF!$C$31+DCF!$C$32))/DCF!$C$34 -> 899.45404 | J22: =(SUMPRODUCT(DCF!$E$11:$N$11,1/(1+J$19)^DCF!$E$7:$N$7)+Forecast!$Q$14*$B22/(1+J$19)^DCF!$N$6+(DCF!$C$30-DCF!$C$31+DCF!$C$32))/DCF!$C$34 -> 870.79357 | K22: =(SUMPRODUCT(DCF!$E$11:$N$11,1/(1+K$19)^DCF!$E$7:$N$7)+Forecast!$Q$14*$B22/(1+K$19)^DCF!$N$6+(DCF!$C$30-DCF!$C$31+DCF!$C$32))/DCF!$C$34 -> 843.33813
B23: =$B$24+(-1)*$N$7 -> 18 | C23: =(SUMPRODUCT(DCF!$E$11:$N$11,1/(1+C$19)^DCF!$E$7:$N$7)+Forecast!$Q$14*$B23/(1+C$19)^DCF!$N$6+(DCF!$C$30-DCF!$C$31+DCF!$C$32))/DCF!$C$34 -> 1190.0139 | D23: =(SUMPRODUCT(DCF!$E$11:$N$11,1/(1+D$19)^DCF!$E$7:$N$7)+Forecast!$Q$14*$B23/(1+D$19)^DCF!$N$6+(DCF!$C$30-DCF!$C$31+DCF!$C$32))/DCF!$C$34 -> 1148.9631 | E23: =(SUMPRODUCT(DCF!$E$11:$N$11,1/(1+E$19)^DCF!$E$7:$N$7)+Forecast!$Q$14*$B23/(1+E$19)^DCF!$N$6+(DCF!$C$30-DCF!$C$31+DCF!$C$32))/DCF!$C$34 -> 1109.7096 | F23: =(SUMPRODUCT(DCF!$E$11:$N$11,1/(1+F$19)^DCF!$E$7:$N$7)+Forecast!$Q$14*$B23/(1+F$19)^DCF!$N$6+(DCF!$C$30-DCF!$C$31+DCF!$C$32))/DCF!$C$34 -> 1072.165 | G23: =(SUMPRODUCT(DCF!$E$11:$N$11,1/(1+G$19)^DCF!$E$7:$N$7)+Forecast!$Q$14*$B23/(1+G$19)^DCF!$N$6+(DCF!$C$30-DCF!$C$31+DCF!$C$32))/DCF!$C$34 -> 1036.2456 | H23: =(SUMPRODUCT(DCF!$E$11:$N$11,1/(1+H$19)^DCF!$E$7:$N$7)+Forecast!$Q$14*$B23/(1+H$19)^DCF!$N$6+(DCF!$C$30-DCF!$C$31+DCF!$C$32))/DCF!$C$34 -> 1001.8724 | I23: =(SUMPRODUCT(DCF!$E$11:$N$11,1/(1+I$19)^DCF!$E$7:$N$7)+Forecast!$Q$14*$B23/(1+I$19)^DCF!$N$6+(DCF!$C$30-DCF!$C$31+DCF!$C$32))/DCF!$C$34 -> 968.97042 | J23: =(SUMPRODUCT(DCF!$E$11:$N$11,1/(1+J$19)^DCF!$E$7:$N$7)+Forecast!$Q$14*$B23/(1+J$19)^DCF!$N$6+(DCF!$C$30-DCF!$C$31+DCF!$C$32))/DCF!$C$34 -> 937.46876 | K23: =(SUMPRODUCT(DCF!$E$11:$N$11,1/(1+K$19)^DCF!$E$7:$N$7)+Forecast!$Q$14*$B23/(1+K$19)^DCF!$N$6+(DCF!$C$30-DCF!$C$31+DCF!$C$32))/DCF!$C$34 -> 907.30026
B24: =Assumptions!$E$142 -> 20 | C24: =(SUMPRODUCT(DCF!$E$11:$N$11,1/(1+C$19)^DCF!$E$7:$N$7)+Forecast!$Q$14*$B24/(1+C$19)^DCF!$N$6+(DCF!$C$30-DCF!$C$31+DCF!$C$32))/DCF!$C$34 -> 1279.6698 | D24: =(SUMPRODUCT(DCF!$E$11:$N$11,1/(1+D$19)^DCF!$E$7:$N$7)+Forecast!$Q$14*$B24/(1+D$19)^DCF!$N$6+(DCF!$C$30-DCF!$C$31+DCF!$C$32))/DCF!$C$34 -> 1234.8548 | E24: =(SUMPRODUCT(DCF!$E$11:$N$11,1/(1+E$19)^DCF!$E$7:$N$7)+Forecast!$Q$14*$B24/(1+E$19)^DCF!$N$6+(DCF!$C$30-DCF!$C$31+DCF!$C$32))/DCF!$C$34 -> 1192.0114 | F24: =(SUMPRODUCT(DCF!$E$11:$N$11,1/(1+F$19)^DCF!$E$7:$N$7)+Forecast!$Q$14*$B24/(1+F$19)^DCF!$N$6+(DCF!$C$30-DCF!$C$31+DCF!$C$32))/DCF!$C$34 -> 1151.0424 | G24: =(SUMPRODUCT(DCF!$E$11:$N$11,1/(1+G$19)^DCF!$E$7:$N$7)+Forecast!$Q$14*$B24/(1+G$19)^DCF!$N$6+(DCF!$C$30-DCF!$C$31+DCF!$C$32))/DCF!$C$34 -> 1111.8558 | H24: =(SUMPRODUCT(DCF!$E$11:$N$11,1/(1+H$19)^DCF!$E$7:$N$7)+Forecast!$Q$14*$B24/(1+H$19)^DCF!$N$6+(DCF!$C$30-DCF!$C$31+DCF!$C$32))/DCF!$C$34 -> 1074.3648 | I24: =(SUMPRODUCT(DCF!$E$11:$N$11,1/(1+I$19)^DCF!$E$7:$N$7)+Forecast!$Q$14*$B24/(1+I$19)^DCF!$N$6+(DCF!$C$30-DCF!$C$31+DCF!$C$32))/DCF!$C$34 -> 1038.4868 | J24: =(SUMPRODUCT(DCF!$E$11:$N$11,1/(1+J$19)^DCF!$E$7:$N$7)+Forecast!$Q$14*$B24/(1+J$19)^DCF!$N$6+(DCF!$C$30-DCF!$C$31+DCF!$C$32))/DCF!$C$34 -> 1004.144 | K24: =(SUMPRODUCT(DCF!$E$11:$N$11,1/(1+K$19)^DCF!$E$7:$N$7)+Forecast!$Q$14*$B24/(1+K$19)^DCF!$N$6+(DCF!$C$30-DCF!$C$31+DCF!$C$32))/DCF!$C$34 -> 971.2624
B25: =$B$24+(1)*$N$7 -> 22 | C25: =(SUMPRODUCT(DCF!$E$11:$N$11,1/(1+C$19)^DCF!$E$7:$N$7)+Forecast!$Q$14*$B25/(1+C$19)^DCF!$N$6+(DCF!$C$30-DCF!$C$31+DCF!$C$32))/DCF!$C$34 -> 1369.3258 | D25: =(SUMPRODUCT(DCF!$E$11:$N$11,1/(1+D$19)^DCF!$E$7:$N$7)+Forecast!$Q$14*$B25/(1+D$19)^DCF!$N$6+(DCF!$C$30-DCF!$C$31+DCF!$C$32))/DCF!$C$34 -> 1320.7464 | E25: =(SUMPRODUCT(DCF!$E$11:$N$11,1/(1+E$19)^DCF!$E$7:$N$7)+Forecast!$Q$14*$B25/(1+E$19)^DCF!$N$6+(DCF!$C$30-DCF!$C$31+DCF!$C$32))/DCF!$C$34 -> 1274.3131 | F25: =(SUMPRODUCT(DCF!$E$11:$N$11,1/(1+F$19)^DCF!$E$7:$N$7)+Forecast!$Q$14*$B25/(1+F$19)^DCF!$N$6+(DCF!$C$30-DCF!$C$31+DCF!$C$32))/DCF!$C$34 -> 1229.9197 | G25: =(SUMPRODUCT(DCF!$E$11:$N$11,1/(1+G$19)^DCF!$E$7:$N$7)+Forecast!$Q$14*$B25/(1+G$19)^DCF!$N$6+(DCF!$C$30-DCF!$C$31+DCF!$C$32))/DCF!$C$34 -> 1187.4661 | H25: =(SUMPRODUCT(DCF!$E$11:$N$11,1/(1+H$19)^DCF!$E$7:$N$7)+Forecast!$Q$14*$B25/(1+H$19)^DCF!$N$6+(DCF!$C$30-DCF!$C$31+DCF!$C$32))/DCF!$C$34 -> 1146.8571 | I25: =(SUMPRODUCT(DCF!$E$11:$N$11,1/(1+I$19)^DCF!$E$7:$N$7)+Forecast!$Q$14*$B25/(1+I$19)^DCF!$N$6+(DCF!$C$30-DCF!$C$31+DCF!$C$32))/DCF!$C$34 -> 1108.0032 | J25: =(SUMPRODUCT(DCF!$E$11:$N$11,1/(1+J$19)^DCF!$E$7:$N$7)+Forecast!$Q$14*$B25/(1+J$19)^DCF!$N$6+(DCF!$C$30-DCF!$C$31+DCF!$C$32))/DCF!$C$34 -> 1070.8191 | K25: =(SUMPRODUCT(DCF!$E$11:$N$11,1/(1+K$19)^DCF!$E$7:$N$7)+Forecast!$Q$14*$B25/(1+K$19)^DCF!$N$6+(DCF!$C$30-DCF!$C$31+DCF!$C$32))/DCF!$C$34 -> 1035.2245
B26: =$B$24+(2)*$N$7 -> 24 | C26: =(SUMPRODUCT(DCF!$E$11:$N$11,1/(1+C$19)^DCF!$E$7:$N$7)+Forecast!$Q$14*$B26/(1+C$19)^DCF!$N$6+(DCF!$C$30-DCF!$C$31+DCF!$C$32))/DCF!$C$34 -> 1458.9817 | D26: =(SUMPRODUCT(DCF!$E$11:$N$11,1/(1+D$19)^DCF!$E$7:$N$7)+Forecast!$Q$14*$B26/(1+D$19)^DCF!$N$6+(DCF!$C$30-DCF!$C$31+DCF!$C$32))/DCF!$C$34 -> 1406.6381 | E26: =(SUMPRODUCT(DCF!$E$11:$N$11,1/(1+E$19)^DCF!$E$7:$N$7)+Forecast!$Q$14*$B26/(1+E$19)^DCF!$N$6+(DCF!$C$30-DCF!$C$31+DCF!$C$32))/DCF!$C$34 -> 1356.6148 | F26: =(SUMPRODUCT(DCF!$E$11:$N$11,1/(1+F$19)^DCF!$E$7:$N$7)+Forecast!$Q$14*$B26/(1+F$19)^DCF!$N$6+(DCF!$C$30-DCF!$C$31+DCF!$C$32))/DCF!$C$34 -> 1308.7971 | G26: =(SUMPRODUCT(DCF!$E$11:$N$11,1/(1+G$19)^DCF!$E$7:$N$7)+Forecast!$Q$14*$B26/(1+G$19)^DCF!$N$6+(DCF!$C$30-DCF!$C$31+DCF!$C$32))/DCF!$C$34 -> 1263.0763 | H26: =(SUMPRODUCT(DCF!$E$11:$N$11,1/(1+H$19)^DCF!$E$7:$N$7)+Forecast!$Q$14*$B26/(1+H$19)^DCF!$N$6+(DCF!$C$30-DCF!$C$31+DCF!$C$32))/DCF!$C$34 -> 1219.3495 | I26: =(SUMPRODUCT(DCF!$E$11:$N$11,1/(1+I$19)^DCF!$E$7:$N$7)+Forecast!$Q$14*$B26/(1+I$19)^DCF!$N$6+(DCF!$C$30-DCF!$C$31+DCF!$C$32))/DCF!$C$34 -> 1177.5196 | J26: =(SUMPRODUCT(DCF!$E$11:$N$11,1/(1+J$19)^DCF!$E$7:$N$7)+Forecast!$Q$14*$B26/(1+J$19)^DCF!$N$6+(DCF!$C$30-DCF!$C$31+DCF!$C$32))/DCF!$C$34 -> 1137.4943 | K26: =(SUMPRODUCT(DCF!$E$11:$N$11,1/(1+K$19)^DCF!$E$7:$N$7)+Forecast!$Q$14*$B26/(1+K$19)^DCF!$N$6+(DCF!$C$30-DCF!$C$31+DCF!$C$32))/DCF!$C$34 -> 1099.1867
B27: =$B$24+(3)*$N$7 -> 26 | C27: =(SUMPRODUCT(DCF!$E$11:$N$11,1/(1+C$19)^DCF!$E$7:$N$7)+Forecast!$Q$14*$B27/(1+C$19)^DCF!$N$6+(DCF!$C$30-DCF!$C$31+DCF!$C$32))/DCF!$C$34 -> 1548.6376 | D27: =(SUMPRODUCT(DCF!$E$11:$N$11,1/(1+D$19)^DCF!$E$7:$N$7)+Forecast!$Q$14*$B27/(1+D$19)^DCF!$N$6+(DCF!$C$30-DCF!$C$31+DCF!$C$32))/DCF!$C$34 -> 1492.5297 | E27: =(SUMPRODUCT(DCF!$E$11:$N$11,1/(1+E$19)^DCF!$E$7:$N$7)+Forecast!$Q$14*$B27/(1+E$19)^DCF!$N$6+(DCF!$C$30-DCF!$C$31+DCF!$C$32))/DCF!$C$34 -> 1438.9166 | F27: =(SUMPRODUCT(DCF!$E$11:$N$11,1/(1+F$19)^DCF!$E$7:$N$7)+Forecast!$Q$14*$B27/(1+F$19)^DCF!$N$6+(DCF!$C$30-DCF!$C$31+DCF!$C$32))/DCF!$C$34 -> 1387.6745 | G27: =(SUMPRODUCT(DCF!$E$11:$N$11,1/(1+G$19)^DCF!$E$7:$N$7)+Forecast!$Q$14*$B27/(1+G$19)^DCF!$N$6+(DCF!$C$30-DCF!$C$31+DCF!$C$32))/DCF!$C$34 -> 1338.6865 | H27: =(SUMPRODUCT(DCF!$E$11:$N$11,1/(1+H$19)^DCF!$E$7:$N$7)+Forecast!$Q$14*$B27/(1+H$19)^DCF!$N$6+(DCF!$C$30-DCF!$C$31+DCF!$C$32))/DCF!$C$34 -> 1291.8419 | I27: =(SUMPRODUCT(DCF!$E$11:$N$11,1/(1+I$19)^DCF!$E$7:$N$7)+Forecast!$Q$14*$B27/(1+I$19)^DCF!$N$6+(DCF!$C$30-DCF!$C$31+DCF!$C$32))/DCF!$C$34 -> 1247.0359 | J27: =(SUMPRODUCT(DCF!$E$11:$N$11,1/(1+J$19)^DCF!$E$7:$N$7)+Forecast!$Q$14*$B27/(1+J$19)^DCF!$N$6+(DCF!$C$30-DCF!$C$31+DCF!$C$32))/DCF!$C$34 -> 1204.1695 | K27: =(SUMPRODUCT(DCF!$E$11:$N$11,1/(1+K$19)^DCF!$E$7:$N$7)+Forecast!$Q$14*$B27/(1+K$19)^DCF!$N$6+(DCF!$C$30-DCF!$C$31+DCF!$C$32))/DCF!$C$34 -> 1163.1488
B28: =$B$24+(4)*$N$7 -> 28 | C28: =(SUMPRODUCT(DCF!$E$11:$N$11,1/(1+C$19)^DCF!$E$7:$N$7)+Forecast!$Q$14*$B28/(1+C$19)^DCF!$N$6+(DCF!$C$30-DCF!$C$31+DCF!$C$32))/DCF!$C$34 -> 1638.2935 | D28: =(SUMPRODUCT(DCF!$E$11:$N$11,1/(1+D$19)^DCF!$E$7:$N$7)+Forecast!$Q$14*$B28/(1+D$19)^DCF!$N$6+(DCF!$C$30-DCF!$C$31+DCF!$C$32))/DCF!$C$34 -> 1578.4214 | E28: =(SUMPRODUCT(DCF!$E$11:$N$11,1/(1+E$19)^DCF!$E$7:$N$7)+Forecast!$Q$14*$B28/(1+E$19)^DCF!$N$6+(DCF!$C$30-DCF!$C$31+DCF!$C$32))/DCF!$C$34 -> 1521.2183 | F28: =(SUMPRODUCT(DCF!$E$11:$N$11,1/(1+F$19)^DCF!$E$7:$N$7)+Forecast!$Q$14*$B28/(1+F$19)^DCF!$N$6+(DCF!$C$30-DCF!$C$31+DCF!$C$32))/DCF!$C$34 -> 1466.5519 | G28: =(SUMPRODUCT(DCF!$E$11:$N$11,1/(1+G$19)^DCF!$E$7:$N$7)+Forecast!$Q$14*$B28/(1+G$19)^DCF!$N$6+(DCF!$C$30-DCF!$C$31+DCF!$C$32))/DCF!$C$34 -> 1414.2967 | H28: =(SUMPRODUCT(DCF!$E$11:$N$11,1/(1+H$19)^DCF!$E$7:$N$7)+Forecast!$Q$14*$B28/(1+H$19)^DCF!$N$6+(DCF!$C$30-DCF!$C$31+DCF!$C$32))/DCF!$C$34 -> 1364.3343 | I28: =(SUMPRODUCT(DCF!$E$11:$N$11,1/(1+I$19)^DCF!$E$7:$N$7)+Forecast!$Q$14*$B28/(1+I$19)^DCF!$N$6+(DCF!$C$30-DCF!$C$31+DCF!$C$32))/DCF!$C$34 -> 1316.5523 | J28: =(SUMPRODUCT(DCF!$E$11:$N$11,1/(1+J$19)^DCF!$E$7:$N$7)+Forecast!$Q$14*$B28/(1+J$19)^DCF!$N$6+(DCF!$C$30-DCF!$C$31+DCF!$C$32))/DCF!$C$34 -> 1270.8447 | K28: =(SUMPRODUCT(DCF!$E$11:$N$11,1/(1+K$19)^DCF!$E$7:$N$7)+Forecast!$Q$14*$B28/(1+K$19)^DCF!$N$6+(DCF!$C$30-DCF!$C$31+DCF!$C$32))/DCF!$C$34 -> 1227.1109
B30: Shaded cell = live base case and equals the DCF tab price. Bold underlined = implied price at or above today's share price.
B31: Table 3: Blended price, WACC vs terminal growth (multiple held at base)
C32: WACC →
B33: g ↓ / WACC → | C33: =$G$33+(-4)*$N$5 -> 0.073779813 | D33: =$G$33+(-3)*$N$5 -> 0.078779813 | E33: =$G$33+(-2)*$N$5 -> 0.083779813 | F33: =$G$33+(-1)*$N$5 -> 0.088779813 | G33: =WACC!$C$35 -> 0.093779813 | H33: =$G$33+(1)*$N$5 -> 0.098779813 | I33: =$G$33+(2)*$N$5 -> 0.10377981 | J33: =$G$33+(3)*$N$5 -> 0.10877981 | K33: =$G$33+(4)*$N$5 -> 0.11377981
B34: =$B$38+(-4)*$N$6 -> 0.015 | C34: =Assumptions!$C$12*((SUMPRODUCT(DCF!$E$11:$N$11,1/(1+C$33)^DCF!$E$7:$N$7)+DCF!$N$9*(1+$B34)/(C$33-$B34)/(1+C$33)^DCF!$N$6+(DCF!$C$30-DCF!$C$31+DCF!$C$32))/DCF!$C$34)+(1-Assumptions!$C$12)*((SUMPRODUCT(DCF!$E$11:$N$11,1/(1+C$33)^DCF!$E$7:$N$7)+Forecast!$Q$14*Assumptions!$E$142/(1+C$33)^DCF!$N$6+(DCF!$C$30-DCF!$C$31+DCF!$C$32))/DCF!$C$34) -> 1108.2386 | D34: =Assumptions!$C$12*((SUMPRODUCT(DCF!$E$11:$N$11,1/(1+D$33)^DCF!$E$7:$N$7)+DCF!$N$9*(1+$B34)/(D$33-$B34)/(1+D$33)^DCF!$N$6+(DCF!$C$30-DCF!$C$31+DCF!$C$32))/DCF!$C$34)+(1-Assumptions!$C$12)*((SUMPRODUCT(DCF!$E$11:$N$11,1/(1+D$33)^DCF!$E$7:$N$7)+Forecast!$Q$14*Assumptions!$E$142/(1+D$33)^DCF!$N$6+(DCF!$C$30-DCF!$C$31+DCF!$C$32))/DCF!$C$34) -> 1049.829 | E34: =Assumptions!$C$12*((SUMPRODUCT(DCF!$E$11:$N$11,1/(1+E$33)^DCF!$E$7:$N$7)+DCF!$N$9*(1+$B34)/(E$33-$B34)/(1+E$33)^DCF!$N$6+(DCF!$C$30-DCF!$C$31+DCF!$C$32))/DCF!$C$34)+(1-Assumptions!$C$12)*((SUMPRODUCT(DCF!$E$11:$N$11,1/(1+E$33)^DCF!$E$7:$N$7)+Forecast!$Q$14*Assumptions!$E$142/(1+E$33)^DCF!$N$6+(DCF!$C$30-DCF!$C$31+DCF!$C$32))/DCF!$C$34) -> 997.69236 | F34: =Assumptions!$C$12*((SUMPRODUCT(DCF!$E$11:$N$11,1/(1+F$33)^DCF!$E$7:$N$7)+DCF!$N$9*(1+$B34)/(F$33-$B34)/(1+F$33)^DCF!$N$6+(DCF!$C$30-DCF!$C$31+DCF!$C$32))/DCF!$C$34)+(1-Assumptions!$C$12)*((SUMPRODUCT(DCF!$E$11:$N$11,1/(1+F$33)^DCF!$E$7:$N$7)+Forecast!$Q$14*Assumptions!$E$142/(1+F$33)^DCF!$N$6+(DCF!$C$30-DCF!$C$31+DCF!$C$32))/DCF!$C$34) -> 950.7021 | G34: =Assumptions!$C$12*((SUMPRODUCT(DCF!$E$11:$N$11,1/(1+G$33)^DCF!$E$7:$N$7)+DCF!$N$9*(1+$B34)/(G$33-$B34)/(1+G$33)^DCF!$N$6+(DCF!$C$30-DCF!$C$31+DCF!$C$32))/DCF!$C$34)+(1-Assumptions!$C$12)*((SUMPRODUCT(DCF!$E$11:$N$11,1/(1+G$33)^DCF!$E$7:$N$7)+Forecast!$Q$14*Assumptions!$E$142/(1+G$33)^DCF!$N$6+(DCF!$C$30-DCF!$C$31+DCF!$C$32))/DCF!$C$34) -> 908.00819 | H34: =Assumptions!$C$12*((SUMPRODUCT(DCF!$E$11:$N$11,1/(1+H$33)^DCF!$E$7:$N$7)+DCF!$N$9*(1+$B34)/(H$33-$B34)/(1+H$33)^DCF!$N$6+(DCF!$C$30-DCF!$C$31+DCF!$C$32))/DCF!$C$34)+(1-Assumptions!$C$12)*((SUMPRODUCT(DCF!$E$11:$N$11,1/(1+H$33)^DCF!$E$7:$N$7)+Forecast!$Q$14*Assumptions!$E$142/(1+H$33)^DCF!$N$6+(DCF!$C$30-DCF!$C$31+DCF!$C$32))/DCF!$C$34) -> 868.95515 | I34: =Assumptions!$C$12*((SUMPRODUCT(DCF!$E$11:$N$11,1/(1+I$33)^DCF!$E$7:$N$7)+DCF!$N$9*(1+$B34)/(I$33-$B34)/(1+I$33)^DCF!$N$6+(DCF!$C$30-DCF!$C$31+DCF!$C$32))/DCF!$C$34)+(1-Assumptions!$C$12)*((SUMPRODUCT(DCF!$E$11:$N$11,1/(1+I$33)^DCF!$E$7:$N$7)+Forecast!$Q$14*Assumptions!$E$142/(1+I$33)^DCF!$N$6+(DCF!$C$30-DCF!$C$31+DCF!$C$32))/DCF!$C$34) -> 833.02782 | J34: =Assumptions!$C$12*((SUMPRODUCT(DCF!$E$11:$N$11,1/(1+J$33)^DCF!$E$7:$N$7)+DCF!$N$9*(1+$B34)/(J$33-$B34)/(1+J$33)^DCF!$N$6+(DCF!$C$30-DCF!$C$31+DCF!$C$32))/DCF!$C$34)+(1-Assumptions!$C$12)*((SUMPRODUCT(DCF!$E$11:$N$11,1/(1+J$33)^DCF!$E$7:$N$7)+Forecast!$Q$14*Assumptions!$E$142/(1+J$33)^DCF!$N$6+(DCF!$C$30-DCF!$C$31+DCF!$C$32))/DCF!$C$34) -> 799.81446 | K34: =Assumptions!$C$12*((SUMPRODUCT(DCF!$E$11:$N$11,1/(1+K$33)^DCF!$E$7:$N$7)+DCF!$N$9*(1+$B34)/(K$33-$B34)/(1+K$33)^DCF!$N$6+(DCF!$C$30-DCF!$C$31+DCF!$C$32))/DCF!$C$34)+(1-Assumptions!$C$12)*((SUMPRODUCT(DCF!$E$11:$N$11,1/(1+K$33)^DCF!$E$7:$N$7)+Forecast!$Q$14*Assumptions!$E$142/(1+K$33)^DCF!$N$6+(DCF!$C$30-DCF!$C$31+DCF!$C$32))/DCF!$C$34) -> 768.98098
B35: =$B$38+(-3)*$N$6 -> 0.0175 | C35: =Assumptions!$C$12*((SUMPRODUCT(DCF!$E$11:$N$11,1/(1+C$33)^DCF!$E$7:$N$7)+DCF!$N$9*(1+$B35)/(C$33-$B35)/(1+C$33)^DCF!$N$6+(DCF!$C$30-DCF!$C$31+DCF!$C$32))/DCF!$C$34)+(1-Assumptions!$C$12)*((SUMPRODUCT(DCF!$E$11:$N$11,1/(1+C$33)^DCF!$E$7:$N$7)+Forecast!$Q$14*Assumptions!$E$142/(1+C$33)^DCF!$N$6+(DCF!$C$30-DCF!$C$31+DCF!$C$32))/DCF!$C$34) -> 1121.2487 | D35: =Assumptions!$C$12*((SUMPRODUCT(DCF!$E$11:$N$11,1/(1+D$33)^DCF!$E$7:$N$7)+DCF!$N$9*(1+$B35)/(D$33-$B35)/(1+D$33)^DCF!$N$6+(DCF!$C$30-DCF!$C$31+DCF!$C$32))/DCF!$C$34)+(1-Assumptions!$C$12)*((SUMPRODUCT(DCF!$E$11:$N$11,1/(1+D$33)^DCF!$E$7:$N$7)+Forecast!$Q$14*Assumptions!$E$142/(1+D$33)^DCF!$N$6+(DCF!$C$30-DCF!$C$31+DCF!$C$32))/DCF!$C$34) -> 1060.4276 | E35: =Assumptions!$C$12*((SUMPRODUCT(DCF!$E$11:$N$11,1/(1+E$33)^DCF!$E$7:$N$7)+DCF!$N$9*(1+$B35)/(E$33-$B35)/(1+E$33)^DCF!$N$6+(DCF!$C$30-DCF!$C$31+DCF!$C$32))/DCF!$C$34)+(1-Assumptions!$C$12)*((SUMPRODUCT(DCF!$E$11:$N$11,1/(1+E$33)^DCF!$E$7:$N$7)+Forecast!$Q$14*Assumptions!$E$142/(1+E$33)^DCF!$N$6+(DCF!$C$30-DCF!$C$31+DCF!$C$32))/DCF!$C$34) -> 1006.4396 | F35: =Assumptions!$C$12*((SUMPRODUCT(DCF!$E$11:$N$11,1/(1+F$33)^DCF!$E$7:$N$7)+DCF!$N$9*(1+$B35)/(F$33-$B35)/(1+F$33)^DCF!$N$6+(DCF!$C$30-DCF!$C$31+DCF!$C$32))/DCF!$C$34)+(1-Assumptions!$C$12)*((SUMPRODUCT(DCF!$E$11:$N$11,1/(1+F$33)^DCF!$E$7:$N$7)+Forecast!$Q$14*Assumptions!$E$142/(1+F$33)^DCF!$N$6+(DCF!$C$30-DCF!$C$31+DCF!$C$32))/DCF!$C$34) -> 958.00262 | G35: =Assumptions!$C$12*((SUMPRODUCT(DCF!$E$11:$N$11,1/(1+G$33)^DCF!$E$7:$N$7)+DCF!$N$9*(1+$B35)/(G$33-$B35)/(1+G$33)^DCF!$N$6+(DCF!$C$30-DCF!$C$31+DCF!$C$32))/DCF!$C$34)+(1-Assumptions!$C$12)*((SUMPRODUCT(DCF!$E$11:$N$11,1/(1+G$33)^DCF!$E$7:$N$7)+Forecast!$Q$14*Assumptions!$E$142/(1+G$33)^DCF!$N$6+(DCF!$C$30-DCF!$C$31+DCF!$C$32))/DCF!$C$34) -> 914.16068 | H35: =Assumptions!$C$12*((SUMPRODUCT(DCF!$E$11:$N$11,1/(1+H$33)^DCF!$E$7:$N$7)+DCF!$N$9*(1+$B35)/(H$33-$B35)/(1+H$33)^DCF!$N$6+(DCF!$C$30-DCF!$C$31+DCF!$C$32))/DCF!$C$34)+(1-Assumptions!$C$12)*((SUMPRODUCT(DCF!$E$11:$N$11,1/(1+H$33)^DCF!$E$7:$N$7)+Forecast!$Q$14*Assumptions!$E$142/(1+H$33)^DCF!$N$6+(DCF!$C$30-DCF!$C$31+DCF!$C$32))/DCF!$C$34) -> 874.18448 | I35: =Assumptions!$C$12*((SUMPRODUCT(DCF!$E$11:$N$11,1/(1+I$33)^DCF!$E$7:$N$7)+DCF!$N$9*(1+$B35)/(I$33-$B35)/(1+I$33)^DCF!$N$6+(DCF!$C$30-DCF!$C$31+DCF!$C$32))/DCF!$C$34)+(1-Assumptions!$C$12)*((SUMPRODUCT(DCF!$E$11:$N$11,1/(1+I$33)^DCF!$E$7:$N$7)+Forecast!$Q$14*Assumptions!$E$142/(1+I$33)^DCF!$N$6+(DCF!$C$30-DCF!$C$31+DCF!$C$32))/DCF!$C$34) -> 837.5061 | J35: =Assumptions!$C$12*((SUMPRODUCT(DCF!$E$11:$N$11,1/(1+J$33)^DCF!$E$7:$N$7)+DCF!$N$9*(1+$B35)/(J$33-$B35)/(1+J$33)^DCF!$N$6+(DCF!$C$30-DCF!$C$31+DCF!$C$32))/DCF!$C$34)+(1-Assumptions!$C$12)*((SUMPRODUCT(DCF!$E$11:$N$11,1/(1+J$33)^DCF!$E$7:$N$7)+Forecast!$Q$14*Assumptions!$E$142/(1+J$33)^DCF!$N$6+(DCF!$C$30-DCF!$C$31+DCF!$C$32))/DCF!$C$34) -> 803.67538 | K35: =Assumptions!$C$12*((SUMPRODUCT(DCF!$E$11:$N$11,1/(1+K$33)^DCF!$E$7:$N$7)+DCF!$N$9*(1+$B35)/(K$33-$B35)/(1+K$33)^DCF!$N$6+(DCF!$C$30-DCF!$C$31+DCF!$C$32))/DCF!$C$34)+(1-Assumptions!$C$12)*((SUMPRODUCT(DCF!$E$11:$N$11,1/(1+K$33)^DCF!$E$7:$N$7)+Forecast!$Q$14*Assumptions!$E$142/(1+K$33)^DCF!$N$6+(DCF!$C$30-DCF!$C$31+DCF!$C$32))/DCF!$C$34) -> 772.32974
B36: =$B$38+(-2)*$N$6 -> 0.02 | C36: =Assumptions!$C$12*((SUMPRODUCT(DCF!$E$11:$N$11,1/(1+C$33)^DCF!$E$7:$N$7)+DCF!$N$9*(1+$B36)/(C$33-$B36)/(1+C$33)^DCF!$N$6+(DCF!$C$30-DCF!$C$31+DCF!$C$32))/DCF!$C$34)+(1-Assumptions!$C$12)*((SUMPRODUCT(DCF!$E$11:$N$11,1/(1+C$33)^DCF!$E$7:$N$7)+Forecast!$Q$14*Assumptions!$E$142/(1+C$33)^DCF!$N$6+(DCF!$C$30-DCF!$C$31+DCF!$C$32))/DCF!$C$34) -> 1135.4683 | D36: =Assumptions!$C$12*((SUMPRODUCT(DCF!$E$11:$N$11,1/(1+D$33)^DCF!$E$7:$N$7)+DCF!$N$9*(1+$B36)/(D$33-$B36)/(1+D$33)^DCF!$N$6+(DCF!$C$30-DCF!$C$31+DCF!$C$32))/DCF!$C$34)+(1-Assumptions!$C$12)*((SUMPRODUCT(DCF!$E$11:$N$11,1/(1+D$33)^DCF!$E$7:$N$7)+Forecast!$Q$14*Assumptions!$E$142/(1+D$33)^DCF!$N$6+(DCF!$C$30-DCF!$C$31+DCF!$C$32))/DCF!$C$34) -> 1071.9278 | E36: =Assumptions!$C$12*((SUMPRODUCT(DCF!$E$11:$N$11,1/(1+E$33)^DCF!$E$7:$N$7)+DCF!$N$9*(1+$B36)/(E$33-$B36)/(1+E$33)^DCF!$N$6+(DCF!$C$30-DCF!$C$31+DCF!$C$32))/DCF!$C$34)+(1-Assumptions!$C$12)*((SUMPRODUCT(DCF!$E$11:$N$11,1/(1+E$33)^DCF!$E$7:$N$7)+Forecast!$Q$14*Assumptions!$E$142/(1+E$33)^DCF!$N$6+(DCF!$C$30-DCF!$C$31+DCF!$C$32))/DCF!$C$34) -> 1015.8727 | F36: =Assumptions!$C$12*((SUMPRODUCT(DCF!$E$11:$N$11,1/(1+F$33)^DCF!$E$7:$N$7)+DCF!$N$9*(1+$B36)/(F$33-$B36)/(1+F$33)^DCF!$N$6+(DCF!$C$30-DCF!$C$31+DCF!$C$32))/DCF!$C$34)+(1-Assumptions!$C$12)*((SUMPRODUCT(DCF!$E$11:$N$11,1/(1+F$33)^DCF!$E$7:$N$7)+Forecast!$Q$14*Assumptions!$E$142/(1+F$33)^DCF!$N$6+(DCF!$C$30-DCF!$C$31+DCF!$C$32))/DCF!$C$34) -> 965.83385 | G36: =Assumptions!$C$12*((SUMPRODUCT(DCF!$E$11:$N$11,1/(1+G$33)^DCF!$E$7:$N$7)+DCF!$N$9*(1+$B36)/(G$33-$B36)/(1+G$33)^DCF!$N$6+(DCF!$C$30-DCF!$C$31+DCF!$C$32))/DCF!$C$34)+(1-Assumptions!$C$12)*((SUMPRODUCT(DCF!$E$11:$N$11,1/(1+G$33)^DCF!$E$7:$N$7)+Forecast!$Q$14*Assumptions!$E$142/(1+G$33)^DCF!$N$6+(DCF!$C$30-DCF!$C$31+DCF!$C$32))/DCF!$C$34) -> 920.73012 | H36: =Assumptions!$C$12*((SUMPRODUCT(DCF!$E$11:$N$11,1/(1+H$33)^DCF!$E$7:$N$7)+DCF!$N$9*(1+$B36)/(H$33-$B36)/(1+H$33)^DCF!$N$6+(DCF!$C$30-DCF!$C$31+DCF!$C$32))/DCF!$C$34)+(1-Assumptions!$C$12)*((SUMPRODUCT(DCF!$E$11:$N$11,1/(1+H$33)^DCF!$E$7:$N$7)+Forecast!$Q$14*Assumptions!$E$142/(1+H$33)^DCF!$N$6+(DCF!$C$30-DCF!$C$31+DCF!$C$32))/DCF!$C$34) -> 879.7457 | I36: =Assumptions!$C$12*((SUMPRODUCT(DCF!$E$11:$N$11,1/(1+I$33)^DCF!$E$7:$N$7)+DCF!$N$9*(1+$B36)/(I$33-$B36)/(1+I$33)^DCF!$N$6+(DCF!$C$30-DCF!$C$31+DCF!$C$32))/DCF!$C$34)+(1-Assumptions!$C$12)*((SUMPRODUCT(DCF!$E$11:$N$11,1/(1+I$33)^DCF!$E$7:$N$7)+Forecast!$Q$14*Assumptions!$E$142/(1+I$33)^DCF!$N$6+(DCF!$C$30-DCF!$C$31+DCF!$C$32))/DCF!$C$34) -> 842.25165 | J36: =Assumptions!$C$12*((SUMPRODUCT(DCF!$E$11:$N$11,1/(1+J$33)^DCF!$E$7:$N$7)+DCF!$N$9*(1+$B36)/(J$33-$B36)/(1+J$33)^DCF!$N$6+(DCF!$C$30-DCF!$C$31+DCF!$C$32))/DCF!$C$34)+(1-Assumptions!$C$12)*((SUMPRODUCT(DCF!$E$11:$N$11,1/(1+J$33)^DCF!$E$7:$N$7)+Forecast!$Q$14*Assumptions!$E$142/(1+J$33)^DCF!$N$6+(DCF!$C$30-DCF!$C$31+DCF!$C$32))/DCF!$C$34) -> 807.75375 | K36: =Assumptions!$C$12*((SUMPRODUCT(DCF!$E$11:$N$11,1/(1+K$33)^DCF!$E$7:$N$7)+DCF!$N$9*(1+$B36)/(K$33-$B36)/(1+K$33)^DCF!$N$6+(DCF!$C$30-DCF!$C$31+DCF!$C$32))/DCF!$C$34)+(1-Assumptions!$C$12)*((SUMPRODUCT(DCF!$E$11:$N$11,1/(1+K$33)^DCF!$E$7:$N$7)+Forecast!$Q$14*Assumptions!$E$142/(1+K$33)^DCF!$N$6+(DCF!$C$30-DCF!$C$31+DCF!$C$32))/DCF!$C$34) -> 775.85704
B37: =$B$38+(-1)*$N$6 -> 0.0225 | C37: =Assumptions!$C$12*((SUMPRODUCT(DCF!$E$11:$N$11,1/(1+C$33)^DCF!$E$7:$N$7)+DCF!$N$9*(1+$B37)/(C$33-$B37)/(1+C$33)^DCF!$N$6+(DCF!$C$30-DCF!$C$31+DCF!$C$32))/DCF!$C$34)+(1-Assumptions!$C$12)*((SUMPRODUCT(DCF!$E$11:$N$11,1/(1+C$33)^DCF!$E$7:$N$7)+Forecast!$Q$14*Assumptions!$E$142/(1+C$33)^DCF!$N$6+(DCF!$C$30-DCF!$C$31+DCF!$C$32))/DCF!$C$34) -> 1151.0743 | D37: =Assumptions!$C$12*((SUMPRODUCT(DCF!$E$11:$N$11,1/(1+D$33)^DCF!$E$7:$N$7)+DCF!$N$9*(1+$B37)/(D$33-$B37)/(1+D$33)^DCF!$N$6+(DCF!$C$30-DCF!$C$31+DCF!$C$32))/DCF!$C$34)+(1-Assumptions!$C$12)*((SUMPRODUCT(DCF!$E$11:$N$11,1/(1+D$33)^DCF!$E$7:$N$7)+Forecast!$Q$14*Assumptions!$E$142/(1+D$33)^DCF!$N$6+(DCF!$C$30-DCF!$C$31+DCF!$C$32))/DCF!$C$34) -> 1084.4496 | E37: =Assumptions!$C$12*((SUMPRODUCT(DCF!$E$11:$N$11,1/(1+E$33)^DCF!$E$7:$N$7)+DCF!$N$9*(1+$B37)/(E$33-$B37)/(1+E$33)^DCF!$N$6+(DCF!$C$30-DCF!$C$31+DCF!$C$32))/DCF!$C$34)+(1-Assumptions!$C$12)*((SUMPRODUCT(DCF!$E$11:$N$11,1/(1+E$33)^DCF!$E$7:$N$7)+Forecast!$Q$14*Assumptions!$E$142/(1+E$33)^DCF!$N$6+(DCF!$C$30-DCF!$C$31+DCF!$C$32))/DCF!$C$34) -> 1026.0753 | F37: =Assumptions!$C$12*((SUMPRODUCT(DCF!$E$11:$N$11,1/(1+F$33)^DCF!$E$7:$N$7)+DCF!$N$9*(1+$B37)/(F$33-$B37)/(1+F$33)^DCF!$N$6+(DCF!$C$30-DCF!$C$31+DCF!$C$32))/DCF!$C$34)+(1-Assumptions!$C$12)*((SUMPRODUCT(DCF!$E$11:$N$11,1/(1+F$33)^DCF!$E$7:$N$7)+Forecast!$Q$14*Assumptions!$E$142/(1+F$33)^DCF!$N$6+(DCF!$C$30-DCF!$C$31+DCF!$C$32))/DCF!$C$34) -> 974.25586 | G37: =Assumptions!$C$12*((SUMPRODUCT(DCF!$E$11:$N$11,1/(1+G$33)^DCF!$E$7:$N$7)+DCF!$N$9*(1+$B37)/(G$33-$B37)/(1+G$33)^DCF!$N$6+(DCF!$C$30-DCF!$C$31+DCF!$C$32))/DCF!$C$34)+(1-Assumptions!$C$12)*((SUMPRODUCT(DCF!$E$11:$N$11,1/(1+G$33)^DCF!$E$7:$N$7)+Forecast!$Q$14*Assumptions!$E$142/(1+G$33)^DCF!$N$6+(DCF!$C$30-DCF!$C$31+DCF!$C$32))/DCF!$C$34) -> 927.76039 | H37: =Assumptions!$C$12*((SUMPRODUCT(DCF!$E$11:$N$11,1/(1+H$33)^DCF!$E$7:$N$7)+DCF!$N$9*(1+$B37)/(H$33-$B37)/(1+H$33)^DCF!$N$6+(DCF!$C$30-DCF!$C$31+DCF!$C$32))/DCF!$C$34)+(1-Assumptions!$C$12)*((SUMPRODUCT(DCF!$E$11:$N$11,1/(1+H$33)^DCF!$E$7:$N$7)+Forecast!$Q$14*Assumptions!$E$142/(1+H$33)^DCF!$N$6+(DCF!$C$30-DCF!$C$31+DCF!$C$32))/DCF!$C$34) -> 885.67146 | I37: =Assumptions!$C$12*((SUMPRODUCT(DCF!$E$11:$N$11,1/(1+I$33)^DCF!$E$7:$N$7)+DCF!$N$9*(1+$B37)/(I$33-$B37)/(1+I$33)^DCF!$N$6+(DCF!$C$30-DCF!$C$31+DCF!$C$32))/DCF!$C$34)+(1-Assumptions!$C$12)*((SUMPRODUCT(DCF!$E$11:$N$11,1/(1+I$33)^DCF!$E$7:$N$7)+Forecast!$Q$14*Assumptions!$E$142/(1+I$33)^DCF!$N$6+(DCF!$C$30-DCF!$C$31+DCF!$C$32))/DCF!$C$34) -> 847.28912 | J37: =Assumptions!$C$12*((SUMPRODUCT(DCF!$E$11:$N$11,1/(1+J$33)^DCF!$E$7:$N$7)+DCF!$N$9*(1+$B37)/(J$33-$B37)/(1+J$33)^DCF!$N$6+(DCF!$C$30-DCF!$C$31+DCF!$C$32))/DCF!$C$34)+(1-Assumptions!$C$12)*((SUMPRODUCT(DCF!$E$11:$N$11,1/(1+J$33)^DCF!$E$7:$N$7)+Forecast!$Q$14*Assumptions!$E$142/(1+J$33)^DCF!$N$6+(DCF!$C$30-DCF!$C$31+DCF!$C$32))/DCF!$C$34) -> 812.06845 | K37: =Assumptions!$C$12*((SUMPRODUCT(DCF!$E$11:$N$11,1/(1+K$33)^DCF!$E$7:$N$7)+DCF!$N$9*(1+$B37)/(K$33-$B37)/(1+K$33)^DCF!$N$6+(DCF!$C$30-DCF!$C$31+DCF!$C$32))/DCF!$C$34)+(1-Assumptions!$C$12)*((SUMPRODUCT(DCF!$E$11:$N$11,1/(1+K$33)^DCF!$E$7:$N$7)+Forecast!$Q$14*Assumptions!$E$142/(1+K$33)^DCF!$N$6+(DCF!$C$30-DCF!$C$31+DCF!$C$32))/DCF!$C$34) -> 779.57756
B38: =Assumptions!$E$137 -> 0.025 | C38: =Assumptions!$C$12*((SUMPRODUCT(DCF!$E$11:$N$11,1/(1+C$33)^DCF!$E$7:$N$7)+DCF!$N$9*(1+$B38)/(C$33-$B38)/(1+C$33)^DCF!$N$6+(DCF!$C$30-DCF!$C$31+DCF!$C$32))/DCF!$C$34)+(1-Assumptions!$C$12)*((SUMPRODUCT(DCF!$E$11:$N$11,1/(1+C$33)^DCF!$E$7:$N$7)+Forecast!$Q$14*Assumptions!$E$142/(1+C$33)^DCF!$N$6+(DCF!$C$30-DCF!$C$31+DCF!$C$32))/DCF!$C$34) -> 1168.2801 | D38: =Assumptions!$C$12*((SUMPRODUCT(DCF!$E$11:$N$11,1/(1+D$33)^DCF!$E$7:$N$7)+DCF!$N$9*(1+$B38)/(D$33-$B38)/(1+D$33)^DCF!$N$6+(DCF!$C$30-DCF!$C$31+DCF!$C$32))/DCF!$C$34)+(1-Assumptions!$C$12)*((SUMPRODUCT(DCF!$E$11:$N$11,1/(1+D$33)^DCF!$E$7:$N$7)+Forecast!$Q$14*Assumptions!$E$142/(1+D$33)^DCF!$N$6+(DCF!$C$30-DCF!$C$31+DCF!$C$32))/DCF!$C$34) -> 1098.1356 | E38: =Assumptions!$C$12*((SUMPRODUCT(DCF!$E$11:$N$11,1/(1+E$33)^DCF!$E$7:$N$7)+DCF!$N$9*(1+$B38)/(E$33-$B38)/(1+E$33)^DCF!$N$6+(DCF!$C$30-DCF!$C$31+DCF!$C$32))/DCF!$C$34)+(1-Assumptions!$C$12)*((SUMPRODUCT(DCF!$E$11:$N$11,1/(1+E$33)^DCF!$E$7:$N$7)+Forecast!$Q$14*Assumptions!$E$142/(1+E$33)^DCF!$N$6+(DCF!$C$30-DCF!$C$31+DCF!$C$32))/DCF!$C$34) -> 1037.1459 | F38: =Assumptions!$C$12*((SUMPRODUCT(DCF!$E$11:$N$11,1/(1+F$33)^DCF!$E$7:$N$7)+DCF!$N$9*(1+$B38)/(F$33-$B38)/(1+F$33)^DCF!$N$6+(DCF!$C$30-DCF!$C$31+DCF!$C$32))/DCF!$C$34)+(1-Assumptions!$C$12)*((SUMPRODUCT(DCF!$E$11:$N$11,1/(1+F$33)^DCF!$E$7:$N$7)+Forecast!$Q$14*Assumptions!$E$142/(1+F$33)^DCF!$N$6+(DCF!$C$30-DCF!$C$31+DCF!$C$32))/DCF!$C$34) -> 983.3381 | G38: =Assumptions!$C$12*((SUMPRODUCT(DCF!$E$11:$N$11,1/(1+G$33)^DCF!$E$7:$N$7)+DCF!$N$9*(1+$B38)/(G$33-$B38)/(1+G$33)^DCF!$N$6+(DCF!$C$30-DCF!$C$31+DCF!$C$32))/DCF!$C$34)+(1-Assumptions!$C$12)*((SUMPRODUCT(DCF!$E$11:$N$11,1/(1+G$33)^DCF!$E$7:$N$7)+Forecast!$Q$14*Assumptions!$E$142/(1+G$33)^DCF!$N$6+(DCF!$C$30-DCF!$C$31+DCF!$C$32))/DCF!$C$34) -> 935.30172 | H38: =Assumptions!$C$12*((SUMPRODUCT(DCF!$E$11:$N$11,1/(1+H$33)^DCF!$E$7:$N$7)+DCF!$N$9*(1+$B38)/(H$33-$B38)/(1+H$33)^DCF!$N$6+(DCF!$C$30-DCF!$C$31+DCF!$C$32))/DCF!$C$34)+(1-Assumptions!$C$12)*((SUMPRODUCT(DCF!$E$11:$N$11,1/(1+H$33)^DCF!$E$7:$N$7)+Forecast!$Q$14*Assumptions!$E$142/(1+H$33)^DCF!$N$6+(DCF!$C$30-DCF!$C$31+DCF!$C$32))/DCF!$C$34) -> 891.99879 | I38: =Assumptions!$C$12*((SUMPRODUCT(DCF!$E$11:$N$11,1/(1+I$33)^DCF!$E$7:$N$7)+DCF!$N$9*(1+$B38)/(I$33-$B38)/(1+I$33)^DCF!$N$6+(DCF!$C$30-DCF!$C$31+DCF!$C$32))/DCF!$C$34)+(1-Assumptions!$C$12)*((SUMPRODUCT(DCF!$E$11:$N$11,1/(1+I$33)^DCF!$E$7:$N$7)+Forecast!$Q$14*Assumptions!$E$142/(1+I$33)^DCF!$N$6+(DCF!$C$30-DCF!$C$31+DCF!$C$32))/DCF!$C$34) -> 852.64631 | J38: =Assumptions!$C$12*((SUMPRODUCT(DCF!$E$11:$N$11,1/(1+J$33)^DCF!$E$7:$N$7)+DCF!$N$9*(1+$B38)/(J$33-$B38)/(1+J$33)^DCF!$N$6+(DCF!$C$30-DCF!$C$31+DCF!$C$32))/DCF!$C$34)+(1-Assumptions!$C$12)*((SUMPRODUCT(DCF!$E$11:$N$11,1/(1+J$33)^DCF!$E$7:$N$7)+Forecast!$Q$14*Assumptions!$E$142/(1+J$33)^DCF!$N$6+(DCF!$C$30-DCF!$C$31+DCF!$C$32))/DCF!$C$34) -> 816.64066 | K38: =Assumptions!$C$12*((SUMPRODUCT(DCF!$E$11:$N$11,1/(1+K$33)^DCF!$E$7:$N$7)+DCF!$N$9*(1+$B38)/(K$33-$B38)/(1+K$33)^DCF!$N$6+(DCF!$C$30-DCF!$C$31+DCF!$C$32))/DCF!$C$34)+(1-Assumptions!$C$12)*((SUMPRODUCT(DCF!$E$11:$N$11,1/(1+K$33)^DCF!$E$7:$N$7)+Forecast!$Q$14*Assumptions!$E$142/(1+K$33)^DCF!$N$6+(DCF!$C$30-DCF!$C$31+DCF!$C$32))/DCF!$C$34) -> 783.50761
B39: =$B$38+(1)*$N$6 -> 0.0275 | C39: =Assumptions!$C$12*((SUMPRODUCT(DCF!$E$11:$N$11,1/(1+C$33)^DCF!$E$7:$N$7)+DCF!$N$9*(1+$B39)/(C$33-$B39)/(1+C$33)^DCF!$N$6+(DCF!$C$30-DCF!$C$31+DCF!$C$32))/DCF!$C$34)+(1-Assumptions!$C$12)*((SUMPRODUCT(DCF!$E$11:$N$11,1/(1+C$33)^DCF!$E$7:$N$7)+Forecast!$Q$14*Assumptions!$E$142/(1+C$33)^DCF!$N$6+(DCF!$C$30-DCF!$C$31+DCF!$C$32))/DCF!$C$34) -> 1187.3447 | D39: =Assumptions!$C$12*((SUMPRODUCT(DCF!$E$11:$N$11,1/(1+D$33)^DCF!$E$7:$N$7)+DCF!$N$9*(1+$B39)/(D$33-$B39)/(1+D$33)^DCF!$N$6+(DCF!$C$30-DCF!$C$31+DCF!$C$32))/DCF!$C$34)+(1-Assumptions!$C$12)*((SUMPRODUCT(DCF!$E$11:$N$11,1/(1+D$33)^DCF!$E$7:$N$7)+Forecast!$Q$14*Assumptions!$E$142/(1+D$33)^DCF!$N$6+(DCF!$C$30-DCF!$C$31+DCF!$C$32))/DCF!$C$34) -> 1113.1561 | E39: =Assumptions!$C$12*((SUMPRODUCT(DCF!$E$11:$N$11,1/(1+E$33)^DCF!$E$7:$N$7)+DCF!$N$9*(1+$B39)/(E$33-$B39)/(1+E$33)^DCF!$N$6+(DCF!$C$30-DCF!$C$31+DCF!$C$32))/DCF!$C$34)+(1-Assumptions!$C$12)*((SUMPRODUCT(DCF!$E$11:$N$11,1/(1+E$33)^DCF!$E$7:$N$7)+Forecast!$Q$14*Assumptions!$E$142/(1+E$33)^DCF!$N$6+(DCF!$C$30-DCF!$C$31+DCF!$C$32))/DCF!$C$34) -> 1049.2 | F39: =Assumptions!$C$12*((SUMPRODUCT(DCF!$E$11:$N$11,1/(1+F$33)^DCF!$E$7:$N$7)+DCF!$N$9*(1+$B39)/(F$33-$B39)/(1+F$33)^DCF!$N$6+(DCF!$C$30-DCF!$C$31+DCF!$C$32))/DCF!$C$34)+(1-Assumptions!$C$12)*((SUMPRODUCT(DCF!$E$11:$N$11,1/(1+F$33)^DCF!$E$7:$N$7)+Forecast!$Q$14*Assumptions!$E$142/(1+F$33)^DCF!$N$6+(DCF!$C$30-DCF!$C$31+DCF!$C$32))/DCF!$C$34) -> 993.1614 | G39: =Assumptions!$C$12*((SUMPRODUCT(DCF!$E$11:$N$11,1/(1+G$33)^DCF!$E$7:$N$7)+DCF!$N$9*(1+$B39)/(G$33-$B39)/(1+G$33)^DCF!$N$6+(DCF!$C$30-DCF!$C$31+DCF!$C$32))/DCF!$C$34)+(1-Assumptions!$C$12)*((SUMPRODUCT(DCF!$E$11:$N$11,1/(1+G$33)^DCF!$E$7:$N$7)+Forecast!$Q$14*Assumptions!$E$142/(1+G$33)^DCF!$N$6+(DCF!$C$30-DCF!$C$31+DCF!$C$32))/DCF!$C$34) -> 943.41195 | H39: =Assumptions!$C$12*((SUMPRODUCT(DCF!$E$11:$N$11,1/(1+H$33)^DCF!$E$7:$N$7)+DCF!$N$9*(1+$B39)/(H$33-$B39)/(1+H$33)^DCF!$N$6+(DCF!$C$30-DCF!$C$31+DCF!$C$32))/DCF!$C$34)+(1-Assumptions!$C$12)*((SUMPRODUCT(DCF!$E$11:$N$11,1/(1+H$33)^DCF!$E$7:$N$7)+Forecast!$Q$14*Assumptions!$E$142/(1+H$33)^DCF!$N$6+(DCF!$C$30-DCF!$C$31+DCF!$C$32))/DCF!$C$34) -> 898.76997 | I39: =Assumptions!$C$12*((SUMPRODUCT(DCF!$E$11:$N$11,1/(1+I$33)^DCF!$E$7:$N$7)+DCF!$N$9*(1+$B39)/(I$33-$B39)/(1+I$33)^DCF!$N$6+(DCF!$C$30-DCF!$C$31+DCF!$C$32))/DCF!$C$34)+(1-Assumptions!$C$12)*((SUMPRODUCT(DCF!$E$11:$N$11,1/(1+I$33)^DCF!$E$7:$N$7)+Forecast!$Q$14*Assumptions!$E$142/(1+I$33)^DCF!$N$6+(DCF!$C$30-DCF!$C$31+DCF!$C$32))/DCF!$C$34) -> 858.35466 | J39: =Assumptions!$C$12*((SUMPRODUCT(DCF!$E$11:$N$11,1/(1+J$33)^DCF!$E$7:$N$7)+DCF!$N$9*(1+$B39)/(J$33-$B39)/(1+J$33)^DCF!$N$6+(DCF!$C$30-DCF!$C$31+DCF!$C$32))/DCF!$C$34)+(1-Assumptions!$C$12)*((SUMPRODUCT(DCF!$E$11:$N$11,1/(1+J$33)^DCF!$E$7:$N$7)+Forecast!$Q$14*Assumptions!$E$142/(1+J$33)^DCF!$N$6+(DCF!$C$30-DCF!$C$31+DCF!$C$32))/DCF!$C$34) -> 821.49414 | K39: =Assumptions!$C$12*((SUMPRODUCT(DCF!$E$11:$N$11,1/(1+K$33)^DCF!$E$7:$N$7)+DCF!$N$9*(1+$B39)/(K$33-$B39)/(1+K$33)^DCF!$N$6+(DCF!$C$30-DCF!$C$31+DCF!$C$32))/DCF!$C$34)+(1-Assumptions!$C$12)*((SUMPRODUCT(DCF!$E$11:$N$11,1/(1+K$33)^DCF!$E$7:$N$7)+Forecast!$Q$14*Assumptions!$E$142/(1+K$33)^DCF!$N$6+(DCF!$C$30-DCF!$C$31+DCF!$C$32))/DCF!$C$34) -> 787.66542
B40: =$B$38+(2)*$N$6 -> 0.03 | C40: =Assumptions!$C$12*((SUMPRODUCT(DCF!$E$11:$N$11,1/(1+C$33)^DCF!$E$7:$N$7)+DCF!$N$9*(1+$B40)/(C$33-$B40)/(1+C$33)^DCF!$N$6+(DCF!$C$30-DCF!$C$31+DCF!$C$32))/DCF!$C$34)+(1-Assumptions!$C$12)*((SUMPRODUCT(DCF!$E$11:$N$11,1/(1+C$33)^DCF!$E$7:$N$7)+Forecast!$Q$14*Assumptions!$E$142/(1+C$33)^DCF!$N$6+(DCF!$C$30-DCF!$C$31+DCF!$C$32))/DCF!$C$34) -> 1208.5866 | D40: =Assumptions!$C$12*((SUMPRODUCT(DCF!$E$11:$N$11,1/(1+D$33)^DCF!$E$7:$N$7)+DCF!$N$9*(1+$B40)/(D$33-$B40)/(1+D$33)^DCF!$N$6+(DCF!$C$30-DCF!$C$31+DCF!$C$32))/DCF!$C$34)+(1-Assumptions!$C$12)*((SUMPRODUCT(DCF!$E$11:$N$11,1/(1+D$33)^DCF!$E$7:$N$7)+Forecast!$Q$14*Assumptions!$E$142/(1+D$33)^DCF!$N$6+(DCF!$C$30-DCF!$C$31+DCF!$C$32))/DCF!$C$34) -> 1129.7162 | E40: =Assumptions!$C$12*((SUMPRODUCT(DCF!$E$11:$N$11,1/(1+E$33)^DCF!$E$7:$N$7)+DCF!$N$9*(1+$B40)/(E$33-$B40)/(1+E$33)^DCF!$N$6+(DCF!$C$30-DCF!$C$31+DCF!$C$32))/DCF!$C$34)+(1-Assumptions!$C$12)*((SUMPRODUCT(DCF!$E$11:$N$11,1/(1+E$33)^DCF!$E$7:$N$7)+Forecast!$Q$14*Assumptions!$E$142/(1+E$33)^DCF!$N$6+(DCF!$C$30-DCF!$C$31+DCF!$C$32))/DCF!$C$34) -> 1062.3748 | F40: =Assumptions!$C$12*((SUMPRODUCT(DCF!$E$11:$N$11,1/(1+F$33)^DCF!$E$7:$N$7)+DCF!$N$9*(1+$B40)/(F$33-$B40)/(1+F$33)^DCF!$N$6+(DCF!$C$30-DCF!$C$31+DCF!$C$32))/DCF!$C$34)+(1-Assumptions!$C$12)*((SUMPRODUCT(DCF!$E$11:$N$11,1/(1+F$33)^DCF!$E$7:$N$7)+Forecast!$Q$14*Assumptions!$E$142/(1+F$33)^DCF!$N$6+(DCF!$C$30-DCF!$C$31+DCF!$C$32))/DCF!$C$34) -> 1003.8203 | G40: =Assumptions!$C$12*((SUMPRODUCT(DCF!$E$11:$N$11,1/(1+G$33)^DCF!$E$7:$N$7)+DCF!$N$9*(1+$B40)/(G$33-$B40)/(1+G$33)^DCF!$N$6+(DCF!$C$30-DCF!$C$31+DCF!$C$32))/DCF!$C$34)+(1-Assumptions!$C$12)*((SUMPRODUCT(DCF!$E$11:$N$11,1/(1+G$33)^DCF!$E$7:$N$7)+Forecast!$Q$14*Assumptions!$E$142/(1+G$33)^DCF!$N$6+(DCF!$C$30-DCF!$C$31+DCF!$C$32))/DCF!$C$34) -> 952.15798 | H40: =Assumptions!$C$12*((SUMPRODUCT(DCF!$E$11:$N$11,1/(1+H$33)^DCF!$E$7:$N$7)+DCF!$N$9*(1+$B40)/(H$33-$B40)/(1+H$33)^DCF!$N$6+(DCF!$C$30-DCF!$C$31+DCF!$C$32))/DCF!$C$34)+(1-Assumptions!$C$12)*((SUMPRODUCT(DCF!$E$11:$N$11,1/(1+H$33)^DCF!$E$7:$N$7)+Forecast!$Q$14*Assumptions!$E$142/(1+H$33)^DCF!$N$6+(DCF!$C$30-DCF!$C$31+DCF!$C$32))/DCF!$C$34) -> 906.03338 | I40: =Assumptions!$C$12*((SUMPRODUCT(DCF!$E$11:$N$11,1/(1+I$33)^DCF!$E$7:$N$7)+DCF!$N$9*(1+$B40)/(I$33-$B40)/(1+I$33)^DCF!$N$6+(DCF!$C$30-DCF!$C$31+DCF!$C$32))/DCF!$C$34)+(1-Assumptions!$C$12)*((SUMPRODUCT(DCF!$E$11:$N$11,1/(1+I$33)^DCF!$E$7:$N$7)+Forecast!$Q$14*Assumptions!$E$142/(1+I$33)^DCF!$N$6+(DCF!$C$30-DCF!$C$31+DCF!$C$32))/DCF!$C$34) -> 864.44985 | J40: =Assumptions!$C$12*((SUMPRODUCT(DCF!$E$11:$N$11,1/(1+J$33)^DCF!$E$7:$N$7)+DCF!$N$9*(1+$B40)/(J$33-$B40)/(1+J$33)^DCF!$N$6+(DCF!$C$30-DCF!$C$31+DCF!$C$32))/DCF!$C$34)+(1-Assumptions!$C$12)*((SUMPRODUCT(DCF!$E$11:$N$11,1/(1+J$33)^DCF!$E$7:$N$7)+Forecast!$Q$14*Assumptions!$E$142/(1+J$33)^DCF!$N$6+(DCF!$C$30-DCF!$C$31+DCF!$C$32))/DCF!$C$34) -> 826.65565 | K40: =Assumptions!$C$12*((SUMPRODUCT(DCF!$E$11:$N$11,1/(1+K$33)^DCF!$E$7:$N$7)+DCF!$N$9*(1+$B40)/(K$33-$B40)/(1+K$33)^DCF!$N$6+(DCF!$C$30-DCF!$C$31+DCF!$C$32))/DCF!$C$34)+(1-Assumptions!$C$12)*((SUMPRODUCT(DCF!$E$11:$N$11,1/(1+K$33)^DCF!$E$7:$N$7)+Forecast!$Q$14*Assumptions!$E$142/(1+K$33)^DCF!$N$6+(DCF!$C$30-DCF!$C$31+DCF!$C$32))/DCF!$C$34) -> 792.07136
B41: =$B$38+(3)*$N$6 -> 0.0325 | C41: =Assumptions!$C$12*((SUMPRODUCT(DCF!$E$11:$N$11,1/(1+C$33)^DCF!$E$7:$N$7)+DCF!$N$9*(1+$B41)/(C$33-$B41)/(1+C$33)^DCF!$N$6+(DCF!$C$30-DCF!$C$31+DCF!$C$32))/DCF!$C$34)+(1-Assumptions!$C$12)*((SUMPRODUCT(DCF!$E$11:$N$11,1/(1+C$33)^DCF!$E$7:$N$7)+Forecast!$Q$14*Assumptions!$E$142/(1+C$33)^DCF!$N$6+(DCF!$C$30-DCF!$C$31+DCF!$C$32))/DCF!$C$34) -> 1232.4014 | D41: =Assumptions!$C$12*((SUMPRODUCT(DCF!$E$11:$N$11,1/(1+D$33)^DCF!$E$7:$N$7)+DCF!$N$9*(1+$B41)/(D$33-$B41)/(1+D$33)^DCF!$N$6+(DCF!$C$30-DCF!$C$31+DCF!$C$32))/DCF!$C$34)+(1-Assumptions!$C$12)*((SUMPRODUCT(DCF!$E$11:$N$11,1/(1+D$33)^DCF!$E$7:$N$7)+Forecast!$Q$14*Assumptions!$E$142/(1+D$33)^DCF!$N$6+(DCF!$C$30-DCF!$C$31+DCF!$C$32))/DCF!$C$34) -> 1148.0654 | E41: =Assumptions!$C$12*((SUMPRODUCT(DCF!$E$11:$N$11,1/(1+E$33)^DCF!$E$7:$N$7)+DCF!$N$9*(1+$B41)/(E$33-$B41)/(1+E$33)^DCF!$N$6+(DCF!$C$30-DCF!$C$31+DCF!$C$32))/DCF!$C$34)+(1-Assumptions!$C$12)*((SUMPRODUCT(DCF!$E$11:$N$11,1/(1+E$33)^DCF!$E$7:$N$7)+Forecast!$Q$14*Assumptions!$E$142/(1+E$33)^DCF!$N$6+(DCF!$C$30-DCF!$C$31+DCF!$C$32))/DCF!$C$34) -> 1076.8342 | F41: =Assumptions!$C$12*((SUMPRODUCT(DCF!$E$11:$N$11,1/(1+F$33)^DCF!$E$7:$N$7)+DCF!$N$9*(1+$B41)/(F$33-$B41)/(1+F$33)^DCF!$N$6+(DCF!$C$30-DCF!$C$31+DCF!$C$32))/DCF!$C$34)+(1-Assumptions!$C$12)*((SUMPRODUCT(DCF!$E$11:$N$11,1/(1+F$33)^DCF!$E$7:$N$7)+Forecast!$Q$14*Assumptions!$E$142/(1+F$33)^DCF!$N$6+(DCF!$C$30-DCF!$C$31+DCF!$C$32))/DCF!$C$34) -> 1015.4261 | G41: =Assumptions!$C$12*((SUMPRODUCT(DCF!$E$11:$N$11,1/(1+G$33)^DCF!$E$7:$N$7)+DCF!$N$9*(1+$B41)/(G$33-$B41)/(1+G$33)^DCF!$N$6+(DCF!$C$30-DCF!$C$31+DCF!$C$32))/DCF!$C$34)+(1-Assumptions!$C$12)*((SUMPRODUCT(DCF!$E$11:$N$11,1/(1+G$33)^DCF!$E$7:$N$7)+Forecast!$Q$14*Assumptions!$E$142/(1+G$33)^DCF!$N$6+(DCF!$C$30-DCF!$C$31+DCF!$C$32))/DCF!$C$34) -> 961.61763 | H41: =Assumptions!$C$12*((SUMPRODUCT(DCF!$E$11:$N$11,1/(1+H$33)^DCF!$E$7:$N$7)+DCF!$N$9*(1+$B41)/(H$33-$B41)/(1+H$33)^DCF!$N$6+(DCF!$C$30-DCF!$C$31+DCF!$C$32))/DCF!$C$34)+(1-Assumptions!$C$12)*((SUMPRODUCT(DCF!$E$11:$N$11,1/(1+H$33)^DCF!$E$7:$N$7)+Forecast!$Q$14*Assumptions!$E$142/(1+H$33)^DCF!$N$6+(DCF!$C$30-DCF!$C$31+DCF!$C$32))/DCF!$C$34) -> 913.84473 | I41: =Assumptions!$C$12*((SUMPRODUCT(DCF!$E$11:$N$11,1/(1+I$33)^DCF!$E$7:$N$7)+DCF!$N$9*(1+$B41)/(I$33-$B41)/(1+I$33)^DCF!$N$6+(DCF!$C$30-DCF!$C$31+DCF!$C$32))/DCF!$C$34)+(1-Assumptions!$C$12)*((SUMPRODUCT(DCF!$E$11:$N$11,1/(1+I$33)^DCF!$E$7:$N$7)+Forecast!$Q$14*Assumptions!$E$142/(1+I$33)^DCF!$N$6+(DCF!$C$30-DCF!$C$31+DCF!$C$32))/DCF!$C$34) -> 870.9726 | J41: =Assumptions!$C$12*((SUMPRODUCT(DCF!$E$11:$N$11,1/(1+J$33)^DCF!$E$7:$N$7)+DCF!$N$9*(1+$B41)/(J$33-$B41)/(1+J$33)^DCF!$N$6+(DCF!$C$30-DCF!$C$31+DCF!$C$32))/DCF!$C$34)+(1-Assumptions!$C$12)*((SUMPRODUCT(DCF!$E$11:$N$11,1/(1+J$33)^DCF!$E$7:$N$7)+Forecast!$Q$14*Assumptions!$E$142/(1+J$33)^DCF!$N$6+(DCF!$C$30-DCF!$C$31+DCF!$C$32))/DCF!$C$34) -> 832.15549 | K41: =Assumptions!$C$12*((SUMPRODUCT(DCF!$E$11:$N$11,1/(1+K$33)^DCF!$E$7:$N$7)+DCF!$N$9*(1+$B41)/(K$33-$B41)/(1+K$33)^DCF!$N$6+(DCF!$C$30-DCF!$C$31+DCF!$C$32))/DCF!$C$34)+(1-Assumptions!$C$12)*((SUMPRODUCT(DCF!$E$11:$N$11,1/(1+K$33)^DCF!$E$7:$N$7)+Forecast!$Q$14*Assumptions!$E$142/(1+K$33)^DCF!$N$6+(DCF!$C$30-DCF!$C$31+DCF!$C$32))/DCF!$C$34) -> 796.74834
B42: =$B$38+(4)*$N$6 -> 0.035 | C42: =Assumptions!$C$12*((SUMPRODUCT(DCF!$E$11:$N$11,1/(1+C$33)^DCF!$E$7:$N$7)+DCF!$N$9*(1+$B42)/(C$33-$B42)/(1+C$33)^DCF!$N$6+(DCF!$C$30-DCF!$C$31+DCF!$C$32))/DCF!$C$34)+(1-Assumptions!$C$12)*((SUMPRODUCT(DCF!$E$11:$N$11,1/(1+C$33)^DCF!$E$7:$N$7)+Forecast!$Q$14*Assumptions!$E$142/(1+C$33)^DCF!$N$6+(DCF!$C$30-DCF!$C$31+DCF!$C$32))/DCF!$C$34) -> 1259.2868 | D42: =Assumptions!$C$12*((SUMPRODUCT(DCF!$E$11:$N$11,1/(1+D$33)^DCF!$E$7:$N$7)+DCF!$N$9*(1+$B42)/(D$33-$B42)/(1+D$33)^DCF!$N$6+(DCF!$C$30-DCF!$C$31+DCF!$C$32))/DCF!$C$34)+(1-Assumptions!$C$12)*((SUMPRODUCT(DCF!$E$11:$N$11,1/(1+D$33)^DCF!$E$7:$N$7)+Forecast!$Q$14*Assumptions!$E$142/(1+D$33)^DCF!$N$6+(DCF!$C$30-DCF!$C$31+DCF!$C$32))/DCF!$C$34) -> 1168.5102 | E42: =Assumptions!$C$12*((SUMPRODUCT(DCF!$E$11:$N$11,1/(1+E$33)^DCF!$E$7:$N$7)+DCF!$N$9*(1+$B42)/(E$33-$B42)/(1+E$33)^DCF!$N$6+(DCF!$C$30-DCF!$C$31+DCF!$C$32))/DCF!$C$34)+(1-Assumptions!$C$12)*((SUMPRODUCT(DCF!$E$11:$N$11,1/(1+E$33)^DCF!$E$7:$N$7)+Forecast!$Q$14*Assumptions!$E$142/(1+E$33)^DCF!$N$6+(DCF!$C$30-DCF!$C$31+DCF!$C$32))/DCF!$C$34) -> 1092.7756 | F42: =Assumptions!$C$12*((SUMPRODUCT(DCF!$E$11:$N$11,1/(1+F$33)^DCF!$E$7:$N$7)+DCF!$N$9*(1+$B42)/(F$33-$B42)/(1+F$33)^DCF!$N$6+(DCF!$C$30-DCF!$C$31+DCF!$C$32))/DCF!$C$34)+(1-Assumptions!$C$12)*((SUMPRODUCT(DCF!$E$11:$N$11,1/(1+F$33)^DCF!$E$7:$N$7)+Forecast!$Q$14*Assumptions!$E$142/(1+F$33)^DCF!$N$6+(DCF!$C$30-DCF!$C$31+DCF!$C$32))/DCF!$C$34) -> 1028.111 | G42: =Assumptions!$C$12*((SUMPRODUCT(DCF!$E$11:$N$11,1/(1+G$33)^DCF!$E$7:$N$7)+DCF!$N$9*(1+$B42)/(G$33-$B42)/(1+G$33)^DCF!$N$6+(DCF!$C$30-DCF!$C$31+DCF!$C$32))/DCF!$C$34)+(1-Assumptions!$C$12)*((SUMPRODUCT(DCF!$E$11:$N$11,1/(1+G$33)^DCF!$E$7:$N$7)+Forecast!$Q$14*Assumptions!$E$142/(1+G$33)^DCF!$N$6+(DCF!$C$30-DCF!$C$31+DCF!$C$32))/DCF!$C$34) -> 971.88194 | H42: =Assumptions!$C$12*((SUMPRODUCT(DCF!$E$11:$N$11,1/(1+H$33)^DCF!$E$7:$N$7)+DCF!$N$9*(1+$B42)/(H$33-$B42)/(1+H$33)^DCF!$N$6+(DCF!$C$30-DCF!$C$31+DCF!$C$32))/DCF!$C$34)+(1-Assumptions!$C$12)*((SUMPRODUCT(DCF!$E$11:$N$11,1/(1+H$33)^DCF!$E$7:$N$7)+Forecast!$Q$14*Assumptions!$E$142/(1+H$33)^DCF!$N$6+(DCF!$C$30-DCF!$C$31+DCF!$C$32))/DCF!$C$34) -> 922.26844 | I42: =Assumptions!$C$12*((SUMPRODUCT(DCF!$E$11:$N$11,1/(1+I$33)^DCF!$E$7:$N$7)+DCF!$N$9*(1+$B42)/(I$33-$B42)/(1+I$33)^DCF!$N$6+(DCF!$C$30-DCF!$C$31+DCF!$C$32))/DCF!$C$34)+(1-Assumptions!$C$12)*((SUMPRODUCT(DCF!$E$11:$N$11,1/(1+I$33)^DCF!$E$7:$N$7)+Forecast!$Q$14*Assumptions!$E$142/(1+I$33)^DCF!$N$6+(DCF!$C$30-DCF!$C$31+DCF!$C$32))/DCF!$C$34) -> 877.96953 | J42: =Assumptions!$C$12*((SUMPRODUCT(DCF!$E$11:$N$11,1/(1+J$33)^DCF!$E$7:$N$7)+DCF!$N$9*(1+$B42)/(J$33-$B42)/(1+J$33)^DCF!$N$6+(DCF!$C$30-DCF!$C$31+DCF!$C$32))/DCF!$C$34)+(1-Assumptions!$C$12)*((SUMPRODUCT(DCF!$E$11:$N$11,1/(1+J$33)^DCF!$E$7:$N$7)+Forecast!$Q$14*Assumptions!$E$142/(1+J$33)^DCF!$N$6+(DCF!$C$30-DCF!$C$31+DCF!$C$32))/DCF!$C$34) -> 838.02805 | K42: =Assumptions!$C$12*((SUMPRODUCT(DCF!$E$11:$N$11,1/(1+K$33)^DCF!$E$7:$N$7)+DCF!$N$9*(1+$B42)/(K$33-$B42)/(1+K$33)^DCF!$N$6+(DCF!$C$30-DCF!$C$31+DCF!$C$32))/DCF!$C$34)+(1-Assumptions!$C$12)*((SUMPRODUCT(DCF!$E$11:$N$11,1/(1+K$33)^DCF!$E$7:$N$7)+Forecast!$Q$14*Assumptions!$E$142/(1+K$33)^DCF!$N$6+(DCF!$C$30-DCF!$C$31+DCF!$C$32))/DCF!$C$34) -> 801.72216

Sheet Scenarios
B1: Scenario Analysis
B2: Each case is a self-contained 10-year build (units x ASP, fade, terminal) off its own Assumptions rows, so Bear, Base and Bull compute side by side.
B4: Summary | C4: Bear | D4: Base | E4: Bull
B5: FY30E revenue | C5: =I35 -> 46737.52 | D5: =I66 -> 64007.665 | E5: =I97 -> 80934.454
B6: Revenue CAGR FY25A-FY30E | C6: =(I35/Historical!$H$6)^(1/5)-1 -> 0.074262672 | D6: =(I66/Historical!$H$6)^(1/5)-1 -> 0.143994 | E6: =(I97/Historical!$H$6)^(1/5)-1 -> 0.19895819
B7: Average EBITDA margin FY26-30 | C7: =AVERAGE(Assumptions!$E$109:$I$109) -> 0.364 | D7: =AVERAGE(Assumptions!$E$110:$I$110) -> 0.423 | E7: =AVERAGE(Assumptions!$E$111:$I$111) -> 0.445
B8: Average CapEx % revenue | C8: =AVERAGE(Assumptions!$E$119:$I$119) -> 0.062 | D8: =AVERAGE(Assumptions!$E$120:$I$120) -> 0.055 | E8: =AVERAGE(Assumptions!$E$121:$I$121) -> 0.05
B9: WACC | C9: =C49 -> 0.098779813 | D9: =C80 -> 0.093779813 | E9: =C111 -> 0.088779813
B10: Terminal growth | C10: =C50 -> 0.02 | D10: =C81 -> 0.025 | E10: =C112 -> 0.03
B11: Exit EV/EBITDA (FY35) | C11: =C51 -> 15 | D11: =C82 -> 20 | E11: =C113 -> 25
B12: Enterprise value (Gordon) | C12: =C52+C53 -> 150626.91 | D12: =C83+C84 -> 285847.45 | E12: =C114+C115 -> 472732.09
B13: Enterprise value (Exit) | C13: =C52+C54 -> 205183.82 | D13: =C83+C85 -> 421758.81 | E13: =C114+C116 -> 736227.95
B14: Enterprise value (blended) | C14: =Assumptions!$C$12*C12+(1-Assumptions!$C$12)*C13 -> 177905.36 | D14: =Assumptions!$C$12*D12+(1-Assumptions!$C$12)*D13 -> 353803.13 | E14: =Assumptions!$C$12*E12+(1-Assumptions!$C$12)*E13 -> 604480.02
B15: Equity value (blended) | C15: =C14+(DCF!$C$30-DCF!$C$31+DCF!$C$32) -> 184099.86 | D15: =D14+(DCF!$C$30-DCF!$C$31+DCF!$C$32) -> 359997.63 | E15: =E14+(DCF!$C$30-DCF!$C$31+DCF!$C$32) -> 610674.52
B16: Implied price, Gordon (EUR) | C16: =(C12+(DCF!$C$30-DCF!$C$31+DCF!$C$32))/DCF!$C$34 -> 407.43416 | D16: =(D12+(DCF!$C$30-DCF!$C$31+DCF!$C$32))/DCF!$C$34 -> 758.7476 | E16: =(E12+(DCF!$C$30-DCF!$C$31+DCF!$C$32))/DCF!$C$34 -> 1244.2884
B17: Implied price, Exit (EUR) | C17: =(C13+(DCF!$C$30-DCF!$C$31+DCF!$C$32))/DCF!$C$34 -> 549.17724 | D17: =(D13+(DCF!$C$30-DCF!$C$31+DCF!$C$32))/DCF!$C$34 -> 1111.8558 | E17: =(E13+(DCF!$C$30-DCF!$C$31+DCF!$C$32))/DCF!$C$34 -> 1928.871
B18: Implied price, blended (EUR) | C18: =C15/DCF!$C$34 -> 478.3057 | D18: =D15/DCF!$C$34 -> 935.30172 | E18: =E15/DCF!$C$34 -> 1586.5797
B19: Upside / (downside), blended | C19: =C18/Assumptions!$C$16-1 -> -0.70317382 | D19: =D18/Assumptions!$C$16-1 -> -0.41957198 | E19: =E18/Assumptions!$C$16-1 -> -0.015402958
B20: Current share price (EUR) | C20: =Assumptions!$C$16 -> 1611.4
B22: What drives each case
B23: Bear | C23: AI capex digestion in 2027-28 coincides with tighter China export controls (DUV immersion and servicing). Customers push out EUV orders, the down-payment float shrinks and margins compress as fixed R&D is held.
B24: Base | C24: 2026 guidance is delivered, the backlog converts, and EUV/High-NA adoption in logic and DRAM lift revenue to about EUR 64bn by 2030 (88 low-NA and 22 High-NA EUV systems) with margins at the 2030 target band.
B25: Bull | C25: A sustained AI-driven leading-edge build-out plus faster High-NA adoption push EUV shipments to 110 low-NA and 32 High-NA systems and revenue to about EUR 81bn, with gross margin at 60% and services scaling on the installed base.
B27: Bear case build
B28: EUR m | E28: FY26E | F28: FY27E | G28: FY28E | H28: FY29E | I28: FY30E | J28: FY31E | K28: FY32E | L28: FY33E | M28: FY34E | N28: FY35E
B29: EUV low-NA revenue (units x ASP) | E29: =Assumptions!$E$58*Assumptions!$E$63 -> 16128 | F29: =Assumptions!$F$58*Assumptions!$F$63 -> 16500 | G29: =Assumptions!$G$58*Assumptions!$G$63 -> 15120 | H29: =Assumptions!$H$58*Assumptions!$H$63 -> 16830 | I29: =Assumptions!$I$58*Assumptions!$I$63 -> 18060
B30: EUV High-NA revenue | E30: =Assumptions!$E$68*Assumptions!$E$73 -> 2760 | F30: =Assumptions!$F$68*Assumptions!$F$73 -> 3150 | G30: =Assumptions!$G$68*Assumptions!$G$73 -> 3550 | H30: =Assumptions!$H$68*Assumptions!$H$73 -> 4320 | I30: =Assumptions!$I$68*Assumptions!$I$73 -> 5110
B31: DUV immersion revenue | E31: =Assumptions!$E$78*Assumptions!$E$83 -> 10920 | F31: =Assumptions!$F$78*Assumptions!$F$83 -> 9240 | G31: =Assumptions!$G$78*Assumptions!$G$83 -> 7980 | H31: =Assumptions!$H$78*Assumptions!$H$83 -> 8500 | I31: =Assumptions!$I$78*Assumptions!$I$83 -> 9030
B32: Other DUV revenue | E32: =Assumptions!$C$47*(1+Assumptions!$E$88) -> 1648.82 | F32: =E32*(1+Assumptions!$F$88) -> 1483.938 | G32: =F32*(1+Assumptions!$G$88) -> 1335.5442 | H32: =G32*(1+Assumptions!$H$88) -> 1335.5442 | I32: =H32*(1+Assumptions!$I$88) -> 1335.5442
B33: Metrology & inspection revenue | E33: =Assumptions!$C$48*(1+Assumptions!$E$93) -> 907.06 | F33: =E33*(1+Assumptions!$F$93) -> 925.2012 | G33: =F33*(1+Assumptions!$G$93) -> 925.2012 | H33: =G33*(1+Assumptions!$H$93) -> 952.95724 | I33: =H33*(1+Assumptions!$I$93) -> 981.54595
B34: Installed base revenue | E34: =Assumptions!$C$49*(1+Assumptions!$E$98) -> 10650.9 | F34: =E34*(1+Assumptions!$F$98) -> 11076.936 | G34: =F34*(1+Assumptions!$G$98) -> 11298.475 | H34: =G34*(1+Assumptions!$H$98) -> 11750.414 | I34: =H34*(1+Assumptions!$I$98) -> 12220.43
B35: Revenue | E35: =SUM(E29:E34) -> 43014.78 | F35: =SUM(F29:F34) -> 42376.075 | G35: =SUM(G29:G34) -> 40209.22 | H35: =SUM(H29:H34) -> 43688.915 | I35: =SUM(I29:I34) -> 46737.52 | J35: =I35*(1+J36) -> 49533.54 | K35: =J35*(1+K36) -> 52003.673 | L35: =K35*(1+L36) -> 54079.24 | M35: =L35*(1+M36) -> 55699.236 | N35: =M35*(1+N36) -> 56813.221
B36: Growth % | E36: =E35/Historical!$H$6-1 -> 0.31675345 | F36: =F35/E35-1 -> -0.014848496 | G36: =G35/F35-1 -> -0.051133926 | H36: =H35/G35-1 -> 0.086539729 | I36: =I35/H35-1 -> 0.069779834 | J36: =$I36+($C$50-$I36)*(COLUMN()-COLUMN($I36))/Assumptions!$C$13 -> 0.059823868 | K36: =$I36+($C$50-$I36)*(COLUMN()-COLUMN($I36))/Assumptions!$C$13 -> 0.049867901 | L36: =$I36+($C$50-$I36)*(COLUMN()-COLUMN($I36))/Assumptions!$C$13 -> 0.039911934 | M36: =$I36+($C$50-$I36)*(COLUMN()-COLUMN($I36))/Assumptions!$C$13 -> 0.029955967 | N36: =$I36+($C$50-$I36)*(COLUMN()-COLUMN($I36))/Assumptions!$C$13 -> 0.02
B37: EBITDA | E37: =E35*Assumptions!$E$109 -> 16990.838 | F37: =F35*Assumptions!$F$109 -> 15255.387 | G37: =G35*Assumptions!$G$109 -> 13872.181 | H37: =H35*Assumptions!$H$109 -> 15509.565 | I37: =I35*Assumptions!$I$109 -> 17059.195 | J37: =J35*Assumptions!$I$109 -> 18079.742 | K37: =K35*Assumptions!$I$109 -> 18981.341 | L37: =L35*Assumptions!$I$109 -> 19738.923 | M37: =M35*Assumptions!$I$109 -> 20330.221 | N37: =N35*Assumptions!$I$109 -> 20736.826
B38: D&A | E38: =E35*Assumptions!$E$114 -> 1204.4138 | F38: =F35*Assumptions!$F$114 -> 1271.2823 | G38: =G35*Assumptions!$G$114 -> 1206.2766 | H38: =H35*Assumptions!$H$114 -> 1310.6675 | I38: =I35*Assumptions!$I$114 -> 1402.1256 | J38: =J35*Assumptions!$I$114 -> 1486.0062 | K38: =K35*Assumptions!$I$114 -> 1560.1102 | L38: =L35*Assumptions!$I$114 -> 1622.3772 | M38: =M35*Assumptions!$I$114 -> 1670.9771 | N38: =N35*Assumptions!$I$114 -> 1704.3966
B39: EBIT | E39: =E37-E38 -> 15786.424 | F39: =F37-F38 -> 13984.105 | G39: =G37-G38 -> 12665.904 | H39: =H37-H38 -> 14198.897 | I39: =I37-I38 -> 15657.069 | J39: =J37-J38 -> 16593.736 | K39: =K37-K38 -> 17421.231 | L39: =L37-L38 -> 18116.546 | ... N39: =N37-N38 -> 19032.429
B40: NOPAT | E40: =E39*(1-Assumptions!$E$129) -> 12944.868 | F40: =F39*(1-Assumptions!$F$129) -> 11466.966 | G40: =G39*(1-Assumptions!$G$129) -> 10386.042 | H40: =H39*(1-Assumptions!$H$129) -> 11643.096 | I40: =I39*(1-Assumptions!$I$129) -> 12838.797 | J40: =J39*(1-Assumptions!$I$129) -> 13606.863 | K40: =K39*(1-Assumptions!$I$129) -> 14285.409 | L40: =L39*(1-Assumptions!$I$129) -> 14855.567 | M40: =M39*(1-Assumptions!$I$129) -> 15300.58 | N40: =N39*(1-Assumptions!$I$129) -> 15606.592
B41: CapEx | E41: =E35*Assumptions!$E$119 -> 2580.8868 | F41: =F35*Assumptions!$F$119 -> 2754.4449 | G41: =G35*Assumptions!$G$119 -> 2613.5993 | H41: =H35*Assumptions!$H$119 -> 2621.3349 | I41: =I35*Assumptions!$I$119 -> 2804.2512 | J41: =J35*Assumptions!$I$119 -> 2972.0124 | K41: =K35*Assumptions!$I$119 -> 3120.2204 | L41: =L35*Assumptions!$I$119 -> 3244.7544 | M41: =M35*Assumptions!$I$119 -> 3341.9542 | N41: =N35*Assumptions!$I$119 -> 3408.7933
B42: NWC | E42: =E35*Assumptions!$E$124 -> -3441.1824 | F42: =F35*Assumptions!$F$124 -> -2542.5645 | G42: =G35*Assumptions!$G$124 -> -2412.5532 | H42: =H35*Assumptions!$H$124 -> -2621.3349 | I42: =I35*Assumptions!$I$124 -> -2804.2512 | J42: =J35*Assumptions!$I$124 -> -2972.0124 | K42: =K35*Assumptions!$I$124 -> -3120.2204 | L42: =L35*Assumptions!$I$124 -> -3244.7544 | M42: =M35*Assumptions!$I$124 -> -3341.9542 | N42: =N35*Assumptions!$I$124 -> -3408.7933
B43: Change in NWC | E43: =E42-Historical!$H$43 -> 5479.0176 | F43: =F42-E42 -> 898.61789 | G43: =G42-F42 -> 130.0113 | H43: =H42-G42 -> -208.7817 | I43: =I42-H42 -> -182.91632 | J43: =J42-I42 -> -167.76115 | K43: =K42-J42 -> -148.20802 | L43: =L42-K42 -> -124.53403 | M43: =M42-L42 -> -97.199756 | N43: =N42-M42 -> -66.839084
B44: Unlevered FCF | E44: =E40+E38-E41-E43 -> 6089.3773 | F44: =F40+F38-F41-F43 -> 9085.1854 | G44: =G40+G38-G41-G43 -> 8848.7075 | H44: =H40+H38-H41-H43 -> 10541.21 | I44: =I40+I38-I41-I43 -> 11619.588 | J44: =J40+J38-J41-J43 -> 12288.618 | K44: =K40+K38-K41-K43 -> 12873.507 | L44: =L40+L38-L41-L43 -> 13357.724 | ... N44: =N40+N38-N41-N43 -> 13969.034
B45: Cash flow to discount (FY26 net of H1 actual) | E45: =E44-Assumptions!$C$21 -> 7380.2773 | F45: =F44 -> 9085.1854 | G45: =G44 -> 8848.7075 | H45: =H44 -> 10541.21 | I45: =I44 -> 11619.588 | J45: =J44 -> 12288.618 | K45: =K44 -> 12873.507 | L45: =L44 -> 13357.724 | M45: =M44 -> 13726.803 | N45: =N44 -> 13969.034
B46: Discount factor | E46: =1/(1+$C$49)^DCF!E$7 -> 0.98909141 | F46: =1/(1+$C$49)^DCF!F$7 -> 0.93329195 | G46: =1/(1+$C$49)^DCF!G$7 -> 0.84938943 | H46: =1/(1+$C$49)^DCF!H$7 -> 0.7730297 | I46: =1/(1+$C$49)^DCF!I$7 -> 0.70353467 | J46: =1/(1+$C$49)^DCF!J$7 -> 0.64028722 | K46: =1/(1+$C$49)^DCF!K$7 -> 0.58272569 | L46: =1/(1+$C$49)^DCF!L$7 -> 0.53033891 | ... N46: =1/(1+$C$49)^DCF!N$7 -> 0.43927061
B47: PV of cash flow | E47: =E45*E46 -> 7299.7689 | F47: =F45*F46 -> 8479.1305 | G47: =G45*G46 -> 7515.9986 | H47: =H45*H46 -> 8148.6685 | I47: =I45*I46 -> 8174.7827 | J47: =J45*J46 -> 7868.2453 | K47: =K45*K46 -> 7501.7231 | L47: =L45*L46 -> 7084.1209 | ... N47: =N45*N46 -> 6136.1862
B49: WACC | C49: =WACC!$C$33+Assumptions!$E$144 -> 0.098779813
B50: Terminal growth | C50: =Assumptions!$E$134 -> 0.02
B51: Exit multiple | C51: =Assumptions!$E$139 -> 15
B52: Sum PV of cash flows | C52: =SUM(E47:N47) -> 74834.026
B53: PV terminal value (Gordon) | C53: =N44*(1+C50)/(C49-C50)/(1+C49)^DCF!$N$6 -> 75792.882
B54: PV terminal value (Exit) | C54: =N37*C51/(1+C49)^DCF!$N$6 -> 130349.79
B58: Base case build
B59: EUR m | E59: FY26E | F59: FY27E | G59: FY28E | H59: FY29E | I59: FY30E | J59: FY31E | K59: FY32E | L59: FY33E | M59: FY34E | N59: FY35E
B60: EUV low-NA revenue (units x ASP) | E60: =Assumptions!$E$59*Assumptions!$E$64 -> 16575 | F60: =Assumptions!$F$59*Assumptions!$F$64 -> 19500 | G60: =Assumptions!$G$59*Assumptions!$G$64 -> 21730 | H60: =Assumptions!$H$59*Assumptions!$H$64 -> 23220 | I60: =Assumptions!$I$59*Assumptions!$I$64 -> 24200
B61: EUV High-NA revenue | E61: =Assumptions!$E$69*Assumptions!$E$74 -> 2800 | F61: =Assumptions!$F$69*Assumptions!$F$74 -> 3600 | G61: =Assumptions!$G$69*Assumptions!$G$74 -> 5180 | H61: =Assumptions!$H$69*Assumptions!$H$74 -> 6840 | I61: =Assumptions!$I$69*Assumptions!$I$74 -> 8580
B62: DUV immersion revenue | E62: =Assumptions!$E$79*Assumptions!$E$84 -> 11180 | F62: =Assumptions!$F$79*Assumptions!$F$84 -> 12615 | G62: =Assumptions!$G$79*Assumptions!$G$84 -> 13350 | H62: =Assumptions!$H$79*Assumptions!$H$84 -> 13195 | I62: =Assumptions!$I$79*Assumptions!$I$84 -> 13020
B63: Other DUV revenue | E63: =Assumptions!$C$47*(1+Assumptions!$E$89) -> 1735.6 | F63: =E63*(1+Assumptions!$F$89) -> 1735.6 | G63: =F63*(1+Assumptions!$G$89) -> 1735.6 | H63: =G63*(1+Assumptions!$H$89) -> 1735.6 | I63: =H63*(1+Assumptions!$I$89) -> 1735.6
B64: Metrology & inspection revenue | E64: =Assumptions!$C$48*(1+Assumptions!$E$94) -> 989.52 | F64: =E64*(1+Assumptions!$F$94) -> 1088.472 | G64: =F64*(1+Assumptions!$G$94) -> 1175.5498 | H64: =G64*(1+Assumptions!$H$94) -> 1246.0827 | I64: =H64*(1+Assumptions!$I$94) -> 1308.3869
B65: Installed base revenue | E65: =Assumptions!$C$49*(1+Assumptions!$E$99) -> 10650.9 | F65: =E65*(1+Assumptions!$F$99) -> 11929.008 | G65: =F65*(1+Assumptions!$G$99) -> 13121.909 | H65: =G65*(1+Assumptions!$H$99) -> 14171.662 | I65: =H65*(1+Assumptions!$I$99) -> 15163.678
B66: Revenue | E66: =SUM(E60:E65) -> 43931.02 | F66: =SUM(F60:F65) -> 50468.08 | G66: =SUM(G60:G65) -> 56293.059 | H66: =SUM(H60:H65) -> 60408.344 | I66: =SUM(I60:I65) -> 64007.665 | J66: =I66*(1+J67) -> 67378.726 | K66: =J66*(1+K67) -> 70461.296 | L66: =K66*(1+L67) -> 73197.539 | M66: =L66*(1+M67) -> 75533.758 | N66: =M66*(1+N67) -> 77422.102
B67: Growth % | E67: =E66/Historical!$H$6-1 -> 0.34480107 | F67: =F66/E66-1 -> 0.14880283 | G67: =G66/F66-1 -> 0.11541906 | H67: =H66/G66-1 -> 0.073104674 | I67: =I66/H66-1 -> 0.059583167 | J67: =$I67+($C$81-$I67)*(COLUMN()-COLUMN($I67))/Assumptions!$C$13 -> 0.052666533 | K67: =$I67+($C$81-$I67)*(COLUMN()-COLUMN($I67))/Assumptions!$C$13 -> 0.0457499 | L67: =$I67+($C$81-$I67)*(COLUMN()-COLUMN($I67))/Assumptions!$C$13 -> 0.038833267 | M67: =$I67+($C$81-$I67)*(COLUMN()-COLUMN($I67))/Assumptions!$C$13 -> 0.031916633 | N67: =$I67+($C$81-$I67)*(COLUMN()-COLUMN($I67))/Assumptions!$C$13 -> 0.025
B68: EBITDA | E68: =E66*Assumptions!$E$110 -> 18011.718 | F68: =F66*Assumptions!$F$110 -> 21196.594 | G68: =G66*Assumptions!$G$110 -> 23924.55 | H68: =H66*Assumptions!$H$110 -> 25975.588 | I68: =I66*Assumptions!$I$110 -> 27523.296 | J68: =J66*Assumptions!$I$110 -> 28972.852 | K68: =K66*Assumptions!$I$110 -> 30298.357 | L68: =L66*Assumptions!$I$110 -> 31474.942 | M68: =M66*Assumptions!$I$110 -> 32479.516 | N68: =N66*Assumptions!$I$110 -> 33291.504
B69: D&A | E69: =E66*Assumptions!$E$115 -> 1230.0686 | F69: =F66*Assumptions!$F$115 -> 1413.1062 | G69: =G66*Assumptions!$G$115 -> 1576.2056 | H69: =H66*Assumptions!$H$115 -> 1691.4336 | I69: =I66*Assumptions!$I$115 -> 1792.2146 | J69: =J66*Assumptions!$I$115 -> 1886.6043 | K69: =K66*Assumptions!$I$115 -> 1972.9163 | L69: =L66*Assumptions!$I$115 -> 2049.5311 | M69: =M66*Assumptions!$I$115 -> 2114.9452 | N69: =N66*Assumptions!$I$115 -> 2167.8188
B70: EBIT | E70: =E68-E69 -> 16781.65 | F70: =F68-F69 -> 19783.487 | G70: =G68-G69 -> 22348.344 | H70: =H68-H69 -> 24284.154 | I70: =I68-I69 -> 25731.081 | J70: =J68-J69 -> 27086.248 | K70: =K68-K69 -> 28325.441 | L70: =L68-L69 -> 29425.411 | ... N70: =N68-N69 -> 31123.685
B71: NOPAT | E71: =E70*(1-Assumptions!$E$130) -> 13844.861 | F71: =F70*(1-Assumptions!$F$130) -> 16321.377 | G71: =G70*(1-Assumptions!$G$130) -> 18437.384 | H71: =H70*(1-Assumptions!$H$130) -> 20034.427 | I71: =I70*(1-Assumptions!$I$130) -> 21228.142 | J71: =J70*(1-Assumptions!$I$130) -> 22346.155 | K71: =K70*(1-Assumptions!$I$130) -> 23368.489 | L71: =L70*(1-Assumptions!$I$130) -> 24275.964 | M71: =M70*(1-Assumptions!$I$130) -> 25050.771 | N71: =N70*(1-Assumptions!$I$130) -> 25677.04
B72: CapEx | E72: =E66*Assumptions!$E$120 -> 2416.2061 | F72: =F66*Assumptions!$F$120 -> 2775.7444 | G72: =G66*Assumptions!$G$120 -> 3096.1182 | H72: =H66*Assumptions!$H$120 -> 3322.4589 | I72: =I66*Assumptions!$I$120 -> 3520.4216 | J72: =J66*Assumptions!$I$120 -> 3705.83 | K72: =K66*Assumptions!$I$120 -> 3875.3713 | L72: =L66*Assumptions!$I$120 -> 4025.8646 | M72: =M66*Assumptions!$I$120 -> 4154.3567 | N72: =N66*Assumptions!$I$120 -> 4258.2156
B73: NWC | E73: =E66*Assumptions!$E$125 -> -5271.7224 | F73: =F66*Assumptions!$F$125 -> -6056.1696 | G73: =G66*Assumptions!$G$125 -> -6755.167 | H73: =H66*Assumptions!$H$125 -> -7249.0013 | I73: =I66*Assumptions!$I$125 -> -7680.9198 | J73: =J66*Assumptions!$I$125 -> -8085.4472 | K73: =K66*Assumptions!$I$125 -> -8455.3556 | L73: =L66*Assumptions!$I$125 -> -8783.7047 | M73: =M66*Assumptions!$I$125 -> -9064.0509 | N73: =N66*Assumptions!$I$125 -> -9290.6522
B74: Change in NWC | E74: =E73-Historical!$H$43 -> 3648.4776 | F74: =F73-E73 -> -784.4472 | G74: =G73-F73 -> -698.99743 | H74: =H73-G73 -> -493.83428 | I74: =I73-H73 -> -431.91845 | J74: =J73-I73 -> -404.52742 | K74: =K73-J73 -> -369.9084 | L74: =L73-K73 -> -328.34908 | M74: =M73-L73 -> -280.34628 | N74: =N73-M73 -> -226.60127
B75: Unlevered FCF | E75: =E71+E69-E72-E74 -> 9010.2458 | F75: =F71+F69-F72-F74 -> 15743.186 | G75: =G71+G69-G72-G74 -> 17616.469 | H75: =H71+H69-H72-H74 -> 18897.236 | I75: =I71+I69-I72-I74 -> 19931.854 | J75: =J71+J69-J72-J74 -> 20931.456 | K75: =K71+K69-K72-K74 -> 21835.942 | L75: =L71+L69-L72-L74 -> 22627.979 | ... N75: =N71+N69-N72-N74 -> 23813.245
B76: Cash flow to discount (FY26 net of H1 actual) | E76: =E75-Assumptions!$C$21 -> 10301.146 | F76: =F75 -> 15743.186 | G76: =G75 -> 17616.469 | H76: =H75 -> 18897.236 | I76: =I75 -> 19931.854 | J76: =J75 -> 20931.456 | K76: =K75 -> 21835.942 | L76: =L75 -> 22627.979 | M76: =M75 -> 23291.706 | N76: =N75 -> 23813.245
B77: Discount factor | E77: =1/(1+$C$80)^DCF!E$7 -> 0.98961682 | F77: =1/(1+$C$80)^DCF!F$7 -> 0.93641676 | G77: =1/(1+$C$80)^DCF!G$7 -> 0.85612913 | H77: =1/(1+$C$80)^DCF!H$7 -> 0.7827253 | I77: =1/(1+$C$80)^DCF!I$7 -> 0.71561506 | J77: =1/(1+$C$80)^DCF!J$7 -> 0.65425879 | K77: =1/(1+$C$80)^DCF!K$7 -> 0.59816316 | L77: =1/(1+$C$80)^DCF!L$7 -> 0.54687713 | ... N77: =1/(1+$C$80)^DCF!N$7 -> 0.45711971
B78: PV of cash flow | E78: =E76*E77 -> 10194.187 | F78: =F76*F77 -> 14742.183 | G78: =G76*G77 -> 15081.972 | H78: =H76*H77 -> 14791.345 | I78: =I76*I77 -> 14263.534 | J78: =J76*J77 -> 13694.589 | K78: =K76*K77 -> 13061.456 | L78: =L76*L77 -> 12374.724 | ... N78: =N76*N77 -> 10885.504
B80: WACC | C80: =WACC!$C$33+Assumptions!$E$145 -> 0.093779813
B81: Terminal growth | C81: =Assumptions!$E$135 -> 0.025
B82: Exit multiple | C82: =Assumptions!$E$140 -> 20
B83: Sum PV of cash flows | C83: =SUM(E78:N78) -> 130735.08
B84: PV terminal value (Gordon) | C84: =N75*(1+C81)/(C80-C81)/(1+C80)^DCF!$N$6 -> 155112.38
B85: PV terminal value (Exit) | C85: =N68*C82/(1+C80)^DCF!$N$6 -> 291023.73
B89: Bull case build
B90: EUR m | E90: FY26E | F90: FY27E | G90: FY28E | H90: FY29E | I90: FY30E | J90: FY31E | K90: FY32E | L90: FY33E | M90: FY34E | N90: FY35E
B91: EUV low-NA revenue (units x ASP) | E91: =Assumptions!$E$60*Assumptions!$E$65 -> 16770 | F91: =Assumptions!$F$60*Assumptions!$F$65 -> 22008 | G91: =Assumptions!$G$60*Assumptions!$G$65 -> 27000 | H91: =Assumptions!$H$60*Assumptions!$H$65 -> 29362 | I91: =Assumptions!$I$60*Assumptions!$I$65 -> 31240
B92: EUV High-NA revenue | E92: =Assumptions!$E$70*Assumptions!$E$75 -> 3195 | F92: =Assumptions!$F$70*Assumptions!$F$75 -> 5180 | G92: =Assumptions!$G$70*Assumptions!$G$75 -> 7700 | H92: =Assumptions!$H$70*Assumptions!$H$75 -> 10270 | I92: =Assumptions!$I$70*Assumptions!$I$75 -> 12960
B93: DUV immersion revenue | E93: =Assumptions!$E$80*Assumptions!$E$85 -> 11440 | F93: =Assumptions!$F$80*Assumptions!$F$85 -> 14685 | G93: =Assumptions!$G$80*Assumptions!$G$85 -> 16560 | H93: =Assumptions!$H$80*Assumptions!$H$85 -> 16450 | I93: =Assumptions!$I$80*Assumptions!$I$85 -> 16320
B94: Other DUV revenue | E94: =Assumptions!$C$47*(1+Assumptions!$E$90) -> 1770.312 | F94: =E94*(1+Assumptions!$F$90) -> 1858.8276 | G94: =F94*(1+Assumptions!$G$90) -> 1858.8276 | H94: =G94*(1+Assumptions!$H$90) -> 1858.8276 | I94: =H94*(1+Assumptions!$I$90) -> 1858.8276
B95: Metrology & inspection revenue | E95: =Assumptions!$C$48*(1+Assumptions!$E$95) -> 1006.012 | F95: =E95*(1+Assumptions!$F$95) -> 1146.8537 | G95: =F95*(1+Assumptions!$G$95) -> 1284.4761 | H95: =G95*(1+Assumptions!$H$95) -> 1412.9237 | I95: =H95*(1+Assumptions!$I$95) -> 1525.9576
B96: Installed base revenue | E96: =Assumptions!$C$49*(1+Assumptions!$E$100) -> 10732.83 | F96: =E96*(1+Assumptions!$F$100) -> 12342.754 | G96: =F96*(1+Assumptions!$G$100) -> 13947.313 | H96: =G96*(1+Assumptions!$H$100) -> 15481.517 | I96: =H96*(1+Assumptions!$I$100) -> 17029.669
B97: Revenue | E97: =SUM(E91:E96) -> 44914.154 | F97: =SUM(F91:F96) -> 57221.436 | G97: =SUM(G91:G96) -> 68350.616 | H97: =SUM(H91:H96) -> 74835.268 | I97: =SUM(I91:I96) -> 80934.454 | J97: =I97*(1+J98) -> 86697.083 | K97: =J97*(1+K98) -> 91977.013 | L97: =K97*(1+L98) -> 96631.104 | M97: =L97*(1+M98) -> 100525.37 | N97: =M97*(1+N98) -> 103541.13
B98: Growth % | E98: =E97/Historical!$H$6-1 -> 0.37489643 | F98: =F97/E97-1 -> 0.27401789 | G98: =G97/F97-1 -> 0.19449321 | H98: =H97/G97-1 -> 0.094873351 | I98: =I97/H97-1 -> 0.081501486 | J98: =$I98+($C$112-$I98)*(COLUMN()-COLUMN($I98))/Assumptions!$C$13 -> 0.071201189 | K98: =$I98+($C$112-$I98)*(COLUMN()-COLUMN($I98))/Assumptions!$C$13 -> 0.060900892 | L98: =$I98+($C$112-$I98)*(COLUMN()-COLUMN($I98))/Assumptions!$C$13 -> 0.050600595 | M98: =$I98+($C$112-$I98)*(COLUMN()-COLUMN($I98))/Assumptions!$C$13 -> 0.040300297 | N98: =$I98+($C$112-$I98)*(COLUMN()-COLUMN($I98))/Assumptions!$C$13 -> 0.03
B99: EBITDA | E99: =E97*Assumptions!$E$111 -> 18639.374 | F99: =F97*Assumptions!$F$111 -> 24891.325 | G99: =G97*Assumptions!$G$111 -> 30757.777 | H99: =H97*Assumptions!$H$111 -> 34424.223 | I99: =I97*Assumptions!$I$111 -> 37634.521 | J99: =J97*Assumptions!$I$111 -> 40314.144 | K99: =K97*Assumptions!$I$111 -> 42769.311 | L99: =L97*Assumptions!$I$111 -> 44933.464 | M99: =M97*Assumptions!$I$111 -> 46744.296 | N99: =N97*Assumptions!$I$111 -> 48146.624
B100: D&A | E100: =E97*Assumptions!$E$116 -> 1257.5963 | F100: =F97*Assumptions!$F$116 -> 1544.9788 | G100: =G97*Assumptions!$G$116 -> 1845.4666 | H100: =H97*Assumptions!$H$116 -> 2020.5522 | I100: =I97*Assumptions!$I$116 -> 2185.2303 | J100: =J97*Assumptions!$I$116 -> 2340.8212 | K100: =K97*Assumptions!$I$116 -> 2483.3793 | L100: =L97*Assumptions!$I$116 -> 2609.0398 | M100: =M97*Assumptions!$I$116 -> 2714.1849 | N100: =N97*Assumptions!$I$116 -> 2795.6104
B101: EBIT | E101: =E99-E100 -> 17381.778 | F101: =F99-F100 -> 23346.346 | G101: =G99-G100 -> 28912.311 | H101: =H99-H100 -> 32403.671 | I101: =I99-I100 -> 35449.291 | J101: =J99-J100 -> 37973.322 | K101: =K99-K100 -> 40285.932 | L101: =L99-L100 -> 42324.424 | ... N101: =N99-N100 -> 45351.014
B102: NOPAT | E102: =E101*(1-Assumptions!$E$131) -> 14426.875 | F102: =F101*(1-Assumptions!$F$131) -> 19377.467 | G102: =G101*(1-Assumptions!$G$131) -> 23997.218 | H102: =H101*(1-Assumptions!$H$131) -> 26895.047 | I102: =I101*(1-Assumptions!$I$131) -> 29422.911 | J102: =J101*(1-Assumptions!$I$131) -> 31517.858 | K102: =K101*(1-Assumptions!$I$131) -> 33437.323 | L102: =L101*(1-Assumptions!$I$131) -> 35129.272 | M102: =M101*(1-Assumptions!$I$131) -> 36544.992 | N102: =N101*(1-Assumptions!$I$131) -> 37641.342
B103: CapEx | E103: =E97*Assumptions!$E$121 -> 2245.7077 | F103: =F97*Assumptions!$F$121 -> 2861.0718 | G103: =G97*Assumptions!$G$121 -> 3417.5308 | H103: =H97*Assumptions!$H$121 -> 3741.7634 | I103: =I97*Assumptions!$I$121 -> 4046.7227 | J103: =J97*Assumptions!$I$121 -> 4334.8542 | K103: =K97*Assumptions!$I$121 -> 4598.8506 | L103: =L97*Assumptions!$I$121 -> 4831.5552 | M103: =M97*Assumptions!$I$121 -> 5026.2683 | N103: =N97*Assumptions!$I$121 -> 5177.0564
B104: NWC | E104: =E97*Assumptions!$E$126 -> -6737.1231 | F104: =F97*Assumptions!$F$126 -> -8583.2154 | G104: =G97*Assumptions!$G$126 -> -10252.592 | H104: =H97*Assumptions!$H$126 -> -11225.29 | I104: =I97*Assumptions!$I$126 -> -12140.168 | J104: =J97*Assumptions!$I$126 -> -13004.562 | K104: =K97*Assumptions!$I$126 -> -13796.552 | L104: =L97*Assumptions!$I$126 -> -14494.666 | M104: =M97*Assumptions!$I$126 -> -15078.805 | N104: =N97*Assumptions!$I$126 -> -15531.169
B105: Change in NWC | E105: =E104-Historical!$H$43 -> 2183.0769 | F105: =F104-E104 -> -1846.0923 | G105: =G104-F104 -> -1669.3771 | H105: =H104-G104 -> -972.6978 | I105: =I104-H104 -> -914.87784 | J105: =J104-I104 -> -864.3944 | K105: =K104-J104 -> -791.98945 | L105: =L104-K104 -> -698.11373 | M105: =M104-L104 -> -584.13934 | N105: =N104-M104 -> -452.36415
B106: Unlevered FCF | E106: =E102+E100-E103-E105 -> 11255.687 | F106: =F102+F100-F103-F105 -> 19907.466 | G106: =G102+G100-G103-G105 -> 24094.531 | H106: =H102+H100-H103-H105 -> 26146.534 | I106: =I102+I100-I103-I105 -> 28476.297 | J106: =J102+J100-J103-J105 -> 30388.219 | K106: =K102+K100-K103-K105 -> 32113.841 | L106: =L102+L100-L103-L105 -> 33604.87 | ... N106: =N102+N100-N103-N105 -> 35712.26
B107: Cash flow to discount (FY26 net of H1 actual) | E107: =E106-Assumptions!$C$21 -> 12546.587 | F107: =F106 -> 19907.466 | G107: =G106 -> 24094.531 | H107: =H106 -> 26146.534 | I107: =I106 -> 28476.297 | J107: =J106 -> 30388.219 | K107: =K106 -> 32113.841 | L107: =L106 -> 33604.87 | M107: =M106 -> 34817.048 | N107: =N106 -> 35712.26
B108: Discount factor | E108: =1/(1+$C$111)^DCF!E$7 -> 0.99014491 | F108: =1/(1+$C$111)^DCF!F$7 -> 0.93956643 | G108: =1/(1+$C$111)^DCF!G$7 -> 0.86295357 | H108: =1/(1+$C$111)^DCF!H$7 -> 0.79258778 | I108: =1/(1+$C$111)^DCF!I$7 -> 0.72795966 | J108: =1/(1+$C$111)^DCF!J$7 -> 0.66860135 | K108: =1/(1+$C$111)^DCF!K$7 -> 0.61408316 | L108: =1/(1+$C$111)^DCF!L$7 -> 0.56401042 | ... N108: =1/(1+$C$111)^DCF!N$7 -> 0.47578091
B109: PV of cash flow | E109: =E107*E108 -> 12422.939 | F109: =F107*F108 -> 18704.387 | G109: =G107*G108 -> 20792.461 | H109: =H107*H108 -> 20723.423 | I109: =I107*I108 -> 20729.595 | J109: =J107*J108 -> 20317.604 | K109: =K107*K108 -> 19720.569 | L109: =L107*L108 -> 18953.497 | ... N109: =N107*N108 -> 16991.211
B111: WACC | C111: =WACC!$C$33+Assumptions!$E$146 -> 0.088779813
B112: Terminal growth | C112: =Assumptions!$E$136 -> 0.03
...

Sheet Comps
B1: Trading Comparables
B2: Semiconductor equipment peers, 7-8 Oct 2026 [S12]. EV and EBITDA in billions of local currency; multiples are currency-neutral.
B4: Company | C4: Ticker | D4: Ccy | E4: EV (bn) | F4: EBITDA TTM (bn) | G4: EV / EBITDA TTM | H4: Forward P/E | I4: Gross margin | J4: Op. margin
B5: Applied Materials | C5: AMAT | D5: USD | E5: 411.3 | F5: 10.16 | G5: =E5/F5 -> 40.482283 | H5: 29.56 | I5: 0.494 | J5: 0.3122
B6: Lam Research | C6: LRCX | D6: USD | E6: 410.9 | F6: 8.64 | G6: =E6/F6 -> 47.55787 | H6: 34.78 | I6: 0.5047 | J6: 0.3529
B7: KLA | C7: KLAC | D7: USD | E7: 258.11 | F7: 6.05 | G7: =E7/F7 -> 42.66281 | H7: 36.2 | I7: 0.613 | J7: 0.4169
B8: Tokyo Electron | C8: 8035.T | D8: JPY | E8: 27300 | F8: 778.34 | G8: =E8/F8 -> 35.074646 | H8: 33.33 | I8: 0.4556 | J8: 0.2634
B10: Peer low | G10: =MIN(G5:G8) -> 35.074646 | H10: =MIN(H5:H8) -> 29.56 | I10: =MIN(I5:I8) -> 0.4556 | J10: =MIN(J5:J8) -> 0.2634
B11: Peer median | G11: =MEDIAN(G5:G8) -> 41.572547 | H11: =MEDIAN(H5:H8) -> 34.055 | I11: =MEDIAN(I5:I8) -> 0.49935 | J11: =MEDIAN(J5:J8) -> 0.33255
B12: Peer mean | G12: =AVERAGE(G5:G8) -> 41.444402 | H12: =AVERAGE(H5:H8) -> 33.4675 | I12: =AVERAGE(I5:I8) -> 0.516825 | J12: =AVERAGE(J5:J8) -> 0.33635
B13: Peer high | G13: =MAX(G5:G8) -> 47.55787 | H13: =MAX(H5:H8) -> 36.2 | I13: =MAX(I5:I8) -> 0.613 | J13: =MAX(J5:J8) -> 0.4169
B15: ASML (for reference) | C15: ASML | D15: EUR | E15: 607 | F15: 13.49 | G15: =E15/F15 -> 44.996294 | H15: 32.93 | I15: 0.5273 | J15: 0.3542
B16: ASML 5-yr average year-end EV/EBITDA (FY21-25) | G16: =Historical!$C$63 -> 29.847636
B18: Implied ASML value from peer EV / LTM EBITDA
B19: ASML LTM EBITDA to 28 Jun 2026 (EUR m) | E19: =Historical!H33+Assumptions!$C$26+Assumptions!$C$27-Assumptions!$C$28-Assumptions!$C$29 -> 13549.3 | K19: FY25 EBITDA + H1-26 - H1-25 (EBIT + D&A)
E20: Low | F20: Median | G20: High
B21: Peer EV / EBITDA multiple | E21: =G10 -> 35.074646 | F21: =G11 -> 41.572547 | G21: =G13 -> 47.55787
B22: Implied enterprise value (EUR m) | E22: =E21*$E$19 -> 475236.9 | F22: =F21*$E$19 -> 563278.91 | G22: =G21*$E$19 -> 644375.85
B23: Equity value (+ cash - debt + investments) | E23: =E22+(DCF!$C$30-DCF!$C$31+DCF!$C$32) -> 481431.4 | F23: =F22+(DCF!$C$30-DCF!$C$31+DCF!$C$32) -> 569473.41 | G23: =G22+(DCF!$C$30-DCF!$C$31+DCF!$C$32) -> 650570.35
B24: Implied share price (EUR) | E24: =E23/DCF!$C$34 -> 1250.7961 | F24: =F23/DCF!$C$34 -> 1479.536 | G24: =G23/DCF!$C$34 -> 1690.2321
B25: Upside / (downside) | E25: =E24/Assumptions!$C$16-1 -> -0.22378301 | F25: =F24/Assumptions!$C$16-1 -> -0.081831947 | G25: =G24/Assumptions!$C$16-1 -> 0.048921525
B27: Reading: peers trade on peak-cycle trailing EBITDA. On these multiples ASML looks fairly priced relative to the sector; the DCF asks whether the sector itself is priced for growth that will last.

Sheet Dashboard
B1: ASML Holding N.V. | Valuation Dashboard
B2: Live summary of the model. Change inputs on Assumptions; everything here updates.
B4: Valuation | E4: Model drivers
B5: Scenario shown: | C5: =Assumptions!$C$9 -> Base
B6: Current share price | C6: =Assumptions!$C$16 -> 1611.4 | E6: Enterprise value (blended, EUR m) | F6: =DCF!$E$28 -> 353803.13
B7: DCF price, blended (headline) | C7: =DCF!$E$35 -> 935.30172 | E7: Equity value (blended, EUR m) | F7: =DCF!$E$33 -> 359997.63
B8: DCF price, Gordon Growth | C8: =DCF!$C$35 -> 758.7476 | E8: WACC | F8: =WACC!$C$35 -> 0.093779813
B9: DCF price, Exit Multiple | C9: =DCF!$D$35 -> 1111.8558 | E9: Terminal growth rate | F9: =Assumptions!$E$137 -> 0.025
B10: Potential upside / (downside) | C10: =DCF!$E$37 -> -0.41957198 | E10: Exit EV/EBITDA (FY35) | F10: =Assumptions!$E$142 -> 20
B11: Bear case price (blended) | C11: =Scenarios!$C$18 -> 478.3057 | E11: 5-yr revenue CAGR FY25-30 | F11: =Forecast!$C$39 -> 0.143994
B12: Base case price (blended) | C12: =Scenarios!$D$18 -> 935.30172 | E12: Average EBITDA margin FY26-30 | F12: =Forecast!$C$40 -> 0.423
B13: Bull case price (blended) | C13: =Scenarios!$E$18 -> 1586.5797 | E13: Reverse DCF: exit multiple needed | F13: =DCF!$D$39 -> 33.213668
B14: Trading comps price (peer median) | C14: =Comps!$F$24 -> 1479.536 | E14: Model checks | F14: =Checks!$C$4 -> ALL PASS
B16: Verdict | C16: =IF(DCF!$E$37>0.15,"Undervalued",IF(DCF!$E$37<-0.15,"Overvalued","Fairly valued")) -> Overvalued
B17: Verdict band: more than +/-15% from market price (blended DCF)
B19: Chart data (linked)
B20: Year | C20: FY21A | D20: FY22A | E20: FY23A | F20: FY24A | G20: FY25A | H20: FY26E | I20: FY27E | J20: FY28E | K20: FY29E | L20: FY30E | M20: FY31E | N20: FY32E | O20: FY33E | P20: FY34E | Q20: FY35E
B21: Revenue (EUR m) | C21: =Forecast!C8 -> 18611 | D21: =Forecast!D8 -> 21173.4 | E21: =Forecast!E8 -> 27558.5 | F21: =Forecast!F8 -> 28262.9 | G21: =Forecast!G8 -> 32667.3 | H21: =Forecast!H8 -> 43931.02 | I21: =Forecast!I8 -> 50468.08 | J21: =Forecast!J8 -> 56293.059 | ... Q21: =Forecast!Q8 -> 77422.102
B22: EBITDA margin | C22: =Forecast!C15 -> 0.38800172 | D22: =Forecast!D15 -> 0.3345849 | E22: =Forecast!E15 -> 0.35495764 | F22: =Forecast!F15 -> 0.35174027 | G22: =Forecast!G15 -> 0.37735901 | H22: =Forecast!H15 -> 0.41 | I22: =Forecast!I15 -> 0.42 | J22: =Forecast!J15 -> 0.425 | ... Q22: =Forecast!Q15 -> 0.43
B23: Unlevered FCF (EUR m) | C23: =Forecast!C34 -> 10017.706 | D23: =Forecast!D34 -> 7192.0997 | E23: =Forecast!E34 -> 3054.5124 | F23: =Forecast!F34 -> 9135.28 | G23: =Forecast!G34 -> 10950.982 | H23: =Forecast!H34 -> 9010.2458 | I23: =Forecast!I34 -> 15743.186 | J23: =Forecast!J34 -> 17616.469 | ... Q23: =Forecast!Q34 -> 23813.245
B25: Revenue build (EUR m) | C25: FY25A | D25: FY26E | E25: FY27E | F25: FY28E | G25: FY29E | H25: FY30E
B26: EUV (low-NA + High-NA) | C26: ='Revenue Build'!C10+'Revenue Build'!C15 -> 11602.7 | D26: ='Revenue Build'!D10+'Revenue Build'!D15 -> 19375 | E26: ='Revenue Build'!E10+'Revenue Build'!E15 -> 23100 | F26: ='Revenue Build'!F10+'Revenue Build'!F15 -> 26910 | G26: ='Revenue Build'!G10+'Revenue Build'!G15 -> 30060 | H26: ='Revenue Build'!H10+'Revenue Build'!H15 -> 32780
B27: DUV (immersion + other) | C27: ='Revenue Build'!C20+'Revenue Build'!C24 -> 12047 | D27: ='Revenue Build'!D20+'Revenue Build'!D24 -> 12915.6 | E27: ='Revenue Build'!E20+'Revenue Build'!E24 -> 14350.6 | F27: ='Revenue Build'!F20+'Revenue Build'!F24 -> 15085.6 | G27: ='Revenue Build'!G20+'Revenue Build'!G24 -> 14930.6 | H27: ='Revenue Build'!H20+'Revenue Build'!H24 -> 14755.6
B28: Metrology & inspection | C28: ='Revenue Build'!C26 -> 824.6 | D28: ='Revenue Build'!D26 -> 989.52 | E28: ='Revenue Build'!E26 -> 1088.472 | F28: ='Revenue Build'!F26 -> 1175.5498 | G28: ='Revenue Build'!G26 -> 1246.0827 | H28: ='Revenue Build'!H26 -> 1308.3869
B29: Installed base | C29: ='Revenue Build'!C28 -> 8193 | D29: ='Revenue Build'!D28 -> 10650.9 | E29: ='Revenue Build'!E28 -> 11929.008 | F29: ='Revenue Build'!F28 -> 13121.909 | G29: ='Revenue Build'!G28 -> 14171.662 | H29: ='Revenue Build'!H28 -> 15163.678
B32: Football field (EUR / share) | C32: Low | E32: Range (high - low) | F32: High
B33: 52-week trading range | C33: =Assumptions!$C$22 -> 813.9 | E33: =F33-C33 -> 907.5 | F33: =Assumptions!$C$23 -> 1721.4
B34: Trading comps (peer EV/EBITDA) | C34: =Comps!$E$24 -> 1250.7961 | E34: =F34-C34 -> 439.43609 | F34: =Comps!$G$24 -> 1690.2321
B35: DCF, Exit Multiple (WACC +/-0.5%, +/-2x) | C35: =MIN(Sensitivity!$F$23:$H$25) -> 1001.8724 | E35: =F35-C35 -> 228.04735 | F35: =MAX(Sensitivity!$F$23:$H$25) -> 1229.9197
B36: DCF, Gordon Growth (WACC +/-0.5%, g +/-0.25%) | C36: =MIN(Sensitivity!$F$10:$H$12) -> 696.97815 | E36: =F36-C36 -> 138.30228 | F36: =MAX(Sensitivity!$F$10:$H$12) -> 835.28043
B37: Scenarios (Bear to Bull, blended) | C37: =Scenarios!$C$18 -> 478.3057 | E37: =F37-C37 -> 1108.274 | F37: =Scenarios!$E$18 -> 1586.5797
B39: Current market price | C39: =Assumptions!$C$16 -> 1611.4

Sheet Checks
B1: Model Integrity Checks
B2: Automatic tests. PASS = test met; CHECK = review the inputs. INFO = reported for judgement, not a pass/fail test.
B4: Overall status | C4: =IF(COUNTIF(D7:D36,"CHECK")=0,"ALL PASS","REVIEW") -> ALL PASS
B6: Test | C6: Value | D6: Status | E6: What it guards against
B7: WACC > terminal growth (live) | C7: =WACC!$C$35-Assumptions!$E$137 -> 0.068779813 | D7: =IF(C7>0,"PASS","CHECK") -> PASS | E7: Gordon formula explodes / turns negative if g >= WACC
B8: WACC > terminal growth in every scenario | C8: =MIN(Scenarios!$C$9-Scenarios!$C$10,Scenarios!$D$9-Scenarios!$D$10,Scenarios!$E$9-Scenarios!$E$10) -> 0.058779813 | D8: =IF(C8>0,"PASS","CHECK") -> PASS | E8: Same test for Bear / Base / Bull
B9: Revenue build FY26 within 2026 guidance (EUR 43-45bn) | C9: ='Revenue Build'!$D$32 -> 43931.02 | D9: =IF(AND(C9>=Assumptions!$C$53,C9<=Assumptions!$C$54),"PASS","CHECK") -> PASS | E9: Forecast anchored to company guidance
B10: Low-NA EUV units within stated capacity FY26-28 | C10: =MAX('Revenue Build'!D39:F39) -> 1 | D10: =IF(C10<=1,"PASS","CHECK") -> PASS | E10: Units cannot exceed announced capacity
B11: DUV immersion units within stated capacity FY26-28 | C11: =MAX('Revenue Build'!D41:F41) -> 1 | D11: =IF(C11<=1,"PASS","CHECK") -> PASS
B12: Revenue build total = Forecast revenue (FY26-30) | C12: =SUMPRODUCT(ABS('Revenue Build'!D32:H32-Forecast!H8:L8)) -> 0 | D12: =IF(C12<0.01,"PASS","CHECK") -> PASS | E12: Linkage integrity
B13: Fade ends at terminal growth (FY35 growth = g) | C13: =Forecast!Q9-Assumptions!$E$137 -> 0 | D13: =IF(ABS(C13)<0.000001,"PASS","CHECK") -> PASS | E13: No growth cliff between the fade period and the perpetuity
B14: EV reconciles: EV - (sum PV FCF + PV TV), Gordon | C14: =DCF!$C$28-(SUMPRODUCT(DCF!E11:N11,DCF!E13:N13)+DCF!C26) -> 0 | D14: =IF(ABS(C14)<0.01,"PASS","CHECK") -> PASS | E14: Independent recomputation of EV
B15: EV reconciles, Exit | C15: =DCF!$D$28-(SUMPRODUCT(DCF!E11:N11,DCF!E13:N13)+DCF!D26) -> 0 | D15: =IF(ABS(C15)<0.01,"PASS","CHECK") -> PASS
B16: Equity bridge: equity - (EV + cash - debt + investments) | C16: =DCF!$C$33-(DCF!$C$28+Assumptions!$C$18-Assumptions!$C$19+Assumptions!$C$20) -> 0 | D16: =IF(ABS(C16)<0.01,"PASS","CHECK") -> PASS | E16: Bridge items applied once with correct signs
B17: Forecast UFCF = NOPAT + D&A - CapEx - change in NWC (FY26-35) | C17: =SUMPRODUCT(ABS(Forecast!H34:Q34-(Forecast!H25:Q25+Forecast!H17:Q17-Forecast!H27:Q27-Forecast!H32:Q32))) -> 0 | D17: =IF(C17<0.01,"PASS","CHECK") -> PASS | E17: Formula consistency across forecast years
B18: Historical gross profit ties to sales - COGS | C18: =SUMPRODUCT(ABS(Historical!D54:H54)) -> 3.6379788e-12 | D18: =IF(C18<0.5,"PASS","CHECK") -> PASS | E18: Data entry errors in reported figures
B19: Forecast EBITDA margin < gross margin (all years) | C19: =SUMPRODUCT(--(Forecast!H15:Q15>=Forecast!H12:Q12)) -> 0 | D19: =IF(C19=0,"PASS","CHECK") -> PASS | E19: Opex cannot be negative
B20: EBITDA margins between 25% and 55% (economic realism) | C20: =SUMPRODUCT((Forecast!H15:Q15<0.25)+(Forecast!H15:Q15>0.55)) -> 0 | D20: =IF(C20=0,"PASS","CHECK") -> PASS | E20: Outside ASML's FY21-25 range of 34-39% plus headroom
B21: Implied opex % within 10-25% of revenue | C21: =SUMPRODUCT((Forecast!H37:Q37<0.10)+(Forecast!H37:Q37>0.25)) -> 0 | D21: =IF(C21=0,"PASS","CHECK") -> PASS | E21: Gross margin and EBITDA margin assumptions are mutually consistent
B22: Terminal value share of EV (Gordon) below 75% | C22: =DCF!C29 -> 0.5426404 | D22: =IF(C22<0.75,"PASS","CHECK") -> PASS | E22: The 10-year horizon keeps value from being dominated by the perpetuity
B23: Terminal value share of EV (Exit) | C23: =DCF!D29 -> 0.69002408 | D23: ="INFO" -> INFO | E23: Higher by construction; see sensitivity
B24: Capital structure weights sum to 100% | C24: =WACC!C29+WACC!C30-1 -> 0 | D24: =IF(ABS(C24)<0.000001,"PASS","CHECK") -> PASS
B25: Sensitivity table 1 centre = DCF Gordon price | C25: =Sensitivity!$G$11-DCF!$C$35 -> 0 | D25: =IF(ABS(C25)<0.01,"PASS","CHECK") -> PASS | E25: Closed-form grid formula matches the full DCF
B26: Sensitivity table 2 centre = DCF Exit price | C26: =Sensitivity!$G$24-DCF!$D$35 -> 0 | D26: =IF(ABS(C26)<0.01,"PASS","CHECK") -> PASS
B27: Sensitivity table 3 centre = DCF blended price | C27: =Sensitivity!$G$38-DCF!$E$35 -> 0 | D27: =IF(ABS(C27)<0.01,"PASS","CHECK") -> PASS
B28: Selected scenario on Scenarios tab = main DCF (blended price) | C28: =CHOOSE(Assumptions!$C$8,Scenarios!$C$18,Scenarios!$D$18,Scenarios!$E$18)-DCF!$E$35 -> -1.1368684e-13 | D28: =IF(ABS(C28)<0.01,"PASS","CHECK") -> PASS | E28: Scenario engine and main model use identical logic
B29: Scenario ordering: Bear < Base < Bull | C29: =AND(Scenarios!$C$18<Scenarios!$D$18,Scenarios!$D$18<Scenarios!$E$18) -> TRUE | D29: =IF(C29,"PASS","CHECK") -> PASS | E29: Output moves logically with assumptions
B30: Price falls when WACC rises (sensitivity row monotonic) | C30: =AND(Sensitivity!C11>Sensitivity!G11,Sensitivity!G11>Sensitivity!K11) -> TRUE | D30: =IF(C30,"PASS","CHECK") -> PASS | E30: Direction of WACC effect
B31: Price rises with terminal growth (sensitivity column monotonic) | C31: =AND(Sensitivity!G7<Sensitivity!G11,Sensitivity!G11<Sensitivity!G15) -> TRUE | D31: =IF(C31,"PASS","CHECK") -> PASS | E31: Direction of g effect
B32: No double counting: FY26 cash flow excludes H1 actual (stub) | C32: =DCF!E11-(DCF!E9-Assumptions!$C$21) -> 0 | D32: =IF(ABS(C32)<0.01,"PASS","CHECK") -> PASS | E32: H1-26 cash flows sit in the 28-Jun cash balance
B33: Balance-sheet date precedes valuation date | C33: =Assumptions!$C$5-Assumptions!$C$6 -> 101 | D33: =IF(C33>0,"PASS","CHECK") -> PASS
B34: Exit multiple below ASML's 5-yr average and peer median | C34: =Assumptions!$E$142 -> 20 | D34: =IF(AND(C34<=Historical!$C$63,C34<=Comps!$G$11),"PASS","CHECK") -> PASS | E34: Terminal multiple for a mature 2035 business should not exceed today's growth multiples
B35: Gordon implied exit multiple (for judgement) | C35: =DCF!C38 -> 10.659775 | D35: ="INFO" -> INFO | E35: Compare with the exit multiple assumption
B36: Exit-method implied perpetual growth (for judgement) | C36: =DCF!D38 -> 0.056011817 | D36: =IF(C36<WACC!$C$35,"INFO","CHECK") -> INFO | E36: Above long-run GDP growth = exit multiple embeds growth beyond FY35
