Workbook

Sheet Cover
B3: ASML Holding N.V.
B5: Discounted Cash Flow Valuation
B8: Ticker | C8: ASML (Euronext Amsterdam) / ASML (Nasdaq)
B9: Valuation date | C9: =Assumptions!$C$5
B10: Currency | C10: EUR, millions unless stated
B11: Analyst | C11: Ates Parilti
B12: Active scenario | C12: =Assumptions!$C$9
B13: DCF price (blended) | C13: =DCF!$E$33
B14: Current share price | C14: =Assumptions!$C$14
B15: Upside / (downside) | C15: =DCF!$E$35
B16: Model checks | C16: =Checks!$C$4
B18: Company
C19: ASML designs and builds the lithography systems that print circuit patterns onto silicon wafers. It is the sole supplier of EUV lithography, which every leading-edge logic and DRAM fab depends on. Revenue comes from system sales (EUV, DUV, metrology & inspection) and a growing, recurring installed-base business (service and upgrades).
B24: How to use
B25: 1. Change inputs only on Assumptions (blue on yellow). The scenario selector switches Bear / Base / Bull.
B26: 2. Forecast, WACC, DCF, Sensitivity, Scenarios and Dashboard are 100% formulas.
B27: 3. Checks tests the model; the status is shown above and on the Dashboard.
B28: Colour code: blue = hard-coded input; black = formula; green = link to another sheet; grey header = historical; blue header = forecast.
B30: Sources
B31: [S1] ASML Form 20-F / Annual Report 2025 (US GAAP), filed 25 Feb 2026, incl. XBRL data | C31: https://www.sec.gov/Archives/edgar/data/937966/000162828026011378/asml-20251231.htm
B32: [S2] SEC EDGAR XBRL company facts for ASML (20-F filings FY2020-FY2025) | C32: https://data.sec.gov/api/xbrl/companyfacts/CIK0000937966.json
B33: [S3] ASML Financial Statements US GAAP Q4 2025 (Form 6-K, 28 Jan 2026) | C33: https://www.sec.gov/Archives/edgar/data/937966/000162828026003701/
B34: [S4] ASML Q2 2026 press release and Financial Statements US GAAP (Form 6-K, 15 Jul 2026) | C34: https://www.sec.gov/Archives/edgar/data/0000937966/000162828026048235/pressreleasefinancialresul.htm
B35: [S5] ASML (Euronext Amsterdam: ASML) closing price 7 Oct 2026, via stockanalysis.com | C35: https://stockanalysis.com/quote/ams/ASML/history/
B36: [S6] Germany 10Y Bund yield, 7 Oct 2026, Trading Economics | C36: https://tradingeconomics.com/germany/government-bond-yield
B37: [S7] A. Damodaran, Country risk premiums (Jan 2026): Netherlands total ERP 4.23%, CRP 0% | C37: https://pages.stern.nyu.edu/~adamodar/New_Home_Page/datafile/ctryprem.html
B38: [S8] A. Damodaran, Betas by sector (Jan 2026): Semiconductor Equip unlevered beta corrected for cash 1.39 | C38: https://pages.stern.nyu.edu/~adamodar/New_Home_Page/datafile/Betas.html
B39: [S9] Yahoo Finance, ASML Beta (5Y monthly) 1.12 | C39: https://finance.yahoo.com/quote/ASML/
B40: [S10] ASML 2024 Investor Day: 2030 revenue opportunity EUR 44-60bn, gross margin 56-60% | C40: https://investor.asml.com/news-releases/news-release-details/asml-provides-updated-view-market-opportunities-2024-investor-day-meeting
B41: [S11] ASML Q4 2025 press release: 2025 sales EUR 32.7bn, backlog EUR 38.8bn | C41: https://www.asml.com/en/news/press-releases/2026/q4-2025-financial-results
B43: For educational purposes only. Not investment advice.

Sheet Assumptions
B1: Assumptions
B2: All model inputs live here. Blue on yellow = hard-coded input; black = formula. EUR millions unless stated.
B4: General
B5: Valuation date | C5: 46302 | D5: date | K5: Pricing date for market data
B6: Latest balance sheet date | C6: 46201 | D6: date | K6: Q2 2026 balance sheet (S4); cash flows after this date are valued
B7: FY2026 year end | C7: 46387 | D7: date | K7: ASML fiscal year = calendar year
B8: Scenario selector (1 Bear, 2 Base, 3 Bull) | C8: 2 | D8: # | K8: Drives the live model (Forecast, DCF, Sensitivity)
B9: Active scenario | C9: =CHOOSE(Assumptions!$C$8,"Bear","Base","Bull")
B10: Mid-year discounting (1 = on, 0 = off) | C10: 1 | K10: Cash flows assumed to arrive evenly through each year (standard banking convention)
B11: Weight of Gordon Growth in blended price | C11: 0.5 | K11: Blended DCF price = weight x Gordon + (1 - weight) x Exit Multiple
B13: Market data & latest balance sheet | J13: Type | K13: Source / note
B14: Current share price (EUR) | C14: 1611.4 | J14: MARKET | K14: [S5] Closing price Euronext Amsterdam, 7 Oct 2026 (EUR)
B15: Diluted shares outstanding (m) | C15: 384.9 | J15: REPORTED | K15: [S4] Diluted weighted avg. shares Q2 2026 (m)
B16: Cash & short-term investments | C16: 7581.5 | J16: REPORTED | K16: [S4] Cash 6,671.9 + short-term investments 909.6 at 28 Jun 2026
B17: Total debt (bonds + commercial paper) | C17: 3697.7 | J17: DERIVED | K17: [S1/S4] FY25 borrowings 4,390.9 (LT 2,709.0 + current 1,681.9 incl. ECP) less H1-26 repayments 693.2
B18: Non-operating investments | C18: 2310.7 | J18: REPORTED | K18: [S4] Equity investments 1,324.9 + equity-method investments 985.8 at 28 Jun 2026
B19: H1-2026 actual unlevered FCF | C19: -1290.9 | J19: DERIVED | K19: [S4] H1-26 CFO (482.5) - PP&E capex 701.8 - intangibles 106.6; already reflected in 28 Jun cash
B21: Cost of capital inputs
B22: Risk-free rate (10Y Bund) | C22: 0.0351 | J22: MARKET | K22: [S6] German 10Y Bund yield 7 Oct 2026; EUR risk-free matching EUR cash flows
B23: Equity risk premium | C23: 0.0423 | J23: MARKET | K23: [S7] Damodaran implied mature-market ERP, Netherlands CRP = 0
B24: Regression beta (5Y monthly) | C24: 1.12 | J24: MARKET | K24: [S9] Regression beta, 5Y monthly
B25: Industry unlevered beta (semi equipment) | C25: 1.39 | J25: MARKET | K25: [S8] Semiconductor equipment unlevered beta, cash-corrected
B26: Weight on regression beta | C26: 0.5 | J26: ASSUMPTION | K26: Equal weight regression vs bottom-up: regression is noisy, industry beta captures cyclicality
B27: Credit spread over risk-free (A1/A+) | C27: 0.006 | J27: ASSUMPTION | K27: [S1] Credit spread for A1/A+ (Moody's/Fitch) EUR corporate issuer
B28: Marginal tax rate (debt tax shield) | C28: 0.258 | J28: ASSUMPTION | K28: Dutch statutory CIT rate 25.8% for the interest tax shield
B30: Scenario drivers (FY2026E - FY2030E)
B31: Driver | C31: Case | D31: Unit | E31: FY26E | F31: FY27E | G31: FY28E | H31: FY29E | I31: FY30E | J31: Average | K31: Rationale
B32: Revenue growth | C32: Bear | D32: % | E32: 0.3163 | F32: 0.04 | G32: -0.03 | H32: 0.04 | I32: 0.04 | J32: =AVERAGE(E32:I32) | K32: FY26 = 2026 guidance EUR 43-45bn (Q2-26). FY27 reflects record backlog and AI-driven capacity adds, then growth fades to ~5% as the cycle normalises. Base FY30 revenue sits just above the 2030 range of EUR 44-60bn because FY26 already exceeds its low end.
C33: Base | D33: % | E33: 0.3469 | F33: 0.16 | G33: 0.1 | H33: 0.07 | I33: 0.05 | J33: =AVERAGE(E33:I33)
C34: Bull | D34: % | E34: 0.3775 | F34: 0.24 | G34: 0.15 | H34: 0.1 | I34: 0.08 | J34: =AVERAGE(E34:I34)
C35: Live ► | D35: % | E35: =CHOOSE(Assumptions!$C$8,E32,E33,E34) | F35: =CHOOSE(Assumptions!$C$8,F32,F33,F34) | G35: =CHOOSE(Assumptions!$C$8,G32,G33,G34) | H35: =CHOOSE(Assumptions!$C$8,H32,H33,H34) | I35: =CHOOSE(Assumptions!$C$8,I32,I33,I34) | J35: =AVERAGE(E35:I35)
B37: Gross margin | C37: Bear | D37: % | E37: 0.54 | F37: 0.51 | G37: 0.5 | H37: 0.51 | I37: 0.52 | J37: =AVERAGE(E37:I37) | K37: FY26 guide 54-56%. Base trends to 57%, inside ASML's 2030 target band of 56-60% (EUV mix, High-NA maturing, services).
C38: Base | D38: % | E38: 0.55 | F38: 0.56 | G38: 0.565 | H38: 0.57 | I38: 0.57 | J38: =AVERAGE(E38:I38)
C39: Bull | D39: % | E39: 0.555 | F39: 0.57 | G39: 0.58 | H39: 0.59 | I39: 0.6 | J39: =AVERAGE(E39:I39)
C40: Live ► | D40: % | E40: =CHOOSE(Assumptions!$C$8,E37,E38,E39) | F40: =CHOOSE(Assumptions!$C$8,F37,F38,F39) | G40: =CHOOSE(Assumptions!$C$8,G37,G38,G39) | H40: =CHOOSE(Assumptions!$C$8,H37,H38,H39) | I40: =CHOOSE(Assumptions!$C$8,I37,I38,I39) | J40: =AVERAGE(E40:I40)
B42: EBITDA margin | C42: Bear | D42: % | E42: 0.395 | F42: 0.36 | G42: 0.345 | H42: 0.355 | I42: 0.365 | J42: =AVERAGE(E42:I42) | K42: FY25A 37.7%, H1-26 op. margin 36.6% with H2 guided higher. Opex (R&D ~14% of sales) grows slower than revenue = operating leverage. Bear shows a downturn with R&D held flat in absolute terms.
C43: Base | D43: % | E43: 0.41 | F43: 0.42 | G43: 0.425 | H43: 0.43 | I43: 0.43 | J43: =AVERAGE(E43:I43)
C44: Bull | D44: % | E44: 0.415 | F44: 0.435 | G44: 0.45 | H44: 0.46 | I44: 0.465 | J44: =AVERAGE(E44:I44)
C45: Live ► | D45: % | E45: =CHOOSE(Assumptions!$C$8,E42,E43,E44) | F45: =CHOOSE(Assumptions!$C$8,F42,F43,F44) | G45: =CHOOSE(Assumptions!$C$8,G42,G43,G44) | H45: =CHOOSE(Assumptions!$C$8,H42,H43,H44) | I45: =CHOOSE(Assumptions!$C$8,I42,I43,I44) | J45: =AVERAGE(E45:I45)
B47: D&A % revenue | C47: Bear | D47: % | E47: 0.028 | F47: 0.03 | G47: 0.03 | H47: 0.03 | I47: 0.03 | J47: =AVERAGE(E47:I47) | K47: FY21-25 range 2.5-3.3%, FY25 3.1%. The new capacity build-out lifts the absolute D&A level.
C48: Base | D48: % | E48: 0.028 | F48: 0.028 | G48: 0.028 | H48: 0.028 | I48: 0.028 | J48: =AVERAGE(E48:I48)
C49: Bull | D49: % | E49: 0.028 | F49: 0.027 | G49: 0.027 | H49: 0.027 | I49: 0.027 | J49: =AVERAGE(E49:I49)
C50: Live ► | D50: % | E50: =CHOOSE(Assumptions!$C$8,E47,E48,E49) | F50: =CHOOSE(Assumptions!$C$8,F47,F48,F49) | G50: =CHOOSE(Assumptions!$C$8,G47,G48,G49) | H50: =CHOOSE(Assumptions!$C$8,H47,H48,H49) | I50: =CHOOSE(Assumptions!$C$8,I47,I48,I49) | J50: =AVERAGE(E50:I50)
B52: CapEx % revenue | C52: Bear | D52: % | E52: 0.06 | F52: 0.065 | G52: 0.065 | H52: 0.06 | I52: 0.06 | J52: =AVERAGE(E52:I52) | K52: FY21-25 average 6.4% (peak 8.0% in FY23 capacity expansion, 5.0% in FY25). Base 5.5% as capex normalises but EUV/High-NA capacity is still added.
C53: Base | D53: % | E53: 0.055 | F53: 0.055 | G53: 0.055 | H53: 0.055 | I53: 0.055 | J53: =AVERAGE(E53:I53)
C54: Bull | D54: % | E54: 0.05 | F54: 0.05 | G54: 0.05 | H54: 0.05 | I54: 0.05 | J54: =AVERAGE(E54:I54)
C55: Live ► | D55: % | E55: =CHOOSE(Assumptions!$C$8,E52,E53,E54) | F55: =CHOOSE(Assumptions!$C$8,F52,F53,F54) | G55: =CHOOSE(Assumptions!$C$8,G52,G53,G54) | H55: =CHOOSE(Assumptions!$C$8,H52,H53,H54) | I55: =CHOOSE(Assumptions!$C$8,I52,I53,I54) | J55: =AVERAGE(E55:I55)
B57: Net working capital % revenue | C57: Bear | D57: % | E57: -0.08 | F57: -0.06 | G57: -0.06 | H57: -0.06 | I57: -0.06 | J57: =AVERAGE(E57:I57) | K57: ASML runs negative NWC because customers pay EUV down payments (contract liabilities). It was -27% in FY25 but fell to about -7% of LTM sales by Jun-26 as down payments were consumed. Base normalises to -12%, below the FY21-25 average.
C58: Base | D58: % | E58: -0.12 | F58: -0.12 | G58: -0.12 | H58: -0.12 | I58: -0.12 | J58: =AVERAGE(E58:I58)
C59: Bull | D59: % | E59: -0.15 | F59: -0.15 | G59: -0.15 | H59: -0.15 | I59: -0.15 | J59: =AVERAGE(E59:I59)
C60: Live ► | D60: % | E60: =CHOOSE(Assumptions!$C$8,E57,E58,E59) | F60: =CHOOSE(Assumptions!$C$8,F57,F58,F59) | G60: =CHOOSE(Assumptions!$C$8,G57,G58,G59) | H60: =CHOOSE(Assumptions!$C$8,H57,H58,H59) | I60: =CHOOSE(Assumptions!$C$8,I57,I58,I59) | J60: =AVERAGE(E60:I60)
B62: Tax rate on EBIT | C62: Bear | D62: % | E62: 0.18 | F62: 0.18 | G62: 0.18 | H62: 0.18 | I62: 0.18 | J62: =AVERAGE(E62:I62) | K62: Effective tax rate FY21-25 15.0-18.6% (Dutch innovation box), FY25 17.7%. Pillar Two 15% minimum is not binding.
C63: Base | D63: % | E63: 0.175 | F63: 0.175 | G63: 0.175 | H63: 0.175 | I63: 0.175 | J63: =AVERAGE(E63:I63)
C64: Bull | D64: % | E64: 0.17 | F64: 0.17 | G64: 0.17 | H64: 0.17 | I64: 0.17 | J64: =AVERAGE(E64:I64)
C65: Live ► | D65: % | E65: =CHOOSE(Assumptions!$C$8,E62,E63,E64) | F65: =CHOOSE(Assumptions!$C$8,F62,F63,F64) | G65: =CHOOSE(Assumptions!$C$8,G62,G63,G64) | H65: =CHOOSE(Assumptions!$C$8,H62,H63,H64) | I65: =CHOOSE(Assumptions!$C$8,I62,I63,I64) | J65: =AVERAGE(E65:I65)
B67: Terminal growth rate | C67: Bear | D67: % | E67: 0.02 | K67: Long-run nominal growth: euro-area inflation ~2% + modest real growth in semiconductor content. It is kept below the risk-free rate (3.5%) and nominal GDP.
C68: Base | D68: % | E68: 0.025
C69: Bull | D69: % | E69: 0.03
C70: Live ► | D70: % | E70: =CHOOSE(Assumptions!$C$8,E67,E68,E69)
B72: Exit EV/EBITDA multiple | C72: Bear | D72: x | E72: 18 | K72: ASML's 5-yr average EV/EBITDA is ~30x (35x forward in Aug-26). 25x applies a discount because growth has decelerated by FY30. Semi-equipment peers (AMAT, LRCX, KLAC) have traded at ~18-25x.
C73: Base | D73: x | E73: 25
C74: Bull | D74: x | E74: 30
C75: Live ► | D75: x | E75: =CHOOSE(Assumptions!$C$8,E72,E73,E74)
B77: WACC adjustment vs. CAPM WACC | C77: Bear | D77: % | E77: 0.005 | K77: Bear prices extra risk for export-control and cyclical exposure. Bull assumes a lower risk premium for a structural AI capex cycle.
C78: Base | D78: % | E78: 0
C79: Bull | D79: % | E79: -0.005
C80: Live ► | D80: % | E80: =CHOOSE(Assumptions!$C$8,E77,E78,E79)
B83: Scenario narrative
B84: Bear | C84: AI capex digestion in 2027-28 coincides with tighter China export controls (DUV immersion and servicing). Customers push out EUV orders, the down-payment float shrinks and margins compress as fixed R&D is held.
B85: Base | C85: 2026 guidance is delivered, the backlog converts, and EUV/High-NA adoption in logic and DRAM grows revenue to about EUR 63bn by 2030 with margins at the 2030 target band.
B86: Bull | C86: A sustained AI-driven leading-edge build-out plus faster High-NA adoption push revenue beyond the 2030 range, with gross margin at 60% and services scaling on the installed base.

Sheet Historical
B1: Historical Financials
B2: Reported US GAAP figures (blue) from ASML 20-F filings via SEC XBRL [S1, S2, S3]; ratios and FCF are calculated (black). EUR millions.
B4: EUR m, fiscal year ending 31 Dec | C4: FY20A (ref) | D4: FY21A | E4: FY22A | F4: FY23A | G4: FY24A | H4: FY25A | I4: Type | J4: Source / definition
B5: Reported (US GAAP)
B6: Total net sales | C6: 13978.5 | D6: 18611 | E6: 21173.4 | F6: 27558.5 | G6: 28262.9 | H6: 32667.3 | I6: REPORTED | J6: [S2] XBRL 20-F
B7: Cost of sales | D7: 8802 | E7: 10473.3 | F7: 13422.4 | G7: 13770.9 | H7: 15409.3 | I7: REPORTED | J7: [S2] XBRL 20-F
B8: Gross profit | D8: 9809 | E8: 10700.1 | F8: 14136.1 | G8: 14492 | H8: 17258 | I8: REPORTED | J8: [S2] XBRL 20-F
B9: Research & development | D9: 2547 | E9: 3253.5 | F9: 3980.6 | G9: 4303.7 | H9: 4698.8 | I9: REPORTED | J9: [S2] XBRL 20-F
B10: Selling, general & administrative | D10: 725.6 | E10: 945.9 | F10: 1113.2 | G10: 1165.7 | H10: 1257.8 | I10: REPORTED | J10: [S2] XBRL 20-F
B11: Income from operations (EBIT) | D11: 6750.1 | E11: 6500.7 | F11: 9042.3 | G11: 9022.6 | H11: 11301.4 | I11: REPORTED | J11: [S2] XBRL 20-F
B12: Depreciation & amortization (cash flow statement) | D12: 471 | E12: 583.6 | F12: 739.8 | G12: 918.6 | H12: 1025.9 | I12: REPORTED | J12: [S2] XBRL 20-F
B13: Income before income taxes | D13: 6705.5 | E13: 6456.1 | F13: 9083.5 | G13: 9042.4 | H13: 11406.1 | I13: REPORTED | J13: [S2] XBRL 20-F
B14: Income tax expense | D14: 1021.4 | E14: 969.9 | F14: 1435.8 | G14: 1680.6 | H14: 2013.4 | I14: REPORTED | J14: [S2] XBRL 20-F
B15: Net income | D15: 5883.2 | E15: 5624.2 | F15: 7839 | G15: 7571.6 | H15: 9609.4 | I15: REPORTED | J15: [S2] XBRL 20-F
B16: Purchase of PP&E | D16: 900.7 | E16: 1281.8 | F16: 2155.6 | G16: 2067.2 | H16: 1573.6 | I16: REPORTED | J16: [S2] XBRL 20-F
B17: Purchase of intangible assets | D17: 39.6 | E17: 37.5 | F17: 40.6 | G17: 15.9 | H17: 57.6 | I17: REPORTED | J17: [S2] XBRL 20-F
B18: Net cash from operating activities | D18: 10845.8 | E18: 8486.8 | F18: 5443.4 | G18: 11166.2 | H18: 12658.5 | I18: REPORTED | J18: [S2] XBRL 20-F
B19: Cash & cash equivalents | C19: 6049.4 | D19: 6951.8 | E19: 7268.3 | F19: 7004.7 | G19: 12735.9 | H19: 12916 | I19: REPORTED | J19: [S2] XBRL 20-F
B20: Short-term investments | C20: 1302.2 | D20: 638.5 | E20: 107.7 | F20: 5.4 | G20: 5.4 | H20: 405.9 | I20: REPORTED | J20: [S2] XBRL 20-F
B21: Total current assets | C21: 15930 | D21: 18190.2 | E21: 23064.9 | F21: 24393.9 | G21: 30737.4 | H21: 30616.1 | I21: REPORTED | J21: [S2] XBRL 20-F
B22: Loans receivable, current (non-operating) | C22: 0 | D22: 0 | E22: 0 | F22: 0 | G22: 0 | H22: 266.1 | I22: REPORTED | J22: [S2] XBRL 20-F; new line in FY25 [S3]
B23: Total current liabilities | C23: 6603.5 | D23: 12298 | E23: 17983.6 | F23: 16274.7 | G23: 20051.4 | H23: 24263.9 | I23: REPORTED | J23: [S2] XBRL 20-F
B24: Current debt incl. commercial paper | C24: 15.4 | D24: 509.1 | E24: 746.2 | F24: 0.1 | G24: 1010.3 | H24: 1681.9 | I24: REPORTED | J24: [S2] XBRL 20-F; FY25 current debt = bonds 990.2 + ECP 691.7 [S1]
B25: Long-term debt | D25: 4075 | E25: 3514.2 | F25: 4631.5 | G25: 3677.3 | H25: 2709 | I25: REPORTED | J25: [S2] XBRL 20-F
B26: Contract liabilities, non-current | C26: 1639.9 | D26: 3225.7 | E26: 5269.9 | F26: 4825.5 | G26: 5625.4 | H26: 3366.3 | I26: REPORTED | J26: [S2] XBRL 20-F
B27: Diluted weighted avg. shares (m) | D27: 410.4 | E27: 398 | F27: 394.1 | G27: 393.6 | H27: 388.9 | I27: REPORTED | J27: [S2] XBRL 20-F
B29: Calculated
B30: Revenue growth % | D30: =D6/C6-1 | E30: =E6/D6-1 | F30: =F6/E6-1 | G30: =G6/F6-1 | H30: =H6/G6-1 | I30: CALCULATED | J30: Revenue / prior-year revenue - 1
B31: Gross margin % | D31: =D8/D6 | E31: =E8/E6 | F31: =F8/F6 | G31: =G8/G6 | H31: =H8/H6 | I31: CALCULATED | J31: Gross profit / revenue
B32: EBITDA | D32: =D11+D12 | E32: =E11+E12 | F32: =F11+F12 | G32: =G11+G12 | H32: =H11+H12 | I32: CALCULATED | J32: EBIT + D&A
B33: EBITDA margin % | D33: =D32/D6 | E33: =E32/E6 | F33: =F32/F6 | G33: =G32/G6 | H33: =H32/H6 | I33: CALCULATED | J33: EBITDA / revenue
B34: EBIT margin % | D34: =D11/D6 | E34: =E11/E6 | F34: =F11/F6 | G34: =G11/G6 | H34: =H11/H6 | I34: CALCULATED | J34: EBIT / revenue
B35: D&A % revenue | D35: =D12/D6 | E35: =E12/E6 | F35: =F12/F6 | G35: =G12/G6 | H35: =H12/H6 | I35: CALCULATED | J35: D&A / revenue
B36: R&D % revenue | D36: =D9/D6 | E36: =E9/E6 | F36: =F9/F6 | G36: =G9/G6 | H36: =H9/H6 | I36: CALCULATED | J36: R&D / revenue
B37: Effective tax rate | D37: =D14/D13 | E37: =E14/E13 | F37: =F14/F13 | G37: =G14/G13 | H37: =H14/H13 | I37: CALCULATED | J37: Income tax expense / income before taxes
B38: Taxes on EBIT | D38: =D11*D37 | E38: =E11*E37 | F38: =F11*F37 | G38: =G11*G37 | H38: =H11*H37 | I38: CALCULATED | J38: EBIT x effective tax rate (unlevered taxes)
B39: NOPAT | D39: =D11-D38 | E39: =E11-E38 | F39: =F11-F38 | G39: =G11-G38 | H39: =H11-H38 | I39: CALCULATED | J39: EBIT - taxes on EBIT
B40: Total CapEx (PP&E + intangibles) | D40: =D16+D17 | E40: =E16+E17 | F40: =F16+F17 | G40: =G16+G17 | H40: =H16+H17 | I40: CALCULATED
B41: CapEx % revenue | D41: =D40/D6 | E41: =E40/E6 | F41: =F40/F6 | G41: =G40/G6 | H41: =H40/H6 | I41: CALCULATED
B42: Operating net working capital | C42: =(C21-C19-C20-C22)-(C23-C24)-C26 | D42: =(D21-D19-D20-D22)-(D23-D24)-D26 | E42: =(E21-E19-E20-E22)-(E23-E24)-E26 | F42: =(F21-F19-F20-F22)-(F23-F24)-F26 | G42: =(G21-G19-G20-G22)-(G23-G24)-G26 | H42: =(H21-H19-H20-H22)-(H23-H24)-H26 | I42: CALCULATED | J42: (Current assets - cash - STI - current loans rec.) - (current liabilities - current debt) - non-current contract liabilities
B43: NWC % revenue | D43: =D42/D6 | E43: =E42/E6 | F43: =F42/F6 | G43: =G42/G6 | H43: =H42/H6 | I43: CALCULATED | J43: Negative = customers pre-fund ASML via EUV down payments
B44: Change in NWC (increase = cash outflow) | D44: =D42-C42 | E44: =E42-D42 | F44: =F42-E42 | G44: =G42-F42 | H44: =H42-G42 | I44: CALCULATED
B45: Unlevered free cash flow | D45: =D39+D12-D40-D44 | E45: =E39+E12-E40-E44 | F45: =F39+F12-F40-F44 | G45: =G39+G12-G40-G44 | H45: =H39+H12-H40-H44 | I45: CALCULATED | J45: NOPAT + D&A - CapEx - change in NWC
B46: UFCF margin % | D46: =D45/D6 | E46: =E45/E6 | F46: =F45/F6 | G46: =G45/G6 | H46: =H45/H6 | I46: CALCULATED
B47: UFCF / NOPAT (cash conversion) | D47: =D45/D39 | E47: =E45/E39 | F47: =F45/F39 | G47: =G45/G39 | H47: =H45/H39 | I47: CALCULATED
B48: Total debt | D48: =D24+D25 | E48: =E24+E25 | F48: =F24+F25 | G48: =G24+G25 | H48: =H24+H25 | I48: CALCULATED
B49: Net cash (cash + STI - debt) | D49: =D19+D20-D48 | E49: =E19+E20-E48 | F49: =F19+F20-F48 | G49: =G19+G20-G48 | H49: =H19+H20-H48 | I49: CALCULATED
B50: Check: gross profit - (sales - COGS) | D50: =D8-(D6-D7) | E50: =E8-(E6-E7) | F50: =F8-(F6-F7) | G50: =G8-(G6-G7) | H50: =H8-(H6-H7) | I50: CALCULATED | J50: Should be 0
B52: Summary FY21-FY25
B53: Revenue CAGR FY20-FY25 | C53: =(H6/C6)^(1/5)-1
B54: Average gross margin | C54: =AVERAGE(D31:H31)
B55: Average EBITDA margin | C55: =AVERAGE(D33:H33)
B56: Average effective tax rate | C56: =AVERAGE(D37:H37)
B57: Average CapEx % revenue | C57: =AVERAGE(D41:H41)
B58: Average NWC % revenue | C58: =AVERAGE(D43:H43)
B59: Cumulative UFCF FY21-FY25 | C59: =SUM(D45:H45)
B61: Trend analysis: what matters for the forecast
B62: 1. Growth is strong but cyclical: revenue rose from EUR 18.6bn (FY21) to EUR 32.7bn (FY25), a 19% CAGR since FY20, but FY24 grew only 2.6% (a digestion year). The forecast must therefore fade growth rather than extrapolate it.
B63: 2. Margins expand with EUV mix and scale: gross margin 50.5% (FY22) to 52.8% (FY25); EBITDA margin 33.5% to 37.7%. R&D stays at ~14-15% of sales, so operating leverage drives the margin path.
B64: 3. The tax rate is low and stable: ETR 15.0%-18.6% thanks to the Dutch innovation box.
B65: 4. Capex is light but lumpy: 5.0%-8.0% of sales; the FY23-24 capacity build (EUV, High-NA) has now normalised.
B66: 5. Working capital is the swing factor: NWC is negative (-27% of FY25 sales) because customers prepay EUV systems. Swings of EUR 2-5bn a year (e.g. a FY23 outflow when down payments were consumed) make reported FCF far more volatile than NOPAT.
B67: 6. The balance sheet is net cash, and buybacks plus dividends (EUR 8.5bn in FY25) return most FCF, so the EV-to-equity bridge is small relative to EV.

Sheet Forecast
B1: Operating Forecast
B2: FY21A-FY25A linked from Historical (green); FY26E-FY30E driven by the live scenario on Assumptions. EUR millions.
B4: EUR m | C4: FY21A | D4: FY22A | E4: FY23A | F4: FY24A | G4: FY25A | H4: FY26E | I4: FY27E | J4: FY28E | K4: FY29E | L4: FY30E | M4: Logic
B5: Scenario: | C5: =Assumptions!$C$9
B7: Revenue | C7: =Historical!D6 | D7: =Historical!E6 | E7: =Historical!F6 | F7: =Historical!G6 | G7: =Historical!H6 | H7: =G7*(1+H8) | I7: =H7*(1+I8) | J7: =I7*(1+J8) | K7: =J7*(1+K8) | L7: =K7*(1+L8) | M7: Prior year x (1 + growth)
B8: Revenue growth % | C8: =Historical!D30 | D8: =Historical!E30 | E8: =Historical!F30 | F8: =Historical!G30 | G8: =Historical!H30 | H8: =Assumptions!E35 | I8: =Assumptions!F35 | J8: =Assumptions!G35 | K8: =Assumptions!H35 | L8: =Assumptions!I35
B10: Gross profit | C10: =Historical!D8 | D10: =Historical!E8 | E10: =Historical!F8 | F10: =Historical!G8 | G10: =Historical!H8 | H10: =H7*H11 | I10: =I7*I11 | J10: =J7*J11 | K10: =K7*K11 | L10: =L7*L11 | M10: Revenue x gross margin
B11: Gross margin % | C11: =Historical!D31 | D11: =Historical!E31 | E11: =Historical!F31 | F11: =Historical!G31 | G11: =Historical!H31 | H11: =Assumptions!E40 | I11: =Assumptions!F40 | J11: =Assumptions!G40 | K11: =Assumptions!H40 | L11: =Assumptions!I40
B13: EBITDA | C13: =Historical!D32 | D13: =Historical!E32 | E13: =Historical!F32 | F13: =Historical!G32 | G13: =Historical!H32 | H13: =H7*H14 | I13: =I7*I14 | J13: =J7*J14 | K13: =K7*K14 | L13: =L7*L14 | M13: Revenue x EBITDA margin
B14: EBITDA margin % | C14: =Historical!D33 | D14: =Historical!E33 | E14: =Historical!F33 | F14: =Historical!G33 | G14: =Historical!H33 | H14: =Assumptions!E45 | I14: =Assumptions!F45 | J14: =Assumptions!G45 | K14: =Assumptions!H45 | L14: =Assumptions!I45
B16: Depreciation & amortization | C16: =Historical!D12 | D16: =Historical!E12 | E16: =Historical!F12 | F16: =Historical!G12 | G16: =Historical!H12 | H16: =H7*H17 | I16: =I7*I17 | J16: =J7*J17 | K16: =K7*K17 | L16: =L7*L17 | M16: Revenue x D&A %
B17: D&A % revenue | C17: =Historical!D35 | D17: =Historical!E35 | E17: =Historical!F35 | F17: =Historical!G35 | G17: =Historical!H35 | H17: =Assumptions!E50 | I17: =Assumptions!F50 | J17: =Assumptions!G50 | K17: =Assumptions!H50 | L17: =Assumptions!I50
B19: EBIT | C19: =Historical!D11 | D19: =Historical!E11 | E19: =Historical!F11 | F19: =Historical!G11 | G19: =Historical!H11 | H19: =H13-H16 | I19: =I13-I16 | J19: =J13-J16 | K19: =K13-K16 | L19: =L13-L16 | M19: EBITDA - D&A
B20: EBIT margin % | C20: =Historical!D34 | D20: =Historical!E34 | E20: =Historical!F34 | F20: =Historical!G34 | G20: =Historical!H34 | H20: =H19/H7 | I20: =I19/I7 | J20: =J19/J7 | K20: =K19/K7 | L20: =L19/L7
B22: Taxes on EBIT | C22: =Historical!D38 | D22: =Historical!E38 | E22: =Historical!F38 | F22: =Historical!G38 | G22: =Historical!H38 | H22: =H19*H23 | I22: =I19*I23 | J22: =J19*J23 | K22: =K19*K23 | L22: =L19*L23 | M22: EBIT x tax rate
B23: Tax rate | C23: =Historical!D37 | D23: =Historical!E37 | E23: =Historical!F37 | F23: =Historical!G37 | G23: =Historical!H37 | H23: =Assumptions!E65 | I23: =Assumptions!F65 | J23: =Assumptions!G65 | K23: =Assumptions!H65 | L23: =Assumptions!I65
B24: NOPAT | C24: =Historical!D39 | D24: =Historical!E39 | E24: =Historical!F39 | F24: =Historical!G39 | G24: =Historical!H39 | H24: =H19-H22 | I24: =I19-I22 | J24: =J19-J22 | K24: =K19-K22 | L24: =L19-L22 | M24: EBIT - taxes
B26: Capital expenditures | C26: =Historical!D40 | D26: =Historical!E40 | E26: =Historical!F40 | F26: =Historical!G40 | G26: =Historical!H40 | H26: =H7*H27 | I26: =I7*I27 | J26: =J7*J27 | K26: =K7*K27 | L26: =L7*L27 | M26: Revenue x CapEx %
B27: CapEx % revenue | C27: =Historical!D41 | D27: =Historical!E41 | E27: =Historical!F41 | F27: =Historical!G41 | G27: =Historical!H41 | H27: =Assumptions!E55 | I27: =Assumptions!F55 | J27: =Assumptions!G55 | K27: =Assumptions!H55 | L27: =Assumptions!I55
B29: Net working capital | C29: =Historical!D42 | D29: =Historical!E42 | E29: =Historical!F42 | F29: =Historical!G42 | G29: =Historical!H42 | H29: =H7*H30 | I29: =I7*I30 | J29: =J7*J30 | K29: =K7*K30 | L29: =L7*L30 | M29: Revenue x NWC %
B30: NWC % revenue | C30: =Historical!D43 | D30: =Historical!E43 | E30: =Historical!F43 | F30: =Historical!G43 | G30: =Historical!H43 | H30: =Assumptions!E60 | I30: =Assumptions!F60 | J30: =Assumptions!G60 | K30: =Assumptions!H60 | L30: =Assumptions!I60
B31: Change in NWC (increase = outflow) | C31: =Historical!D44 | D31: =Historical!E44 | E31: =Historical!F44 | F31: =Historical!G44 | G31: =Historical!H44 | H31: =H29-G29 | I31: =I29-H29 | J31: =J29-I29 | K31: =K29-J29 | L31: =L29-K29 | M31: NWC - prior NWC
B33: Unlevered free cash flow | C33: =Historical!D45 | D33: =Historical!E45 | E33: =Historical!F45 | F33: =Historical!G45 | G33: =Historical!H45 | H33: =H24+H16-H26-H31 | I33: =I24+I16-I26-I31 | J33: =J24+J16-J26-J31 | K33: =K24+K16-K26-K31 | L33: =L24+L16-L26-L31 | M33: NOPAT + D&A - CapEx - change in NWC
B34: UFCF margin % | C34: =Historical!D46 | D34: =Historical!E46 | E34: =Historical!F46 | F34: =Historical!G46 | G34: =Historical!H46 | H34: =H33/H7 | I34: =I33/I7 | J34: =J33/J7 | K34: =K33/K7 | L34: =L33/L7
B36: Memo: implied opex % (GM - EBIT margin) | C36: =C11-C20 | D36: =D11-D20 | E36: =E11-E20 | F36: =F11-F20 | G36: =G11-G20 | H36: =H11-H20 | I36: =I11-I20 | J36: =J11-J20 | ... L36: =L11-L20 | M36: Sanity check: R&D + SG&A ~ 16-19% historically
B38: Revenue CAGR FY25A-FY30E | C38: =(L7/G7)^(1/5)-1
B39: Average forecast EBITDA margin | C39: =AVERAGE(H14:L14)
B40: FY30E revenue vs 2030 company range (EUR 44-60bn) [S10] | C40: =IF(L7>60000,"Above range",IF(L7<44000,"Below range","Within range"))

Sheet WACC
B1: Weighted Average Cost of Capital
B2: CAPM cost of equity, market-value weights. Inputs are linked from Assumptions (green).
B5: Cost of equity
B6: Risk-free rate | C6: =Assumptions!$C$22 | D6: 10Y German Bund: EUR, long-duration, matches EUR cash flows
B7: Regression beta (5Y monthly) | C7: =Assumptions!$C$24 | D7: Observed vs. market index; noisy for a single stock
B8: Industry unlevered beta | C8: =Assumptions!$C$25 | D8: Semiconductor equipment peers, cash-corrected (Damodaran)
B9: ASML market D/E | C9: =C27/C26 | D9: Debt / market capitalisation
B10: Relevered industry beta | C10: =C8*(1+(1-C20)*C9) | D10: Hamada: Bu x (1 + (1 - t) x D/E)
B11: Weight on regression beta | C11: =Assumptions!$C$26
B12: Selected beta | C12: =C11*C7+(1-C11)*C10 | D12: Blend of regression and bottom-up beta
B13: Equity risk premium | C13: =Assumptions!$C$23 | D13: Implied mature-market ERP; Netherlands has no country premium
B14: Cost of equity (CAPM) | C14: =C6+C12*C13 | D14: Rf + beta x ERP
B16: Cost of debt
B17: Risk-free rate | C17: =C6
B18: Credit spread (A1 / A+) | C18: =Assumptions!$C$27 | D18: Spread for single-A EUR corporate bonds
B19: Pre-tax cost of debt | C19: =C17+C18 | D19: Rf + spread
B20: Tax rate (statutory) | C20: =Assumptions!$C$28 | D20: Interest is deductible at the Dutch statutory rate
B21: After-tax cost of debt | C21: =C19*(1-C20) | D21: Kd x (1 - t)
B23: Capital structure (market values)
B24: Share price (EUR) | C24: =Assumptions!$C$14
B25: Diluted shares (m) | C25: =Assumptions!$C$15
B26: Market value of equity (E) | C26: =C24*C25 | D26: Price x diluted shares
B27: Debt (D) | C27: =Assumptions!$C$17 | D27: Book value used as proxy for market value (fair value ~ book for A1 issuer)
B28: Total capital (D + E) | C28: =C26+C27
B29: Equity weight E / (D + E) | C29: =C26/C28
B30: Debt weight D / (D + E) | C30: =C27/C28
B32: WACC
B33: WACC (CAPM) | C33: =C29*C14+C30*C21 | D33: E/(D+E) x Ke + D/(D+E) x Kd x (1 - t)
B34: Scenario adjustment | C34: =Assumptions!$E$80 | D34: 0 in Base; +/-0.5% in Bear/Bull
B35: WACC applied in DCF | C35: =C33+C34

Sheet DCF
B1: Discounted Cash Flow
B2: Valuation at the valuation date using the 28-Jun-26 balance sheet; FY26 counts only H2 cash flows (stub). EUR millions.
B4: EUR m | E4: FY26E | F4: FY27E | G4: FY28E | H4: FY29E | I4: FY30E
B5: Period end | E5: =Assumptions!$C$7 | F5: =DATE(YEAR(E5)+1,12,31) | G5: =DATE(YEAR(F5)+1,12,31) | H5: =DATE(YEAR(G5)+1,12,31) | I5: =DATE(YEAR(H5)+1,12,31)
B6: Years from valuation date to period end | E6: =(E5-Assumptions!$C$5)/365 | F6: =E6+1 | G6: =F6+1 | H6: =G6+1 | I6: =H6+1
B7: Discount period (mid-year if switched on) | E7: =IF(Assumptions!$C$10=1,E6/2,E6) | F7: =IF(Assumptions!$C$10=1,F6-0.5,F6) | G7: =IF(Assumptions!$C$10=1,G6-0.5,G6) | H7: =IF(Assumptions!$C$10=1,H6-0.5,H6) | I7: =IF(Assumptions!$C$10=1,I6-0.5,I6) | J7: FY26 stub: mid-point of remaining period; later years: mid-year
B9: Unlevered free cash flow | E9: =Forecast!H33 | F9: =Forecast!I33 | G9: =Forecast!J33 | H9: =Forecast!K33 | I9: =Forecast!L33
B10: Less: H1-26 actual UFCF (already in 28-Jun cash) | E10: =-Assumptions!$C$19 | F10: 0 | G10: 0 | H10: 0 | I10: 0 | J10: Avoids double counting: H1 cash flows are in the balance sheet already
B11: Cash flow to discount | E11: =E9+E10 | F11: =F9+F10 | G11: =G9+G10 | H11: =H9+H10 | I11: =I9+I10
B12: WACC | E12: =WACC!$C$35 | F12: =WACC!$C$35 | G12: =WACC!$C$35 | H12: =WACC!$C$35 | I12: =WACC!$C$35
B13: Discount factor | E13: =1/(1+E12)^E7 | F13: =1/(1+F12)^F7 | G13: =1/(1+G12)^G7 | H13: =1/(1+H12)^H7 | I13: =1/(1+I12)^I7
B14: PV of cash flow | E14: =E11*E13 | F14: =F11*F13 | G14: =G11*G13 | H14: =H11*H13 | I14: =I11*I13
B15: Sum of PV of forecast cash flows | C15: =SUM(E14:I14)
B17: Valuation | C17: Gordon Growth | D17: Exit Multiple | E17: Blended
B18: Terminal-year UFCF (FY30E) | C18: =I9
B19: Terminal growth rate | C19: =Assumptions!$E$70
B20: Terminal-year EBITDA (FY30E) | D20: =Forecast!L13
B21: Exit EV/EBITDA multiple | D21: =Assumptions!$E$75
B22: Terminal value at end FY30 | C22: =C18*(1+C19)/(WACC!$C$35-C19) | D22: =D20*D21 | F22: Gordon: FCF30 x (1 + g) / (WACC - g). Exit: EBITDA30 x multiple
B23: Discount period for terminal value | C23: =$I$6 | D23: =$I$6 | F23: Both terminal values discounted from end of FY30 (conservative)
B24: PV of terminal value | C24: =C22/(1+WACC!$C$35)^C23 | D24: =D22/(1+WACC!$C$35)^D23
B25: PV of forecast cash flows | C25: =$C$15 | D25: =$C$15
B26: Enterprise value | C26: =C25+C24 | D26: =D25+D24 | E26: =Assumptions!$C$11*C26+(1-Assumptions!$C$11)*D26
B27: Terminal value % of EV | C27: =C24/C26 | D27: =D24/D26
B28: Plus: cash & short-term investments | C28: =Assumptions!$C$16 | D28: =Assumptions!$C$16
B29: Less: total debt | C29: =Assumptions!$C$17 | D29: =Assumptions!$C$17 | F29: Bonds + commercial paper; US GAAP operating leases excluded (lease cost already in EBITDA)
B30: Plus: non-operating investments | C30: =Assumptions!$C$18 | D30: =Assumptions!$C$18 | F30: Equity stakes (e.g. Mistral AI) and equity-method investments; their income is not in EBIT
B31: Equity value | C31: =C26+C28-C29+C30 | D31: =D26+D28-D29+D30 | E31: =Assumptions!$C$11*C31+(1-Assumptions!$C$11)*D31
B32: Diluted shares (m) | C32: =Assumptions!$C$15 | D32: =Assumptions!$C$15
B33: Implied share price (EUR) | C33: =C31/C32 | D33: =D31/D32 | E33: =Assumptions!$C$11*C33+(1-Assumptions!$C$11)*D33
B34: Current share price (EUR) | C34: =Assumptions!$C$14 | D34: =Assumptions!$C$14 | E34: =Assumptions!$C$14
B35: Upside / (downside) | C35: =C33/C34-1 | D35: =D33/D34-1 | E35: =E33/E34-1
B36: Cross-check: implied exit multiple / implied g | C36: =C22/D20 | D36: =(D22*WACC!$C$35-C18)/(D22+C18) | F36: Gordon TV / EBITDA (x) | g implied by exit TV
B37: Reverse DCF: exit multiple implied by market price | D37: =((C34*C32-C28+C29-C30-C25)*(1+WACC!$C$35)^D23)/D20 | F37: Multiple needed in the Exit method to justify today's price
B38: Reverse DCF: perpetual growth implied by market price | C38: =(((C34*C32-C28+C29-C30-C25)*(1+WACC!$C$35)^C23)*WACC!$C$35-C18)/(((C34*C32-C28+C29-C30-C25)*(1+WACC!$C$35)^C23)+C18) | F38: Perpetual growth needed in the Gordon method to justify today's price

Sheet Sensitivity
B1: Sensitivity Analysis
B2: Implied share price (EUR). Every cell is a live closed-form DCF; the grid re-centres on the live WACC, g and multiple. Base case boxed and shaded.
B4: Table 1: WACC vs terminal growth (Gordon Growth method) | M4: Grid steps
C5: WACC → | M5: WACC step | N5: 0.005
B6: g ↓ / WACC → | C6: =$G$6+(-4)*$N$5 | D6: =$G$6+(-3)*$N$5 | E6: =$G$6+(-2)*$N$5 | F6: =$G$6+(-1)*$N$5 | G6: =WACC!$C$35 | H6: =$G$6+(1)*$N$5 | I6: =$G$6+(2)*$N$5 | J6: =$G$6+(3)*$N$5 | K6: =$G$6+(4)*$N$5 | M6: Terminal growth step | N6: 0.0025
B7: =$B$11+(-4)*$N$6 | C7: =(SUMPRODUCT(DCF!$E$11:$I$11,1/(1+C$6)^DCF!$E$7:$I$7)+DCF!$I$9*(1+$B7)/(C$6-$B7)/(1+C$6)^DCF!$I$6+(DCF!$C$28-DCF!$C$29+DCF!$C$30))/DCF!$C$32 | D7: =(SUMPRODUCT(DCF!$E$11:$I$11,1/(1+D$6)^DCF!$E$7:$I$7)+DCF!$I$9*(1+$B7)/(D$6-$B7)/(1+D$6)^DCF!$I$6+(DCF!$C$28-DCF!$C$29+DCF!$C$30))/DCF!$C$32 | E7: =(SUMPRODUCT(DCF!$E$11:$I$11,1/(1+E$6)^DCF!$E$7:$I$7)+DCF!$I$9*(1+$B7)/(E$6-$B7)/(1+E$6)^DCF!$I$6+(DCF!$C$28-DCF!$C$29+DCF!$C$30))/DCF!$C$32 | F7: =(SUMPRODUCT(DCF!$E$11:$I$11,1/(1+F$6)^DCF!$E$7:$I$7)+DCF!$I$9*(1+$B7)/(F$6-$B7)/(1+F$6)^DCF!$I$6+(DCF!$C$28-DCF!$C$29+DCF!$C$30))/DCF!$C$32 | G7: =(SUMPRODUCT(DCF!$E$11:$I$11,1/(1+G$6)^DCF!$E$7:$I$7)+DCF!$I$9*(1+$B7)/(G$6-$B7)/(1+G$6)^DCF!$I$6+(DCF!$C$28-DCF!$C$29+DCF!$C$30))/DCF!$C$32 | H7: =(SUMPRODUCT(DCF!$E$11:$I$11,1/(1+H$6)^DCF!$E$7:$I$7)+DCF!$I$9*(1+$B7)/(H$6-$B7)/(1+H$6)^DCF!$I$6+(DCF!$C$28-DCF!$C$29+DCF!$C$30))/DCF!$C$32 | I7: =(SUMPRODUCT(DCF!$E$11:$I$11,1/(1+I$6)^DCF!$E$7:$I$7)+DCF!$I$9*(1+$B7)/(I$6-$B7)/(1+I$6)^DCF!$I$6+(DCF!$C$28-DCF!$C$29+DCF!$C$30))/DCF!$C$32 | J7: =(SUMPRODUCT(DCF!$E$11:$I$11,1/(1+J$6)^DCF!$E$7:$I$7)+DCF!$I$9*(1+$B7)/(J$6-$B7)/(1+J$6)^DCF!$I$6+(DCF!$C$28-DCF!$C$29+DCF!$C$30))/DCF!$C$32 | K7: =(SUMPRODUCT(DCF!$E$11:$I$11,1/(1+K$6)^DCF!$E$7:$I$7)+DCF!$I$9*(1+$B7)/(K$6-$B7)/(1+K$6)^DCF!$I$6+(DCF!$C$28-DCF!$C$29+DCF!$C$30))/DCF!$C$32 | M7: Exit multiple step | N7: 2
B8: =$B$11+(-3)*$N$6 | C8: =(SUMPRODUCT(DCF!$E$11:$I$11,1/(1+C$6)^DCF!$E$7:$I$7)+DCF!$I$9*(1+$B8)/(C$6-$B8)/(1+C$6)^DCF!$I$6+(DCF!$C$28-DCF!$C$29+DCF!$C$30))/DCF!$C$32 | D8: =(SUMPRODUCT(DCF!$E$11:$I$11,1/(1+D$6)^DCF!$E$7:$I$7)+DCF!$I$9*(1+$B8)/(D$6-$B8)/(1+D$6)^DCF!$I$6+(DCF!$C$28-DCF!$C$29+DCF!$C$30))/DCF!$C$32 | E8: =(SUMPRODUCT(DCF!$E$11:$I$11,1/(1+E$6)^DCF!$E$7:$I$7)+DCF!$I$9*(1+$B8)/(E$6-$B8)/(1+E$6)^DCF!$I$6+(DCF!$C$28-DCF!$C$29+DCF!$C$30))/DCF!$C$32 | F8: =(SUMPRODUCT(DCF!$E$11:$I$11,1/(1+F$6)^DCF!$E$7:$I$7)+DCF!$I$9*(1+$B8)/(F$6-$B8)/(1+F$6)^DCF!$I$6+(DCF!$C$28-DCF!$C$29+DCF!$C$30))/DCF!$C$32 | G8: =(SUMPRODUCT(DCF!$E$11:$I$11,1/(1+G$6)^DCF!$E$7:$I$7)+DCF!$I$9*(1+$B8)/(G$6-$B8)/(1+G$6)^DCF!$I$6+(DCF!$C$28-DCF!$C$29+DCF!$C$30))/DCF!$C$32 | H8: =(SUMPRODUCT(DCF!$E$11:$I$11,1/(1+H$6)^DCF!$E$7:$I$7)+DCF!$I$9*(1+$B8)/(H$6-$B8)/(1+H$6)^DCF!$I$6+(DCF!$C$28-DCF!$C$29+DCF!$C$30))/DCF!$C$32 | I8: =(SUMPRODUCT(DCF!$E$11:$I$11,1/(1+I$6)^DCF!$E$7:$I$7)+DCF!$I$9*(1+$B8)/(I$6-$B8)/(1+I$6)^DCF!$I$6+(DCF!$C$28-DCF!$C$29+DCF!$C$30))/DCF!$C$32 | J8: =(SUMPRODUCT(DCF!$E$11:$I$11,1/(1+J$6)^DCF!$E$7:$I$7)+DCF!$I$9*(1+$B8)/(J$6-$B8)/(1+J$6)^DCF!$I$6+(DCF!$C$28-DCF!$C$29+DCF!$C$30))/DCF!$C$32 | K8: =(SUMPRODUCT(DCF!$E$11:$I$11,1/(1+K$6)^DCF!$E$7:$I$7)+DCF!$I$9*(1+$B8)/(K$6-$B8)/(1+K$6)^DCF!$I$6+(DCF!$C$28-DCF!$C$29+DCF!$C$30))/DCF!$C$32
B9: =$B$11+(-2)*$N$6 | C9: =(SUMPRODUCT(DCF!$E$11:$I$11,1/(1+C$6)^DCF!$E$7:$I$7)+DCF!$I$9*(1+$B9)/(C$6-$B9)/(1+C$6)^DCF!$I$6+(DCF!$C$28-DCF!$C$29+DCF!$C$30))/DCF!$C$32 | D9: =(SUMPRODUCT(DCF!$E$11:$I$11,1/(1+D$6)^DCF!$E$7:$I$7)+DCF!$I$9*(1+$B9)/(D$6-$B9)/(1+D$6)^DCF!$I$6+(DCF!$C$28-DCF!$C$29+DCF!$C$30))/DCF!$C$32 | E9: =(SUMPRODUCT(DCF!$E$11:$I$11,1/(1+E$6)^DCF!$E$7:$I$7)+DCF!$I$9*(1+$B9)/(E$6-$B9)/(1+E$6)^DCF!$I$6+(DCF!$C$28-DCF!$C$29+DCF!$C$30))/DCF!$C$32 | F9: =(SUMPRODUCT(DCF!$E$11:$I$11,1/(1+F$6)^DCF!$E$7:$I$7)+DCF!$I$9*(1+$B9)/(F$6-$B9)/(1+F$6)^DCF!$I$6+(DCF!$C$28-DCF!$C$29+DCF!$C$30))/DCF!$C$32 | G9: =(SUMPRODUCT(DCF!$E$11:$I$11,1/(1+G$6)^DCF!$E$7:$I$7)+DCF!$I$9*(1+$B9)/(G$6-$B9)/(1+G$6)^DCF!$I$6+(DCF!$C$28-DCF!$C$29+DCF!$C$30))/DCF!$C$32 | H9: =(SUMPRODUCT(DCF!$E$11:$I$11,1/(1+H$6)^DCF!$E$7:$I$7)+DCF!$I$9*(1+$B9)/(H$6-$B9)/(1+H$6)^DCF!$I$6+(DCF!$C$28-DCF!$C$29+DCF!$C$30))/DCF!$C$32 | I9: =(SUMPRODUCT(DCF!$E$11:$I$11,1/(1+I$6)^DCF!$E$7:$I$7)+DCF!$I$9*(1+$B9)/(I$6-$B9)/(1+I$6)^DCF!$I$6+(DCF!$C$28-DCF!$C$29+DCF!$C$30))/DCF!$C$32 | J9: =(SUMPRODUCT(DCF!$E$11:$I$11,1/(1+J$6)^DCF!$E$7:$I$7)+DCF!$I$9*(1+$B9)/(J$6-$B9)/(1+J$6)^DCF!$I$6+(DCF!$C$28-DCF!$C$29+DCF!$C$30))/DCF!$C$32 | K9: =(SUMPRODUCT(DCF!$E$11:$I$11,1/(1+K$6)^DCF!$E$7:$I$7)+DCF!$I$9*(1+$B9)/(K$6-$B9)/(1+K$6)^DCF!$I$6+(DCF!$C$28-DCF!$C$29+DCF!$C$30))/DCF!$C$32
B10: =$B$11+(-1)*$N$6 | C10: =(SUMPRODUCT(DCF!$E$11:$I$11,1/(1+C$6)^DCF!$E$7:$I$7)+DCF!$I$9*(1+$B10)/(C$6-$B10)/(1+C$6)^DCF!$I$6+(DCF!$C$28-DCF!$C$29+DCF!$C$30))/DCF!$C$32 | D10: =(SUMPRODUCT(DCF!$E$11:$I$11,1/(1+D$6)^DCF!$E$7:$I$7)+DCF!$I$9*(1+$B10)/(D$6-$B10)/(1+D$6)^DCF!$I$6+(DCF!$C$28-DCF!$C$29+DCF!$C$30))/DCF!$C$32 | E10: =(SUMPRODUCT(DCF!$E$11:$I$11,1/(1+E$6)^DCF!$E$7:$I$7)+DCF!$I$9*(1+$B10)/(E$6-$B10)/(1+E$6)^DCF!$I$6+(DCF!$C$28-DCF!$C$29+DCF!$C$30))/DCF!$C$32 | F10: =(SUMPRODUCT(DCF!$E$11:$I$11,1/(1+F$6)^DCF!$E$7:$I$7)+DCF!$I$9*(1+$B10)/(F$6-$B10)/(1+F$6)^DCF!$I$6+(DCF!$C$28-DCF!$C$29+DCF!$C$30))/DCF!$C$32 | G10: =(SUMPRODUCT(DCF!$E$11:$I$11,1/(1+G$6)^DCF!$E$7:$I$7)+DCF!$I$9*(1+$B10)/(G$6-$B10)/(1+G$6)^DCF!$I$6+(DCF!$C$28-DCF!$C$29+DCF!$C$30))/DCF!$C$32 | H10: =(SUMPRODUCT(DCF!$E$11:$I$11,1/(1+H$6)^DCF!$E$7:$I$7)+DCF!$I$9*(1+$B10)/(H$6-$B10)/(1+H$6)^DCF!$I$6+(DCF!$C$28-DCF!$C$29+DCF!$C$30))/DCF!$C$32 | I10: =(SUMPRODUCT(DCF!$E$11:$I$11,1/(1+I$6)^DCF!$E$7:$I$7)+DCF!$I$9*(1+$B10)/(I$6-$B10)/(1+I$6)^DCF!$I$6+(DCF!$C$28-DCF!$C$29+DCF!$C$30))/DCF!$C$32 | J10: =(SUMPRODUCT(DCF!$E$11:$I$11,1/(1+J$6)^DCF!$E$7:$I$7)+DCF!$I$9*(1+$B10)/(J$6-$B10)/(1+J$6)^DCF!$I$6+(DCF!$C$28-DCF!$C$29+DCF!$C$30))/DCF!$C$32 | K10: =(SUMPRODUCT(DCF!$E$11:$I$11,1/(1+K$6)^DCF!$E$7:$I$7)+DCF!$I$9*(1+$B10)/(K$6-$B10)/(1+K$6)^DCF!$I$6+(DCF!$C$28-DCF!$C$29+DCF!$C$30))/DCF!$C$32
B11: =Assumptions!$E$70 | C11: =(SUMPRODUCT(DCF!$E$11:$I$11,1/(1+C$6)^DCF!$E$7:$I$7)+DCF!$I$9*(1+$B11)/(C$6-$B11)/(1+C$6)^DCF!$I$6+(DCF!$C$28-DCF!$C$29+DCF!$C$30))/DCF!$C$32 | D11: =(SUMPRODUCT(DCF!$E$11:$I$11,1/(1+D$6)^DCF!$E$7:$I$7)+DCF!$I$9*(1+$B11)/(D$6-$B11)/(1+D$6)^DCF!$I$6+(DCF!$C$28-DCF!$C$29+DCF!$C$30))/DCF!$C$32 | E11: =(SUMPRODUCT(DCF!$E$11:$I$11,1/(1+E$6)^DCF!$E$7:$I$7)+DCF!$I$9*(1+$B11)/(E$6-$B11)/(1+E$6)^DCF!$I$6+(DCF!$C$28-DCF!$C$29+DCF!$C$30))/DCF!$C$32 | F11: =(SUMPRODUCT(DCF!$E$11:$I$11,1/(1+F$6)^DCF!$E$7:$I$7)+DCF!$I$9*(1+$B11)/(F$6-$B11)/(1+F$6)^DCF!$I$6+(DCF!$C$28-DCF!$C$29+DCF!$C$30))/DCF!$C$32 | G11: =(SUMPRODUCT(DCF!$E$11:$I$11,1/(1+G$6)^DCF!$E$7:$I$7)+DCF!$I$9*(1+$B11)/(G$6-$B11)/(1+G$6)^DCF!$I$6+(DCF!$C$28-DCF!$C$29+DCF!$C$30))/DCF!$C$32 | H11: =(SUMPRODUCT(DCF!$E$11:$I$11,1/(1+H$6)^DCF!$E$7:$I$7)+DCF!$I$9*(1+$B11)/(H$6-$B11)/(1+H$6)^DCF!$I$6+(DCF!$C$28-DCF!$C$29+DCF!$C$30))/DCF!$C$32 | I11: =(SUMPRODUCT(DCF!$E$11:$I$11,1/(1+I$6)^DCF!$E$7:$I$7)+DCF!$I$9*(1+$B11)/(I$6-$B11)/(1+I$6)^DCF!$I$6+(DCF!$C$28-DCF!$C$29+DCF!$C$30))/DCF!$C$32 | J11: =(SUMPRODUCT(DCF!$E$11:$I$11,1/(1+J$6)^DCF!$E$7:$I$7)+DCF!$I$9*(1+$B11)/(J$6-$B11)/(1+J$6)^DCF!$I$6+(DCF!$C$28-DCF!$C$29+DCF!$C$30))/DCF!$C$32 | K11: =(SUMPRODUCT(DCF!$E$11:$I$11,1/(1+K$6)^DCF!$E$7:$I$7)+DCF!$I$9*(1+$B11)/(K$6-$B11)/(1+K$6)^DCF!$I$6+(DCF!$C$28-DCF!$C$29+DCF!$C$30))/DCF!$C$32
B12: =$B$11+(1)*$N$6 | C12: =(SUMPRODUCT(DCF!$E$11:$I$11,1/(1+C$6)^DCF!$E$7:$I$7)+DCF!$I$9*(1+$B12)/(C$6-$B12)/(1+C$6)^DCF!$I$6+(DCF!$C$28-DCF!$C$29+DCF!$C$30))/DCF!$C$32 | D12: =(SUMPRODUCT(DCF!$E$11:$I$11,1/(1+D$6)^DCF!$E$7:$I$7)+DCF!$I$9*(1+$B12)/(D$6-$B12)/(1+D$6)^DCF!$I$6+(DCF!$C$28-DCF!$C$29+DCF!$C$30))/DCF!$C$32 | E12: =(SUMPRODUCT(DCF!$E$11:$I$11,1/(1+E$6)^DCF!$E$7:$I$7)+DCF!$I$9*(1+$B12)/(E$6-$B12)/(1+E$6)^DCF!$I$6+(DCF!$C$28-DCF!$C$29+DCF!$C$30))/DCF!$C$32 | F12: =(SUMPRODUCT(DCF!$E$11:$I$11,1/(1+F$6)^DCF!$E$7:$I$7)+DCF!$I$9*(1+$B12)/(F$6-$B12)/(1+F$6)^DCF!$I$6+(DCF!$C$28-DCF!$C$29+DCF!$C$30))/DCF!$C$32 | G12: =(SUMPRODUCT(DCF!$E$11:$I$11,1/(1+G$6)^DCF!$E$7:$I$7)+DCF!$I$9*(1+$B12)/(G$6-$B12)/(1+G$6)^DCF!$I$6+(DCF!$C$28-DCF!$C$29+DCF!$C$30))/DCF!$C$32 | H12: =(SUMPRODUCT(DCF!$E$11:$I$11,1/(1+H$6)^DCF!$E$7:$I$7)+DCF!$I$9*(1+$B12)/(H$6-$B12)/(1+H$6)^DCF!$I$6+(DCF!$C$28-DCF!$C$29+DCF!$C$30))/DCF!$C$32 | I12: =(SUMPRODUCT(DCF!$E$11:$I$11,1/(1+I$6)^DCF!$E$7:$I$7)+DCF!$I$9*(1+$B12)/(I$6-$B12)/(1+I$6)^DCF!$I$6+(DCF!$C$28-DCF!$C$29+DCF!$C$30))/DCF!$C$32 | J12: =(SUMPRODUCT(DCF!$E$11:$I$11,1/(1+J$6)^DCF!$E$7:$I$7)+DCF!$I$9*(1+$B12)/(J$6-$B12)/(1+J$6)^DCF!$I$6+(DCF!$C$28-DCF!$C$29+DCF!$C$30))/DCF!$C$32 | K12: =(SUMPRODUCT(DCF!$E$11:$I$11,1/(1+K$6)^DCF!$E$7:$I$7)+DCF!$I$9*(1+$B12)/(K$6-$B12)/(1+K$6)^DCF!$I$6+(DCF!$C$28-DCF!$C$29+DCF!$C$30))/DCF!$C$32
B13: =$B$11+(2)*$N$6 | C13: =(SUMPRODUCT(DCF!$E$11:$I$11,1/(1+C$6)^DCF!$E$7:$I$7)+DCF!$I$9*(1+$B13)/(C$6-$B13)/(1+C$6)^DCF!$I$6+(DCF!$C$28-DCF!$C$29+DCF!$C$30))/DCF!$C$32 | D13: =(SUMPRODUCT(DCF!$E$11:$I$11,1/(1+D$6)^DCF!$E$7:$I$7)+DCF!$I$9*(1+$B13)/(D$6-$B13)/(1+D$6)^DCF!$I$6+(DCF!$C$28-DCF!$C$29+DCF!$C$30))/DCF!$C$32 | E13: =(SUMPRODUCT(DCF!$E$11:$I$11,1/(1+E$6)^DCF!$E$7:$I$7)+DCF!$I$9*(1+$B13)/(E$6-$B13)/(1+E$6)^DCF!$I$6+(DCF!$C$28-DCF!$C$29+DCF!$C$30))/DCF!$C$32 | F13: =(SUMPRODUCT(DCF!$E$11:$I$11,1/(1+F$6)^DCF!$E$7:$I$7)+DCF!$I$9*(1+$B13)/(F$6-$B13)/(1+F$6)^DCF!$I$6+(DCF!$C$28-DCF!$C$29+DCF!$C$30))/DCF!$C$32 | G13: =(SUMPRODUCT(DCF!$E$11:$I$11,1/(1+G$6)^DCF!$E$7:$I$7)+DCF!$I$9*(1+$B13)/(G$6-$B13)/(1+G$6)^DCF!$I$6+(DCF!$C$28-DCF!$C$29+DCF!$C$30))/DCF!$C$32 | H13: =(SUMPRODUCT(DCF!$E$11:$I$11,1/(1+H$6)^DCF!$E$7:$I$7)+DCF!$I$9*(1+$B13)/(H$6-$B13)/(1+H$6)^DCF!$I$6+(DCF!$C$28-DCF!$C$29+DCF!$C$30))/DCF!$C$32 | I13: =(SUMPRODUCT(DCF!$E$11:$I$11,1/(1+I$6)^DCF!$E$7:$I$7)+DCF!$I$9*(1+$B13)/(I$6-$B13)/(1+I$6)^DCF!$I$6+(DCF!$C$28-DCF!$C$29+DCF!$C$30))/DCF!$C$32 | J13: =(SUMPRODUCT(DCF!$E$11:$I$11,1/(1+J$6)^DCF!$E$7:$I$7)+DCF!$I$9*(1+$B13)/(J$6-$B13)/(1+J$6)^DCF!$I$6+(DCF!$C$28-DCF!$C$29+DCF!$C$30))/DCF!$C$32 | K13: =(SUMPRODUCT(DCF!$E$11:$I$11,1/(1+K$6)^DCF!$E$7:$I$7)+DCF!$I$9*(1+$B13)/(K$6-$B13)/(1+K$6)^DCF!$I$6+(DCF!$C$28-DCF!$C$29+DCF!$C$30))/DCF!$C$32
B14: =$B$11+(3)*$N$6 | C14: =(SUMPRODUCT(DCF!$E$11:$I$11,1/(1+C$6)^DCF!$E$7:$I$7)+DCF!$I$9*(1+$B14)/(C$6-$B14)/(1+C$6)^DCF!$I$6+(DCF!$C$28-DCF!$C$29+DCF!$C$30))/DCF!$C$32 | D14: =(SUMPRODUCT(DCF!$E$11:$I$11,1/(1+D$6)^DCF!$E$7:$I$7)+DCF!$I$9*(1+$B14)/(D$6-$B14)/(1+D$6)^DCF!$I$6+(DCF!$C$28-DCF!$C$29+DCF!$C$30))/DCF!$C$32 | E14: =(SUMPRODUCT(DCF!$E$11:$I$11,1/(1+E$6)^DCF!$E$7:$I$7)+DCF!$I$9*(1+$B14)/(E$6-$B14)/(1+E$6)^DCF!$I$6+(DCF!$C$28-DCF!$C$29+DCF!$C$30))/DCF!$C$32 | F14: =(SUMPRODUCT(DCF!$E$11:$I$11,1/(1+F$6)^DCF!$E$7:$I$7)+DCF!$I$9*(1+$B14)/(F$6-$B14)/(1+F$6)^DCF!$I$6+(DCF!$C$28-DCF!$C$29+DCF!$C$30))/DCF!$C$32 | G14: =(SUMPRODUCT(DCF!$E$11:$I$11,1/(1+G$6)^DCF!$E$7:$I$7)+DCF!$I$9*(1+$B14)/(G$6-$B14)/(1+G$6)^DCF!$I$6+(DCF!$C$28-DCF!$C$29+DCF!$C$30))/DCF!$C$32 | H14: =(SUMPRODUCT(DCF!$E$11:$I$11,1/(1+H$6)^DCF!$E$7:$I$7)+DCF!$I$9*(1+$B14)/(H$6-$B14)/(1+H$6)^DCF!$I$6+(DCF!$C$28-DCF!$C$29+DCF!$C$30))/DCF!$C$32 | I14: =(SUMPRODUCT(DCF!$E$11:$I$11,1/(1+I$6)^DCF!$E$7:$I$7)+DCF!$I$9*(1+$B14)/(I$6-$B14)/(1+I$6)^DCF!$I$6+(DCF!$C$28-DCF!$C$29+DCF!$C$30))/DCF!$C$32 | J14: =(SUMPRODUCT(DCF!$E$11:$I$11,1/(1+J$6)^DCF!$E$7:$I$7)+DCF!$I$9*(1+$B14)/(J$6-$B14)/(1+J$6)^DCF!$I$6+(DCF!$C$28-DCF!$C$29+DCF!$C$30))/DCF!$C$32 | K14: =(SUMPRODUCT(DCF!$E$11:$I$11,1/(1+K$6)^DCF!$E$7:$I$7)+DCF!$I$9*(1+$B14)/(K$6-$B14)/(1+K$6)^DCF!$I$6+(DCF!$C$28-DCF!$C$29+DCF!$C$30))/DCF!$C$32
B15: =$B$11+(4)*$N$6 | C15: =(SUMPRODUCT(DCF!$E$11:$I$11,1/(1+C$6)^DCF!$E$7:$I$7)+DCF!$I$9*(1+$B15)/(C$6-$B15)/(1+C$6)^DCF!$I$6+(DCF!$C$28-DCF!$C$29+DCF!$C$30))/DCF!$C$32 | D15: =(SUMPRODUCT(DCF!$E$11:$I$11,1/(1+D$6)^DCF!$E$7:$I$7)+DCF!$I$9*(1+$B15)/(D$6-$B15)/(1+D$6)^DCF!$I$6+(DCF!$C$28-DCF!$C$29+DCF!$C$30))/DCF!$C$32 | E15: =(SUMPRODUCT(DCF!$E$11:$I$11,1/(1+E$6)^DCF!$E$7:$I$7)+DCF!$I$9*(1+$B15)/(E$6-$B15)/(1+E$6)^DCF!$I$6+(DCF!$C$28-DCF!$C$29+DCF!$C$30))/DCF!$C$32 | F15: =(SUMPRODUCT(DCF!$E$11:$I$11,1/(1+F$6)^DCF!$E$7:$I$7)+DCF!$I$9*(1+$B15)/(F$6-$B15)/(1+F$6)^DCF!$I$6+(DCF!$C$28-DCF!$C$29+DCF!$C$30))/DCF!$C$32 | G15: =(SUMPRODUCT(DCF!$E$11:$I$11,1/(1+G$6)^DCF!$E$7:$I$7)+DCF!$I$9*(1+$B15)/(G$6-$B15)/(1+G$6)^DCF!$I$6+(DCF!$C$28-DCF!$C$29+DCF!$C$30))/DCF!$C$32 | H15: =(SUMPRODUCT(DCF!$E$11:$I$11,1/(1+H$6)^DCF!$E$7:$I$7)+DCF!$I$9*(1+$B15)/(H$6-$B15)/(1+H$6)^DCF!$I$6+(DCF!$C$28-DCF!$C$29+DCF!$C$30))/DCF!$C$32 | I15: =(SUMPRODUCT(DCF!$E$11:$I$11,1/(1+I$6)^DCF!$E$7:$I$7)+DCF!$I$9*(1+$B15)/(I$6-$B15)/(1+I$6)^DCF!$I$6+(DCF!$C$28-DCF!$C$29+DCF!$C$30))/DCF!$C$32 | J15: =(SUMPRODUCT(DCF!$E$11:$I$11,1/(1+J$6)^DCF!$E$7:$I$7)+DCF!$I$9*(1+$B15)/(J$6-$B15)/(1+J$6)^DCF!$I$6+(DCF!$C$28-DCF!$C$29+DCF!$C$30))/DCF!$C$32 | K15: =(SUMPRODUCT(DCF!$E$11:$I$11,1/(1+K$6)^DCF!$E$7:$I$7)+DCF!$I$9*(1+$B15)/(K$6-$B15)/(1+K$6)^DCF!$I$6+(DCF!$C$28-DCF!$C$29+DCF!$C$30))/DCF!$C$32
B17: Table 2: WACC vs exit EV/EBITDA multiple (Exit Multiple method)
C18: WACC →
B19: Multiple ↓ / WACC → | C19: =$G$19+(-4)*$N$5 | D19: =$G$19+(-3)*$N$5 | E19: =$G$19+(-2)*$N$5 | F19: =$G$19+(-1)*$N$5 | G19: =WACC!$C$35 | H19: =$G$19+(1)*$N$5 | I19: =$G$19+(2)*$N$5 | J19: =$G$19+(3)*$N$5 | K19: =$G$19+(4)*$N$5
B20: =$B$24+(-4)*$N$7 | C20: =(SUMPRODUCT(DCF!$E$11:$I$11,1/(1+C$19)^DCF!$E$7:$I$7)+Forecast!$L$13*$B20/(1+C$19)^DCF!$I$6+(DCF!$C$28-DCF!$C$29+DCF!$C$30))/DCF!$C$32 | D20: =(SUMPRODUCT(DCF!$E$11:$I$11,1/(1+D$19)^DCF!$E$7:$I$7)+Forecast!$L$13*$B20/(1+D$19)^DCF!$I$6+(DCF!$C$28-DCF!$C$29+DCF!$C$30))/DCF!$C$32 | E20: =(SUMPRODUCT(DCF!$E$11:$I$11,1/(1+E$19)^DCF!$E$7:$I$7)+Forecast!$L$13*$B20/(1+E$19)^DCF!$I$6+(DCF!$C$28-DCF!$C$29+DCF!$C$30))/DCF!$C$32 | F20: =(SUMPRODUCT(DCF!$E$11:$I$11,1/(1+F$19)^DCF!$E$7:$I$7)+Forecast!$L$13*$B20/(1+F$19)^DCF!$I$6+(DCF!$C$28-DCF!$C$29+DCF!$C$30))/DCF!$C$32 | G20: =(SUMPRODUCT(DCF!$E$11:$I$11,1/(1+G$19)^DCF!$E$7:$I$7)+Forecast!$L$13*$B20/(1+G$19)^DCF!$I$6+(DCF!$C$28-DCF!$C$29+DCF!$C$30))/DCF!$C$32 | H20: =(SUMPRODUCT(DCF!$E$11:$I$11,1/(1+H$19)^DCF!$E$7:$I$7)+Forecast!$L$13*$B20/(1+H$19)^DCF!$I$6+(DCF!$C$28-DCF!$C$29+DCF!$C$30))/DCF!$C$32 | I20: =(SUMPRODUCT(DCF!$E$11:$I$11,1/(1+I$19)^DCF!$E$7:$I$7)+Forecast!$L$13*$B20/(1+I$19)^DCF!$I$6+(DCF!$C$28-DCF!$C$29+DCF!$C$30))/DCF!$C$32 | J20: =(SUMPRODUCT(DCF!$E$11:$I$11,1/(1+J$19)^DCF!$E$7:$I$7)+Forecast!$L$13*$B20/(1+J$19)^DCF!$I$6+(DCF!$C$28-DCF!$C$29+DCF!$C$30))/DCF!$C$32 | K20: =(SUMPRODUCT(DCF!$E$11:$I$11,1/(1+K$19)^DCF!$E$7:$I$7)+Forecast!$L$13*$B20/(1+K$19)^DCF!$I$6+(DCF!$C$28-DCF!$C$29+DCF!$C$30))/DCF!$C$32
B21: =$B$24+(-3)*$N$7 | C21: =(SUMPRODUCT(DCF!$E$11:$I$11,1/(1+C$19)^DCF!$E$7:$I$7)+Forecast!$L$13*$B21/(1+C$19)^DCF!$I$6+(DCF!$C$28-DCF!$C$29+DCF!$C$30))/DCF!$C$32 | D21: =(SUMPRODUCT(DCF!$E$11:$I$11,1/(1+D$19)^DCF!$E$7:$I$7)+Forecast!$L$13*$B21/(1+D$19)^DCF!$I$6+(DCF!$C$28-DCF!$C$29+DCF!$C$30))/DCF!$C$32 | E21: =(SUMPRODUCT(DCF!$E$11:$I$11,1/(1+E$19)^DCF!$E$7:$I$7)+Forecast!$L$13*$B21/(1+E$19)^DCF!$I$6+(DCF!$C$28-DCF!$C$29+DCF!$C$30))/DCF!$C$32 | F21: =(SUMPRODUCT(DCF!$E$11:$I$11,1/(1+F$19)^DCF!$E$7:$I$7)+Forecast!$L$13*$B21/(1+F$19)^DCF!$I$6+(DCF!$C$28-DCF!$C$29+DCF!$C$30))/DCF!$C$32 | G21: =(SUMPRODUCT(DCF!$E$11:$I$11,1/(1+G$19)^DCF!$E$7:$I$7)+Forecast!$L$13*$B21/(1+G$19)^DCF!$I$6+(DCF!$C$28-DCF!$C$29+DCF!$C$30))/DCF!$C$32 | H21: =(SUMPRODUCT(DCF!$E$11:$I$11,1/(1+H$19)^DCF!$E$7:$I$7)+Forecast!$L$13*$B21/(1+H$19)^DCF!$I$6+(DCF!$C$28-DCF!$C$29+DCF!$C$30))/DCF!$C$32 | I21: =(SUMPRODUCT(DCF!$E$11:$I$11,1/(1+I$19)^DCF!$E$7:$I$7)+Forecast!$L$13*$B21/(1+I$19)^DCF!$I$6+(DCF!$C$28-DCF!$C$29+DCF!$C$30))/DCF!$C$32 | J21: =(SUMPRODUCT(DCF!$E$11:$I$11,1/(1+J$19)^DCF!$E$7:$I$7)+Forecast!$L$13*$B21/(1+J$19)^DCF!$I$6+(DCF!$C$28-DCF!$C$29+DCF!$C$30))/DCF!$C$32 | K21: =(SUMPRODUCT(DCF!$E$11:$I$11,1/(1+K$19)^DCF!$E$7:$I$7)+Forecast!$L$13*$B21/(1+K$19)^DCF!$I$6+(DCF!$C$28-DCF!$C$29+DCF!$C$30))/DCF!$C$32
B22: =$B$24+(-2)*$N$7 | C22: =(SUMPRODUCT(DCF!$E$11:$I$11,1/(1+C$19)^DCF!$E$7:$I$7)+Forecast!$L$13*$B22/(1+C$19)^DCF!$I$6+(DCF!$C$28-DCF!$C$29+DCF!$C$30))/DCF!$C$32 | D22: =(SUMPRODUCT(DCF!$E$11:$I$11,1/(1+D$19)^DCF!$E$7:$I$7)+Forecast!$L$13*$B22/(1+D$19)^DCF!$I$6+(DCF!$C$28-DCF!$C$29+DCF!$C$30))/DCF!$C$32 | E22: =(SUMPRODUCT(DCF!$E$11:$I$11,1/(1+E$19)^DCF!$E$7:$I$7)+Forecast!$L$13*$B22/(1+E$19)^DCF!$I$6+(DCF!$C$28-DCF!$C$29+DCF!$C$30))/DCF!$C$32 | F22: =(SUMPRODUCT(DCF!$E$11:$I$11,1/(1+F$19)^DCF!$E$7:$I$7)+Forecast!$L$13*$B22/(1+F$19)^DCF!$I$6+(DCF!$C$28-DCF!$C$29+DCF!$C$30))/DCF!$C$32 | G22: =(SUMPRODUCT(DCF!$E$11:$I$11,1/(1+G$19)^DCF!$E$7:$I$7)+Forecast!$L$13*$B22/(1+G$19)^DCF!$I$6+(DCF!$C$28-DCF!$C$29+DCF!$C$30))/DCF!$C$32 | H22: =(SUMPRODUCT(DCF!$E$11:$I$11,1/(1+H$19)^DCF!$E$7:$I$7)+Forecast!$L$13*$B22/(1+H$19)^DCF!$I$6+(DCF!$C$28-DCF!$C$29+DCF!$C$30))/DCF!$C$32 | I22: =(SUMPRODUCT(DCF!$E$11:$I$11,1/(1+I$19)^DCF!$E$7:$I$7)+Forecast!$L$13*$B22/(1+I$19)^DCF!$I$6+(DCF!$C$28-DCF!$C$29+DCF!$C$30))/DCF!$C$32 | J22: =(SUMPRODUCT(DCF!$E$11:$I$11,1/(1+J$19)^DCF!$E$7:$I$7)+Forecast!$L$13*$B22/(1+J$19)^DCF!$I$6+(DCF!$C$28-DCF!$C$29+DCF!$C$30))/DCF!$C$32 | K22: =(SUMPRODUCT(DCF!$E$11:$I$11,1/(1+K$19)^DCF!$E$7:$I$7)+Forecast!$L$13*$B22/(1+K$19)^DCF!$I$6+(DCF!$C$28-DCF!$C$29+DCF!$C$30))/DCF!$C$32
B23: =$B$24+(-1)*$N$7 | C23: =(SUMPRODUCT(DCF!$E$11:$I$11,1/(1+C$19)^DCF!$E$7:$I$7)+Forecast!$L$13*$B23/(1+C$19)^DCF!$I$6+(DCF!$C$28-DCF!$C$29+DCF!$C$30))/DCF!$C$32 | D23: =(SUMPRODUCT(DCF!$E$11:$I$11,1/(1+D$19)^DCF!$E$7:$I$7)+Forecast!$L$13*$B23/(1+D$19)^DCF!$I$6+(DCF!$C$28-DCF!$C$29+DCF!$C$30))/DCF!$C$32 | E23: =(SUMPRODUCT(DCF!$E$11:$I$11,1/(1+E$19)^DCF!$E$7:$I$7)+Forecast!$L$13*$B23/(1+E$19)^DCF!$I$6+(DCF!$C$28-DCF!$C$29+DCF!$C$30))/DCF!$C$32 | F23: =(SUMPRODUCT(DCF!$E$11:$I$11,1/(1+F$19)^DCF!$E$7:$I$7)+Forecast!$L$13*$B23/(1+F$19)^DCF!$I$6+(DCF!$C$28-DCF!$C$29+DCF!$C$30))/DCF!$C$32 | G23: =(SUMPRODUCT(DCF!$E$11:$I$11,1/(1+G$19)^DCF!$E$7:$I$7)+Forecast!$L$13*$B23/(1+G$19)^DCF!$I$6+(DCF!$C$28-DCF!$C$29+DCF!$C$30))/DCF!$C$32 | H23: =(SUMPRODUCT(DCF!$E$11:$I$11,1/(1+H$19)^DCF!$E$7:$I$7)+Forecast!$L$13*$B23/(1+H$19)^DCF!$I$6+(DCF!$C$28-DCF!$C$29+DCF!$C$30))/DCF!$C$32 | I23: =(SUMPRODUCT(DCF!$E$11:$I$11,1/(1+I$19)^DCF!$E$7:$I$7)+Forecast!$L$13*$B23/(1+I$19)^DCF!$I$6+(DCF!$C$28-DCF!$C$29+DCF!$C$30))/DCF!$C$32 | J23: =(SUMPRODUCT(DCF!$E$11:$I$11,1/(1+J$19)^DCF!$E$7:$I$7)+Forecast!$L$13*$B23/(1+J$19)^DCF!$I$6+(DCF!$C$28-DCF!$C$29+DCF!$C$30))/DCF!$C$32 | K23: =(SUMPRODUCT(DCF!$E$11:$I$11,1/(1+K$19)^DCF!$E$7:$I$7)+Forecast!$L$13*$B23/(1+K$19)^DCF!$I$6+(DCF!$C$28-DCF!$C$29+DCF!$C$30))/DCF!$C$32
B24: =Assumptions!$E$75 | C24: =(SUMPRODUCT(DCF!$E$11:$I$11,1/(1+C$19)^DCF!$E$7:$I$7)+Forecast!$L$13*$B24/(1+C$19)^DCF!$I$6+(DCF!$C$28-DCF!$C$29+DCF!$C$30))/DCF!$C$32 | D24: =(SUMPRODUCT(DCF!$E$11:$I$11,1/(1+D$19)^DCF!$E$7:$I$7)+Forecast!$L$13*$B24/(1+D$19)^DCF!$I$6+(DCF!$C$28-DCF!$C$29+DCF!$C$30))/DCF!$C$32 | E24: =(SUMPRODUCT(DCF!$E$11:$I$11,1/(1+E$19)^DCF!$E$7:$I$7)+Forecast!$L$13*$B24/(1+E$19)^DCF!$I$6+(DCF!$C$28-DCF!$C$29+DCF!$C$30))/DCF!$C$32 | F24: =(SUMPRODUCT(DCF!$E$11:$I$11,1/(1+F$19)^DCF!$E$7:$I$7)+Forecast!$L$13*$B24/(1+F$19)^DCF!$I$6+(DCF!$C$28-DCF!$C$29+DCF!$C$30))/DCF!$C$32 | G24: =(SUMPRODUCT(DCF!$E$11:$I$11,1/(1+G$19)^DCF!$E$7:$I$7)+Forecast!$L$13*$B24/(1+G$19)^DCF!$I$6+(DCF!$C$28-DCF!$C$29+DCF!$C$30))/DCF!$C$32 | H24: =(SUMPRODUCT(DCF!$E$11:$I$11,1/(1+H$19)^DCF!$E$7:$I$7)+Forecast!$L$13*$B24/(1+H$19)^DCF!$I$6+(DCF!$C$28-DCF!$C$29+DCF!$C$30))/DCF!$C$32 | I24: =(SUMPRODUCT(DCF!$E$11:$I$11,1/(1+I$19)^DCF!$E$7:$I$7)+Forecast!$L$13*$B24/(1+I$19)^DCF!$I$6+(DCF!$C$28-DCF!$C$29+DCF!$C$30))/DCF!$C$32 | J24: =(SUMPRODUCT(DCF!$E$11:$I$11,1/(1+J$19)^DCF!$E$7:$I$7)+Forecast!$L$13*$B24/(1+J$19)^DCF!$I$6+(DCF!$C$28-DCF!$C$29+DCF!$C$30))/DCF!$C$32 | K24: =(SUMPRODUCT(DCF!$E$11:$I$11,1/(1+K$19)^DCF!$E$7:$I$7)+Forecast!$L$13*$B24/(1+K$19)^DCF!$I$6+(DCF!$C$28-DCF!$C$29+DCF!$C$30))/DCF!$C$32
B25: =$B$24+(1)*$N$7 | C25: =(SUMPRODUCT(DCF!$E$11:$I$11,1/(1+C$19)^DCF!$E$7:$I$7)+Forecast!$L$13*$B25/(1+C$19)^DCF!$I$6+(DCF!$C$28-DCF!$C$29+DCF!$C$30))/DCF!$C$32 | D25: =(SUMPRODUCT(DCF!$E$11:$I$11,1/(1+D$19)^DCF!$E$7:$I$7)+Forecast!$L$13*$B25/(1+D$19)^DCF!$I$6+(DCF!$C$28-DCF!$C$29+DCF!$C$30))/DCF!$C$32 | E25: =(SUMPRODUCT(DCF!$E$11:$I$11,1/(1+E$19)^DCF!$E$7:$I$7)+Forecast!$L$13*$B25/(1+E$19)^DCF!$I$6+(DCF!$C$28-DCF!$C$29+DCF!$C$30))/DCF!$C$32 | F25: =(SUMPRODUCT(DCF!$E$11:$I$11,1/(1+F$19)^DCF!$E$7:$I$7)+Forecast!$L$13*$B25/(1+F$19)^DCF!$I$6+(DCF!$C$28-DCF!$C$29+DCF!$C$30))/DCF!$C$32 | G25: =(SUMPRODUCT(DCF!$E$11:$I$11,1/(1+G$19)^DCF!$E$7:$I$7)+Forecast!$L$13*$B25/(1+G$19)^DCF!$I$6+(DCF!$C$28-DCF!$C$29+DCF!$C$30))/DCF!$C$32 | H25: =(SUMPRODUCT(DCF!$E$11:$I$11,1/(1+H$19)^DCF!$E$7:$I$7)+Forecast!$L$13*$B25/(1+H$19)^DCF!$I$6+(DCF!$C$28-DCF!$C$29+DCF!$C$30))/DCF!$C$32 | I25: =(SUMPRODUCT(DCF!$E$11:$I$11,1/(1+I$19)^DCF!$E$7:$I$7)+Forecast!$L$13*$B25/(1+I$19)^DCF!$I$6+(DCF!$C$28-DCF!$C$29+DCF!$C$30))/DCF!$C$32 | J25: =(SUMPRODUCT(DCF!$E$11:$I$11,1/(1+J$19)^DCF!$E$7:$I$7)+Forecast!$L$13*$B25/(1+J$19)^DCF!$I$6+(DCF!$C$28-DCF!$C$29+DCF!$C$30))/DCF!$C$32 | K25: =(SUMPRODUCT(DCF!$E$11:$I$11,1/(1+K$19)^DCF!$E$7:$I$7)+Forecast!$L$13*$B25/(1+K$19)^DCF!$I$6+(DCF!$C$28-DCF!$C$29+DCF!$C$30))/DCF!$C$32
B26: =$B$24+(2)*$N$7 | C26: =(SUMPRODUCT(DCF!$E$11:$I$11,1/(1+C$19)^DCF!$E$7:$I$7)+Forecast!$L$13*$B26/(1+C$19)^DCF!$I$6+(DCF!$C$28-DCF!$C$29+DCF!$C$30))/DCF!$C$32 | D26: =(SUMPRODUCT(DCF!$E$11:$I$11,1/(1+D$19)^DCF!$E$7:$I$7)+Forecast!$L$13*$B26/(1+D$19)^DCF!$I$6+(DCF!$C$28-DCF!$C$29+DCF!$C$30))/DCF!$C$32 | E26: =(SUMPRODUCT(DCF!$E$11:$I$11,1/(1+E$19)^DCF!$E$7:$I$7)+Forecast!$L$13*$B26/(1+E$19)^DCF!$I$6+(DCF!$C$28-DCF!$C$29+DCF!$C$30))/DCF!$C$32 | F26: =(SUMPRODUCT(DCF!$E$11:$I$11,1/(1+F$19)^DCF!$E$7:$I$7)+Forecast!$L$13*$B26/(1+F$19)^DCF!$I$6+(DCF!$C$28-DCF!$C$29+DCF!$C$30))/DCF!$C$32 | G26: =(SUMPRODUCT(DCF!$E$11:$I$11,1/(1+G$19)^DCF!$E$7:$I$7)+Forecast!$L$13*$B26/(1+G$19)^DCF!$I$6+(DCF!$C$28-DCF!$C$29+DCF!$C$30))/DCF!$C$32 | H26: =(SUMPRODUCT(DCF!$E$11:$I$11,1/(1+H$19)^DCF!$E$7:$I$7)+Forecast!$L$13*$B26/(1+H$19)^DCF!$I$6+(DCF!$C$28-DCF!$C$29+DCF!$C$30))/DCF!$C$32 | I26: =(SUMPRODUCT(DCF!$E$11:$I$11,1/(1+I$19)^DCF!$E$7:$I$7)+Forecast!$L$13*$B26/(1+I$19)^DCF!$I$6+(DCF!$C$28-DCF!$C$29+DCF!$C$30))/DCF!$C$32 | J26: =(SUMPRODUCT(DCF!$E$11:$I$11,1/(1+J$19)^DCF!$E$7:$I$7)+Forecast!$L$13*$B26/(1+J$19)^DCF!$I$6+(DCF!$C$28-DCF!$C$29+DCF!$C$30))/DCF!$C$32 | K26: =(SUMPRODUCT(DCF!$E$11:$I$11,1/(1+K$19)^DCF!$E$7:$I$7)+Forecast!$L$13*$B26/(1+K$19)^DCF!$I$6+(DCF!$C$28-DCF!$C$29+DCF!$C$30))/DCF!$C$32
B27: =$B$24+(3)*$N$7 | C27: =(SUMPRODUCT(DCF!$E$11:$I$11,1/(1+C$19)^DCF!$E$7:$I$7)+Forecast!$L$13*$B27/(1+C$19)^DCF!$I$6+(DCF!$C$28-DCF!$C$29+DCF!$C$30))/DCF!$C$32 | D27: =(SUMPRODUCT(DCF!$E$11:$I$11,1/(1+D$19)^DCF!$E$7:$I$7)+Forecast!$L$13*$B27/(1+D$19)^DCF!$I$6+(DCF!$C$28-DCF!$C$29+DCF!$C$30))/DCF!$C$32 | E27: =(SUMPRODUCT(DCF!$E$11:$I$11,1/(1+E$19)^DCF!$E$7:$I$7)+Forecast!$L$13*$B27/(1+E$19)^DCF!$I$6+(DCF!$C$28-DCF!$C$29+DCF!$C$30))/DCF!$C$32 | F27: =(SUMPRODUCT(DCF!$E$11:$I$11,1/(1+F$19)^DCF!$E$7:$I$7)+Forecast!$L$13*$B27/(1+F$19)^DCF!$I$6+(DCF!$C$28-DCF!$C$29+DCF!$C$30))/DCF!$C$32 | G27: =(SUMPRODUCT(DCF!$E$11:$I$11,1/(1+G$19)^DCF!$E$7:$I$7)+Forecast!$L$13*$B27/(1+G$19)^DCF!$I$6+(DCF!$C$28-DCF!$C$29+DCF!$C$30))/DCF!$C$32 | H27: =(SUMPRODUCT(DCF!$E$11:$I$11,1/(1+H$19)^DCF!$E$7:$I$7)+Forecast!$L$13*$B27/(1+H$19)^DCF!$I$6+(DCF!$C$28-DCF!$C$29+DCF!$C$30))/DCF!$C$32 | I27: =(SUMPRODUCT(DCF!$E$11:$I$11,1/(1+I$19)^DCF!$E$7:$I$7)+Forecast!$L$13*$B27/(1+I$19)^DCF!$I$6+(DCF!$C$28-DCF!$C$29+DCF!$C$30))/DCF!$C$32 | J27: =(SUMPRODUCT(DCF!$E$11:$I$11,1/(1+J$19)^DCF!$E$7:$I$7)+Forecast!$L$13*$B27/(1+J$19)^DCF!$I$6+(DCF!$C$28-DCF!$C$29+DCF!$C$30))/DCF!$C$32 | K27: =(SUMPRODUCT(DCF!$E$11:$I$11,1/(1+K$19)^DCF!$E$7:$I$7)+Forecast!$L$13*$B27/(1+K$19)^DCF!$I$6+(DCF!$C$28-DCF!$C$29+DCF!$C$30))/DCF!$C$32
B28: =$B$24+(4)*$N$7 | C28: =(SUMPRODUCT(DCF!$E$11:$I$11,1/(1+C$19)^DCF!$E$7:$I$7)+Forecast!$L$13*$B28/(1+C$19)^DCF!$I$6+(DCF!$C$28-DCF!$C$29+DCF!$C$30))/DCF!$C$32 | D28: =(SUMPRODUCT(DCF!$E$11:$I$11,1/(1+D$19)^DCF!$E$7:$I$7)+Forecast!$L$13*$B28/(1+D$19)^DCF!$I$6+(DCF!$C$28-DCF!$C$29+DCF!$C$30))/DCF!$C$32 | E28: =(SUMPRODUCT(DCF!$E$11:$I$11,1/(1+E$19)^DCF!$E$7:$I$7)+Forecast!$L$13*$B28/(1+E$19)^DCF!$I$6+(DCF!$C$28-DCF!$C$29+DCF!$C$30))/DCF!$C$32 | F28: =(SUMPRODUCT(DCF!$E$11:$I$11,1/(1+F$19)^DCF!$E$7:$I$7)+Forecast!$L$13*$B28/(1+F$19)^DCF!$I$6+(DCF!$C$28-DCF!$C$29+DCF!$C$30))/DCF!$C$32 | G28: =(SUMPRODUCT(DCF!$E$11:$I$11,1/(1+G$19)^DCF!$E$7:$I$7)+Forecast!$L$13*$B28/(1+G$19)^DCF!$I$6+(DCF!$C$28-DCF!$C$29+DCF!$C$30))/DCF!$C$32 | H28: =(SUMPRODUCT(DCF!$E$11:$I$11,1/(1+H$19)^DCF!$E$7:$I$7)+Forecast!$L$13*$B28/(1+H$19)^DCF!$I$6+(DCF!$C$28-DCF!$C$29+DCF!$C$30))/DCF!$C$32 | I28: =(SUMPRODUCT(DCF!$E$11:$I$11,1/(1+I$19)^DCF!$E$7:$I$7)+Forecast!$L$13*$B28/(1+I$19)^DCF!$I$6+(DCF!$C$28-DCF!$C$29+DCF!$C$30))/DCF!$C$32 | J28: =(SUMPRODUCT(DCF!$E$11:$I$11,1/(1+J$19)^DCF!$E$7:$I$7)+Forecast!$L$13*$B28/(1+J$19)^DCF!$I$6+(DCF!$C$28-DCF!$C$29+DCF!$C$30))/DCF!$C$32 | K28: =(SUMPRODUCT(DCF!$E$11:$I$11,1/(1+K$19)^DCF!$E$7:$I$7)+Forecast!$L$13*$B28/(1+K$19)^DCF!$I$6+(DCF!$C$28-DCF!$C$29+DCF!$C$30))/DCF!$C$32
B30: Reading the tables: shaded cell = live base case and equals the DCF tab price. Bold underlined = implied price at or above today's share price.
B31: Table 3: Blended price, WACC vs terminal growth (multiple held at base)
C32: WACC →
B33: g ↓ / WACC → | C33: =$G$33+(-4)*$N$5 | D33: =$G$33+(-3)*$N$5 | E33: =$G$33+(-2)*$N$5 | F33: =$G$33+(-1)*$N$5 | G33: =WACC!$C$35 | H33: =$G$33+(1)*$N$5 | I33: =$G$33+(2)*$N$5 | J33: =$G$33+(3)*$N$5 | K33: =$G$33+(4)*$N$5
B34: =$B$38+(-4)*$N$6 | C34: =Assumptions!$C$11*((SUMPRODUCT(DCF!$E$11:$I$11,1/(1+C$33)^DCF!$E$7:$I$7)+DCF!$I$9*(1+$B34)/(C$33-$B34)/(1+C$33)^DCF!$I$6+(DCF!$C$28-DCF!$C$29+DCF!$C$30))/DCF!$C$32)+(1-Assumptions!$C$11)*((SUMPRODUCT(DCF!$E$11:$I$11,1/(1+C$33)^DCF!$E$7:$I$7)+Forecast!$L$13*Assumptions!$E$75/(1+C$33)^DCF!$I$6+(DCF!$C$28-DCF!$C$29+DCF!$C$30))/DCF!$C$32) | D34: =Assumptions!$C$11*((SUMPRODUCT(DCF!$E$11:$I$11,1/(1+D$33)^DCF!$E$7:$I$7)+DCF!$I$9*(1+$B34)/(D$33-$B34)/(1+D$33)^DCF!$I$6+(DCF!$C$28-DCF!$C$29+DCF!$C$30))/DCF!$C$32)+(1-Assumptions!$C$11)*((SUMPRODUCT(DCF!$E$11:$I$11,1/(1+D$33)^DCF!$E$7:$I$7)+Forecast!$L$13*Assumptions!$E$75/(1+D$33)^DCF!$I$6+(DCF!$C$28-DCF!$C$29+DCF!$C$30))/DCF!$C$32) | E34: =Assumptions!$C$11*((SUMPRODUCT(DCF!$E$11:$I$11,1/(1+E$33)^DCF!$E$7:$I$7)+DCF!$I$9*(1+$B34)/(E$33-$B34)/(1+E$33)^DCF!$I$6+(DCF!$C$28-DCF!$C$29+DCF!$C$30))/DCF!$C$32)+(1-Assumptions!$C$11)*((SUMPRODUCT(DCF!$E$11:$I$11,1/(1+E$33)^DCF!$E$7:$I$7)+Forecast!$L$13*Assumptions!$E$75/(1+E$33)^DCF!$I$6+(DCF!$C$28-DCF!$C$29+DCF!$C$30))/DCF!$C$32) | F34: =Assumptions!$C$11*((SUMPRODUCT(DCF!$E$11:$I$11,1/(1+F$33)^DCF!$E$7:$I$7)+DCF!$I$9*(1+$B34)/(F$33-$B34)/(1+F$33)^DCF!$I$6+(DCF!$C$28-DCF!$C$29+DCF!$C$30))/DCF!$C$32)+(1-Assumptions!$C$11)*((SUMPRODUCT(DCF!$E$11:$I$11,1/(1+F$33)^DCF!$E$7:$I$7)+Forecast!$L$13*Assumptions!$E$75/(1+F$33)^DCF!$I$6+(DCF!$C$28-DCF!$C$29+DCF!$C$30))/DCF!$C$32) | G34: =Assumptions!$C$11*((SUMPRODUCT(DCF!$E$11:$I$11,1/(1+G$33)^DCF!$E$7:$I$7)+DCF!$I$9*(1+$B34)/(G$33-$B34)/(1+G$33)^DCF!$I$6+(DCF!$C$28-DCF!$C$29+DCF!$C$30))/DCF!$C$32)+(1-Assumptions!$C$11)*((SUMPRODUCT(DCF!$E$11:$I$11,1/(1+G$33)^DCF!$E$7:$I$7)+Forecast!$L$13*Assumptions!$E$75/(1+G$33)^DCF!$I$6+(DCF!$C$28-DCF!$C$29+DCF!$C$30))/DCF!$C$32) | H34: =Assumptions!$C$11*((SUMPRODUCT(DCF!$E$11:$I$11,1/(1+H$33)^DCF!$E$7:$I$7)+DCF!$I$9*(1+$B34)/(H$33-$B34)/(1+H$33)^DCF!$I$6+(DCF!$C$28-DCF!$C$29+DCF!$C$30))/DCF!$C$32)+(1-Assumptions!$C$11)*((SUMPRODUCT(DCF!$E$11:$I$11,1/(1+H$33)^DCF!$E$7:$I$7)+Forecast!$L$13*Assumptions!$E$75/(1+H$33)^DCF!$I$6+(DCF!$C$28-DCF!$C$29+DCF!$C$30))/DCF!$C$32) | I34: =Assumptions!$C$11*((SUMPRODUCT(DCF!$E$11:$I$11,1/(1+I$33)^DCF!$E$7:$I$7)+DCF!$I$9*(1+$B34)/(I$33-$B34)/(1+I$33)^DCF!$I$6+(DCF!$C$28-DCF!$C$29+DCF!$C$30))/DCF!$C$32)+(1-Assumptions!$C$11)*((SUMPRODUCT(DCF!$E$11:$I$11,1/(1+I$33)^DCF!$E$7:$I$7)+Forecast!$L$13*Assumptions!$E$75/(1+I$33)^DCF!$I$6+(DCF!$C$28-DCF!$C$29+DCF!$C$30))/DCF!$C$32) | J34: =Assumptions!$C$11*((SUMPRODUCT(DCF!$E$11:$I$11,1/(1+J$33)^DCF!$E$7:$I$7)+DCF!$I$9*(1+$B34)/(J$33-$B34)/(1+J$33)^DCF!$I$6+(DCF!$C$28-DCF!$C$29+DCF!$C$30))/DCF!$C$32)+(1-Assumptions!$C$11)*((SUMPRODUCT(DCF!$E$11:$I$11,1/(1+J$33)^DCF!$E$7:$I$7)+Forecast!$L$13*Assumptions!$E$75/(1+J$33)^DCF!$I$6+(DCF!$C$28-DCF!$C$29+DCF!$C$30))/DCF!$C$32) | K34: =Assumptions!$C$11*((SUMPRODUCT(DCF!$E$11:$I$11,1/(1+K$33)^DCF!$E$7:$I$7)+DCF!$I$9*(1+$B34)/(K$33-$B34)/(1+K$33)^DCF!$I$6+(DCF!$C$28-DCF!$C$29+DCF!$C$30))/DCF!$C$32)+(1-Assumptions!$C$11)*((SUMPRODUCT(DCF!$E$11:$I$11,1/(1+K$33)^DCF!$E$7:$I$7)+Forecast!$L$13*Assumptions!$E$75/(1+K$33)^DCF!$I$6+(DCF!$C$28-DCF!$C$29+DCF!$C$30))/DCF!$C$32)
B35: =$B$38+(-3)*$N$6 | C35: =Assumptions!$C$11*((SUMPRODUCT(DCF!$E$11:$I$11,1/(1+C$33)^DCF!$E$7:$I$7)+DCF!$I$9*(1+$B35)/(C$33-$B35)/(1+C$33)^DCF!$I$6+(DCF!$C$28-DCF!$C$29+DCF!$C$30))/DCF!$C$32)+(1-Assumptions!$C$11)*((SUMPRODUCT(DCF!$E$11:$I$11,1/(1+C$33)^DCF!$E$7:$I$7)+Forecast!$L$13*Assumptions!$E$75/(1+C$33)^DCF!$I$6+(DCF!$C$28-DCF!$C$29+DCF!$C$30))/DCF!$C$32) | D35: =Assumptions!$C$11*((SUMPRODUCT(DCF!$E$11:$I$11,1/(1+D$33)^DCF!$E$7:$I$7)+DCF!$I$9*(1+$B35)/(D$33-$B35)/(1+D$33)^DCF!$I$6+(DCF!$C$28-DCF!$C$29+DCF!$C$30))/DCF!$C$32)+(1-Assumptions!$C$11)*((SUMPRODUCT(DCF!$E$11:$I$11,1/(1+D$33)^DCF!$E$7:$I$7)+Forecast!$L$13*Assumptions!$E$75/(1+D$33)^DCF!$I$6+(DCF!$C$28-DCF!$C$29+DCF!$C$30))/DCF!$C$32) | E35: =Assumptions!$C$11*((SUMPRODUCT(DCF!$E$11:$I$11,1/(1+E$33)^DCF!$E$7:$I$7)+DCF!$I$9*(1+$B35)/(E$33-$B35)/(1+E$33)^DCF!$I$6+(DCF!$C$28-DCF!$C$29+DCF!$C$30))/DCF!$C$32)+(1-Assumptions!$C$11)*((SUMPRODUCT(DCF!$E$11:$I$11,1/(1+E$33)^DCF!$E$7:$I$7)+Forecast!$L$13*Assumptions!$E$75/(1+E$33)^DCF!$I$6+(DCF!$C$28-DCF!$C$29+DCF!$C$30))/DCF!$C$32) | F35: =Assumptions!$C$11*((SUMPRODUCT(DCF!$E$11:$I$11,1/(1+F$33)^DCF!$E$7:$I$7)+DCF!$I$9*(1+$B35)/(F$33-$B35)/(1+F$33)^DCF!$I$6+(DCF!$C$28-DCF!$C$29+DCF!$C$30))/DCF!$C$32)+(1-Assumptions!$C$11)*((SUMPRODUCT(DCF!$E$11:$I$11,1/(1+F$33)^DCF!$E$7:$I$7)+Forecast!$L$13*Assumptions!$E$75/(1+F$33)^DCF!$I$6+(DCF!$C$28-DCF!$C$29+DCF!$C$30))/DCF!$C$32) | G35: =Assumptions!$C$11*((SUMPRODUCT(DCF!$E$11:$I$11,1/(1+G$33)^DCF!$E$7:$I$7)+DCF!$I$9*(1+$B35)/(G$33-$B35)/(1+G$33)^DCF!$I$6+(DCF!$C$28-DCF!$C$29+DCF!$C$30))/DCF!$C$32)+(1-Assumptions!$C$11)*((SUMPRODUCT(DCF!$E$11:$I$11,1/(1+G$33)^DCF!$E$7:$I$7)+Forecast!$L$13*Assumptions!$E$75/(1+G$33)^DCF!$I$6+(DCF!$C$28-DCF!$C$29+DCF!$C$30))/DCF!$C$32) | H35: =Assumptions!$C$11*((SUMPRODUCT(DCF!$E$11:$I$11,1/(1+H$33)^DCF!$E$7:$I$7)+DCF!$I$9*(1+$B35)/(H$33-$B35)/(1+H$33)^DCF!$I$6+(DCF!$C$28-DCF!$C$29+DCF!$C$30))/DCF!$C$32)+(1-Assumptions!$C$11)*((SUMPRODUCT(DCF!$E$11:$I$11,1/(1+H$33)^DCF!$E$7:$I$7)+Forecast!$L$13*Assumptions!$E$75/(1+H$33)^DCF!$I$6+(DCF!$C$28-DCF!$C$29+DCF!$C$30))/DCF!$C$32) | I35: =Assumptions!$C$11*((SUMPRODUCT(DCF!$E$11:$I$11,1/(1+I$33)^DCF!$E$7:$I$7)+DCF!$I$9*(1+$B35)/(I$33-$B35)/(1+I$33)^DCF!$I$6+(DCF!$C$28-DCF!$C$29+DCF!$C$30))/DCF!$C$32)+(1-Assumptions!$C$11)*((SUMPRODUCT(DCF!$E$11:$I$11,1/(1+I$33)^DCF!$E$7:$I$7)+Forecast!$L$13*Assumptions!$E$75/(1+I$33)^DCF!$I$6+(DCF!$C$28-DCF!$C$29+DCF!$C$30))/DCF!$C$32) | J35: =Assumptions!$C$11*((SUMPRODUCT(DCF!$E$11:$I$11,1/(1+J$33)^DCF!$E$7:$I$7)+DCF!$I$9*(1+$B35)/(J$33-$B35)/(1+J$33)^DCF!$I$6+(DCF!$C$28-DCF!$C$29+DCF!$C$30))/DCF!$C$32)+(1-Assumptions!$C$11)*((SUMPRODUCT(DCF!$E$11:$I$11,1/(1+J$33)^DCF!$E$7:$I$7)+Forecast!$L$13*Assumptions!$E$75/(1+J$33)^DCF!$I$6+(DCF!$C$28-DCF!$C$29+DCF!$C$30))/DCF!$C$32) | K35: =Assumptions!$C$11*((SUMPRODUCT(DCF!$E$11:$I$11,1/(1+K$33)^DCF!$E$7:$I$7)+DCF!$I$9*(1+$B35)/(K$33-$B35)/(1+K$33)^DCF!$I$6+(DCF!$C$28-DCF!$C$29+DCF!$C$30))/DCF!$C$32)+(1-Assumptions!$C$11)*((SUMPRODUCT(DCF!$E$11:$I$11,1/(1+K$33)^DCF!$E$7:$I$7)+Forecast!$L$13*Assumptions!$E$75/(1+K$33)^DCF!$I$6+(DCF!$C$28-DCF!$C$29+DCF!$C$30))/DCF!$C$32)
B36: =$B$38+(-2)*$N$6 | C36: =Assumptions!$C$11*((SUMPRODUCT(DCF!$E$11:$I$11,1/(1+C$33)^DCF!$E$7:$I$7)+DCF!$I$9*(1+$B36)/(C$33-$B36)/(1+C$33)^DCF!$I$6+(DCF!$C$28-DCF!$C$29+DCF!$C$30))/DCF!$C$32)+(1-Assumptions!$C$11)*((SUMPRODUCT(DCF!$E$11:$I$11,1/(1+C$33)^DCF!$E$7:$I$7)+Forecast!$L$13*Assumptions!$E$75/(1+C$33)^DCF!$I$6+(DCF!$C$28-DCF!$C$29+DCF!$C$30))/DCF!$C$32) | D36: =Assumptions!$C$11*((SUMPRODUCT(DCF!$E$11:$I$11,1/(1+D$33)^DCF!$E$7:$I$7)+DCF!$I$9*(1+$B36)/(D$33-$B36)/(1+D$33)^DCF!$I$6+(DCF!$C$28-DCF!$C$29+DCF!$C$30))/DCF!$C$32)+(1-Assumptions!$C$11)*((SUMPRODUCT(DCF!$E$11:$I$11,1/(1+D$33)^DCF!$E$7:$I$7)+Forecast!$L$13*Assumptions!$E$75/(1+D$33)^DCF!$I$6+(DCF!$C$28-DCF!$C$29+DCF!$C$30))/DCF!$C$32) | E36: =Assumptions!$C$11*((SUMPRODUCT(DCF!$E$11:$I$11,1/(1+E$33)^DCF!$E$7:$I$7)+DCF!$I$9*(1+$B36)/(E$33-$B36)/(1+E$33)^DCF!$I$6+(DCF!$C$28-DCF!$C$29+DCF!$C$30))/DCF!$C$32)+(1-Assumptions!$C$11)*((SUMPRODUCT(DCF!$E$11:$I$11,1/(1+E$33)^DCF!$E$7:$I$7)+Forecast!$L$13*Assumptions!$E$75/(1+E$33)^DCF!$I$6+(DCF!$C$28-DCF!$C$29+DCF!$C$30))/DCF!$C$32) | F36: =Assumptions!$C$11*((SUMPRODUCT(DCF!$E$11:$I$11,1/(1+F$33)^DCF!$E$7:$I$7)+DCF!$I$9*(1+$B36)/(F$33-$B36)/(1+F$33)^DCF!$I$6+(DCF!$C$28-DCF!$C$29+DCF!$C$30))/DCF!$C$32)+(1-Assumptions!$C$11)*((SUMPRODUCT(DCF!$E$11:$I$11,1/(1+F$33)^DCF!$E$7:$I$7)+Forecast!$L$13*Assumptions!$E$75/(1+F$33)^DCF!$I$6+(DCF!$C$28-DCF!$C$29+DCF!$C$30))/DCF!$C$32) | G36: =Assumptions!$C$11*((SUMPRODUCT(DCF!$E$11:$I$11,1/(1+G$33)^DCF!$E$7:$I$7)+DCF!$I$9*(1+$B36)/(G$33-$B36)/(1+G$33)^DCF!$I$6+(DCF!$C$28-DCF!$C$29+DCF!$C$30))/DCF!$C$32)+(1-Assumptions!$C$11)*((SUMPRODUCT(DCF!$E$11:$I$11,1/(1+G$33)^DCF!$E$7:$I$7)+Forecast!$L$13*Assumptions!$E$75/(1+G$33)^DCF!$I$6+(DCF!$C$28-DCF!$C$29+DCF!$C$30))/DCF!$C$32) | H36: =Assumptions!$C$11*((SUMPRODUCT(DCF!$E$11:$I$11,1/(1+H$33)^DCF!$E$7:$I$7)+DCF!$I$9*(1+$B36)/(H$33-$B36)/(1+H$33)^DCF!$I$6+(DCF!$C$28-DCF!$C$29+DCF!$C$30))/DCF!$C$32)+(1-Assumptions!$C$11)*((SUMPRODUCT(DCF!$E$11:$I$11,1/(1+H$33)^DCF!$E$7:$I$7)+Forecast!$L$13*Assumptions!$E$75/(1+H$33)^DCF!$I$6+(DCF!$C$28-DCF!$C$29+DCF!$C$30))/DCF!$C$32) | I36: =Assumptions!$C$11*((SUMPRODUCT(DCF!$E$11:$I$11,1/(1+I$33)^DCF!$E$7:$I$7)+DCF!$I$9*(1+$B36)/(I$33-$B36)/(1+I$33)^DCF!$I$6+(DCF!$C$28-DCF!$C$29+DCF!$C$30))/DCF!$C$32)+(1-Assumptions!$C$11)*((SUMPRODUCT(DCF!$E$11:$I$11,1/(1+I$33)^DCF!$E$7:$I$7)+Forecast!$L$13*Assumptions!$E$75/(1+I$33)^DCF!$I$6+(DCF!$C$28-DCF!$C$29+DCF!$C$30))/DCF!$C$32) | J36: =Assumptions!$C$11*((SUMPRODUCT(DCF!$E$11:$I$11,1/(1+J$33)^DCF!$E$7:$I$7)+DCF!$I$9*(1+$B36)/(J$33-$B36)/(1+J$33)^DCF!$I$6+(DCF!$C$28-DCF!$C$29+DCF!$C$30))/DCF!$C$32)+(1-Assumptions!$C$11)*((SUMPRODUCT(DCF!$E$11:$I$11,1/(1+J$33)^DCF!$E$7:$I$7)+Forecast!$L$13*Assumptions!$E$75/(1+J$33)^DCF!$I$6+(DCF!$C$28-DCF!$C$29+DCF!$C$30))/DCF!$C$32) | K36: =Assumptions!$C$11*((SUMPRODUCT(DCF!$E$11:$I$11,1/(1+K$33)^DCF!$E$7:$I$7)+DCF!$I$9*(1+$B36)/(K$33-$B36)/(1+K$33)^DCF!$I$6+(DCF!$C$28-DCF!$C$29+DCF!$C$30))/DCF!$C$32)+(1-Assumptions!$C$11)*((SUMPRODUCT(DCF!$E$11:$I$11,1/(1+K$33)^DCF!$E$7:$I$7)+Forecast!$L$13*Assumptions!$E$75/(1+K$33)^DCF!$I$6+(DCF!$C$28-DCF!$C$29+DCF!$C$30))/DCF!$C$32)
B37: =$B$38+(-1)*$N$6 | C37: =Assumptions!$C$11*((SUMPRODUCT(DCF!$E$11:$I$11,1/(1+C$33)^DCF!$E$7:$I$7)+DCF!$I$9*(1+$B37)/(C$33-$B37)/(1+C$33)^DCF!$I$6+(DCF!$C$28-DCF!$C$29+DCF!$C$30))/DCF!$C$32)+(1-Assumptions!$C$11)*((SUMPRODUCT(DCF!$E$11:$I$11,1/(1+C$33)^DCF!$E$7:$I$7)+Forecast!$L$13*Assumptions!$E$75/(1+C$33)^DCF!$I$6+(DCF!$C$28-DCF!$C$29+DCF!$C$30))/DCF!$C$32) | D37: =Assumptions!$C$11*((SUMPRODUCT(DCF!$E$11:$I$11,1/(1+D$33)^DCF!$E$7:$I$7)+DCF!$I$9*(1+$B37)/(D$33-$B37)/(1+D$33)^DCF!$I$6+(DCF!$C$28-DCF!$C$29+DCF!$C$30))/DCF!$C$32)+(1-Assumptions!$C$11)*((SUMPRODUCT(DCF!$E$11:$I$11,1/(1+D$33)^DCF!$E$7:$I$7)+Forecast!$L$13*Assumptions!$E$75/(1+D$33)^DCF!$I$6+(DCF!$C$28-DCF!$C$29+DCF!$C$30))/DCF!$C$32) | E37: =Assumptions!$C$11*((SUMPRODUCT(DCF!$E$11:$I$11,1/(1+E$33)^DCF!$E$7:$I$7)+DCF!$I$9*(1+$B37)/(E$33-$B37)/(1+E$33)^DCF!$I$6+(DCF!$C$28-DCF!$C$29+DCF!$C$30))/DCF!$C$32)+(1-Assumptions!$C$11)*((SUMPRODUCT(DCF!$E$11:$I$11,1/(1+E$33)^DCF!$E$7:$I$7)+Forecast!$L$13*Assumptions!$E$75/(1+E$33)^DCF!$I$6+(DCF!$C$28-DCF!$C$29+DCF!$C$30))/DCF!$C$32) | F37: =Assumptions!$C$11*((SUMPRODUCT(DCF!$E$11:$I$11,1/(1+F$33)^DCF!$E$7:$I$7)+DCF!$I$9*(1+$B37)/(F$33-$B37)/(1+F$33)^DCF!$I$6+(DCF!$C$28-DCF!$C$29+DCF!$C$30))/DCF!$C$32)+(1-Assumptions!$C$11)*((SUMPRODUCT(DCF!$E$11:$I$11,1/(1+F$33)^DCF!$E$7:$I$7)+Forecast!$L$13*Assumptions!$E$75/(1+F$33)^DCF!$I$6+(DCF!$C$28-DCF!$C$29+DCF!$C$30))/DCF!$C$32) | G37: =Assumptions!$C$11*((SUMPRODUCT(DCF!$E$11:$I$11,1/(1+G$33)^DCF!$E$7:$I$7)+DCF!$I$9*(1+$B37)/(G$33-$B37)/(1+G$33)^DCF!$I$6+(DCF!$C$28-DCF!$C$29+DCF!$C$30))/DCF!$C$32)+(1-Assumptions!$C$11)*((SUMPRODUCT(DCF!$E$11:$I$11,1/(1+G$33)^DCF!$E$7:$I$7)+Forecast!$L$13*Assumptions!$E$75/(1+G$33)^DCF!$I$6+(DCF!$C$28-DCF!$C$29+DCF!$C$30))/DCF!$C$32) | H37: =Assumptions!$C$11*((SUMPRODUCT(DCF!$E$11:$I$11,1/(1+H$33)^DCF!$E$7:$I$7)+DCF!$I$9*(1+$B37)/(H$33-$B37)/(1+H$33)^DCF!$I$6+(DCF!$C$28-DCF!$C$29+DCF!$C$30))/DCF!$C$32)+(1-Assumptions!$C$11)*((SUMPRODUCT(DCF!$E$11:$I$11,1/(1+H$33)^DCF!$E$7:$I$7)+Forecast!$L$13*Assumptions!$E$75/(1+H$33)^DCF!$I$6+(DCF!$C$28-DCF!$C$29+DCF!$C$30))/DCF!$C$32) | I37: =Assumptions!$C$11*((SUMPRODUCT(DCF!$E$11:$I$11,1/(1+I$33)^DCF!$E$7:$I$7)+DCF!$I$9*(1+$B37)/(I$33-$B37)/(1+I$33)^DCF!$I$6+(DCF!$C$28-DCF!$C$29+DCF!$C$30))/DCF!$C$32)+(1-Assumptions!$C$11)*((SUMPRODUCT(DCF!$E$11:$I$11,1/(1+I$33)^DCF!$E$7:$I$7)+Forecast!$L$13*Assumptions!$E$75/(1+I$33)^DCF!$I$6+(DCF!$C$28-DCF!$C$29+DCF!$C$30))/DCF!$C$32) | J37: =Assumptions!$C$11*((SUMPRODUCT(DCF!$E$11:$I$11,1/(1+J$33)^DCF!$E$7:$I$7)+DCF!$I$9*(1+$B37)/(J$33-$B37)/(1+J$33)^DCF!$I$6+(DCF!$C$28-DCF!$C$29+DCF!$C$30))/DCF!$C$32)+(1-Assumptions!$C$11)*((SUMPRODUCT(DCF!$E$11:$I$11,1/(1+J$33)^DCF!$E$7:$I$7)+Forecast!$L$13*Assumptions!$E$75/(1+J$33)^DCF!$I$6+(DCF!$C$28-DCF!$C$29+DCF!$C$30))/DCF!$C$32) | K37: =Assumptions!$C$11*((SUMPRODUCT(DCF!$E$11:$I$11,1/(1+K$33)^DCF!$E$7:$I$7)+DCF!$I$9*(1+$B37)/(K$33-$B37)/(1+K$33)^DCF!$I$6+(DCF!$C$28-DCF!$C$29+DCF!$C$30))/DCF!$C$32)+(1-Assumptions!$C$11)*((SUMPRODUCT(DCF!$E$11:$I$11,1/(1+K$33)^DCF!$E$7:$I$7)+Forecast!$L$13*Assumptions!$E$75/(1+K$33)^DCF!$I$6+(DCF!$C$28-DCF!$C$29+DCF!$C$30))/DCF!$C$32)
B38: =Assumptions!$E$70 | C38: =Assumptions!$C$11*((SUMPRODUCT(DCF!$E$11:$I$11,1/(1+C$33)^DCF!$E$7:$I$7)+DCF!$I$9*(1+$B38)/(C$33-$B38)/(1+C$33)^DCF!$I$6+(DCF!$C$28-DCF!$C$29+DCF!$C$30))/DCF!$C$32)+(1-Assumptions!$C$11)*((SUMPRODUCT(DCF!$E$11:$I$11,1/(1+C$33)^DCF!$E$7:$I$7)+Forecast!$L$13*Assumptions!$E$75/(1+C$33)^DCF!$I$6+(DCF!$C$28-DCF!$C$29+DCF!$C$30))/DCF!$C$32) | D38: =Assumptions!$C$11*((SUMPRODUCT(DCF!$E$11:$I$11,1/(1+D$33)^DCF!$E$7:$I$7)+DCF!$I$9*(1+$B38)/(D$33-$B38)/(1+D$33)^DCF!$I$6+(DCF!$C$28-DCF!$C$29+DCF!$C$30))/DCF!$C$32)+(1-Assumptions!$C$11)*((SUMPRODUCT(DCF!$E$11:$I$11,1/(1+D$33)^DCF!$E$7:$I$7)+Forecast!$L$13*Assumptions!$E$75/(1+D$33)^DCF!$I$6+(DCF!$C$28-DCF!$C$29+DCF!$C$30))/DCF!$C$32) | E38: =Assumptions!$C$11*((SUMPRODUCT(DCF!$E$11:$I$11,1/(1+E$33)^DCF!$E$7:$I$7)+DCF!$I$9*(1+$B38)/(E$33-$B38)/(1+E$33)^DCF!$I$6+(DCF!$C$28-DCF!$C$29+DCF!$C$30))/DCF!$C$32)+(1-Assumptions!$C$11)*((SUMPRODUCT(DCF!$E$11:$I$11,1/(1+E$33)^DCF!$E$7:$I$7)+Forecast!$L$13*Assumptions!$E$75/(1+E$33)^DCF!$I$6+(DCF!$C$28-DCF!$C$29+DCF!$C$30))/DCF!$C$32) | F38: =Assumptions!$C$11*((SUMPRODUCT(DCF!$E$11:$I$11,1/(1+F$33)^DCF!$E$7:$I$7)+DCF!$I$9*(1+$B38)/(F$33-$B38)/(1+F$33)^DCF!$I$6+(DCF!$C$28-DCF!$C$29+DCF!$C$30))/DCF!$C$32)+(1-Assumptions!$C$11)*((SUMPRODUCT(DCF!$E$11:$I$11,1/(1+F$33)^DCF!$E$7:$I$7)+Forecast!$L$13*Assumptions!$E$75/(1+F$33)^DCF!$I$6+(DCF!$C$28-DCF!$C$29+DCF!$C$30))/DCF!$C$32) | G38: =Assumptions!$C$11*((SUMPRODUCT(DCF!$E$11:$I$11,1/(1+G$33)^DCF!$E$7:$I$7)+DCF!$I$9*(1+$B38)/(G$33-$B38)/(1+G$33)^DCF!$I$6+(DCF!$C$28-DCF!$C$29+DCF!$C$30))/DCF!$C$32)+(1-Assumptions!$C$11)*((SUMPRODUCT(DCF!$E$11:$I$11,1/(1+G$33)^DCF!$E$7:$I$7)+Forecast!$L$13*Assumptions!$E$75/(1+G$33)^DCF!$I$6+(DCF!$C$28-DCF!$C$29+DCF!$C$30))/DCF!$C$32) | H38: =Assumptions!$C$11*((SUMPRODUCT(DCF!$E$11:$I$11,1/(1+H$33)^DCF!$E$7:$I$7)+DCF!$I$9*(1+$B38)/(H$33-$B38)/(1+H$33)^DCF!$I$6+(DCF!$C$28-DCF!$C$29+DCF!$C$30))/DCF!$C$32)+(1-Assumptions!$C$11)*((SUMPRODUCT(DCF!$E$11:$I$11,1/(1+H$33)^DCF!$E$7:$I$7)+Forecast!$L$13*Assumptions!$E$75/(1+H$33)^DCF!$I$6+(DCF!$C$28-DCF!$C$29+DCF!$C$30))/DCF!$C$32) | I38: =Assumptions!$C$11*((SUMPRODUCT(DCF!$E$11:$I$11,1/(1+I$33)^DCF!$E$7:$I$7)+DCF!$I$9*(1+$B38)/(I$33-$B38)/(1+I$33)^DCF!$I$6+(DCF!$C$28-DCF!$C$29+DCF!$C$30))/DCF!$C$32)+(1-Assumptions!$C$11)*((SUMPRODUCT(DCF!$E$11:$I$11,1/(1+I$33)^DCF!$E$7:$I$7)+Forecast!$L$13*Assumptions!$E$75/(1+I$33)^DCF!$I$6+(DCF!$C$28-DCF!$C$29+DCF!$C$30))/DCF!$C$32) | J38: =Assumptions!$C$11*((SUMPRODUCT(DCF!$E$11:$I$11,1/(1+J$33)^DCF!$E$7:$I$7)+DCF!$I$9*(1+$B38)/(J$33-$B38)/(1+J$33)^DCF!$I$6+(DCF!$C$28-DCF!$C$29+DCF!$C$30))/DCF!$C$32)+(1-Assumptions!$C$11)*((SUMPRODUCT(DCF!$E$11:$I$11,1/(1+J$33)^DCF!$E$7:$I$7)+Forecast!$L$13*Assumptions!$E$75/(1+J$33)^DCF!$I$6+(DCF!$C$28-DCF!$C$29+DCF!$C$30))/DCF!$C$32) | K38: =Assumptions!$C$11*((SUMPRODUCT(DCF!$E$11:$I$11,1/(1+K$33)^DCF!$E$7:$I$7)+DCF!$I$9*(1+$B38)/(K$33-$B38)/(1+K$33)^DCF!$I$6+(DCF!$C$28-DCF!$C$29+DCF!$C$30))/DCF!$C$32)+(1-Assumptions!$C$11)*((SUMPRODUCT(DCF!$E$11:$I$11,1/(1+K$33)^DCF!$E$7:$I$7)+Forecast!$L$13*Assumptions!$E$75/(1+K$33)^DCF!$I$6+(DCF!$C$28-DCF!$C$29+DCF!$C$30))/DCF!$C$32)
B39: =$B$38+(1)*$N$6 | C39: =Assumptions!$C$11*((SUMPRODUCT(DCF!$E$11:$I$11,1/(1+C$33)^DCF!$E$7:$I$7)+DCF!$I$9*(1+$B39)/(C$33-$B39)/(1+C$33)^DCF!$I$6+(DCF!$C$28-DCF!$C$29+DCF!$C$30))/DCF!$C$32)+(1-Assumptions!$C$11)*((SUMPRODUCT(DCF!$E$11:$I$11,1/(1+C$33)^DCF!$E$7:$I$7)+Forecast!$L$13*Assumptions!$E$75/(1+C$33)^DCF!$I$6+(DCF!$C$28-DCF!$C$29+DCF!$C$30))/DCF!$C$32) | D39: =Assumptions!$C$11*((SUMPRODUCT(DCF!$E$11:$I$11,1/(1+D$33)^DCF!$E$7:$I$7)+DCF!$I$9*(1+$B39)/(D$33-$B39)/(1+D$33)^DCF!$I$6+(DCF!$C$28-DCF!$C$29+DCF!$C$30))/DCF!$C$32)+(1-Assumptions!$C$11)*((SUMPRODUCT(DCF!$E$11:$I$11,1/(1+D$33)^DCF!$E$7:$I$7)+Forecast!$L$13*Assumptions!$E$75/(1+D$33)^DCF!$I$6+(DCF!$C$28-DCF!$C$29+DCF!$C$30))/DCF!$C$32) | E39: =Assumptions!$C$11*((SUMPRODUCT(DCF!$E$11:$I$11,1/(1+E$33)^DCF!$E$7:$I$7)+DCF!$I$9*(1+$B39)/(E$33-$B39)/(1+E$33)^DCF!$I$6+(DCF!$C$28-DCF!$C$29+DCF!$C$30))/DCF!$C$32)+(1-Assumptions!$C$11)*((SUMPRODUCT(DCF!$E$11:$I$11,1/(1+E$33)^DCF!$E$7:$I$7)+Forecast!$L$13*Assumptions!$E$75/(1+E$33)^DCF!$I$6+(DCF!$C$28-DCF!$C$29+DCF!$C$30))/DCF!$C$32) | F39: =Assumptions!$C$11*((SUMPRODUCT(DCF!$E$11:$I$11,1/(1+F$33)^DCF!$E$7:$I$7)+DCF!$I$9*(1+$B39)/(F$33-$B39)/(1+F$33)^DCF!$I$6+(DCF!$C$28-DCF!$C$29+DCF!$C$30))/DCF!$C$32)+(1-Assumptions!$C$11)*((SUMPRODUCT(DCF!$E$11:$I$11,1/(1+F$33)^DCF!$E$7:$I$7)+Forecast!$L$13*Assumptions!$E$75/(1+F$33)^DCF!$I$6+(DCF!$C$28-DCF!$C$29+DCF!$C$30))/DCF!$C$32) | G39: =Assumptions!$C$11*((SUMPRODUCT(DCF!$E$11:$I$11,1/(1+G$33)^DCF!$E$7:$I$7)+DCF!$I$9*(1+$B39)/(G$33-$B39)/(1+G$33)^DCF!$I$6+(DCF!$C$28-DCF!$C$29+DCF!$C$30))/DCF!$C$32)+(1-Assumptions!$C$11)*((SUMPRODUCT(DCF!$E$11:$I$11,1/(1+G$33)^DCF!$E$7:$I$7)+Forecast!$L$13*Assumptions!$E$75/(1+G$33)^DCF!$I$6+(DCF!$C$28-DCF!$C$29+DCF!$C$30))/DCF!$C$32) | H39: =Assumptions!$C$11*((SUMPRODUCT(DCF!$E$11:$I$11,1/(1+H$33)^DCF!$E$7:$I$7)+DCF!$I$9*(1+$B39)/(H$33-$B39)/(1+H$33)^DCF!$I$6+(DCF!$C$28-DCF!$C$29+DCF!$C$30))/DCF!$C$32)+(1-Assumptions!$C$11)*((SUMPRODUCT(DCF!$E$11:$I$11,1/(1+H$33)^DCF!$E$7:$I$7)+Forecast!$L$13*Assumptions!$E$75/(1+H$33)^DCF!$I$6+(DCF!$C$28-DCF!$C$29+DCF!$C$30))/DCF!$C$32) | I39: =Assumptions!$C$11*((SUMPRODUCT(DCF!$E$11:$I$11,1/(1+I$33)^DCF!$E$7:$I$7)+DCF!$I$9*(1+$B39)/(I$33-$B39)/(1+I$33)^DCF!$I$6+(DCF!$C$28-DCF!$C$29+DCF!$C$30))/DCF!$C$32)+(1-Assumptions!$C$11)*((SUMPRODUCT(DCF!$E$11:$I$11,1/(1+I$33)^DCF!$E$7:$I$7)+Forecast!$L$13*Assumptions!$E$75/(1+I$33)^DCF!$I$6+(DCF!$C$28-DCF!$C$29+DCF!$C$30))/DCF!$C$32) | J39: =Assumptions!$C$11*((SUMPRODUCT(DCF!$E$11:$I$11,1/(1+J$33)^DCF!$E$7:$I$7)+DCF!$I$9*(1+$B39)/(J$33-$B39)/(1+J$33)^DCF!$I$6+(DCF!$C$28-DCF!$C$29+DCF!$C$30))/DCF!$C$32)+(1-Assumptions!$C$11)*((SUMPRODUCT(DCF!$E$11:$I$11,1/(1+J$33)^DCF!$E$7:$I$7)+Forecast!$L$13*Assumptions!$E$75/(1+J$33)^DCF!$I$6+(DCF!$C$28-DCF!$C$29+DCF!$C$30))/DCF!$C$32) | K39: =Assumptions!$C$11*((SUMPRODUCT(DCF!$E$11:$I$11,1/(1+K$33)^DCF!$E$7:$I$7)+DCF!$I$9*(1+$B39)/(K$33-$B39)/(1+K$33)^DCF!$I$6+(DCF!$C$28-DCF!$C$29+DCF!$C$30))/DCF!$C$32)+(1-Assumptions!$C$11)*((SUMPRODUCT(DCF!$E$11:$I$11,1/(1+K$33)^DCF!$E$7:$I$7)+Forecast!$L$13*Assumptions!$E$75/(1+K$33)^DCF!$I$6+(DCF!$C$28-DCF!$C$29+DCF!$C$30))/DCF!$C$32)
B40: =$B$38+(2)*$N$6 | C40: =Assumptions!$C$11*((SUMPRODUCT(DCF!$E$11:$I$11,1/(1+C$33)^DCF!$E$7:$I$7)+DCF!$I$9*(1+$B40)/(C$33-$B40)/(1+C$33)^DCF!$I$6+(DCF!$C$28-DCF!$C$29+DCF!$C$30))/DCF!$C$32)+(1-Assumptions!$C$11)*((SUMPRODUCT(DCF!$E$11:$I$11,1/(1+C$33)^DCF!$E$7:$I$7)+Forecast!$L$13*Assumptions!$E$75/(1+C$33)^DCF!$I$6+(DCF!$C$28-DCF!$C$29+DCF!$C$30))/DCF!$C$32) | D40: =Assumptions!$C$11*((SUMPRODUCT(DCF!$E$11:$I$11,1/(1+D$33)^DCF!$E$7:$I$7)+DCF!$I$9*(1+$B40)/(D$33-$B40)/(1+D$33)^DCF!$I$6+(DCF!$C$28-DCF!$C$29+DCF!$C$30))/DCF!$C$32)+(1-Assumptions!$C$11)*((SUMPRODUCT(DCF!$E$11:$I$11,1/(1+D$33)^DCF!$E$7:$I$7)+Forecast!$L$13*Assumptions!$E$75/(1+D$33)^DCF!$I$6+(DCF!$C$28-DCF!$C$29+DCF!$C$30))/DCF!$C$32) | E40: =Assumptions!$C$11*((SUMPRODUCT(DCF!$E$11:$I$11,1/(1+E$33)^DCF!$E$7:$I$7)+DCF!$I$9*(1+$B40)/(E$33-$B40)/(1+E$33)^DCF!$I$6+(DCF!$C$28-DCF!$C$29+DCF!$C$30))/DCF!$C$32)+(1-Assumptions!$C$11)*((SUMPRODUCT(DCF!$E$11:$I$11,1/(1+E$33)^DCF!$E$7:$I$7)+Forecast!$L$13*Assumptions!$E$75/(1+E$33)^DCF!$I$6+(DCF!$C$28-DCF!$C$29+DCF!$C$30))/DCF!$C$32) | F40: =Assumptions!$C$11*((SUMPRODUCT(DCF!$E$11:$I$11,1/(1+F$33)^DCF!$E$7:$I$7)+DCF!$I$9*(1+$B40)/(F$33-$B40)/(1+F$33)^DCF!$I$6+(DCF!$C$28-DCF!$C$29+DCF!$C$30))/DCF!$C$32)+(1-Assumptions!$C$11)*((SUMPRODUCT(DCF!$E$11:$I$11,1/(1+F$33)^DCF!$E$7:$I$7)+Forecast!$L$13*Assumptions!$E$75/(1+F$33)^DCF!$I$6+(DCF!$C$28-DCF!$C$29+DCF!$C$30))/DCF!$C$32) | G40: =Assumptions!$C$11*((SUMPRODUCT(DCF!$E$11:$I$11,1/(1+G$33)^DCF!$E$7:$I$7)+DCF!$I$9*(1+$B40)/(G$33-$B40)/(1+G$33)^DCF!$I$6+(DCF!$C$28-DCF!$C$29+DCF!$C$30))/DCF!$C$32)+(1-Assumptions!$C$11)*((SUMPRODUCT(DCF!$E$11:$I$11,1/(1+G$33)^DCF!$E$7:$I$7)+Forecast!$L$13*Assumptions!$E$75/(1+G$33)^DCF!$I$6+(DCF!$C$28-DCF!$C$29+DCF!$C$30))/DCF!$C$32) | H40: =Assumptions!$C$11*((SUMPRODUCT(DCF!$E$11:$I$11,1/(1+H$33)^DCF!$E$7:$I$7)+DCF!$I$9*(1+$B40)/(H$33-$B40)/(1+H$33)^DCF!$I$6+(DCF!$C$28-DCF!$C$29+DCF!$C$30))/DCF!$C$32)+(1-Assumptions!$C$11)*((SUMPRODUCT(DCF!$E$11:$I$11,1/(1+H$33)^DCF!$E$7:$I$7)+Forecast!$L$13*Assumptions!$E$75/(1+H$33)^DCF!$I$6+(DCF!$C$28-DCF!$C$29+DCF!$C$30))/DCF!$C$32) | I40: =Assumptions!$C$11*((SUMPRODUCT(DCF!$E$11:$I$11,1/(1+I$33)^DCF!$E$7:$I$7)+DCF!$I$9*(1+$B40)/(I$33-$B40)/(1+I$33)^DCF!$I$6+(DCF!$C$28-DCF!$C$29+DCF!$C$30))/DCF!$C$32)+(1-Assumptions!$C$11)*((SUMPRODUCT(DCF!$E$11:$I$11,1/(1+I$33)^DCF!$E$7:$I$7)+Forecast!$L$13*Assumptions!$E$75/(1+I$33)^DCF!$I$6+(DCF!$C$28-DCF!$C$29+DCF!$C$30))/DCF!$C$32) | J40: =Assumptions!$C$11*((SUMPRODUCT(DCF!$E$11:$I$11,1/(1+J$33)^DCF!$E$7:$I$7)+DCF!$I$9*(1+$B40)/(J$33-$B40)/(1+J$33)^DCF!$I$6+(DCF!$C$28-DCF!$C$29+DCF!$C$30))/DCF!$C$32)+(1-Assumptions!$C$11)*((SUMPRODUCT(DCF!$E$11:$I$11,1/(1+J$33)^DCF!$E$7:$I$7)+Forecast!$L$13*Assumptions!$E$75/(1+J$33)^DCF!$I$6+(DCF!$C$28-DCF!$C$29+DCF!$C$30))/DCF!$C$32) | K40: =Assumptions!$C$11*((SUMPRODUCT(DCF!$E$11:$I$11,1/(1+K$33)^DCF!$E$7:$I$7)+DCF!$I$9*(1+$B40)/(K$33-$B40)/(1+K$33)^DCF!$I$6+(DCF!$C$28-DCF!$C$29+DCF!$C$30))/DCF!$C$32)+(1-Assumptions!$C$11)*((SUMPRODUCT(DCF!$E$11:$I$11,1/(1+K$33)^DCF!$E$7:$I$7)+Forecast!$L$13*Assumptions!$E$75/(1+K$33)^DCF!$I$6+(DCF!$C$28-DCF!$C$29+DCF!$C$30))/DCF!$C$32)
B41: =$B$38+(3)*$N$6 | C41: =Assumptions!$C$11*((SUMPRODUCT(DCF!$E$11:$I$11,1/(1+C$33)^DCF!$E$7:$I$7)+DCF!$I$9*(1+$B41)/(C$33-$B41)/(1+C$33)^DCF!$I$6+(DCF!$C$28-DCF!$C$29+DCF!$C$30))/DCF!$C$32)+(1-Assumptions!$C$11)*((SUMPRODUCT(DCF!$E$11:$I$11,1/(1+C$33)^DCF!$E$7:$I$7)+Forecast!$L$13*Assumptions!$E$75/(1+C$33)^DCF!$I$6+(DCF!$C$28-DCF!$C$29+DCF!$C$30))/DCF!$C$32) | D41: =Assumptions!$C$11*((SUMPRODUCT(DCF!$E$11:$I$11,1/(1+D$33)^DCF!$E$7:$I$7)+DCF!$I$9*(1+$B41)/(D$33-$B41)/(1+D$33)^DCF!$I$6+(DCF!$C$28-DCF!$C$29+DCF!$C$30))/DCF!$C$32)+(1-Assumptions!$C$11)*((SUMPRODUCT(DCF!$E$11:$I$11,1/(1+D$33)^DCF!$E$7:$I$7)+Forecast!$L$13*Assumptions!$E$75/(1+D$33)^DCF!$I$6+(DCF!$C$28-DCF!$C$29+DCF!$C$30))/DCF!$C$32) | E41: =Assumptions!$C$11*((SUMPRODUCT(DCF!$E$11:$I$11,1/(1+E$33)^DCF!$E$7:$I$7)+DCF!$I$9*(1+$B41)/(E$33-$B41)/(1+E$33)^DCF!$I$6+(DCF!$C$28-DCF!$C$29+DCF!$C$30))/DCF!$C$32)+(1-Assumptions!$C$11)*((SUMPRODUCT(DCF!$E$11:$I$11,1/(1+E$33)^DCF!$E$7:$I$7)+Forecast!$L$13*Assumptions!$E$75/(1+E$33)^DCF!$I$6+(DCF!$C$28-DCF!$C$29+DCF!$C$30))/DCF!$C$32) | F41: =Assumptions!$C$11*((SUMPRODUCT(DCF!$E$11:$I$11,1/(1+F$33)^DCF!$E$7:$I$7)+DCF!$I$9*(1+$B41)/(F$33-$B41)/(1+F$33)^DCF!$I$6+(DCF!$C$28-DCF!$C$29+DCF!$C$30))/DCF!$C$32)+(1-Assumptions!$C$11)*((SUMPRODUCT(DCF!$E$11:$I$11,1/(1+F$33)^DCF!$E$7:$I$7)+Forecast!$L$13*Assumptions!$E$75/(1+F$33)^DCF!$I$6+(DCF!$C$28-DCF!$C$29+DCF!$C$30))/DCF!$C$32) | G41: =Assumptions!$C$11*((SUMPRODUCT(DCF!$E$11:$I$11,1/(1+G$33)^DCF!$E$7:$I$7)+DCF!$I$9*(1+$B41)/(G$33-$B41)/(1+G$33)^DCF!$I$6+(DCF!$C$28-DCF!$C$29+DCF!$C$30))/DCF!$C$32)+(1-Assumptions!$C$11)*((SUMPRODUCT(DCF!$E$11:$I$11,1/(1+G$33)^DCF!$E$7:$I$7)+Forecast!$L$13*Assumptions!$E$75/(1+G$33)^DCF!$I$6+(DCF!$C$28-DCF!$C$29+DCF!$C$30))/DCF!$C$32) | H41: =Assumptions!$C$11*((SUMPRODUCT(DCF!$E$11:$I$11,1/(1+H$33)^DCF!$E$7:$I$7)+DCF!$I$9*(1+$B41)/(H$33-$B41)/(1+H$33)^DCF!$I$6+(DCF!$C$28-DCF!$C$29+DCF!$C$30))/DCF!$C$32)+(1-Assumptions!$C$11)*((SUMPRODUCT(DCF!$E$11:$I$11,1/(1+H$33)^DCF!$E$7:$I$7)+Forecast!$L$13*Assumptions!$E$75/(1+H$33)^DCF!$I$6+(DCF!$C$28-DCF!$C$29+DCF!$C$30))/DCF!$C$32) | I41: =Assumptions!$C$11*((SUMPRODUCT(DCF!$E$11:$I$11,1/(1+I$33)^DCF!$E$7:$I$7)+DCF!$I$9*(1+$B41)/(I$33-$B41)/(1+I$33)^DCF!$I$6+(DCF!$C$28-DCF!$C$29+DCF!$C$30))/DCF!$C$32)+(1-Assumptions!$C$11)*((SUMPRODUCT(DCF!$E$11:$I$11,1/(1+I$33)^DCF!$E$7:$I$7)+Forecast!$L$13*Assumptions!$E$75/(1+I$33)^DCF!$I$6+(DCF!$C$28-DCF!$C$29+DCF!$C$30))/DCF!$C$32) | J41: =Assumptions!$C$11*((SUMPRODUCT(DCF!$E$11:$I$11,1/(1+J$33)^DCF!$E$7:$I$7)+DCF!$I$9*(1+$B41)/(J$33-$B41)/(1+J$33)^DCF!$I$6+(DCF!$C$28-DCF!$C$29+DCF!$C$30))/DCF!$C$32)+(1-Assumptions!$C$11)*((SUMPRODUCT(DCF!$E$11:$I$11,1/(1+J$33)^DCF!$E$7:$I$7)+Forecast!$L$13*Assumptions!$E$75/(1+J$33)^DCF!$I$6+(DCF!$C$28-DCF!$C$29+DCF!$C$30))/DCF!$C$32) | K41: =Assumptions!$C$11*((SUMPRODUCT(DCF!$E$11:$I$11,1/(1+K$33)^DCF!$E$7:$I$7)+DCF!$I$9*(1+$B41)/(K$33-$B41)/(1+K$33)^DCF!$I$6+(DCF!$C$28-DCF!$C$29+DCF!$C$30))/DCF!$C$32)+(1-Assumptions!$C$11)*((SUMPRODUCT(DCF!$E$11:$I$11,1/(1+K$33)^DCF!$E$7:$I$7)+Forecast!$L$13*Assumptions!$E$75/(1+K$33)^DCF!$I$6+(DCF!$C$28-DCF!$C$29+DCF!$C$30))/DCF!$C$32)
B42: =$B$38+(4)*$N$6 | C42: =Assumptions!$C$11*((SUMPRODUCT(DCF!$E$11:$I$11,1/(1+C$33)^DCF!$E$7:$I$7)+DCF!$I$9*(1+$B42)/(C$33-$B42)/(1+C$33)^DCF!$I$6+(DCF!$C$28-DCF!$C$29+DCF!$C$30))/DCF!$C$32)+(1-Assumptions!$C$11)*((SUMPRODUCT(DCF!$E$11:$I$11,1/(1+C$33)^DCF!$E$7:$I$7)+Forecast!$L$13*Assumptions!$E$75/(1+C$33)^DCF!$I$6+(DCF!$C$28-DCF!$C$29+DCF!$C$30))/DCF!$C$32) | D42: =Assumptions!$C$11*((SUMPRODUCT(DCF!$E$11:$I$11,1/(1+D$33)^DCF!$E$7:$I$7)+DCF!$I$9*(1+$B42)/(D$33-$B42)/(1+D$33)^DCF!$I$6+(DCF!$C$28-DCF!$C$29+DCF!$C$30))/DCF!$C$32)+(1-Assumptions!$C$11)*((SUMPRODUCT(DCF!$E$11:$I$11,1/(1+D$33)^DCF!$E$7:$I$7)+Forecast!$L$13*Assumptions!$E$75/(1+D$33)^DCF!$I$6+(DCF!$C$28-DCF!$C$29+DCF!$C$30))/DCF!$C$32) | E42: =Assumptions!$C$11*((SUMPRODUCT(DCF!$E$11:$I$11,1/(1+E$33)^DCF!$E$7:$I$7)+DCF!$I$9*(1+$B42)/(E$33-$B42)/(1+E$33)^DCF!$I$6+(DCF!$C$28-DCF!$C$29+DCF!$C$30))/DCF!$C$32)+(1-Assumptions!$C$11)*((SUMPRODUCT(DCF!$E$11:$I$11,1/(1+E$33)^DCF!$E$7:$I$7)+Forecast!$L$13*Assumptions!$E$75/(1+E$33)^DCF!$I$6+(DCF!$C$28-DCF!$C$29+DCF!$C$30))/DCF!$C$32) | F42: =Assumptions!$C$11*((SUMPRODUCT(DCF!$E$11:$I$11,1/(1+F$33)^DCF!$E$7:$I$7)+DCF!$I$9*(1+$B42)/(F$33-$B42)/(1+F$33)^DCF!$I$6+(DCF!$C$28-DCF!$C$29+DCF!$C$30))/DCF!$C$32)+(1-Assumptions!$C$11)*((SUMPRODUCT(DCF!$E$11:$I$11,1/(1+F$33)^DCF!$E$7:$I$7)+Forecast!$L$13*Assumptions!$E$75/(1+F$33)^DCF!$I$6+(DCF!$C$28-DCF!$C$29+DCF!$C$30))/DCF!$C$32) | G42: =Assumptions!$C$11*((SUMPRODUCT(DCF!$E$11:$I$11,1/(1+G$33)^DCF!$E$7:$I$7)+DCF!$I$9*(1+$B42)/(G$33-$B42)/(1+G$33)^DCF!$I$6+(DCF!$C$28-DCF!$C$29+DCF!$C$30))/DCF!$C$32)+(1-Assumptions!$C$11)*((SUMPRODUCT(DCF!$E$11:$I$11,1/(1+G$33)^DCF!$E$7:$I$7)+Forecast!$L$13*Assumptions!$E$75/(1+G$33)^DCF!$I$6+(DCF!$C$28-DCF!$C$29+DCF!$C$30))/DCF!$C$32) | H42: =Assumptions!$C$11*((SUMPRODUCT(DCF!$E$11:$I$11,1/(1+H$33)^DCF!$E$7:$I$7)+DCF!$I$9*(1+$B42)/(H$33-$B42)/(1+H$33)^DCF!$I$6+(DCF!$C$28-DCF!$C$29+DCF!$C$30))/DCF!$C$32)+(1-Assumptions!$C$11)*((SUMPRODUCT(DCF!$E$11:$I$11,1/(1+H$33)^DCF!$E$7:$I$7)+Forecast!$L$13*Assumptions!$E$75/(1+H$33)^DCF!$I$6+(DCF!$C$28-DCF!$C$29+DCF!$C$30))/DCF!$C$32) | I42: =Assumptions!$C$11*((SUMPRODUCT(DCF!$E$11:$I$11,1/(1+I$33)^DCF!$E$7:$I$7)+DCF!$I$9*(1+$B42)/(I$33-$B42)/(1+I$33)^DCF!$I$6+(DCF!$C$28-DCF!$C$29+DCF!$C$30))/DCF!$C$32)+(1-Assumptions!$C$11)*((SUMPRODUCT(DCF!$E$11:$I$11,1/(1+I$33)^DCF!$E$7:$I$7)+Forecast!$L$13*Assumptions!$E$75/(1+I$33)^DCF!$I$6+(DCF!$C$28-DCF!$C$29+DCF!$C$30))/DCF!$C$32) | J42: =Assumptions!$C$11*((SUMPRODUCT(DCF!$E$11:$I$11,1/(1+J$33)^DCF!$E$7:$I$7)+DCF!$I$9*(1+$B42)/(J$33-$B42)/(1+J$33)^DCF!$I$6+(DCF!$C$28-DCF!$C$29+DCF!$C$30))/DCF!$C$32)+(1-Assumptions!$C$11)*((SUMPRODUCT(DCF!$E$11:$I$11,1/(1+J$33)^DCF!$E$7:$I$7)+Forecast!$L$13*Assumptions!$E$75/(1+J$33)^DCF!$I$6+(DCF!$C$28-DCF!$C$29+DCF!$C$30))/DCF!$C$32) | K42: =Assumptions!$C$11*((SUMPRODUCT(DCF!$E$11:$I$11,1/(1+K$33)^DCF!$E$7:$I$7)+DCF!$I$9*(1+$B42)/(K$33-$B42)/(1+K$33)^DCF!$I$6+(DCF!$C$28-DCF!$C$29+DCF!$C$30))/DCF!$C$32)+(1-Assumptions!$C$11)*((SUMPRODUCT(DCF!$E$11:$I$11,1/(1+K$33)^DCF!$E$7:$I$7)+Forecast!$L$13*Assumptions!$E$75/(1+K$33)^DCF!$I$6+(DCF!$C$28-DCF!$C$29+DCF!$C$30))/DCF!$C$32)

Sheet Scenarios
B1: Scenario Analysis
B2: Each case is a self-contained 5-year build off its own Assumptions row, so Bear, Base and Bull compute side by side regardless of the selector.
B4: Summary | C4: Bear | D4: Base | E4: Bull
B5: Revenue CAGR FY25A-FY30E | C5: =(I28/Historical!$H$6)^(1/5)-1 | D5: =(I50/Historical!$H$6)^(1/5)-1 | E5: =(I72/Historical!$H$6)^(1/5)-1
B6: Average EBITDA margin FY26-30 | C6: =AVERAGE(Assumptions!$E$42:$I$42) | D6: =AVERAGE(Assumptions!$E$43:$I$43) | E6: =AVERAGE(Assumptions!$E$44:$I$44)
B7: Average CapEx % revenue | C7: =AVERAGE(Assumptions!$E$52:$I$52) | D7: =AVERAGE(Assumptions!$E$53:$I$53) | E7: =AVERAGE(Assumptions!$E$54:$I$54)
B8: WACC | C8: =C41 | D8: =C63 | E8: =C85
B9: Terminal growth | C9: =C42 | D9: =C64 | E9: =C86
B10: Exit EV/EBITDA | C10: =C43 | D10: =C65 | E10: =C87
B11: Enterprise value (Gordon) | C11: =C44+C45 | D11: =C66+C67 | E11: =C88+C89
B12: Enterprise value (Exit) | C12: =C44+C46 | D12: =C66+C68 | E12: =C88+C90
B13: Enterprise value (blended) | C13: =Assumptions!$C$11*C11+(1-Assumptions!$C$11)*C12 | D13: =Assumptions!$C$11*D11+(1-Assumptions!$C$11)*D12 | E13: =Assumptions!$C$11*E11+(1-Assumptions!$C$11)*E12
B14: Equity value (blended) | C14: =C13+(DCF!$C$28-DCF!$C$29+DCF!$C$30) | D14: =D13+(DCF!$C$28-DCF!$C$29+DCF!$C$30) | E14: =E13+(DCF!$C$28-DCF!$C$29+DCF!$C$30)
B15: Implied price, Gordon (EUR) | C15: =(C11+(DCF!$C$28-DCF!$C$29+DCF!$C$30))/DCF!$C$32 | D15: =(D11+(DCF!$C$28-DCF!$C$29+DCF!$C$30))/DCF!$C$32 | E15: =(E11+(DCF!$C$28-DCF!$C$29+DCF!$C$30))/DCF!$C$32
B16: Implied price, Exit (EUR) | C16: =(C12+(DCF!$C$28-DCF!$C$29+DCF!$C$30))/DCF!$C$32 | D16: =(D12+(DCF!$C$28-DCF!$C$29+DCF!$C$30))/DCF!$C$32 | E16: =(E12+(DCF!$C$28-DCF!$C$29+DCF!$C$30))/DCF!$C$32
B17: Implied price, blended (EUR) | C17: =C14/DCF!$C$32 | D17: =D14/DCF!$C$32 | E17: =E14/DCF!$C$32
B18: Upside / (downside), blended | C18: =C17/Assumptions!$C$14-1 | D18: =D17/Assumptions!$C$14-1 | E18: =E17/Assumptions!$C$14-1
B19: Current share price (EUR) | C19: =Assumptions!$C$14
B21: What drives each case
B22: Bear | C22: AI capex digestion in 2027-28 coincides with tighter China export controls (DUV immersion and servicing). Customers push out EUV orders, the down-payment float shrinks and margins compress as fixed R&D is held.
B23: Base | C23: 2026 guidance is delivered, the backlog converts, and EUV/High-NA adoption in logic and DRAM grows revenue to about EUR 63bn by 2030 with margins at the 2030 target band.
B24: Bull | C24: A sustained AI-driven leading-edge build-out plus faster High-NA adoption push revenue beyond the 2030 range, with gross margin at 60% and services scaling on the installed base.
B26: Bear case build
B27: EUR m | E27: FY26E | F27: FY27E | G27: FY28E | H27: FY29E | I27: FY30E
B28: Revenue | E28: =Historical!$H$6*(1+Assumptions!$E$32) | F28: =E28*(1+Assumptions!$F$32) | G28: =F28*(1+Assumptions!$G$32) | H28: =G28*(1+Assumptions!$H$32) | I28: =H28*(1+Assumptions!$I$32)
B29: EBITDA | E29: =E28*Assumptions!$E$42 | F29: =F28*Assumptions!$F$42 | G29: =G28*Assumptions!$G$42 | H29: =H28*Assumptions!$H$42 | I29: =I28*Assumptions!$I$42
B30: D&A | E30: =E28*Assumptions!$E$47 | F30: =F28*Assumptions!$F$47 | G30: =G28*Assumptions!$G$47 | H30: =H28*Assumptions!$H$47 | I30: =I28*Assumptions!$I$47
B31: EBIT | E31: =E29-E30 | F31: =F29-F30 | G31: =G29-G30 | H31: =H29-H30 | I31: =I29-I30
B32: NOPAT | E32: =E31*(1-Assumptions!$E$62) | F32: =F31*(1-Assumptions!$F$62) | G32: =G31*(1-Assumptions!$G$62) | H32: =H31*(1-Assumptions!$H$62) | I32: =I31*(1-Assumptions!$I$62)
B33: CapEx | E33: =E28*Assumptions!$E$52 | F33: =F28*Assumptions!$F$52 | G33: =G28*Assumptions!$G$52 | H33: =H28*Assumptions!$H$52 | I33: =I28*Assumptions!$I$52
B34: NWC | E34: =E28*Assumptions!$E$57 | F34: =F28*Assumptions!$F$57 | G34: =G28*Assumptions!$G$57 | H34: =H28*Assumptions!$H$57 | I34: =I28*Assumptions!$I$57
B35: Change in NWC | E35: =E34-Historical!$H$42 | F35: =F34-E34 | G35: =G34-F34 | H35: =H34-G34 | I35: =I34-H34
B36: Unlevered FCF | E36: =E32+E30-E33-E35 | F36: =F32+F30-F33-F35 | G36: =G32+G30-G33-G35 | H36: =H32+H30-H33-H35 | I36: =I32+I30-I33-I35
B37: Cash flow to discount (FY26 net of H1 actual) | E37: =E36-Assumptions!$C$19 | F37: =F36 | G37: =G36 | H37: =H36 | I37: =I36
B38: Discount factor | E38: =1/(1+$C$41)^DCF!E$7 | F38: =1/(1+$C$41)^DCF!F$7 | G38: =1/(1+$C$41)^DCF!G$7 | H38: =1/(1+$C$41)^DCF!H$7 | I38: =1/(1+$C$41)^DCF!I$7
B39: PV of cash flow | E39: =E37*E38 | F39: =F37*F38 | G39: =G37*G38 | H39: =H37*H38 | I39: =I37*I38
B41: WACC | C41: =WACC!$C$33+Assumptions!$E$77
B42: Terminal growth | C42: =Assumptions!$E$67
B43: Exit multiple | C43: =Assumptions!$E$72
B44: Sum PV of cash flows | C44: =SUM(E39:I39)
B45: PV terminal value (Gordon) | C45: =I36*(1+C42)/(C41-C42)/(1+C41)^DCF!$I$6
B46: PV terminal value (Exit) | C46: =I29*C43/(1+C41)^DCF!$I$6
B48: Base case build
B49: EUR m | E49: FY26E | F49: FY27E | G49: FY28E | H49: FY29E | I49: FY30E
B50: Revenue | E50: =Historical!$H$6*(1+Assumptions!$E$33) | F50: =E50*(1+Assumptions!$F$33) | G50: =F50*(1+Assumptions!$G$33) | H50: =G50*(1+Assumptions!$H$33) | I50: =H50*(1+Assumptions!$I$33)
B51: EBITDA | E51: =E50*Assumptions!$E$43 | F51: =F50*Assumptions!$F$43 | G51: =G50*Assumptions!$G$43 | H51: =H50*Assumptions!$H$43 | I51: =I50*Assumptions!$I$43
B52: D&A | E52: =E50*Assumptions!$E$48 | F52: =F50*Assumptions!$F$48 | G52: =G50*Assumptions!$G$48 | H52: =H50*Assumptions!$H$48 | I52: =I50*Assumptions!$I$48
B53: EBIT | E53: =E51-E52 | F53: =F51-F52 | G53: =G51-G52 | H53: =H51-H52 | I53: =I51-I52
B54: NOPAT | E54: =E53*(1-Assumptions!$E$63) | F54: =F53*(1-Assumptions!$F$63) | G54: =G53*(1-Assumptions!$G$63) | H54: =H53*(1-Assumptions!$H$63) | I54: =I53*(1-Assumptions!$I$63)
B55: CapEx | E55: =E50*Assumptions!$E$53 | F55: =F50*Assumptions!$F$53 | G55: =G50*Assumptions!$G$53 | H55: =H50*Assumptions!$H$53 | I55: =I50*Assumptions!$I$53
B56: NWC | E56: =E50*Assumptions!$E$58 | F56: =F50*Assumptions!$F$58 | G56: =G50*Assumptions!$G$58 | H56: =H50*Assumptions!$H$58 | I56: =I50*Assumptions!$I$58
B57: Change in NWC | E57: =E56-Historical!$H$42 | F57: =F56-E56 | G57: =G56-F56 | H57: =H56-G56 | I57: =I56-H56
B58: Unlevered FCF | E58: =E54+E52-E55-E57 | F58: =F54+F52-F55-F57 | G58: =G54+G52-G55-G57 | H58: =H54+H52-H55-H57 | I58: =I54+I52-I55-I57
B59: Cash flow to discount (FY26 net of H1 actual) | E59: =E58-Assumptions!$C$19 | F59: =F58 | G59: =G58 | H59: =H58 | I59: =I58
B60: Discount factor | E60: =1/(1+$C$63)^DCF!E$7 | F60: =1/(1+$C$63)^DCF!F$7 | G60: =1/(1+$C$63)^DCF!G$7 | H60: =1/(1+$C$63)^DCF!H$7 | I60: =1/(1+$C$63)^DCF!I$7
B61: PV of cash flow | E61: =E59*E60 | F61: =F59*F60 | G61: =G59*G60 | H61: =H59*H60 | I61: =I59*I60
B63: WACC | C63: =WACC!$C$33+Assumptions!$E$78
B64: Terminal growth | C64: =Assumptions!$E$68
B65: Exit multiple | C65: =Assumptions!$E$73
B66: Sum PV of cash flows | C66: =SUM(E61:I61)
B67: PV terminal value (Gordon) | C67: =I58*(1+C64)/(C63-C64)/(1+C63)^DCF!$I$6
B68: PV terminal value (Exit) | C68: =I51*C65/(1+C63)^DCF!$I$6
B70: Bull case build
B71: EUR m | E71: FY26E | F71: FY27E | G71: FY28E | H71: FY29E | I71: FY30E
B72: Revenue | E72: =Historical!$H$6*(1+Assumptions!$E$34) | F72: =E72*(1+Assumptions!$F$34) | G72: =F72*(1+Assumptions!$G$34) | H72: =G72*(1+Assumptions!$H$34) | I72: =H72*(1+Assumptions!$I$34)
B73: EBITDA | E73: =E72*Assumptions!$E$44 | F73: =F72*Assumptions!$F$44 | G73: =G72*Assumptions!$G$44 | H73: =H72*Assumptions!$H$44 | I73: =I72*Assumptions!$I$44
B74: D&A | E74: =E72*Assumptions!$E$49 | F74: =F72*Assumptions!$F$49 | G74: =G72*Assumptions!$G$49 | H74: =H72*Assumptions!$H$49 | I74: =I72*Assumptions!$I$49
B75: EBIT | E75: =E73-E74 | F75: =F73-F74 | G75: =G73-G74 | H75: =H73-H74 | I75: =I73-I74
B76: NOPAT | E76: =E75*(1-Assumptions!$E$64) | F76: =F75*(1-Assumptions!$F$64) | G76: =G75*(1-Assumptions!$G$64) | H76: =H75*(1-Assumptions!$H$64) | I76: =I75*(1-Assumptions!$I$64)
B77: CapEx | E77: =E72*Assumptions!$E$54 | F77: =F72*Assumptions!$F$54 | G77: =G72*Assumptions!$G$54 | H77: =H72*Assumptions!$H$54 | I77: =I72*Assumptions!$I$54
B78: NWC | E78: =E72*Assumptions!$E$59 | F78: =F72*Assumptions!$F$59 | G78: =G72*Assumptions!$G$59 | H78: =H72*Assumptions!$H$59 | I78: =I72*Assumptions!$I$59
B79: Change in NWC | E79: =E78-Historical!$H$42 | F79: =F78-E78 | G79: =G78-F78 | H79: =H78-G78 | I79: =I78-H78
B80: Unlevered FCF | E80: =E76+E74-E77-E79 | F80: =F76+F74-F77-F79 | G80: =G76+G74-G77-G79 | H80: =H76+H74-H77-H79 | I80: =I76+I74-I77-I79
B81: Cash flow to discount (FY26 net of H1 actual) | E81: =E80-Assumptions!$C$19 | F81: =F80 | G81: =G80 | H81: =H80 | I81: =I80
B82: Discount factor | E82: =1/(1+$C$85)^DCF!E$7 | F82: =1/(1+$C$85)^DCF!F$7 | G82: =1/(1+$C$85)^DCF!G$7 | H82: =1/(1+$C$85)^DCF!H$7 | I82: =1/(1+$C$85)^DCF!I$7
B83: PV of cash flow | E83: =E81*E82 | F83: =F81*F82 | G83: =G81*G82 | H83: =H81*H82 | I83: =I81*I82
B85: WACC | C85: =WACC!$C$33+Assumptions!$E$79
B86: Terminal growth | C86: =Assumptions!$E$69
B87: Exit multiple | C87: =Assumptions!$E$74
B88: Sum PV of cash flows | C88: =SUM(E83:I83)
B89: PV terminal value (Gordon) | C89: =I80*(1+C86)/(C85-C86)/(1+C85)^DCF!$I$6
B90: PV terminal value (Exit) | C90: =I73*C87/(1+C85)^DCF!$I$6

Sheet Dashboard
B1: ASML Holding N.V. | Valuation Dashboard
B2: Live summary of the model. Change inputs on Assumptions; everything here updates.
B4: Valuation | E4: Model drivers
B5: Scenario shown: | C5: =Assumptions!$C$9
B6: Current share price | C6: =Assumptions!$C$14 | E6: Enterprise value (blended, EUR m) | F6: =DCF!$E$26
B7: DCF price, blended (headline) | C7: =DCF!$E$33 | E7: Equity value (blended, EUR m) | F7: =DCF!$E$31
B8: DCF price, Gordon Growth | C8: =DCF!$C$33 | E8: WACC | F8: =WACC!$C$35
B9: DCF price, Exit Multiple | C9: =DCF!$D$33 | E9: Terminal growth rate | F9: =Assumptions!$E$70
B10: Potential upside / (downside) | C10: =DCF!$E$35 | E10: Exit EV/EBITDA | F10: =Assumptions!$E$75
B11: Bear case price (blended) | C11: =Scenarios!$C$17 | E11: 5-yr revenue CAGR FY25-30 | F11: =Forecast!$C$38
B12: Base case price (blended) | C12: =Scenarios!$D$17 | E12: Average forecast EBITDA margin | F12: =Forecast!$C$39
B13: Bull case price (blended) | C13: =Scenarios!$E$17 | E13: Model checks | F13: =Checks!$C$4
B14: Verdict | C14: =IF(DCF!$E$35>0.15,"Undervalued",IF(DCF!$E$35<-0.15,"Overvalued","Fairly valued"))
B15: Verdict band: more than +/-15% from market price
B17: Chart data (linked)
B18: Year | C18: FY21A | D18: FY22A | E18: FY23A | F18: FY24A | G18: FY25A | H18: FY26E | I18: FY27E | J18: FY28E | K18: FY29E | L18: FY30E
B19: Revenue (EUR m) | C19: =Forecast!C7 | D19: =Forecast!D7 | E19: =Forecast!E7 | F19: =Forecast!F7 | G19: =Forecast!G7 | H19: =Forecast!H7 | I19: =Forecast!I7 | J19: =Forecast!J7 | ... L19: =Forecast!L7
B20: EBITDA margin | C20: =Forecast!C14 | D20: =Forecast!D14 | E20: =Forecast!E14 | F20: =Forecast!F14 | G20: =Forecast!G14 | H20: =Forecast!H14 | I20: =Forecast!I14 | J20: =Forecast!J14 | ... L20: =Forecast!L14
B21: Unlevered FCF (EUR m) | C21: =Forecast!C33 | D21: =Forecast!D33 | E21: =Forecast!E33 | F21: =Forecast!F33 | G21: =Forecast!G33 | H21: =Forecast!H33 | I21: =Forecast!I33 | J21: =Forecast!J33 | ... L21: =Forecast!L33
B23: Valuation range (EUR / share)
B24: Current market price | C24: =Assumptions!$C$14
B25: Bear (blended) | C25: =Scenarios!$C$17
B26: Base (blended) | C26: =Scenarios!$D$17
B27: Bull (blended) | C27: =Scenarios!$E$17
B28: DCF Gordon Growth | C28: =DCF!$C$33
B29: DCF Exit Multiple | C29: =DCF!$D$33

Sheet Checks
B1: Model Integrity Checks
B2: Automatic tests. PASS = test met; CHECK = review the inputs. INFO = reported for judgement, not a pass/fail test.
B4: Overall status | C4: =IF(COUNTIF(D7:D30,"CHECK")=0,"ALL PASS","REVIEW")
B6: Test | C6: Value | D6: Status | E6: What it guards against
B7: WACC > terminal growth (live) | C7: =WACC!$C$35-Assumptions!$E$70 | D7: =IF(C7>0,"PASS","CHECK") | E7: Gordon formula explodes / turns negative if g >= WACC
B8: WACC > terminal growth in every scenario | C8: =MIN(Scenarios!$C$8-Scenarios!$C$9,Scenarios!$D$8-Scenarios!$D$9,Scenarios!$E$8-Scenarios!$E$9) | D8: =IF(C8>0,"PASS","CHECK") | E8: Same test for Bear / Base / Bull
B9: EV reconciles: EV - (sum PV FCF + PV TV), Gordon | C9: =DCF!$C$26-(SUMPRODUCT(DCF!E11:I11,DCF!E13:I13)+DCF!C24) | D9: =IF(ABS(C9)<0.01,"PASS","CHECK") | E9: Independent recomputation of EV
B10: EV reconciles, Exit | C10: =DCF!$D$26-(SUMPRODUCT(DCF!E11:I11,DCF!E13:I13)+DCF!D24) | D10: =IF(ABS(C10)<0.01,"PASS","CHECK")
B11: Equity bridge: equity - (EV + cash - debt + investments) | C11: =DCF!$C$31-(DCF!$C$26+Assumptions!$C$16-Assumptions!$C$17+Assumptions!$C$18) | D11: =IF(ABS(C11)<0.01,"PASS","CHECK") | E11: Bridge items applied once with correct signs
B12: Forecast UFCF = NOPAT + D&A - CapEx - change in NWC (sum of errors) | C12: =SUMPRODUCT(ABS(Forecast!H33:L33-(Forecast!H24:L24+Forecast!H16:L16-Forecast!H26:L26-Forecast!H31:L31))) | D12: =IF(C12<0.01,"PASS","CHECK") | E12: Formula consistency across forecast years
B13: Historical gross profit ties to sales - COGS | C13: =SUMPRODUCT(ABS(Historical!D50:H50)) | D13: =IF(C13<0.5,"PASS","CHECK") | E13: Data entry errors in reported figures
B14: Forecast EBITDA margin < gross margin (all years) | C14: =SUMPRODUCT(--(Forecast!H14:L14>=Forecast!H11:L11)) | D14: =IF(C14=0,"PASS","CHECK") | E14: Opex cannot be negative
B15: EBITDA margins between 25% and 55% (economic realism) | C15: =SUMPRODUCT((Forecast!H14:L14<0.25)+(Forecast!H14:L14>0.55)) | D15: =IF(C15=0,"PASS","CHECK") | E15: Outside ASML's FY21-25 range of 34-39% plus headroom
B16: Implied opex % within 10-25% of revenue | C16: =SUMPRODUCT((Forecast!H36:L36<0.10)+(Forecast!H36:L36>0.25)) | D16: =IF(C16=0,"PASS","CHECK") | E16: Gross margin and EBITDA margin assumptions are mutually consistent
B17: Terminal value share of EV (Gordon) below 85% | C17: =DCF!C27 | D17: =IF(C17<0.85,"PASS","CHECK") | E17: Valuation not dominated by the perpetuity
B18: Terminal value share of EV (Exit) | C18: =DCF!D27 | D18: ="INFO" | E18: High by construction for a growth company; see sensitivity
B19: Capital structure weights sum to 100% | C19: =WACC!C29+WACC!C30-1 | D19: =IF(ABS(C19)<0.000001,"PASS","CHECK")
B20: Sensitivity table 1 centre = DCF Gordon price | C20: =Sensitivity!$G$11-DCF!$C$33 | D20: =IF(ABS(C20)<0.01,"PASS","CHECK") | E20: Closed-form grid formula matches the full DCF
B21: Sensitivity table 2 centre = DCF Exit price | C21: =Sensitivity!$G$24-DCF!$D$33 | D21: =IF(ABS(C21)<0.01,"PASS","CHECK")
B22: Sensitivity table 3 centre = DCF blended price | C22: =Sensitivity!$G$38-DCF!$E$33 | D22: =IF(ABS(C22)<0.01,"PASS","CHECK")
B23: Selected scenario on Scenarios tab = main DCF (blended price) | C23: =CHOOSE(Assumptions!$C$8,Scenarios!$C$17,Scenarios!$D$17,Scenarios!$E$17)-DCF!$E$33 | D23: =IF(ABS(C23)<0.01,"PASS","CHECK") | E23: Scenario engine and main model use identical logic
B24: Scenario ordering: Bear < Base < Bull | C24: =AND(Scenarios!$C$17<Scenarios!$D$17,Scenarios!$D$17<Scenarios!$E$17) | D24: =IF(C24,"PASS","CHECK") | E24: Output moves logically with assumptions
B25: Price falls when WACC rises (sensitivity row monotonic) | C25: =AND(Sensitivity!C11>Sensitivity!G11,Sensitivity!G11>Sensitivity!K11) | D25: =IF(C25,"PASS","CHECK") | E25: Direction of WACC effect
B26: Price rises with terminal growth (sensitivity column monotonic) | C26: =AND(Sensitivity!G7<Sensitivity!G11,Sensitivity!G11<Sensitivity!G15) | D26: =IF(C26,"PASS","CHECK") | E26: Direction of g effect
B27: No double counting: FY26 cash flow excludes H1 actual (stub) | C27: =DCF!E11-(DCF!E9-Assumptions!$C$19) | D27: =IF(ABS(C27)<0.01,"PASS","CHECK") | E27: H1-26 cash flows sit in the 28-Jun cash balance
B28: Balance-sheet date precedes valuation date | C28: =Assumptions!$C$5-Assumptions!$C$6 | D28: =IF(C28>0,"PASS","CHECK")
B29: Gordon implied exit multiple (for judgement) | C29: =DCF!C36 | D29: ="INFO" | E29: Compare with the exit multiple assumption
B30: Exit-method implied perpetual growth (for judgement) | C30: =DCF!D36 | D30: =IF(C30<WACC!$C$35,"INFO","CHECK") | E30: Above long-run GDP growth = exit multiple embeds growth beyond FY30
